Workbook

Sheet 专业总览
A2: 租金市场法专业试用版
A3: V0.2 2026年10月9日 20条资产记录，12项市场比较，30个模拟案例。
A5: 导出批次 | B5: RP-V02-20261009-140005 | D5: 模拟基准时点 | E5: 46295
A7: 台账记录数 | B7: =COUNTA(资产清单!A6:A25) -> 20
A8: 范围内计租项数 | B8: =COUNTIFS(测算结果!L6:L25,"纳入") -> 18
A9: 范围排除项数 | B9: =COUNTIFS(测算结果!L6:L25,"排除") -> 2
A10: 本年年租金合计元 | B10: =IF(COUNT(测算结果!H6:H25)<>20,"待补计算资料",SUM(测算结果!H6:H25)) -> 765085.2
A11: 其中设备年租金元 | B11: =IF(COUNT(测算结果!H6:H25)<>20,"",SUMIFS(测算结果!H6:H25,测算结果!D6:D25,"设备附表")) -> 5400
A12: 非设备年租金元 | B12: =IF(COUNT(测算结果!H6:H25)<>20,"",SUMIFS(测算结果!H6:H25,测算结果!L6:L25,"纳入",测算结果!D6:D25,"<>设备附表")) -> 759685.2
A13: B类资料核定金额元 | B13: =IF(COUNT(测算结果!H6:H25)<>20,"",SUMIFS(测算结果!H6:H25,测算结果!D6:D25,"资料核定",测算结果!L6:L25,"纳入")) -> 1440
A14: B类金额占非设备比例 | B14: =IF(OR(COUNT(B12:B13)<>2,B12<=0),"",B13/B12) -> 0.001895522
A15: B类占比复核 | B15: =IF(COUNT(B14)<>1,"待补金额资料",IF(B14<=内部复核参数!B11,"未超内部上限","超限待复核")) -> 未超内部上限
A16: 市场比较计算异常数 | B16: =COUNTIFS(测算结果!D6:D25,"市场比较",测算结果!K6:K25,"<>通过") -> 0
A17: 原始资料核验状态 | B17: 全部为模拟，尚无真实核验证据
A20: 使用顺序 | B20: 主要工作表 | C20: 需要完成的判断 | D20: 查看结果
A21: 1范围与用途 | B21: 资产清单、计租与历史 | C21: 核对数量、实际用途、范围和重复记录 | D21: 识别与分组
A22: 2案例资料 | B22: 市场案例库、资料索引 | C22: 核对详情页、日期、价格、面积和底层标的 | D22: 三案例选用
A23: 3逐项评分 | B23: 修正明细、测算参数 | C23: 比较双方条件，确认评分与依据 | D23: 三案例测算
A24: 4非比较项目 | B24: 租赁资料核定、特殊计租、设备附表 | C24: 确认路线、频次、资料口径与年额 | D24: 测算结果
A25: 5专业复核 | B25: 历史离散复核、大幅变动复核 | C25: 填写原因及专业确认，不倒推结论 | D25: 两年金额对比
A26: 6成果导出 | B26: 同步导出.ps1 | C26: 在Excel保存完整版后同步生成两个外部版本 | D26: 三个版本同批一致
A27: 7异常练习 | B27: 异常练习 | C27: 每次只改一个输入，观察并恢复 | D27: 16项情形
A28: 8试用验证 | B28: 工时与反馈 | C28: 同一范围记录实际工时和使用反馈 | D28: 不预填节省比例
A31: 三种成果来自同一计算底座。送审演示版保留独立复算所需数据；交流意见版为同批次结果快照。
A32: 资料核定路线在内部归入B类控制，独立合同核定及专项计租另行列示，不一概混为B类。
A33: 专业复核待办不自动修改价格。模拟证据不可用于真实评估，方法适用和专业结论仍须评估人员判断。
A34: 扩展资产须同步扩展记录、选择、因素和结果依赖；本版预置20条记录，不承诺仅插入一行即可扩容。

Sheet 测算结果
A1: 导出批次 RP-V02-20261009-140005 全部为模拟数据
A2: 逐项租金测算结果
A3: 全部业务数据及依据记录均为模拟。用于试用复算，未核验真实来源。
A5: 资产编码 | B5: 资产名称 | C5: 实际用途 | D5: 测算路线 | E5: 单价单位 | F5: 计租数量 | G5: 最终租金单价 | H5: 本年年租金元 | I5: 上期参考单价 | J5: 单价差异率 | K5: 计算及组合复核 | L5: 范围 | M5: 计租及复核说明 | N5: 真实资料状态
A6: RP-001 | B6: =IF(COUNTIFS(资产清单!$A$6:$A$25,A6)<>1,"",IF(INDEX(资产清单!$D$6:$D$25,MATCH(A6,资产清单!$A$6:$A$25,0))="","",INDEX(资产清单!$D$6:$D$25,MATCH(A6,资产清单!$A$6:$A$25,0)))) -> 沿街商铺一 | C6: =IF(COUNTIFS(资产清单!$A$6:$A$25,A6)<>1,"",IF(INDEX(资产清单!$H$6:$H$25,MATCH(A6,资产清单!$A$6:$A$25,0))="","",INDEX(资产清单!$H$6:$H$25,MATCH(A6,资产清单!$A$6:$A$25,0)))) -> 商业 | D6: =IF(COUNTIFS(计租与历史!$A$6:$A$25,A6)<>1,"",IF(INDEX(计租与历史!$C$6:$C$25,MATCH(A6,计租与历史!$A$6:$A$25,0))="","",INDEX(计租与历史!$C$6:$C$25,MATCH(A6,计租与历史!$A$6:$A$25,0)))) -> 市场比较 | E6: =IF(COUNTIFS(资产清单!$A$6:$A$25,A6)<>1,"",IF(INDEX(资产清单!$J$6:$J$25,MATCH(A6,资产清单!$A$6:$A$25,0))="","",INDEX(资产清单!$J$6:$J$25,MATCH(A6,资产清单!$A$6:$A$25,0)))) -> 元/㎡/月 | F6: =IF(COUNTIFS(资产清单!$A$6:$A$25,A6)<>1,"",IF(COUNT(INDEX(资产清单!$K$6:$K$25,MATCH(A6,资产清单!$A$6:$A$25,0)))<>1,"",INDEX(资产清单!$K$6:$K$25,MATCH(A6,资产清单!$A$6:$A$25,0)))) -> 60 | G6: =IF(L6="排除",0,IF(D6="市场比较",IF(COUNT(三案例测算!H6:H8)<>3,"",ROUND(AVERAGE(三案例测算!H6:H8),测算参数!$B$9)),IF(OR(D6="资料核定",D6="租赁资料核定"),IF(COUNTIFS(租赁资料核定!$A$6:$A$7,A6)<>1,"",IF(COUNT(INDEX(租赁资料核定!$M$6:$M$7,MATCH(A6,租赁资料核定!$A$6:$A$7,0)))<>1,"",INDEX(租赁资料核定!$M$6:$M$7,MATCH(A6,租赁资料核定!$A$6:$A$7,0)))),IF(D6="专项计租",IF(COUNTIFS(特殊计租!$A$6:$A$7,A6)<>1,"",IF(COUNT(INDEX(特殊计租!$D$6:$D$7,MATCH(A6,特殊计租!$A$6:$A$7,0)))<>1,"",INDEX(特殊计租!$D$6:$D$7,MATCH(A6,特殊计租!$A$6:$A$7,0)))),IF(D6="设备附表",IF(COUNTIFS(设备附表!$A$6:$A$7,A6)<>1,"",IF(COUNT(INDEX(设备附表!$F$6:$F$7,MATCH(A6,设备附表!$A$6:$A$7,0)))<>1,"",INDEX(设备附表!$F$6:$F$7,MATCH(A6,设备附表!$A$6:$A$7,0)))),""))))) -> 54.7 | H6: =IF(L6="排除",0,IF(D6="专项计租",IF(COUNTIFS(特殊计租!$A$6:$A$7,A6)<>1,"",IF(COUNT(INDEX(特殊计租!$J$6:$J$7,MATCH(A6,特殊计租!$A$6:$A$7,0)))<>1,"",INDEX(特殊计租!$J$6:$J$7,MATCH(A6,特殊计租!$A$6:$A$7,0)))),IF(D6="设备附表",IF(COUNTIFS(设备附表!$A$6:$A$7,A6)<>1,"",IF(COUNT(INDEX(设备附表!$G$6:$G$7,MATCH(A6,设备附表!$A$6:$A$7,0)))<>1,"",INDEX(设备附表!$G$6:$G$7,MATCH(A6,设备附表!$A$6:$A$7,0)))),IF(OR(D6="资料核定",D6="租赁资料核定"),IF(COUNTIFS(租赁资料核定!$A$6:$A$7,A6)<>1,"",IF(COUNT(INDEX(租赁资料核定!$N$6:$N$7,MATCH(A6,租赁资料核定!$A$6:$A$7,0)))<>1,"",INDEX(租赁资料核定!$N$6:$N$7,MATCH(A6,租赁资料核定!$A$6:$A$7,0)))),IF(OR(COUNT(F6:G6)<>2,F6<=0),"",ROUND(F6*G6*测算参数!$B$10,2)))))) -> 39384 | I6: =IF(COUNTIFS(计租与历史!$A$6:$A$25,A6)<>1,"",IF(COUNT(INDEX(计租与历史!$D$6:$D$25,MATCH(A6,计租与历史!$A$6:$A$25,0)))<>1,"",INDEX(计租与历史!$D$6:$D$25,MATCH(A6,计租与历史!$A$6:$A$25,0)))) -> 48 | J6: =IF(OR(COUNT(G6,I6)<>2,I6<=0,L6<>"纳入"),"",G6/I6-1) -> 0.13958333 | K6: =IF(L6="排除",IF(AND(D6="不重复计租",OR(IF(COUNTIFS(计租与历史!$A$6:$A$25,A6)<>1,"",IF(INDEX(计租与历史!$G$6:$G$25,MATCH(A6,计租与历史!$A$6:$A$25,0))="","",INDEX(计租与历史!$G$6:$G$25,MATCH(A6,计租与历史!$A$6:$A$25,0))))="",COUNTIFS(资产清单!$A$6:$A$25,IF(COUNTIFS(计租与历史!$A$6:$A$25,A6)<>1,"",IF(INDEX(计租与历史!$G$6:$G$25,MATCH(A6,计租与历史!$A$6:$A$25,0))="","",INDEX(计租与历史!$G$6:$G$25,MATCH(A6,计租与历史!$A$6:$A$25,0)))))<>1)),"待核主资产","范围排除"),IF(D6="市场比较",IF(COUNT(三案例测算!H6:H8)<>3,"待补资料或重判评分",IF(OR(COUNTIFS(三案例测算!J6:J8,"通过")<>3,MAX(三案例测算!H6:H8)/MIN(三案例测算!H6:H8)-1>测算参数!$B$8),"超限待复核","通过")),IF(COUNT(H6)<>1,"待补专项或核定资料","独立资料核定"))) -> 通过 | L6: =IF(COUNTIFS(计租与历史!$A$6:$A$25,A6)<>1,"",IF(INDEX(计租与历史!$B$6:$B$25,MATCH(A6,计租与历史!$A$6:$A$25,0))="","",INDEX(计租与历史!$B$6:$B$25,MATCH(A6,计租与历史!$A$6:$A$25,0)))) -> 纳入 | M6: =IF(COUNTIFS(计租与历史!$A$6:$A$25,A6)<>1,"",IF(INDEX(计租与历史!$H$6:$H$25,MATCH(A6,计租与历史!$A$6:$A$25,0))="","",INDEX(计租与历史!$H$6:$H$25,MATCH(A6,计租与历史!$A$6:$A$25,0)))) -> 按相应计租口径测算 | N6: 模拟数据未真实核验
A7: RP-002 | B7: =IF(COUNTIFS(资产清单!$A$6:$A$25,A7)<>1,"",IF(INDEX(资产清单!$D$6:$D$25,MATCH(A7,资产清单!$A$6:$A$25,0))="","",INDEX(资产清单!$D$6:$D$25,MATCH(A7,资产清单!$A$6:$A$25,0)))) -> 沿街商铺二 | C7: =IF(COUNTIFS(资产清单!$A$6:$A$25,A7)<>1,"",IF(INDEX(资产清单!$H$6:$H$25,MATCH(A7,资产清单!$A$6:$A$25,0))="","",INDEX(资产清单!$H$6:$H$25,MATCH(A7,资产清单!$A$6:$A$25,0)))) -> 商业 | D7: =IF(COUNTIFS(计租与历史!$A$6:$A$25,A7)<>1,"",IF(INDEX(计租与历史!$C$6:$C$25,MATCH(A7,计租与历史!$A$6:$A$25,0))="","",INDEX(计租与历史!$C$6:$C$25,MATCH(A7,计租与历史!$A$6:$A$25,0)))) -> 市场比较 | E7: =IF(COUNTIFS(资产清单!$A$6:$A$25,A7)<>1,"",IF(INDEX(资产清单!$J$6:$J$25,MATCH(A7,资产清单!$A$6:$A$25,0))="","",INDEX(资产清单!$J$6:$J$25,MATCH(A7,资产清单!$A$6:$A$25,0)))) -> 元/㎡/月 | F7: =IF(COUNTIFS(资产清单!$A$6:$A$25,A7)<>1,"",IF(COUNT(INDEX(资产清单!$K$6:$K$25,MATCH(A7,资产清单!$A$6:$A$25,0)))<>1,"",INDEX(资产清单!$K$6:$K$25,MATCH(A7,资产清单!$A$6:$A$25,0)))) -> 110 | G7: =IF(L7="排除",0,IF(D7="市场比较",IF(COUNT(三案例测算!H9:H11)<>3,"",ROUND(AVERAGE(三案例测算!H9:H11),测算参数!$B$9)),IF(OR(D7="资料核定",D7="租赁资料核定"),IF(COUNTIFS(租赁资料核定!$A$6:$A$7,A7)<>1,"",IF(COUNT(INDEX(租赁资料核定!$M$6:$M$7,MATCH(A7,租赁资料核定!$A$6:$A$7,0)))<>1,"",INDEX(租赁资料核定!$M$6:$M$7,MATCH(A7,租赁资料核定!$A$6:$A$7,0)))),IF(D7="专项计租",IF(COUNTIFS(特殊计租!$A$6:$A$7,A7)<>1,"",IF(COUNT(INDEX(特殊计租!$D$6:$D$7,MATCH(A7,特殊计租!$A$6:$A$7,0)))<>1,"",INDEX(特殊计租!$D$6:$D$7,MATCH(A7,特殊计租!$A$6:$A$7,0)))),IF(D7="设备附表",IF(COUNTIFS(设备附表!$A$6:$A$7,A7)<>1,"",IF(COUNT(INDEX(设备附表!$F$6:$F$7,MATCH(A7,设备附表!$A$6:$A$7,0)))<>1,"",INDEX(设备附表!$F$6:$F$7,MATCH(A7,设备附表!$A$6:$A$7,0)))),""))))) -> 52.2 | H7: =IF(L7="排除",0,IF(D7="专项计租",IF(COUNTIFS(特殊计租!$A$6:$A$7,A7)<>1,"",IF(COUNT(INDEX(特殊计租!$J$6:$J$7,MATCH(A7,特殊计租!$A$6:$A$7,0)))<>1,"",INDEX(特殊计租!$J$6:$J$7,MATCH(A7,特殊计租!$A$6:$A$7,0)))),IF(D7="设备附表",IF(COUNTIFS(设备附表!$A$6:$A$7,A7)<>1,"",IF(COUNT(INDEX(设备附表!$G$6:$G$7,MATCH(A7,设备附表!$A$6:$A$7,0)))<>1,"",INDEX(设备附表!$G$6:$G$7,MATCH(A7,设备附表!$A$6:$A$7,0)))),IF(OR(D7="资料核定",D7="租赁资料核定"),IF(COUNTIFS(租赁资料核定!$A$6:$A$7,A7)<>1,"",IF(COUNT(INDEX(租赁资料核定!$N$6:$N$7,MATCH(A7,租赁资料核定!$A$6:$A$7,0)))<>1,"",INDEX(租赁资料核定!$N$6:$N$7,MATCH(A7,租赁资料核定!$A$6:$A$7,0)))),IF(OR(COUNT(F7:G7)<>2,F7<=0),"",ROUND(F7*G7*测算参数!$B$10,2)))))) -> 68904 | I7: =IF(COUNTIFS(计租与历史!$A$6:$A$25,A7)<>1,"",IF(COUNT(INDEX(计租与历史!$D$6:$D$25,MATCH(A7,计租与历史!$A$6:$A$25,0)))<>1,"",INDEX(计租与历史!$D$6:$D$25,MATCH(A7,计租与历史!$A$6:$A$25,0)))) -> 47 | J7: =IF(OR(COUNT(G7,I7)<>2,I7<=0,L7<>"纳入"),"",G7/I7-1) -> 0.1106383 | K7: =IF(L7="排除",IF(AND(D7="不重复计租",OR(IF(COUNTIFS(计租与历史!$A$6:$A$25,A7)<>1,"",IF(INDEX(计租与历史!$G$6:$G$25,MATCH(A7,计租与历史!$A$6:$A$25,0))="","",INDEX(计租与历史!$G$6:$G$25,MATCH(A7,计租与历史!$A$6:$A$25,0))))="",COUNTIFS(资产清单!$A$6:$A$25,IF(COUNTIFS(计租与历史!$A$6:$A$25,A7)<>1,"",IF(INDEX(计租与历史!$G$6:$G$25,MATCH(A7,计租与历史!$A$6:$A$25,0))="","",INDEX(计租与历史!$G$6:$G$25,MATCH(A7,计租与历史!$A$6:$A$25,0)))))<>1)),"待核主资产","范围排除"),IF(D7="市场比较",IF(COUNT(三案例测算!H9:H11)<>3,"待补资料或重判评分",IF(OR(COUNTIFS(三案例测算!J9:J11,"通过")<>3,MAX(三案例测算!H9:H11)/MIN(三案例测算!H9:H11)-1>测算参数!$B$8),"超限待复核","通过")),IF(COUNT(H7)<>1,"待补专项或核定资料","独立资料核定"))) -> 通过 | L7: =IF(COUNTIFS(计租与历史!$A$6:$A$25,A7)<>1,"",IF(INDEX(计租与历史!$B$6:$B$25,MATCH(A7,计租与历史!$A$6:$A$25,0))="","",INDEX(计租与历史!$B$6:$B$25,MATCH(A7,计租与历史!$A$6:$A$25,0)))) -> 纳入 | M7: =IF(COUNTIFS(计租与历史!$A$6:$A$25,A7)<>1,"",IF(INDEX(计租与历史!$H$6:$H$25,MATCH(A7,计租与历史!$A$6:$A$25,0))="","",INDEX(计租与历史!$H$6:$H$25,MATCH(A7,计租与历史!$A$6:$A$25,0)))) -> 按相应计租口径测算 | N7: 模拟数据未真实核验
A8: RP-003 | B8: =IF(COUNTIFS(资产清单!$A$6:$A$25,A8)<>1,"",IF(INDEX(资产清单!$D$6:$D$25,MATCH(A8,资产清单!$A$6:$A$25,0))="","",INDEX(资产清单!$D$6:$D$25,MATCH(A8,资产清单!$A$6:$A$25,0)))) -> 二层商铺 | C8: =IF(COUNTIFS(资产清单!$A$6:$A$25,A8)<>1,"",IF(INDEX(资产清单!$H$6:$H$25,MATCH(A8,资产清单!$A$6:$A$25,0))="","",INDEX(资产清单!$H$6:$H$25,MATCH(A8,资产清单!$A$6:$A$25,0)))) -> 商业 | D8: =IF(COUNTIFS(计租与历史!$A$6:$A$25,A8)<>1,"",IF(INDEX(计租与历史!$C$6:$C$25,MATCH(A8,计租与历史!$A$6:$A$25,0))="","",INDEX(计租与历史!$C$6:$C$25,MATCH(A8,计租与历史!$A$6:$A$25,0)))) -> 市场比较 | E8: =IF(COUNTIFS(资产清单!$A$6:$A$25,A8)<>1,"",IF(INDEX(资产清单!$J$6:$J$25,MATCH(A8,资产清单!$A$6:$A$25,0))="","",INDEX(资产清单!$J$6:$J$25,MATCH(A8,资产清单!$A$6:$A$25,0)))) -> 元/㎡/月 | F8: =IF(COUNTIFS(资产清单!$A$6:$A$25,A8)<>1,"",IF(COUNT(INDEX(资产清单!$K$6:$K$25,MATCH(A8,资产清单!$A$6:$A$25,0)))<>1,"",INDEX(资产清单!$K$6:$K$25,MATCH(A8,资产清单!$A$6:$A$25,0)))) -> 95 | G8: =IF(L8="排除",0,IF(D8="市场比较",IF(COUNT(三案例测算!H12:H14)<>3,"",ROUND(AVERAGE(三案例测算!H12:H14),测算参数!$B$9)),IF(OR(D8="资料核定",D8="租赁资料核定"),IF(COUNTIFS(租赁资料核定!$A$6:$A$7,A8)<>1,"",IF(COUNT(INDEX(租赁资料核定!$M$6:$M$7,MATCH(A8,租赁资料核定!$A$6:$A$7,0)))<>1,"",INDEX(租赁资料核定!$M$6:$M$7,MATCH(A8,租赁资料核定!$A$6:$A$7,0)))),IF(D8="专项计租",IF(COUNTIFS(特殊计租!$A$6:$A$7,A8)<>1,"",IF(COUNT(INDEX(特殊计租!$D$6:$D$7,MATCH(A8,特殊计租!$A$6:$A$7,0)))<>1,"",INDEX(特殊计租!$D$6:$D$7,MATCH(A8,特殊计租!$A$6:$A$7,0)))),IF(D8="设备附表",IF(COUNTIFS(设备附表!$A$6:$A$7,A8)<>1,"",IF(COUNT(INDEX(设备附表!$F$6:$F$7,MATCH(A8,设备附表!$A$6:$A$7,0)))<>1,"",INDEX(设备附表!$F$6:$F$7,MATCH(A8,设备附表!$A$6:$A$7,0)))),""))))) -> 44.1 | H8: =IF(L8="排除",0,IF(D8="专项计租",IF(COUNTIFS(特殊计租!$A$6:$A$7,A8)<>1,"",IF(COUNT(INDEX(特殊计租!$J$6:$J$7,MATCH(A8,特殊计租!$A$6:$A$7,0)))<>1,"",INDEX(特殊计租!$J$6:$J$7,MATCH(A8,特殊计租!$A$6:$A$7,0)))),IF(D8="设备附表",IF(COUNTIFS(设备附表!$A$6:$A$7,A8)<>1,"",IF(COUNT(INDEX(设备附表!$G$6:$G$7,MATCH(A8,设备附表!$A$6:$A$7,0)))<>1,"",INDEX(设备附表!$G$6:$G$7,MATCH(A8,设备附表!$A$6:$A$7,0)))),IF(OR(D8="资料核定",D8="租赁资料核定"),IF(COUNTIFS(租赁资料核定!$A$6:$A$7,A8)<>1,"",IF(COUNT(INDEX(租赁资料核定!$N$6:$N$7,MATCH(A8,租赁资料核定!$A$6:$A$7,0)))<>1,"",INDEX(租赁资料核定!$N$6:$N$7,MATCH(A8,租赁资料核定!$A$6:$A$7,0)))),IF(OR(COUNT(F8:G8)<>2,F8<=0),"",ROUND(F8*G8*测算参数!$B$10,2)))))) -> 50274 | I8: =IF(COUNTIFS(计租与历史!$A$6:$A$25,A8)<>1,"",IF(COUNT(INDEX(计租与历史!$D$6:$D$25,MATCH(A8,计租与历史!$A$6:$A$25,0)))<>1,"",INDEX(计租与历史!$D$6:$D$25,MATCH(A8,计租与历史!$A$6:$A$25,0)))) -> 42 | J8: =IF(OR(COUNT(G8,I8)<>2,I8<=0,L8<>"纳入"),"",G8/I8-1) -> 0.05 | K8: =IF(L8="排除",IF(AND(D8="不重复计租",OR(IF(COUNTIFS(计租与历史!$A$6:$A$25,A8)<>1,"",IF(INDEX(计租与历史!$G$6:$G$25,MATCH(A8,计租与历史!$A$6:$A$25,0))="","",INDEX(计租与历史!$G$6:$G$25,MATCH(A8,计租与历史!$A$6:$A$25,0))))="",COUNTIFS(资产清单!$A$6:$A$25,IF(COUNTIFS(计租与历史!$A$6:$A$25,A8)<>1,"",IF(INDEX(计租与历史!$G$6:$G$25,MATCH(A8,计租与历史!$A$6:$A$25,0))="","",INDEX(计租与历史!$G$6:$G$25,MATCH(A8,计租与历史!$A$6:$A$25,0)))))<>1)),"待核主资产","范围排除"),IF(D8="市场比较",IF(COUNT(三案例测算!H12:H14)<>3,"待补资料或重判评分",IF(OR(COUNTIFS(三案例测算!J12:J14,"通过")<>3,MAX(三案例测算!H12:H14)/MIN(三案例测算!H12:H14)-1>测算参数!$B$8),"超限待复核","通过")),IF(COUNT(H8)<>1,"待补专项或核定资料","独立资料核定"))) -> 通过 | L8: =IF(COUNTIFS(计租与历史!$A$6:$A$25,A8)<>1,"",IF(INDEX(计租与历史!$B$6:$B$25,MATCH(A8,计租与历史!$A$6:$A$25,0))="","",INDEX(计租与历史!$B$6:$B$25,MATCH(A8,计租与历史!$A$6:$A$25,0)))) -> 纳入 | M8: =IF(COUNTIFS(计租与历史!$A$6:$A$25,A8)<>1,"",IF(INDEX(计租与历史!$H$6:$H$25,MATCH(A8,计租与历史!$A$6:$A$25,0))="","",INDEX(计租与历史!$H$6:$H$25,MATCH(A8,计租与历史!$A$6:$A$25,0)))) -> 按相应计租口径测算 | N8: 模拟数据未真实核验
A9: RP-004 | B9: =IF(COUNTIFS(资产清单!$A$6:$A$25,A9)<>1,"",IF(INDEX(资产清单!$D$6:$D$25,MATCH(A9,资产清单!$A$6:$A$25,0))="","",INDEX(资产清单!$D$6:$D$25,MATCH(A9,资产清单!$A$6:$A$25,0)))) -> 内部通道商铺 | C9: =IF(COUNTIFS(资产清单!$A$6:$A$25,A9)<>1,"",IF(INDEX(资产清单!$H$6:$H$25,MATCH(A9,资产清单!$A$6:$A$25,0))="","",INDEX(资产清单!$H$6:$H$25,MATCH(A9,资产清单!$A$6:$A$25,0)))) -> 商业 | D9: =IF(COUNTIFS(计租与历史!$A$6:$A$25,A9)<>1,"",IF(INDEX(计租与历史!$C$6:$C$25,MATCH(A9,计租与历史!$A$6:$A$25,0))="","",INDEX(计租与历史!$C$6:$C$25,MATCH(A9,计租与历史!$A$6:$A$25,0)))) -> 市场比较 | E9: =IF(COUNTIFS(资产清单!$A$6:$A$25,A9)<>1,"",IF(INDEX(资产清单!$J$6:$J$25,MATCH(A9,资产清单!$A$6:$A$25,0))="","",INDEX(资产清单!$J$6:$J$25,MATCH(A9,资产清单!$A$6:$A$25,0)))) -> 元/㎡/月 | F9: =IF(COUNTIFS(资产清单!$A$6:$A$25,A9)<>1,"",IF(COUNT(INDEX(资产清单!$K$6:$K$25,MATCH(A9,资产清单!$A$6:$A$25,0)))<>1,"",INDEX(资产清单!$K$6:$K$25,MATCH(A9,资产清单!$A$6:$A$25,0)))) -> 38 | G9: =IF(L9="排除",0,IF(D9="市场比较",IF(COUNT(三案例测算!H15:H17)<>3,"",ROUND(AVERAGE(三案例测算!H15:H17),测算参数!$B$9)),IF(OR(D9="资料核定",D9="租赁资料核定"),IF(COUNTIFS(租赁资料核定!$A$6:$A$7,A9)<>1,"",IF(COUNT(INDEX(租赁资料核定!$M$6:$M$7,MATCH(A9,租赁资料核定!$A$6:$A$7,0)))<>1,"",INDEX(租赁资料核定!$M$6:$M$7,MATCH(A9,租赁资料核定!$A$6:$A$7,0)))),IF(D9="专项计租",IF(COUNTIFS(特殊计租!$A$6:$A$7,A9)<>1,"",IF(COUNT(INDEX(特殊计租!$D$6:$D$7,MATCH(A9,特殊计租!$A$6:$A$7,0)))<>1,"",INDEX(特殊计租!$D$6:$D$7,MATCH(A9,特殊计租!$A$6:$A$7,0)))),IF(D9="设备附表",IF(COUNTIFS(设备附表!$A$6:$A$7,A9)<>1,"",IF(COUNT(INDEX(设备附表!$F$6:$F$7,MATCH(A9,设备附表!$A$6:$A$7,0)))<>1,"",INDEX(设备附表!$F$6:$F$7,MATCH(A9,设备附表!$A$6:$A$7,0)))),""))))) -> 61.9 | H9: =IF(L9="排除",0,IF(D9="专项计租",IF(COUNTIFS(特殊计租!$A$6:$A$7,A9)<>1,"",IF(COUNT(INDEX(特殊计租!$J$6:$J$7,MATCH(A9,特殊计租!$A$6:$A$7,0)))<>1,"",INDEX(特殊计租!$J$6:$J$7,MATCH(A9,特殊计租!$A$6:$A$7,0)))),IF(D9="设备附表",IF(COUNTIFS(设备附表!$A$6:$A$7,A9)<>1,"",IF(COUNT(INDEX(设备附表!$G$6:$G$7,MATCH(A9,设备附表!$A$6:$A$7,0)))<>1,"",INDEX(设备附表!$G$6:$G$7,MATCH(A9,设备附表!$A$6:$A$7,0)))),IF(OR(D9="资料核定",D9="租赁资料核定"),IF(COUNTIFS(租赁资料核定!$A$6:$A$7,A9)<>1,"",IF(COUNT(INDEX(租赁资料核定!$N$6:$N$7,MATCH(A9,租赁资料核定!$A$6:$A$7,0)))<>1,"",INDEX(租赁资料核定!$N$6:$N$7,MATCH(A9,租赁资料核定!$A$6:$A$7,0)))),IF(OR(COUNT(F9:G9)<>2,F9<=0),"",ROUND(F9*G9*测算参数!$B$10,2)))))) -> 28226.4 | I9: =IF(COUNTIFS(计租与历史!$A$6:$A$25,A9)<>1,"",IF(COUNT(INDEX(计租与历史!$D$6:$D$25,MATCH(A9,计租与历史!$A$6:$A$25,0)))<>1,"",INDEX(计租与历史!$D$6:$D$25,MATCH(A9,计租与历史!$A$6:$A$25,0)))) -> 50 | J9: =IF(OR(COUNT(G9,I9)<>2,I9<=0,L9<>"纳入"),"",G9/I9-1) -> 0.238 | K9: =IF(L9="排除",IF(AND(D9="不重复计租",OR(IF(COUNTIFS(计租与历史!$A$6:$A$25,A9)<>1,"",IF(INDEX(计租与历史!$G$6:$G$25,MATCH(A9,计租与历史!$A$6:$A$25,0))="","",INDEX(计租与历史!$G$6:$G$25,MATCH(A9,计租与历史!$A$6:$A$25,0))))="",COUNTIFS(资产清单!$A$6:$A$25,IF(COUNTIFS(计租与历史!$A$6:$A$25,A9)<>1,"",IF(INDEX(计租与历史!$G$6:$G$25,MATCH(A9,计租与历史!$A$6:$A$25,0))="","",INDEX(计租与历史!$G$6:$G$25,MATCH(A9,计租与历史!$A$6:$A$25,0)))))<>1)),"待核主资产","范围排除"),IF(D9="市场比较",IF(COUNT(三案例测算!H15:H17)<>3,"待补资料或重判评分",IF(OR(COUNTIFS(三案例测算!J15:J17,"通过")<>3,MAX(三案例测算!H15:H17)/MIN(三案例测算!H15:H17)-1>测算参数!$B$8),"超限待复核","通过")),IF(COUNT(H9)<>1,"待补专项或核定资料","独立资料核定"))) -> 通过 | L9: =IF(COUNTIFS(计租与历史!$A$6:$A$25,A9)<>1,"",IF(INDEX(计租与历史!$B$6:$B$25,MATCH(A9,计租与历史!$A$6:$A$25,0))="","",INDEX(计租与历史!$B$6:$B$25,MATCH(A9,计租与历史!$A$6:$A$25,0)))) -> 纳入 | M9: =IF(COUNTIFS(计租与历史!$A$6:$A$25,A9)<>1,"",IF(INDEX(计租与历史!$H$6:$H$25,MATCH(A9,计租与历史!$A$6:$A$25,0))="","",INDEX(计租与历史!$H$6:$H$25,MATCH(A9,计租与历史!$A$6:$A$25,0)))) -> 按相应计租口径测算 | N9: 模拟数据未真实核验
A10: RP-005 | B10: =IF(COUNTIFS(资产清单!$A$6:$A$25,A10)<>1,"",IF(INDEX(资产清单!$D$6:$D$25,MATCH(A10,资产清单!$A$6:$A$25,0))="","",INDEX(资产清单!$D$6:$D$25,MATCH(A10,资产清单!$A$6:$A$25,0)))) -> 办公用房一 | C10: =IF(COUNTIFS(资产清单!$A$6:$A$25,A10)<>1,"",IF(INDEX(资产清单!$H$6:$H$25,MATCH(A10,资产清单!$A$6:$A$25,0))="","",INDEX(资产清单!$H$6:$H$25,MATCH(A10,资产清单!$A$6:$A$25,0)))) -> 办公 | D10: =IF(COUNTIFS(计租与历史!$A$6:$A$25,A10)<>1,"",IF(INDEX(计租与历史!$C$6:$C$25,MATCH(A10,计租与历史!$A$6:$A$25,0))="","",INDEX(计租与历史!$C$6:$C$25,MATCH(A10,计租与历史!$A$6:$A$25,0)))) -> 市场比较 | E10: =IF(COUNTIFS(资产清单!$A$6:$A$25,A10)<>1,"",IF(INDEX(资产清单!$J$6:$J$25,MATCH(A10,资产清单!$A$6:$A$25,0))="","",INDEX(资产清单!$J$6:$J$25,MATCH(A10,资产清单!$A$6:$A$25,0)))) -> 元/㎡/月 | F10: =IF(COUNTIFS(资产清单!$A$6:$A$25,A10)<>1,"",IF(COUNT(INDEX(资产清单!$K$6:$K$25,MATCH(A10,资产清单!$A$6:$A$25,0)))<>1,"",INDEX(资产清单!$K$6:$K$25,MATCH(A10,资产清单!$A$6:$A$25,0)))) -> 140 | G10: =IF(L10="排除",0,IF(D10="市场比较",IF(COUNT(三案例测算!H18:H20)<>3,"",ROUND(AVERAGE(三案例测算!H18:H20),测算参数!$B$9)),IF(OR(D10="资料核定",D10="租赁资料核定"),IF(COUNTIFS(租赁资料核定!$A$6:$A$7,A10)<>1,"",IF(COUNT(INDEX(租赁资料核定!$M$6:$M$7,MATCH(A10,租赁资料核定!$A$6:$A$7,0)))<>1,"",INDEX(租赁资料核定!$M$6:$M$7,MATCH(A10,租赁资料核定!$A$6:$A$7,0)))),IF(D10="专项计租",IF(COUNTIFS(特殊计租!$A$6:$A$7,A10)<>1,"",IF(COUNT(INDEX(特殊计租!$D$6:$D$7,MATCH(A10,特殊计租!$A$6:$A$7,0)))<>1,"",INDEX(特殊计租!$D$6:$D$7,MATCH(A10,特殊计租!$A$6:$A$7,0)))),IF(D10="设备附表",IF(COUNTIFS(设备附表!$A$6:$A$7,A10)<>1,"",IF(COUNT(INDEX(设备附表!$F$6:$F$7,MATCH(A10,设备附表!$A$6:$A$7,0)))<>1,"",INDEX(设备附表!$F$6:$F$7,MATCH(A10,设备附表!$A$6:$A$7,0)))),""))))) -> 26.5 | H10: =IF(L10="排除",0,IF(D10="专项计租",IF(COUNTIFS(特殊计租!$A$6:$A$7,A10)<>1,"",IF(COUNT(INDEX(特殊计租!$J$6:$J$7,MATCH(A10,特殊计租!$A$6:$A$7,0)))<>1,"",INDEX(特殊计租!$J$6:$J$7,MATCH(A10,特殊计租!$A$6:$A$7,0)))),IF(D10="设备附表",IF(COUNTIFS(设备附表!$A$6:$A$7,A10)<>1,"",IF(COUNT(INDEX(设备附表!$G$6:$G$7,MATCH(A10,设备附表!$A$6:$A$7,0)))<>1,"",INDEX(设备附表!$G$6:$G$7,MATCH(A10,设备附表!$A$6:$A$7,0)))),IF(OR(D10="资料核定",D10="租赁资料核定"),IF(COUNTIFS(租赁资料核定!$A$6:$A$7,A10)<>1,"",IF(COUNT(INDEX(租赁资料核定!$N$6:$N$7,MATCH(A10,租赁资料核定!$A$6:$A$7,0)))<>1,"",INDEX(租赁资料核定!$N$6:$N$7,MATCH(A10,租赁资料核定!$A$6:$A$7,0)))),IF(OR(COUNT(F10:G10)<>2,F10<=0),"",ROUND(F10*G10*测算参数!$B$10,2)))))) -> 44520 | I10: =IF(COUNTIFS(计租与历史!$A$6:$A$25,A10)<>1,"",IF(COUNT(INDEX(计租与历史!$D$6:$D$25,MATCH(A10,计租与历史!$A$6:$A$25,0)))<>1,"",INDEX(计租与历史!$D$6:$D$25,MATCH(A10,计租与历史!$A$6:$A$25,0)))) -> 14 | J10: =IF(OR(COUNT(G10,I10)<>2,I10<=0,L10<>"纳入"),"",G10/I10-1) -> 0.89285714 | K10: =IF(L10="排除",IF(AND(D10="不重复计租",OR(IF(COUNTIFS(计租与历史!$A$6:$A$25,A10)<>1,"",IF(INDEX(计租与历史!$G$6:$G$25,MATCH(A10,计租与历史!$A$6:$A$25,0))="","",INDEX(计租与历史!$G$6:$G$25,MATCH(A10,计租与历史!$A$6:$A$25,0))))="",COUNTIFS(资产清单!$A$6:$A$25,IF(COUNTIFS(计租与历史!$A$6:$A$25,A10)<>1,"",IF(INDEX(计租与历史!$G$6:$G$25,MATCH(A10,计租与历史!$A$6:$A$25,0))="","",INDEX(计租与历史!$G$6:$G$25,MATCH(A10,计租与历史!$A$6:$A$25,0)))))<>1)),"待核主资产","范围排除"),IF(D10="市场比较",IF(COUNT(三案例测算!H18:H20)<>3,"待补资料或重判评分",IF(OR(COUNTIFS(三案例测算!J18:J20,"通过")<>3,MAX(三案例测算!H18:H20)/MIN(三案例测算!H18:H20)-1>测算参数!$B$8),"超限待复核","通过")),IF(COUNT(H10)<>1,"待补专项或核定资料","独立资料核定"))) -> 通过 | L10: =IF(COUNTIFS(计租与历史!$A$6:$A$25,A10)<>1,"",IF(INDEX(计租与历史!$B$6:$B$25,MATCH(A10,计租与历史!$A$6:$A$25,0))="","",INDEX(计租与历史!$B$6:$B$25,MATCH(A10,计租与历史!$A$6:$A$25,0)))) -> 纳入 | M10: =IF(COUNTIFS(计租与历史!$A$6:$A$25,A10)<>1,"",IF(INDEX(计租与历史!$H$6:$H$25,MATCH(A10,计租与历史!$A$6:$A$25,0))="","",INDEX(计租与历史!$H$6:$H$25,MATCH(A10,计租与历史!$A$6:$A$25,0)))) -> 按相应计租口径测算 | N10: 模拟数据未真实核验
A11: RP-006 | B11: =IF(COUNTIFS(资产清单!$A$6:$A$25,A11)<>1,"",IF(INDEX(资产清单!$D$6:$D$25,MATCH(A11,资产清单!$A$6:$A$25,0))="","",INDEX(资产清单!$D$6:$D$25,MATCH(A11,资产清单!$A$6:$A$25,0)))) -> 办公用房二 | C11: =IF(COUNTIFS(资产清单!$A$6:$A$25,A11)<>1,"",IF(INDEX(资产清单!$H$6:$H$25,MATCH(A11,资产清单!$A$6:$A$25,0))="","",INDEX(资产清单!$H$6:$H$25,MATCH(A11,资产清单!$A$6:$A$25,0)))) -> 办公 | D11: =IF(COUNTIFS(计租与历史!$A$6:$A$25,A11)<>1,"",IF(INDEX(计租与历史!$C$6:$C$25,MATCH(A11,计租与历史!$A$6:$A$25,0))="","",INDEX(计租与历史!$C$6:$C$25,MATCH(A11,计租与历史!$A$6:$A$25,0)))) -> 市场比较 | E11: =IF(COUNTIFS(资产清单!$A$6:$A$25,A11)<>1,"",IF(INDEX(资产清单!$J$6:$J$25,MATCH(A11,资产清单!$A$6:$A$25,0))="","",INDEX(资产清单!$J$6:$J$25,MATCH(A11,资产清单!$A$6:$A$25,0)))) -> 元/㎡/月 | F11: =IF(COUNTIFS(资产清单!$A$6:$A$25,A11)<>1,"",IF(COUNT(INDEX(资产清单!$K$6:$K$25,MATCH(A11,资产清单!$A$6:$A$25,0)))<>1,"",INDEX(资产清单!$K$6:$K$25,MATCH(A11,资产清单!$A$6:$A$25,0)))) -> 180 | G11: =IF(L11="排除",0,IF(D11="市场比较",IF(COUNT(三案例测算!H21:H23)<>3,"",ROUND(AVERAGE(三案例测算!H21:H23),测算参数!$B$9)),IF(OR(D11="资料核定",D11="租赁资料核定"),IF(COUNTIFS(租赁资料核定!$A$6:$A$7,A11)<>1,"",IF(COUNT(INDEX(租赁资料核定!$M$6:$M$7,MATCH(A11,租赁资料核定!$A$6:$A$7,0)))<>1,"",INDEX(租赁资料核定!$M$6:$M$7,MATCH(A11,租赁资料核定!$A$6:$A$7,0)))),IF(D11="专项计租",IF(COUNTIFS(特殊计租!$A$6:$A$7,A11)<>1,"",IF(COUNT(INDEX(特殊计租!$D$6:$D$7,MATCH(A11,特殊计租!$A$6:$A$7,0)))<>1,"",INDEX(特殊计租!$D$6:$D$7,MATCH(A11,特殊计租!$A$6:$A$7,0)))),IF(D11="设备附表",IF(COUNTIFS(设备附表!$A$6:$A$7,A11)<>1,"",IF(COUNT(INDEX(设备附表!$F$6:$F$7,MATCH(A11,设备附表!$A$6:$A$7,0)))<>1,"",INDEX(设备附表!$F$6:$F$7,MATCH(A11,设备附表!$A$6:$A$7,0)))),""))))) -> 26.1 | H11: =IF(L11="排除",0,IF(D11="专项计租",IF(COUNTIFS(特殊计租!$A$6:$A$7,A11)<>1,"",IF(COUNT(INDEX(特殊计租!$J$6:$J$7,MATCH(A11,特殊计租!$A$6:$A$7,0)))<>1,"",INDEX(特殊计租!$J$6:$J$7,MATCH(A11,特殊计租!$A$6:$A$7,0)))),IF(D11="设备附表",IF(COUNTIFS(设备附表!$A$6:$A$7,A11)<>1,"",IF(COUNT(INDEX(设备附表!$G$6:$G$7,MATCH(A11,设备附表!$A$6:$A$7,0)))<>1,"",INDEX(设备附表!$G$6:$G$7,MATCH(A11,设备附表!$A$6:$A$7,0)))),IF(OR(D11="资料核定",D11="租赁资料核定"),IF(COUNTIFS(租赁资料核定!$A$6:$A$7,A11)<>1,"",IF(COUNT(INDEX(租赁资料核定!$N$6:$N$7,MATCH(A11,租赁资料核定!$A$6:$A$7,0)))<>1,"",INDEX(租赁资料核定!$N$6:$N$7,MATCH(A11,租赁资料核定!$A$6:$A$7,0)))),IF(OR(COUNT(F11:G11)<>2,F11<=0),"",ROUND(F11*G11*测算参数!$B$10,2)))))) -> 56376 | I11: =IF(COUNTIFS(计租与历史!$A$6:$A$25,A11)<>1,"",IF(COUNT(INDEX(计租与历史!$D$6:$D$25,MATCH(A11,计租与历史!$A$6:$A$25,0)))<>1,"",INDEX(计租与历史!$D$6:$D$25,MATCH(A11,计租与历史!$A$6:$A$25,0)))) -> 32 | J11: =IF(OR(COUNT(G11,I11)<>2,I11<=0,L11<>"纳入"),"",G11/I11-1) -> -0.184375 | K11: =IF(L11="排除",IF(AND(D11="不重复计租",OR(IF(COUNTIFS(计租与历史!$A$6:$A$25,A11)<>1,"",IF(INDEX(计租与历史!$G$6:$G$25,MATCH(A11,计租与历史!$A$6:$A$25,0))="","",INDEX(计租与历史!$G$6:$G$25,MATCH(A11,计租与历史!$A$6:$A$25,0))))="",COUNTIFS(资产清单!$A$6:$A$25,IF(COUNTIFS(计租与历史!$A$6:$A$25,A11)<>1,"",IF(INDEX(计租与历史!$G$6:$G$25,MATCH(A11,计租与历史!$A$6:$A$25,0))="","",INDEX(计租与历史!$G$6:$G$25,MATCH(A11,计租与历史!$A$6:$A$25,0)))))<>1)),"待核主资产","范围排除"),IF(D11="市场比较",IF(COUNT(三案例测算!H21:H23)<>3,"待补资料或重判评分",IF(OR(COUNTIFS(三案例测算!J21:J23,"通过")<>3,MAX(三案例测算!H21:H23)/MIN(三案例测算!H21:H23)-1>测算参数!$B$8),"超限待复核","通过")),IF(COUNT(H11)<>1,"待补专项或核定资料","独立资料核定"))) -> 通过 | L11: =IF(COUNTIFS(计租与历史!$A$6:$A$25,A11)<>1,"",IF(INDEX(计租与历史!$B$6:$B$25,MATCH(A11,计租与历史!$A$6:$A$25,0))="","",INDEX(计租与历史!$B$6:$B$25,MATCH(A11,计租与历史!$A$6:$A$25,0)))) -> 纳入 | M11: =IF(COUNTIFS(计租与历史!$A$6:$A$25,A11)<>1,"",IF(INDEX(计租与历史!$H$6:$H$25,MATCH(A11,计租与历史!$A$6:$A$25,0))="","",INDEX(计租与历史!$H$6:$H$25,MATCH(A11,计租与历史!$A$6:$A$25,0)))) -> 按相应计租口径测算 | N11: 模拟数据未真实核验
A12: RP-007 | B12: =IF(COUNTIFS(资产清单!$A$6:$A$25,A12)<>1,"",IF(INDEX(资产清单!$D$6:$D$25,MATCH(A12,资产清单!$A$6:$A$25,0))="","",INDEX(资产清单!$D$6:$D$25,MATCH(A12,资产清单!$A$6:$A$25,0)))) -> 仓储库房 | C12: =IF(COUNTIFS(资产清单!$A$6:$A$25,A12)<>1,"",IF(INDEX(资产清单!$H$6:$H$25,MATCH(A12,资产清单!$A$6:$A$25,0))="","",INDEX(资产清单!$H$6:$H$25,MATCH(A12,资产清单!$A$6:$A$25,0)))) -> 仓储 | D12: =IF(COUNTIFS(计租与历史!$A$6:$A$25,A12)<>1,"",IF(INDEX(计租与历史!$C$6:$C$25,MATCH(A12,计租与历史!$A$6:$A$25,0))="","",INDEX(计租与历史!$C$6:$C$25,MATCH(A12,计租与历史!$A$6:$A$25,0)))) -> 市场比较 | E12: =IF(COUNTIFS(资产清单!$A$6:$A$25,A12)<>1,"",IF(INDEX(资产清单!$J$6:$J$25,MATCH(A12,资产清单!$A$6:$A$25,0))="","",INDEX(资产清单!$J$6:$J$25,MATCH(A12,资产清单!$A$6:$A$25,0)))) -> 元/㎡/月 | F12: =IF(COUNTIFS(资产清单!$A$6:$A$25,A12)<>1,"",IF(COUNT(INDEX(资产清单!$K$6:$K$25,MATCH(A12,资产清单!$A$6:$A$25,0)))<>1,"",INDEX(资产清单!$K$6:$K$25,MATCH(A12,资产清单!$A$6:$A$25,0)))) -> 500 | G12: =IF(L12="排除",0,IF(D12="市场比较",IF(COUNT(三案例测算!H24:H26)<>3,"",ROUND(AVERAGE(三案例测算!H24:H26),测算参数!$B$9)),IF(OR(D12="资料核定",D12="租赁资料核定"),IF(COUNTIFS(租赁资料核定!$A$6:$A$7,A12)<>1,"",IF(COUNT(INDEX(租赁资料核定!$M$6:$M$7,MATCH(A12,租赁资料核定!$A$6:$A$7,0)))<>1,"",INDEX(租赁资料核定!$M$6:$M$7,MATCH(A12,租赁资料核定!$A$6:$A$7,0)))),IF(D12="专项计租",IF(COUNTIFS(特殊计租!$A$6:$A$7,A12)<>1,"",IF(COUNT(INDEX(特殊计租!$D$6:$D$7,MATCH(A12,特殊计租!$A$6:$A$7,0)))<>1,"",INDEX(特殊计租!$D$6:$D$7,MATCH(A12,特殊计租!$A$6:$A$7,0)))),IF(D12="设备附表",IF(COUNTIFS(设备附表!$A$6:$A$7,A12)<>1,"",IF(COUNT(INDEX(设备附表!$F$6:$F$7,MATCH(A12,设备附表!$A$6:$A$7,0)))<>1,"",INDEX(设备附表!$F$6:$F$7,MATCH(A12,设备附表!$A$6:$A$7,0)))),""))))) -> 12.1 | H12: =IF(L12="排除",0,IF(D12="专项计租",IF(COUNTIFS(特殊计租!$A$6:$A$7,A12)<>1,"",IF(COUNT(INDEX(特殊计租!$J$6:$J$7,MATCH(A12,特殊计租!$A$6:$A$7,0)))<>1,"",INDEX(特殊计租!$J$6:$J$7,MATCH(A12,特殊计租!$A$6:$A$7,0)))),IF(D12="设备附表",IF(COUNTIFS(设备附表!$A$6:$A$7,A12)<>1,"",IF(COUNT(INDEX(设备附表!$G$6:$G$7,MATCH(A12,设备附表!$A$6:$A$7,0)))<>1,"",INDEX(设备附表!$G$6:$G$7,MATCH(A12,设备附表!$A$6:$A$7,0)))),IF(OR(D12="资料核定",D12="租赁资料核定"),IF(COUNTIFS(租赁资料核定!$A$6:$A$7,A12)<>1,"",IF(COUNT(INDEX(租赁资料核定!$N$6:$N$7,MATCH(A12,租赁资料核定!$A$6:$A$7,0)))<>1,"",INDEX(租赁资料核定!$N$6:$N$7,MATCH(A12,租赁资料核定!$A$6:$A$7,0)))),IF(OR(COUNT(F12:G12)<>2,F12<=0),"",ROUND(F12*G12*测算参数!$B$10,2)))))) -> 72600 | I12: =IF(COUNTIFS(计租与历史!$A$6:$A$25,A12)<>1,"",IF(COUNT(INDEX(计租与历史!$D$6:$D$25,MATCH(A12,计租与历史!$A$6:$A$25,0)))<>1,"",INDEX(计租与历史!$D$6:$D$25,MATCH(A12,计租与历史!$A$6:$A$25,0)))) -> 11 | J12: =IF(OR(COUNT(G12,I12)<>2,I12<=0,L12<>"纳入"),"",G12/I12-1) -> 0.1 | K12: =IF(L12="排除",IF(AND(D12="不重复计租",OR(IF(COUNTIFS(计租与历史!$A$6:$A$25,A12)<>1,"",IF(INDEX(计租与历史!$G$6:$G$25,MATCH(A12,计租与历史!$A$6:$A$25,0))="","",INDEX(计租与历史!$G$6:$G$25,MATCH(A12,计租与历史!$A$6:$A$25,0))))="",COUNTIFS(资产清单!$A$6:$A$25,IF(COUNTIFS(计租与历史!$A$6:$A$25,A12)<>1,"",IF(INDEX(计租与历史!$G$6:$G$25,MATCH(A12,计租与历史!$A$6:$A$25,0))="","",INDEX(计租与历史!$G$6:$G$25,MATCH(A12,计租与历史!$A$6:$A$25,0)))))<>1)),"待核主资产","范围排除"),IF(D12="市场比较",IF(COUNT(三案例测算!H24:H26)<>3,"待补资料或重判评分",IF(OR(COUNTIFS(三案例测算!J24:J26,"通过")<>3,MAX(三案例测算!H24:H26)/MIN(三案例测算!H24:H26)-1>测算参数!$B$8),"超限待复核","通过")),IF(COUNT(H12)<>1,"待补专项或核定资料","独立资料核定"))) -> 通过 | L12: =IF(COUNTIFS(计租与历史!$A$6:$A$25,A12)<>1,"",IF(INDEX(计租与历史!$B$6:$B$25,MATCH(A12,计租与历史!$A$6:$A$25,0))="","",INDEX(计租与历史!$B$6:$B$25,MATCH(A12,计租与历史!$A$6:$A$25,0)))) -> 纳入 | M12: =IF(COUNTIFS(计租与历史!$A$6:$A$25,A12)<>1,"",IF(INDEX(计租与历史!$H$6:$H$25,MATCH(A12,计租与历史!$A$6:$A$25,0))="","",INDEX(计租与历史!$H$6:$H$25,MATCH(A12,计租与历史!$A$6:$A$25,0)))) -> 按相应计租口径测算 | N12: 模拟数据未真实核验
A13: RP-008 | B13: =IF(COUNTIFS(资产清单!$A$6:$A$25,A13)<>1,"",IF(INDEX(资产清单!$D$6:$D$25,MATCH(A13,资产清单!$A$6:$A$25,0))="","",INDEX(资产清单!$D$6:$D$25,MATCH(A13,资产清单!$A$6:$A$25,0)))) -> 工业厂房 | C13: =IF(COUNTIFS(资产清单!$A$6:$A$25,A13)<>1,"",IF(INDEX(资产清单!$H$6:$H$25,MATCH(A13,资产清单!$A$6:$A$25,0))="","",INDEX(资产清单!$H$6:$H$25,MATCH(A13,资产清单!$A$6:$A$25,0)))) -> 厂房 | D13: =IF(COUNTIFS(计租与历史!$A$6:$A$25,A13)<>1,"",IF(INDEX(计租与历史!$C$6:$C$25,MATCH(A13,计租与历史!$A$6:$A$25,0))="","",INDEX(计租与历史!$C$6:$C$25,MATCH(A13,计租与历史!$A$6:$A$25,0)))) -> 市场比较 | E13: =IF(COUNTIFS(资产清单!$A$6:$A$25,A13)<>1,"",IF(INDEX(资产清单!$J$6:$J$25,MATCH(A13,资产清单!$A$6:$A$25,0))="","",INDEX(资产清单!$J$6:$J$25,MATCH(A13,资产清单!$A$6:$A$25,0)))) -> 元/㎡/月 | F13: =IF(COUNTIFS(资产清单!$A$6:$A$25,A13)<>1,"",IF(COUNT(INDEX(资产清单!$K$6:$K$25,MATCH(A13,资产清单!$A$6:$A$25,0)))<>1,"",INDEX(资产清单!$K$6:$K$25,MATCH(A13,资产清单!$A$6:$A$25,0)))) -> 1200 | G13: =IF(L13="排除",0,IF(D13="市场比较",IF(COUNT(三案例测算!H27:H29)<>3,"",ROUND(AVERAGE(三案例测算!H27:H29),测算参数!$B$9)),IF(OR(D13="资料核定",D13="租赁资料核定"),IF(COUNTIFS(租赁资料核定!$A$6:$A$7,A13)<>1,"",IF(COUNT(INDEX(租赁资料核定!$M$6:$M$7,MATCH(A13,租赁资料核定!$A$6:$A$7,0)))<>1,"",INDEX(租赁资料核定!$M$6:$M$7,MATCH(A13,租赁资料核定!$A$6:$A$7,0)))),IF(D13="专项计租",IF(COUNTIFS(特殊计租!$A$6:$A$7,A13)<>1,"",IF(COUNT(INDEX(特殊计租!$D$6:$D$7,MATCH(A13,特殊计租!$A$6:$A$7,0)))<>1,"",INDEX(特殊计租!$D$6:$D$7,MATCH(A13,特殊计租!$A$6:$A$7,0)))),IF(D13="设备附表",IF(COUNTIFS(设备附表!$A$6:$A$7,A13)<>1,"",IF(COUNT(INDEX(设备附表!$F$6:$F$7,MATCH(A13,设备附表!$A$6:$A$7,0)))<>1,"",INDEX(设备附表!$F$6:$F$7,MATCH(A13,设备附表!$A$6:$A$7,0)))),""))))) -> 16.6 | H13: =IF(L13="排除",0,IF(D13="专项计租",IF(COUNTIFS(特殊计租!$A$6:$A$7,A13)<>1,"",IF(COUNT(INDEX(特殊计租!$J$6:$J$7,MATCH(A13,特殊计租!$A$6:$A$7,0)))<>1,"",INDEX(特殊计租!$J$6:$J$7,MATCH(A13,特殊计租!$A$6:$A$7,0)))),IF(D13="设备附表",IF(COUNTIFS(设备附表!$A$6:$A$7,A13)<>1,"",IF(COUNT(INDEX(设备附表!$G$6:$G$7,MATCH(A13,设备附表!$A$6:$A$7,0)))<>1,"",INDEX(设备附表!$G$6:$G$7,MATCH(A13,设备附表!$A$6:$A$7,0)))),IF(OR(D13="资料核定",D13="租赁资料核定"),IF(COUNTIFS(租赁资料核定!$A$6:$A$7,A13)<>1,"",IF(COUNT(INDEX(租赁资料核定!$N$6:$N$7,MATCH(A13,租赁资料核定!$A$6:$A$7,0)))<>1,"",INDEX(租赁资料核定!$N$6:$N$7,MATCH(A13,租赁资料核定!$A$6:$A$7,0)))),IF(OR(COUNT(F13:G13)<>2,F13<=0),"",ROUND(F13*G13*测算参数!$B$10,2)))))) -> 239040 | I13: =IF(COUNTIFS(计租与历史!$A$6:$A$25,A13)<>1,"",IF(COUNT(INDEX(计租与历史!$D$6:$D$25,MATCH(A13,计租与历史!$A$6:$A$25,0)))<>1,"",INDEX(计租与历史!$D$6:$D$25,MATCH(A13,计租与历史!$A$6:$A$25,0)))) -> 15 | J13: =IF(OR(COUNT(G13,I13)<>2,I13<=0,L13<>"纳入"),"",G13/I13-1) -> 0.10666667 | K13: =IF(L13="排除",IF(AND(D13="不重复计租",OR(IF(COUNTIFS(计租与历史!$A$6:$A$25,A13)<>1,"",IF(INDEX(计租与历史!$G$6:$G$25,MATCH(A13,计租与历史!$A$6:$A$25,0))="","",INDEX(计租与历史!$G$6:$G$25,MATCH(A13,计租与历史!$A$6:$A$25,0))))="",COUNTIFS(资产清单!$A$6:$A$25,IF(COUNTIFS(计租与历史!$A$6:$A$25,A13)<>1,"",IF(INDEX(计租与历史!$G$6:$G$25,MATCH(A13,计租与历史!$A$6:$A$25,0))="","",INDEX(计租与历史!$G$6:$G$25,MATCH(A13,计租与历史!$A$6:$A$25,0)))))<>1)),"待核主资产","范围排除"),IF(D13="市场比较",IF(COUNT(三案例测算!H27:H29)<>3,"待补资料或重判评分",IF(OR(COUNTIFS(三案例测算!J27:J29,"通过")<>3,MAX(三案例测算!H27:H29)/MIN(三案例测算!H27:H29)-1>测算参数!$B$8),"超限待复核","通过")),IF(COUNT(H13)<>1,"待补专项或核定资料","独立资料核定"))) -> 通过 | L13: =IF(COUNTIFS(计租与历史!$A$6:$A$25,A13)<>1,"",IF(INDEX(计租与历史!$B$6:$B$25,MATCH(A13,计租与历史!$A$6:$A$25,0))="","",INDEX(计租与历史!$B$6:$B$25,MATCH(A13,计租与历史!$A$6:$A$25,0)))) -> 纳入 | M13: =IF(COUNTIFS(计租与历史!$A$6:$A$25,A13)<>1,"",IF(INDEX(计租与历史!$H$6:$H$25,MATCH(A13,计租与历史!$A$6:$A$25,0))="","",INDEX(计租与历史!$H$6:$H$25,MATCH(A13,计租与历史!$A$6:$A$25,0)))) -> 按相应计租口径测算 | N13: 模拟数据未真实核验
A14: RP-009 | B14: =IF(COUNTIFS(资产清单!$A$6:$A$25,A14)<>1,"",IF(INDEX(资产清单!$D$6:$D$25,MATCH(A14,资产清单!$A$6:$A$25,0))="","",INDEX(资产清单!$D$6:$D$25,MATCH(A14,资产清单!$A$6:$A$25,0)))) -> 露天场地 | C14: =IF(COUNTIFS(资产清单!$A$6:$A$25,A14)<>1,"",IF(INDEX(资产清单!$H$6:$H$25,MATCH(A14,资产清单!$A$6:$A$25,0))="","",INDEX(资产清单!$H$6:$H$25,MATCH(A14,资产清单!$A$6:$A$25,0)))) -> 场地 | D14: =IF(COUNTIFS(计租与历史!$A$6:$A$25,A14)<>1,"",IF(INDEX(计租与历史!$C$6:$C$25,MATCH(A14,计租与历史!$A$6:$A$25,0))="","",INDEX(计租与历史!$C$6:$C$25,MATCH(A14,计租与历史!$A$6:$A$25,0)))) -> 市场比较 | E14: =IF(COUNTIFS(资产清单!$A$6:$A$25,A14)<>1,"",IF(INDEX(资产清单!$J$6:$J$25,MATCH(A14,资产清单!$A$6:$A$25,0))="","",INDEX(资产清单!$J$6:$J$25,MATCH(A14,资产清单!$A$6:$A$25,0)))) -> 元/㎡/月 | F14: =IF(COUNTIFS(资产清单!$A$6:$A$25,A14)<>1,"",IF(COUNT(INDEX(资产清单!$K$6:$K$25,MATCH(A14,资产清单!$A$6:$A$25,0)))<>1,"",INDEX(资产清单!$K$6:$K$25,MATCH(A14,资产清单!$A$6:$A$25,0)))) -> 900 | G14: =IF(L14="排除",0,IF(D14="市场比较",IF(COUNT(三案例测算!H30:H32)<>3,"",ROUND(AVERAGE(三案例测算!H30:H32),测算参数!$B$9)),IF(OR(D14="资料核定",D14="租赁资料核定"),IF(COUNTIFS(租赁资料核定!$A$6:$A$7,A14)<>1,"",IF(COUNT(INDEX(租赁资料核定!$M$6:$M$7,MATCH(A14,租赁资料核定!$A$6:$A$7,0)))<>1,"",INDEX(租赁资料核定!$M$6:$M$7,MATCH(A14,租赁资料核定!$A$6:$A$7,0)))),IF(D14="专项计租",IF(COUNTIFS(特殊计租!$A$6:$A$7,A14)<>1,"",IF(COUNT(INDEX(特殊计租!$D$6:$D$7,MATCH(A14,特殊计租!$A$6:$A$7,0)))<>1,"",INDEX(特殊计租!$D$6:$D$7,MATCH(A14,特殊计租!$A$6:$A$7,0)))),IF(D14="设备附表",IF(COUNTIFS(设备附表!$A$6:$A$7,A14)<>1,"",IF(COUNT(INDEX(设备附表!$F$6:$F$7,MATCH(A14,设备附表!$A$6:$A$7,0)))<>1,"",INDEX(设备附表!$F$6:$F$7,MATCH(A14,设备附表!$A$6:$A$7,0)))),""))))) -> 3.4 | H14: =IF(L14="排除",0,IF(D14="专项计租",IF(COUNTIFS(特殊计租!$A$6:$A$7,A14)<>1,"",IF(COUNT(INDEX(特殊计租!$J$6:$J$7,MATCH(A14,特殊计租!$A$6:$A$7,0)))<>1,"",INDEX(特殊计租!$J$6:$J$7,MATCH(A14,特殊计租!$A$6:$A$7,0)))),IF(D14="设备附表",IF(COUNTIFS(设备附表!$A$6:$A$7,A14)<>1,"",IF(COUNT(INDEX(设备附表!$G$6:$G$7,MATCH(A14,设备附表!$A$6:$A$7,0)))<>1,"",INDEX(设备附表!$G$6:$G$7,MATCH(A14,设备附表!$A$6:$A$7,0)))),IF(OR(D14="资料核定",D14="租赁资料核定"),IF(COUNTIFS(租赁资料核定!$A$6:$A$7,A14)<>1,"",IF(COUNT(INDEX(租赁资料核定!$N$6:$N$7,MATCH(A14,租赁资料核定!$A$6:$A$7,0)))<>1,"",INDEX(租赁资料核定!$N$6:$N$7,MATCH(A14,租赁资料核定!$A$6:$A$7,0)))),IF(OR(COUNT(F14:G14)<>2,F14<=0),"",ROUND(F14*G14*测算参数!$B$10,2)))))) -> 36720 | I14: =IF(COUNTIFS(计租与历史!$A$6:$A$25,A14)<>1,"",IF(COUNT(INDEX(计租与历史!$D$6:$D$25,MATCH(A14,计租与历史!$A$6:$A$25,0)))<>1,"",INDEX(计租与历史!$D$6:$D$25,MATCH(A14,计租与历史!$A$6:$A$25,0)))) -> 3 | J14: =IF(OR(COUNT(G14,I14)<>2,I14<=0,L14<>"纳入"),"",G14/I14-1) -> 0.13333333 | K14: =IF(L14="排除",IF(AND(D14="不重复计租",OR(IF(COUNTIFS(计租与历史!$A$6:$A$25,A14)<>1,"",IF(INDEX(计租与历史!$G$6:$G$25,MATCH(A14,计租与历史!$A$6:$A$25,0))="","",INDEX(计租与历史!$G$6:$G$25,MATCH(A14,计租与历史!$A$6:$A$25,0))))="",COUNTIFS(资产清单!$A$6:$A$25,IF(COUNTIFS(计租与历史!$A$6:$A$25,A14)<>1,"",IF(INDEX(计租与历史!$G$6:$G$25,MATCH(A14,计租与历史!$A$6:$A$25,0))="","",INDEX(计租与历史!$G$6:$G$25,MATCH(A14,计租与历史!$A$6:$A$25,0)))))<>1)),"待核主资产","范围排除"),IF(D14="市场比较",IF(COUNT(三案例测算!H30:H32)<>3,"待补资料或重判评分",IF(OR(COUNTIFS(三案例测算!J30:J32,"通过")<>3,MAX(三案例测算!H30:H32)/MIN(三案例测算!H30:H32)-1>测算参数!$B$8),"超限待复核","通过")),IF(COUNT(H14)<>1,"待补专项或核定资料","独立资料核定"))) -> 通过 | L14: =IF(COUNTIFS(计租与历史!$A$6:$A$25,A14)<>1,"",IF(INDEX(计租与历史!$B$6:$B$25,MATCH(A14,计租与历史!$A$6:$A$25,0))="","",INDEX(计租与历史!$B$6:$B$25,MATCH(A14,计租与历史!$A$6:$A$25,0)))) -> 纳入 | M14: =IF(COUNTIFS(计租与历史!$A$6:$A$25,A14)<>1,"",IF(INDEX(计租与历史!$H$6:$H$25,MATCH(A14,计租与历史!$A$6:$A$25,0))="","",INDEX(计租与历史!$H$6:$H$25,MATCH(A14,计租与历史!$A$6:$A$25,0)))) -> 按相应计租口径测算 | N14: 模拟数据未真实核验
A15: RP-010 | B15: =IF(COUNTIFS(资产清单!$A$6:$A$25,A15)<>1,"",IF(INDEX(资产清单!$D$6:$D$25,MATCH(A15,资产清单!$A$6:$A$25,0))="","",INDEX(资产清单!$D$6:$D$25,MATCH(A15,资产清单!$A$6:$A$25,0)))) -> 地面停车位组 | C15: =IF(COUNTIFS(资产清单!$A$6:$A$25,A15)<>1,"",IF(INDEX(资产清单!$H$6:$H$25,MATCH(A15,资产清单!$A$6:$A$25,0))="","",INDEX(资产清单!$H$6:$H$25,MATCH(A15,资产清单!$A$6:$A$25,0)))) -> 车位 | D15: =IF(COUNTIFS(计租与历史!$A$6:$A$25,A15)<>1,"",IF(INDEX(计租与历史!$C$6:$C$25,MATCH(A15,计租与历史!$A$6:$A$25,0))="","",INDEX(计租与历史!$C$6:$C$25,MATCH(A15,计租与历史!$A$6:$A$25,0)))) -> 市场比较 | E15: =IF(COUNTIFS(资产清单!$A$6:$A$25,A15)<>1,"",IF(INDEX(资产清单!$J$6:$J$25,MATCH(A15,资产清单!$A$6:$A$25,0))="","",INDEX(资产清单!$J$6:$J$25,MATCH(A15,资产清单!$A$6:$A$25,0)))) -> 元/个/月 | F15: =IF(COUNTIFS(资产清单!$A$6:$A$25,A15)<>1,"",IF(COUNT(INDEX(资产清单!$K$6:$K$25,MATCH(A15,资产清单!$A$6:$A$25,0)))<>1,"",INDEX(资产清单!$K$6:$K$25,MATCH(A15,资产清单!$A$6:$A$25,0)))) -> 10 | G15: =IF(L15="排除",0,IF(D15="市场比较",IF(COUNT(三案例测算!H33:H35)<>3,"",ROUND(AVERAGE(三案例测算!H33:H35),测算参数!$B$9)),IF(OR(D15="资料核定",D15="租赁资料核定"),IF(COUNTIFS(租赁资料核定!$A$6:$A$7,A15)<>1,"",IF(COUNT(INDEX(租赁资料核定!$M$6:$M$7,MATCH(A15,租赁资料核定!$A$6:$A$7,0)))<>1,"",INDEX(租赁资料核定!$M$6:$M$7,MATCH(A15,租赁资料核定!$A$6:$A$7,0)))),IF(D15="专项计租",IF(COUNTIFS(特殊计租!$A$6:$A$7,A15)<>1,"",IF(COUNT(INDEX(特殊计租!$D$6:$D$7,MATCH(A15,特殊计租!$A$6:$A$7,0)))<>1,"",INDEX(特殊计租!$D$6:$D$7,MATCH(A15,特殊计租!$A$6:$A$7,0)))),IF(D15="设备附表",IF(COUNTIFS(设备附表!$A$6:$A$7,A15)<>1,"",IF(COUNT(INDEX(设备附表!$F$6:$F$7,MATCH(A15,设备附表!$A$6:$A$7,0)))<>1,"",INDEX(设备附表!$F$6:$F$7,MATCH(A15,设备附表!$A$6:$A$7,0)))),""))))) -> 185 | H15: =IF(L15="排除",0,IF(D15="专项计租",IF(COUNTIFS(特殊计租!$A$6:$A$7,A15)<>1,"",IF(COUNT(INDEX(特殊计租!$J$6:$J$7,MATCH(A15,特殊计租!$A$6:$A$7,0)))<>1,"",INDEX(特殊计租!$J$6:$J$7,MATCH(A15,特殊计租!$A$6:$A$7,0)))),IF(D15="设备附表",IF(COUNTIFS(设备附表!$A$6:$A$7,A15)<>1,"",IF(COUNT(INDEX(设备附表!$G$6:$G$7,MATCH(A15,设备附表!$A$6:$A$7,0)))<>1,"",INDEX(设备附表!$G$6:$G$7,MATCH(A15,设备附表!$A$6:$A$7,0)))),IF(OR(D15="资料核定",D15="租赁资料核定"),IF(COUNTIFS(租赁资料核定!$A$6:$A$7,A15)<>1,"",IF(COUNT(INDEX(租赁资料核定!$N$6:$N$7,MATCH(A15,租赁资料核定!$A$6:$A$7,0)))<>1,"",INDEX(租赁资料核定!$N$6:$N$7,MATCH(A15,租赁资料核定!$A$6:$A$7,0)))),IF(OR(COUNT(F15:G15)<>2,F15<=0),"",ROUND(F15*G15*测算参数!$B$10,2)))))) -> 22200 | I15: =IF(COUNTIFS(计租与历史!$A$6:$A$25,A15)<>1,"",IF(COUNT(INDEX(计租与历史!$D$6:$D$25,MATCH(A15,计租与历史!$A$6:$A$25,0)))<>1,"",INDEX(计租与历史!$D$6:$D$25,MATCH(A15,计租与历史!$A$6:$A$25,0)))) -> 175 | J15: =IF(OR(COUNT(G15,I15)<>2,I15<=0,L15<>"纳入"),"",G15/I15-1) -> 0.057142857 | K15: =IF(L15="排除",IF(AND(D15="不重复计租",OR(IF(COUNTIFS(计租与历史!$A$6:$A$25,A15)<>1,"",IF(INDEX(计租与历史!$G$6:$G$25,MATCH(A15,计租与历史!$A$6:$A$25,0))="","",INDEX(计租与历史!$G$6:$G$25,MATCH(A15,计租与历史!$A$6:$A$25,0))))="",COUNTIFS(资产清单!$A$6:$A$25,IF(COUNTIFS(计租与历史!$A$6:$A$25,A15)<>1,"",IF(INDEX(计租与历史!$G$6:$G$25,MATCH(A15,计租与历史!$A$6:$A$25,0))="","",INDEX(计租与历史!$G$6:$G$25,MATCH(A15,计租与历史!$A$6:$A$25,0)))))<>1)),"待核主资产","范围排除"),IF(D15="市场比较",IF(COUNT(三案例测算!H33:H35)<>3,"待补资料或重判评分",IF(OR(COUNTIFS(三案例测算!J33:J35,"通过")<>3,MAX(三案例测算!H33:H35)/MIN(三案例测算!H33:H35)-1>测算参数!$B$8),"超限待复核","通过")),IF(COUNT(H15)<>1,"待补专项或核定资料","独立资料核定"))) -> 通过 | L15: =IF(COUNTIFS(计租与历史!$A$6:$A$25,A15)<>1,"",IF(INDEX(计租与历史!$B$6:$B$25,MATCH(A15,计租与历史!$A$6:$A$25,0))="","",INDEX(计租与历史!$B$6:$B$25,MATCH(A15,计租与历史!$A$6:$A$25,0)))) -> 纳入 | M15: =IF(COUNTIFS(计租与历史!$A$6:$A$25,A15)<>1,"",IF(INDEX(计租与历史!$H$6:$H$25,MATCH(A15,计租与历史!$A$6:$A$25,0))="","",INDEX(计租与历史!$H$6:$H$25,MATCH(A15,计租与历史!$A$6:$A$25,0)))) -> 按相应计租口径测算 | N15: 模拟数据未真实核验
A16: RP-011 | B16: =IF(COUNTIFS(资产清单!$A$6:$A$25,A16)<>1,"",IF(INDEX(资产清单!$D$6:$D$25,MATCH(A16,资产清单!$A$6:$A$25,0))="","",INDEX(资产清单!$D$6:$D$25,MATCH(A16,资产清单!$A$6:$A$25,0)))) -> 按间计租宿舍 | C16: =IF(COUNTIFS(资产清单!$A$6:$A$25,A16)<>1,"",IF(INDEX(资产清单!$H$6:$H$25,MATCH(A16,资产清单!$A$6:$A$25,0))="","",INDEX(资产清单!$H$6:$H$25,MATCH(A16,资产清单!$A$6:$A$25,0)))) -> 住宅 | D16: =IF(COUNTIFS(计租与历史!$A$6:$A$25,A16)<>1,"",IF(INDEX(计租与历史!$C$6:$C$25,MATCH(A16,计租与历史!$A$6:$A$25,0))="","",INDEX(计租与历史!$C$6:$C$25,MATCH(A16,计租与历史!$A$6:$A$25,0)))) -> 市场比较 | E16: =IF(COUNTIFS(资产清单!$A$6:$A$25,A16)<>1,"",IF(INDEX(资产清单!$J$6:$J$25,MATCH(A16,资产清单!$A$6:$A$25,0))="","",INDEX(资产清单!$J$6:$J$25,MATCH(A16,资产清单!$A$6:$A$25,0)))) -> 元/间/月 | F16: =IF(COUNTIFS(资产清单!$A$6:$A$25,A16)<>1,"",IF(COUNT(INDEX(资产清单!$K$6:$K$25,MATCH(A16,资产清单!$A$6:$A$25,0)))<>1,"",INDEX(资产清单!$K$6:$K$25,MATCH(A16,资产清单!$A$6:$A$25,0)))) -> 1 | G16: =IF(L16="排除",0,IF(D16="市场比较",IF(COUNT(三案例测算!H36:H38)<>3,"",ROUND(AVERAGE(三案例测算!H36:H38),测算参数!$B$9)),IF(OR(D16="资料核定",D16="租赁资料核定"),IF(COUNTIFS(租赁资料核定!$A$6:$A$7,A16)<>1,"",IF(COUNT(INDEX(租赁资料核定!$M$6:$M$7,MATCH(A16,租赁资料核定!$A$6:$A$7,0)))<>1,"",INDEX(租赁资料核定!$M$6:$M$7,MATCH(A16,租赁资料核定!$A$6:$A$7,0)))),IF(D16="专项计租",IF(COUNTIFS(特殊计租!$A$6:$A$7,A16)<>1,"",IF(COUNT(INDEX(特殊计租!$D$6:$D$7,MATCH(A16,特殊计租!$A$6:$A$7,0)))<>1,"",INDEX(特殊计租!$D$6:$D$7,MATCH(A16,特殊计租!$A$6:$A$7,0)))),IF(D16="设备附表",IF(COUNTIFS(设备附表!$A$6:$A$7,A16)<>1,"",IF(COUNT(INDEX(设备附表!$F$6:$F$7,MATCH(A16,设备附表!$A$6:$A$7,0)))<>1,"",INDEX(设备附表!$F$6:$F$7,MATCH(A16,设备附表!$A$6:$A$7,0)))),""))))) -> 664.4 | H16: =IF(L16="排除",0,IF(D16="专项计租",IF(COUNTIFS(特殊计租!$A$6:$A$7,A16)<>1,"",IF(COUNT(INDEX(特殊计租!$J$6:$J$7,MATCH(A16,特殊计租!$A$6:$A$7,0)))<>1,"",INDEX(特殊计租!$J$6:$J$7,MATCH(A16,特殊计租!$A$6:$A$7,0)))),IF(D16="设备附表",IF(COUNTIFS(设备附表!$A$6:$A$7,A16)<>1,"",IF(COUNT(INDEX(设备附表!$G$6:$G$7,MATCH(A16,设备附表!$A$6:$A$7,0)))<>1,"",INDEX(设备附表!$G$6:$G$7,MATCH(A16,设备附表!$A$6:$A$7,0)))),IF(OR(D16="资料核定",D16="租赁资料核定"),IF(COUNTIFS(租赁资料核定!$A$6:$A$7,A16)<>1,"",IF(COUNT(INDEX(租赁资料核定!$N$6:$N$7,MATCH(A16,租赁资料核定!$A$6:$A$7,0)))<>1,"",INDEX(租赁资料核定!$N$6:$N$7,MATCH(A16,租赁资料核定!$A$6:$A$7,0)))),IF(OR(COUNT(F16:G16)<>2,F16<=0),"",ROUND(F16*G16*测算参数!$B$10,2)))))) -> 7972.8 | I16: =IF(COUNTIFS(计租与历史!$A$6:$A$25,A16)<>1,"",IF(COUNT(INDEX(计租与历史!$D$6:$D$25,MATCH(A16,计租与历史!$A$6:$A$25,0)))<>1,"",INDEX(计租与历史!$D$6:$D$25,MATCH(A16,计租与历史!$A$6:$A$25,0)))) -> 620 | J16: =IF(OR(COUNT(G16,I16)<>2,I16<=0,L16<>"纳入"),"",G16/I16-1) -> 0.071612903 | K16: =IF(L16="排除",IF(AND(D16="不重复计租",OR(IF(COUNTIFS(计租与历史!$A$6:$A$25,A16)<>1,"",IF(INDEX(计租与历史!$G$6:$G$25,MATCH(A16,计租与历史!$A$6:$A$25,0))="","",INDEX(计租与历史!$G$6:$G$25,MATCH(A16,计租与历史!$A$6:$A$25,0))))="",COUNTIFS(资产清单!$A$6:$A$25,IF(COUNTIFS(计租与历史!$A$6:$A$25,A16)<>1,"",IF(INDEX(计租与历史!$G$6:$G$25,MATCH(A16,计租与历史!$A$6:$A$25,0))="","",INDEX(计租与历史!$G$6:$G$25,MATCH(A16,计租与历史!$A$6:$A$25,0)))))<>1)),"待核主资产","范围排除"),IF(D16="市场比较",IF(COUNT(三案例测算!H36:H38)<>3,"待补资料或重判评分",IF(OR(COUNTIFS(三案例测算!J36:J38,"通过")<>3,MAX(三案例测算!H36:H38)/MIN(三案例测算!H36:H38)-1>测算参数!$B$8),"超限待复核","通过")),IF(COUNT(H16)<>1,"待补专项或核定资料","独立资料核定"))) -> 通过 | L16: =IF(COUNTIFS(计租与历史!$A$6:$A$25,A16)<>1,"",IF(INDEX(计租与历史!$B$6:$B$25,MATCH(A16,计租与历史!$A$6:$A$25,0))="","",INDEX(计租与历史!$B$6:$B$25,MATCH(A16,计租与历史!$A$6:$A$25,0)))) -> 纳入 | M16: =IF(COUNTIFS(计租与历史!$A$6:$A$25,A16)<>1,"",IF(INDEX(计租与历史!$H$6:$H$25,MATCH(A16,计租与历史!$A$6:$A$25,0))="","",INDEX(计租与历史!$H$6:$H$25,MATCH(A16,计租与历史!$A$6:$A$25,0)))) -> 按相应计租口径测算 | N16: 模拟数据未真实核验
A17: RP-012 | B17: =IF(COUNTIFS(资产清单!$A$6:$A$25,A17)<>1,"",IF(INDEX(资产清单!$D$6:$D$25,MATCH(A17,资产清单!$A$6:$A$25,0))="","",INDEX(资产清单!$D$6:$D$25,MATCH(A17,资产清单!$A$6:$A$25,0)))) -> 通信基站点位 | C17: =IF(COUNTIFS(资产清单!$A$6:$A$25,A17)<>1,"",IF(INDEX(资产清单!$H$6:$H$25,MATCH(A17,资产清单!$A$6:$A$25,0))="","",INDEX(资产清单!$H$6:$H$25,MATCH(A17,资产清单!$A$6:$A$25,0)))) -> 通信基站 | D17: =IF(COUNTIFS(计租与历史!$A$6:$A$25,A17)<>1,"",IF(INDEX(计租与历史!$C$6:$C$25,MATCH(A17,计租与历史!$A$6:$A$25,0))="","",INDEX(计租与历史!$C$6:$C$25,MATCH(A17,计租与历史!$A$6:$A$25,0)))) -> 市场比较 | E17: =IF(COUNTIFS(资产清单!$A$6:$A$25,A17)<>1,"",IF(INDEX(资产清单!$J$6:$J$25,MATCH(A17,资产清单!$A$6:$A$25,0))="","",INDEX(资产清单!$J$6:$J$25,MATCH(A17,资产清单!$A$6:$A$25,0)))) -> 元/处/月 | F17: =IF(COUNTIFS(资产清单!$A$6:$A$25,A17)<>1,"",IF(COUNT(INDEX(资产清单!$K$6:$K$25,MATCH(A17,资产清单!$A$6:$A$25,0)))<>1,"",INDEX(资产清单!$K$6:$K$25,MATCH(A17,资产清单!$A$6:$A$25,0)))) -> 1 | G17: =IF(L17="排除",0,IF(D17="市场比较",IF(COUNT(三案例测算!H39:H41)<>3,"",ROUND(AVERAGE(三案例测算!H39:H41),测算参数!$B$9)),IF(OR(D17="资料核定",D17="租赁资料核定"),IF(COUNTIFS(租赁资料核定!$A$6:$A$7,A17)<>1,"",IF(COUNT(INDEX(租赁资料核定!$M$6:$M$7,MATCH(A17,租赁资料核定!$A$6:$A$7,0)))<>1,"",INDEX(租赁资料核定!$M$6:$M$7,MATCH(A17,租赁资料核定!$A$6:$A$7,0)))),IF(D17="专项计租",IF(COUNTIFS(特殊计租!$A$6:$A$7,A17)<>1,"",IF(COUNT(INDEX(特殊计租!$D$6:$D$7,MATCH(A17,特殊计租!$A$6:$A$7,0)))<>1,"",INDEX(特殊计租!$D$6:$D$7,MATCH(A17,特殊计租!$A$6:$A$7,0)))),IF(D17="设备附表",IF(COUNTIFS(设备附表!$A$6:$A$7,A17)<>1,"",IF(COUNT(INDEX(设备附表!$F$6:$F$7,MATCH(A17,设备附表!$A$6:$A$7,0)))<>1,"",INDEX(设备附表!$F$6:$F$7,MATCH(A17,设备附表!$A$6:$A$7,0)))),""))))) -> 719 | H17: =IF(L17="排除",0,IF(D17="专项计租",IF(COUNTIFS(特殊计租!$A$6:$A$7,A17)<>1,"",IF(COUNT(INDEX(特殊计租!$J$6:$J$7,MATCH(A17,特殊计租!$A$6:$A$7,0)))<>1,"",INDEX(特殊计租!$J$6:$J$7,MATCH(A17,特殊计租!$A$6:$A$7,0)))),IF(D17="设备附表",IF(COUNTIFS(设备附表!$A$6:$A$7,A17)<>1,"",IF(COUNT(INDEX(设备附表!$G$6:$G$7,MATCH(A17,设备附表!$A$6:$A$7,0)))<>1,"",INDEX(设备附表!$G$6:$G$7,MATCH(A17,设备附表!$A$6:$A$7,0)))),IF(OR(D17="资料核定",D17="租赁资料核定"),IF(COUNTIFS(租赁资料核定!$A$6:$A$7,A17)<>1,"",IF(COUNT(INDEX(租赁资料核定!$N$6:$N$7,MATCH(A17,租赁资料核定!$A$6:$A$7,0)))<>1,"",INDEX(租赁资料核定!$N$6:$N$7,MATCH(A17,租赁资料核定!$A$6:$A$7,0)))),IF(OR(COUNT(F17:G17)<>2,F17<=0),"",ROUND(F17*G17*测算参数!$B$10,2)))))) -> 8628 | I17: =IF(COUNTIFS(计租与历史!$A$6:$A$25,A17)<>1,"",IF(COUNT(INDEX(计租与历史!$D$6:$D$25,MATCH(A17,计租与历史!$A$6:$A$25,0)))<>1,"",INDEX(计租与历史!$D$6:$D$25,MATCH(A17,计租与历史!$A$6:$A$25,0)))) -> 680 | J17: =IF(OR(COUNT(G17,I17)<>2,I17<=0,L17<>"纳入"),"",G17/I17-1) -> 0.057352941 | K17: =IF(L17="排除",IF(AND(D17="不重复计租",OR(IF(COUNTIFS(计租与历史!$A$6:$A$25,A17)<>1,"",IF(INDEX(计租与历史!$G$6:$G$25,MATCH(A17,计租与历史!$A$6:$A$25,0))="","",INDEX(计租与历史!$G$6:$G$25,MATCH(A17,计租与历史!$A$6:$A$25,0))))="",COUNTIFS(资产清单!$A$6:$A$25,IF(COUNTIFS(计租与历史!$A$6:$A$25,A17)<>1,"",IF(INDEX(计租与历史!$G$6:$G$25,MATCH(A17,计租与历史!$A$6:$A$25,0))="","",INDEX(计租与历史!$G$6:$G$25,MATCH(A17,计租与历史!$A$6:$A$25,0)))))<>1)),"待核主资产","范围排除"),IF(D17="市场比较",IF(COUNT(三案例测算!H39:H41)<>3,"待补资料或重判评分",IF(OR(COUNTIFS(三案例测算!J39:J41,"通过")<>3,MAX(三案例测算!H39:H41)/MIN(三案例测算!H39:H41)-1>测算参数!$B$8),"超限待复核","通过")),IF(COUNT(H17)<>1,"待补专项或核定资料","独立资料核定"))) -> 通过 | L17: =IF(COUNTIFS(计租与历史!$A$6:$A$25,A17)<>1,"",IF(INDEX(计租与历史!$B$6:$B$25,MATCH(A17,计租与历史!$A$6:$A$25,0))="","",INDEX(计租与历史!$B$6:$B$25,MATCH(A17,计租与历史!$A$6:$A$25,0)))) -> 纳入 | M17: =IF(COUNTIFS(计租与历史!$A$6:$A$25,A17)<>1,"",IF(INDEX(计租与历史!$H$6:$H$25,MATCH(A17,计租与历史!$A$6:$A$25,0))="","",INDEX(计租与历史!$H$6:$H$25,MATCH(A17,计租与历史!$A$6:$A$25,0)))) -> 按相应计租口径测算 | N17: 模拟数据未真实核验
A18: RP-013 | B18: =IF(COUNTIFS(资产清单!$A$6:$A$25,A18)<>1,"",IF(INDEX(资产清单!$D$6:$D$25,MATCH(A18,资产清单!$A$6:$A$25,0))="","",INDEX(资产清单!$D$6:$D$25,MATCH(A18,资产清单!$A$6:$A$25,0)))) -> 小型附属库房 | C18: =IF(COUNTIFS(资产清单!$A$6:$A$25,A18)<>1,"",IF(INDEX(资产清单!$H$6:$H$25,MATCH(A18,资产清单!$A$6:$A$25,0))="","",INDEX(资产清单!$H$6:$H$25,MATCH(A18,资产清单!$A$6:$A$25,0)))) -> 仓储 | D18: =IF(COUNTIFS(计租与历史!$A$6:$A$25,A18)<>1,"",IF(INDEX(计租与历史!$C$6:$C$25,MATCH(A18,计租与历史!$A$6:$A$25,0))="","",INDEX(计租与历史!$C$6:$C$25,MATCH(A18,计租与历史!$A$6:$A$25,0)))) -> 资料核定 | E18: =IF(COUNTIFS(资产清单!$A$6:$A$25,A18)<>1,"",IF(INDEX(资产清单!$J$6:$J$25,MATCH(A18,资产清单!$A$6:$A$25,0))="","",INDEX(资产清单!$J$6:$J$25,MATCH(A18,资产清单!$A$6:$A$25,0)))) -> 元/㎡/月 | F18: =IF(COUNTIFS(资产清单!$A$6:$A$25,A18)<>1,"",IF(COUNT(INDEX(资产清单!$K$6:$K$25,MATCH(A18,资产清单!$A$6:$A$25,0)))<>1,"",INDEX(资产清单!$K$6:$K$25,MATCH(A18,资产清单!$A$6:$A$25,0)))) -> 25 | G18: =IF(L18="排除",0,IF(D18="市场比较","",IF(OR(D18="资料核定",D18="租赁资料核定"),IF(COUNTIFS(租赁资料核定!$A$6:$A$7,A18)<>1,"",IF(COUNT(INDEX(租赁资料核定!$M$6:$M$7,MATCH(A18,租赁资料核定!$A$6:$A$7,0)))<>1,"",INDEX(租赁资料核定!$M$6:$M$7,MATCH(A18,租赁资料核定!$A$6:$A$7,0)))),IF(D18="专项计租",IF(COUNTIFS(特殊计租!$A$6:$A$7,A18)<>1,"",IF(COUNT(INDEX(特殊计租!$D$6:$D$7,MATCH(A18,特殊计租!$A$6:$A$7,0)))<>1,"",INDEX(特殊计租!$D$6:$D$7,MATCH(A18,特殊计租!$A$6:$A$7,0)))),IF(D18="设备附表",IF(COUNTIFS(设备附表!$A$6:$A$7,A18)<>1,"",IF(COUNT(INDEX(设备附表!$F$6:$F$7,MATCH(A18,设备附表!$A$6:$A$7,0)))<>1,"",INDEX(设备附表!$F$6:$F$7,MATCH(A18,设备附表!$A$6:$A$7,0)))),""))))) -> 4.8 | H18: =IF(L18="排除",0,IF(D18="专项计租",IF(COUNTIFS(特殊计租!$A$6:$A$7,A18)<>1,"",IF(COUNT(INDEX(特殊计租!$J$6:$J$7,MATCH(A18,特殊计租!$A$6:$A$7,0)))<>1,"",INDEX(特殊计租!$J$6:$J$7,MATCH(A18,特殊计租!$A$6:$A$7,0)))),IF(D18="设备附表",IF(COUNTIFS(设备附表!$A$6:$A$7,A18)<>1,"",IF(COUNT(INDEX(设备附表!$G$6:$G$7,MATCH(A18,设备附表!$A$6:$A$7,0)))<>1,"",INDEX(设备附表!$G$6:$G$7,MATCH(A18,设备附表!$A$6:$A$7,0)))),IF(OR(D18="资料核定",D18="租赁资料核定"),IF(COUNTIFS(租赁资料核定!$A$6:$A$7,A18)<>1,"",IF(COUNT(INDEX(租赁资料核定!$N$6:$N$7,MATCH(A18,租赁资料核定!$A$6:$A$7,0)))<>1,"",INDEX(租赁资料核定!$N$6:$N$7,MATCH(A18,租赁资料核定!$A$6:$A$7,0)))),IF(OR(COUNT(F18:G18)<>2,F18<=0),"",ROUND(F18*G18*测算参数!$B$10,2)))))) -> 1440 | I18: =IF(COUNTIFS(计租与历史!$A$6:$A$25,A18)<>1,"",IF(COUNT(INDEX(计租与历史!$D$6:$D$25,MATCH(A18,计租与历史!$A$6:$A$25,0)))<>1,"",INDEX(计租与历史!$D$6:$D$25,MATCH(A18,计租与历史!$A$6:$A$25,0)))) -> 4 | J18: =IF(OR(COUNT(G18,I18)<>2,I18<=0,L18<>"纳入"),"",G18/I18-1) -> 0.2 | K18: =IF(L18="排除",IF(AND(D18="不重复计租",OR(IF(COUNTIFS(计租与历史!$A$6:$A$25,A18)<>1,"",IF(INDEX(计租与历史!$G$6:$G$25,MATCH(A18,计租与历史!$A$6:$A$25,0))="","",INDEX(计租与历史!$G$6:$G$25,MATCH(A18,计租与历史!$A$6:$A$25,0))))="",COUNTIFS(资产清单!$A$6:$A$25,IF(COUNTIFS(计租与历史!$A$6:$A$25,A18)<>1,"",IF(INDEX(计租与历史!$G$6:$G$25,MATCH(A18,计租与历史!$A$6:$A$25,0))="","",INDEX(计租与历史!$G$6:$G$25,MATCH(A18,计租与历史!$A$6:$A$25,0)))))<>1)),"待核主资产","范围排除"),IF(D18="市场比较","不适用",IF(COUNT(H18)<>1,"待补专项或核定资料","独立资料核定"))) -> 独立资料核定 | L18: =IF(COUNTIFS(计租与历史!$A$6:$A$25,A18)<>1,"",IF(INDEX(计租与历史!$B$6:$B$25,MATCH(A18,计租与历史!$A$6:$A$25,0))="","",INDEX(计租与历史!$B$6:$B$25,MATCH(A18,计租与历史!$A$6:$A$25,0)))) -> 纳入 | M18: =IF(COUNTIFS(计租与历史!$A$6:$A$25,A18)<>1,"",IF(INDEX(计租与历史!$H$6:$H$25,MATCH(A18,计租与历史!$A$6:$A$25,0))="","",INDEX(计租与历史!$H$6:$H$25,MATCH(A18,计租与历史!$A$6:$A$25,0)))) -> 扩大案例搜集后结合已核定资料 | N18: 模拟数据未真实核验
A19: RP-014 | B19: =IF(COUNTIFS(资产清单!$A$6:$A$25,A19)<>1,"",IF(INDEX(资产清单!$D$6:$D$25,MATCH(A19,资产清单!$A$6:$A$25,0))="","",INDEX(资产清单!$D$6:$D$25,MATCH(A19,资产清单!$A$6:$A$25,0)))) -> 屋顶使用点位 | C19: =IF(COUNTIFS(资产清单!$A$6:$A$25,A19)<>1,"",IF(INDEX(资产清单!$H$6:$H$25,MATCH(A19,资产清单!$A$6:$A$25,0))="","",INDEX(资产清单!$H$6:$H$25,MATCH(A19,资产清单!$A$6:$A$25,0)))) -> 场地 | D19: =IF(COUNTIFS(计租与历史!$A$6:$A$25,A19)<>1,"",IF(INDEX(计租与历史!$C$6:$C$25,MATCH(A19,计租与历史!$A$6:$A$25,0))="","",INDEX(计租与历史!$C$6:$C$25,MATCH(A19,计租与历史!$A$6:$A$25,0)))) -> 租赁资料核定 | E19: =IF(COUNTIFS(资产清单!$A$6:$A$25,A19)<>1,"",IF(INDEX(资产清单!$J$6:$J$25,MATCH(A19,资产清单!$A$6:$A$25,0))="","",INDEX(资产清单!$J$6:$J$25,MATCH(A19,资产清单!$A$6:$A$25,0)))) -> 元/处/月 | F19: =IF(COUNTIFS(资产清单!$A$6:$A$25,A19)<>1,"",IF(COUNT(INDEX(资产清单!$K$6:$K$25,MATCH(A19,资产清单!$A$6:$A$25,0)))<>1,"",INDEX(资产清单!$K$6:$K$25,MATCH(A19,资产清单!$A$6:$A$25,0)))) -> 1 | G19: =IF(L19="排除",0,IF(D19="市场比较","",IF(OR(D19="资料核定",D19="租赁资料核定"),IF(COUNTIFS(租赁资料核定!$A$6:$A$7,A19)<>1,"",IF(COUNT(INDEX(租赁资料核定!$M$6:$M$7,MATCH(A19,租赁资料核定!$A$6:$A$7,0)))<>1,"",INDEX(租赁资料核定!$M$6:$M$7,MATCH(A19,租赁资料核定!$A$6:$A$7,0)))),IF(D19="专项计租",IF(COUNTIFS(特殊计租!$A$6:$A$7,A19)<>1,"",IF(COUNT(INDEX(特殊计租!$D$6:$D$7,MATCH(A19,特殊计租!$A$6:$A$7,0)))<>1,"",INDEX(特殊计租!$D$6:$D$7,MATCH(A19,特殊计租!$A$6:$A$7,0)))),IF(D19="设备附表",IF(COUNTIFS(设备附表!$A$6:$A$7,A19)<>1,"",IF(COUNT(INDEX(设备附表!$F$6:$F$7,MATCH(A19,设备附表!$A$6:$A$7,0)))<>1,"",INDEX(设备附表!$F$6:$F$7,MATCH(A19,设备附表!$A$6:$A$7,0)))),""))))) -> 700 | H19: =IF(L19="排除",0,IF(D19="专项计租",IF(COUNTIFS(特殊计租!$A$6:$A$7,A19)<>1,"",IF(COUNT(INDEX(特殊计租!$J$6:$J$7,MATCH(A19,特殊计租!$A$6:$A$7,0)))<>1,"",INDEX(特殊计租!$J$6:$J$7,MATCH(A19,特殊计租!$A$6:$A$7,0)))),IF(D19="设备附表",IF(COUNTIFS(设备附表!$A$6:$A$7,A19)<>1,"",IF(COUNT(INDEX(设备附表!$G$6:$G$7,MATCH(A19,设备附表!$A$6:$A$7,0)))<>1,"",INDEX(设备附表!$G$6:$G$7,MATCH(A19,设备附表!$A$6:$A$7,0)))),IF(OR(D19="资料核定",D19="租赁资料核定"),IF(COUNTIFS(租赁资料核定!$A$6:$A$7,A19)<>1,"",IF(COUNT(INDEX(租赁资料核定!$N$6:$N$7,MATCH(A19,租赁资料核定!$A$6:$A$7,0)))<>1,"",INDEX(租赁资料核定!$N$6:$N$7,MATCH(A19,租赁资料核定!$A$6:$A$7,0)))),IF(OR(COUNT(F19:G19)<>2,F19<=0),"",ROUND(F19*G19*测算参数!$B$10,2)))))) -> 8400 | I19: =IF(COUNTIFS(计租与历史!$A$6:$A$25,A19)<>1,"",IF(COUNT(INDEX(计租与历史!$D$6:$D$25,MATCH(A19,计租与历史!$A$6:$A$25,0)))<>1,"",INDEX(计租与历史!$D$6:$D$25,MATCH(A19,计租与历史!$A$6:$A$25,0)))) -> 650 | J19: =IF(OR(COUNT(G19,I19)<>2,I19<=0,L19<>"纳入"),"",G19/I19-1) -> 0.076923077 | K19: =IF(L19="排除",IF(AND(D19="不重复计租",OR(IF(COUNTIFS(计租与历史!$A$6:$A$25,A19)<>1,"",IF(INDEX(计租与历史!$G$6:$G$25,MATCH(A19,计租与历史!$A$6:$A$25,0))="","",INDEX(计租与历史!$G$6:$G$25,MATCH(A19,计租与历史!$A$6:$A$25,0))))="",COUNTIFS(资产清单!$A$6:$A$25,IF(COUNTIFS(计租与历史!$A$6:$A$25,A19)<>1,"",IF(INDEX(计租与历史!$G$6:$G$25,MATCH(A19,计租与历史!$A$6:$A$25,0))="","",INDEX(计租与历史!$G$6:$G$25,MATCH(A19,计租与历史!$A$6:$A$25,0)))))<>1)),"待核主资产","范围排除"),IF(D19="市场比较","不适用",IF(COUNT(H19)<>1,"待补专项或核定资料","独立资料核定"))) -> 独立资料核定 | L19: =IF(COUNTIFS(计租与历史!$A$6:$A$25,A19)<>1,"",IF(INDEX(计租与历史!$B$6:$B$25,MATCH(A19,计租与历史!$A$6:$A$25,0))="","",INDEX(计租与历史!$B$6:$B$25,MATCH(A19,计租与历史!$A$6:$A$25,0)))) -> 纳入 | M19: =IF(COUNTIFS(计租与历史!$A$6:$A$25,A19)<>1,"",IF(INDEX(计租与历史!$H$6:$H$25,MATCH(A19,计租与历史!$A$6:$A$25,0))="","",INDEX(计租与历史!$H$6:$H$25,MATCH(A19,计租与历史!$A$6:$A$25,0)))) -> 按模拟合同口径核定 | N19: 模拟数据未真实核验
A20: RP-015 | B20: =IF(COUNTIFS(资产清单!$A$6:$A$25,A20)<>1,"",IF(INDEX(资产清单!$D$6:$D$25,MATCH(A20,资产清单!$A$6:$A$25,0))="","",INDEX(资产清单!$D$6:$D$25,MATCH(A20,资产清单!$A$6:$A$25,0)))) -> 活动场馆 | C20: =IF(COUNTIFS(资产清单!$A$6:$A$25,A20)<>1,"",IF(INDEX(资产清单!$H$6:$H$25,MATCH(A20,资产清单!$A$6:$A$25,0))="","",INDEX(资产清单!$H$6:$H$25,MATCH(A20,资产清单!$A$6:$A$25,0)))) -> 场馆 | D20: =IF(COUNTIFS(计租与历史!$A$6:$A$25,A20)<>1,"",IF(INDEX(计租与历史!$C$6:$C$25,MATCH(A20,计租与历史!$A$6:$A$25,0))="","",INDEX(计租与历史!$C$6:$C$25,MATCH(A20,计租与历史!$A$6:$A$25,0)))) -> 专项计租 | E20: =IF(COUNTIFS(资产清单!$A$6:$A$25,A20)<>1,"",IF(INDEX(资产清单!$J$6:$J$25,MATCH(A20,资产清单!$A$6:$A$25,0))="","",INDEX(资产清单!$J$6:$J$25,MATCH(A20,资产清单!$A$6:$A$25,0)))) -> 元/场·天 | F20: =IF(COUNTIFS(资产清单!$A$6:$A$25,A20)<>1,"",IF(COUNT(INDEX(资产清单!$K$6:$K$25,MATCH(A20,资产清单!$A$6:$A$25,0)))<>1,"",INDEX(资产清单!$K$6:$K$25,MATCH(A20,资产清单!$A$6:$A$25,0)))) -> 1 | G20: =IF(L20="排除",0,IF(D20="市场比较","",IF(OR(D20="资料核定",D20="租赁资料核定"),IF(COUNTIFS(租赁资料核定!$A$6:$A$7,A20)<>1,"",IF(COUNT(INDEX(租赁资料核定!$M$6:$M$7,MATCH(A20,租赁资料核定!$A$6:$A$7,0)))<>1,"",INDEX(租赁资料核定!$M$6:$M$7,MATCH(A20,租赁资料核定!$A$6:$A$7,0)))),IF(D20="专项计租",IF(COUNTIFS(特殊计租!$A$6:$A$7,A20)<>1,"",IF(COUNT(INDEX(特殊计租!$D$6:$D$7,MATCH(A20,特殊计租!$A$6:$A$7,0)))<>1,"",INDEX(特殊计租!$D$6:$D$7,MATCH(A20,特殊计租!$A$6:$A$7,0)))),IF(D20="设备附表",IF(COUNTIFS(设备附表!$A$6:$A$7,A20)<>1,"",IF(COUNT(INDEX(设备附表!$F$6:$F$7,MATCH(A20,设备附表!$A$6:$A$7,0)))<>1,"",INDEX(设备附表!$F$6:$F$7,MATCH(A20,设备附表!$A$6:$A$7,0)))),""))))) -> 1950 | H20: =IF(L20="排除",0,IF(D20="专项计租",IF(COUNTIFS(特殊计租!$A$6:$A$7,A20)<>1,"",IF(COUNT(INDEX(特殊计租!$J$6:$J$7,MATCH(A20,特殊计租!$A$6:$A$7,0)))<>1,"",INDEX(特殊计租!$J$6:$J$7,MATCH(A20,特殊计租!$A$6:$A$7,0)))),IF(D20="设备附表",IF(COUNTIFS(设备附表!$A$6:$A$7,A20)<>1,"",IF(COUNT(INDEX(设备附表!$G$6:$G$7,MATCH(A20,设备附表!$A$6:$A$7,0)))<>1,"",INDEX(设备附表!$G$6:$G$7,MATCH(A20,设备附表!$A$6:$A$7,0)))),IF(OR(D20="资料核定",D20="租赁资料核定"),IF(COUNTIFS(租赁资料核定!$A$6:$A$7,A20)<>1,"",IF(COUNT(INDEX(租赁资料核定!$N$6:$N$7,MATCH(A20,租赁资料核定!$A$6:$A$7,0)))<>1,"",INDEX(租赁资料核定!$N$6:$N$7,MATCH(A20,租赁资料核定!$A$6:$A$7,0)))),IF(OR(COUNT(F20:G20)<>2,F20<=0),"",ROUND(F20*G20*测算参数!$B$10,2)))))) -> 70200 | I20: =IF(COUNTIFS(计租与历史!$A$6:$A$25,A20)<>1,"",IF(COUNT(INDEX(计租与历史!$D$6:$D$25,MATCH(A20,计租与历史!$A$6:$A$25,0)))<>1,"",INDEX(计租与历史!$D$6:$D$25,MATCH(A20,计租与历史!$A$6:$A$25,0)))) -> 1800 | J20: =IF(OR(COUNT(G20,I20)<>2,I20<=0,L20<>"纳入"),"",G20/I20-1) -> 0.083333333 | K20: =IF(L20="排除",IF(AND(D20="不重复计租",OR(IF(COUNTIFS(计租与历史!$A$6:$A$25,A20)<>1,"",IF(INDEX(计租与历史!$G$6:$G$25,MATCH(A20,计租与历史!$A$6:$A$25,0))="","",INDEX(计租与历史!$G$6:$G$25,MATCH(A20,计租与历史!$A$6:$A$25,0))))="",COUNTIFS(资产清单!$A$6:$A$25,IF(COUNTIFS(计租与历史!$A$6:$A$25,A20)<>1,"",IF(INDEX(计租与历史!$G$6:$G$25,MATCH(A20,计租与历史!$A$6:$A$25,0))="","",INDEX(计租与历史!$G$6:$G$25,MATCH(A20,计租与历史!$A$6:$A$25,0)))))<>1)),"待核主资产","范围排除"),IF(D20="市场比较","不适用",IF(COUNT(H20)<>1,"待补专项或核定资料","独立资料核定"))) -> 独立资料核定 | L20: =IF(COUNTIFS(计租与历史!$A$6:$A$25,A20)<>1,"",IF(INDEX(计租与历史!$B$6:$B$25,MATCH(A20,计租与历史!$A$6:$A$25,0))="","",INDEX(计租与历史!$B$6:$B$25,MATCH(A20,计租与历史!$A$6:$A$25,0)))) -> 纳入 | M20: =IF(COUNTIFS(计租与历史!$A$6:$A$25,A20)<>1,"",IF(INDEX(计租与历史!$H$6:$H$25,MATCH(A20,计租与历史!$A$6:$A$25,0))="","",INDEX(计租与历史!$H$6:$H$25,MATCH(A20,计租与历史!$A$6:$A$25,0)))) -> 按相应计租口径测算 | N20: 模拟数据未真实核验
A21: RP-016 | B21: =IF(COUNTIFS(资产清单!$A$6:$A$25,A21)<>1,"",IF(INDEX(资产清单!$D$6:$D$25,MATCH(A21,资产清单!$A$6:$A$25,0))="","",INDEX(资产清单!$D$6:$D$25,MATCH(A21,资产清单!$A$6:$A$25,0)))) -> 广告设置点位 | C21: =IF(COUNTIFS(资产清单!$A$6:$A$25,A21)<>1,"",IF(INDEX(资产清单!$H$6:$H$25,MATCH(A21,资产清单!$A$6:$A$25,0))="","",INDEX(资产清单!$H$6:$H$25,MATCH(A21,资产清单!$A$6:$A$25,0)))) -> 广告位 | D21: =IF(COUNTIFS(计租与历史!$A$6:$A$25,A21)<>1,"",IF(INDEX(计租与历史!$C$6:$C$25,MATCH(A21,计租与历史!$A$6:$A$25,0))="","",INDEX(计租与历史!$C$6:$C$25,MATCH(A21,计租与历史!$A$6:$A$25,0)))) -> 专项计租 | E21: =IF(COUNTIFS(资产清单!$A$6:$A$25,A21)<>1,"",IF(INDEX(资产清单!$J$6:$J$25,MATCH(A21,资产清单!$A$6:$A$25,0))="","",INDEX(资产清单!$J$6:$J$25,MATCH(A21,资产清单!$A$6:$A$25,0)))) -> 元/处/月 | F21: =IF(COUNTIFS(资产清单!$A$6:$A$25,A21)<>1,"",IF(COUNT(INDEX(资产清单!$K$6:$K$25,MATCH(A21,资产清单!$A$6:$A$25,0)))<>1,"",INDEX(资产清单!$K$6:$K$25,MATCH(A21,资产清单!$A$6:$A$25,0)))) -> 1 | G21: =IF(L21="排除",0,IF(D21="市场比较","",IF(OR(D21="资料核定",D21="租赁资料核定"),IF(COUNTIFS(租赁资料核定!$A$6:$A$7,A21)<>1,"",IF(COUNT(INDEX(租赁资料核定!$M$6:$M$7,MATCH(A21,租赁资料核定!$A$6:$A$7,0)))<>1,"",INDEX(租赁资料核定!$M$6:$M$7,MATCH(A21,租赁资料核定!$A$6:$A$7,0)))),IF(D21="专项计租",IF(COUNTIFS(特殊计租!$A$6:$A$7,A21)<>1,"",IF(COUNT(INDEX(特殊计租!$D$6:$D$7,MATCH(A21,特殊计租!$A$6:$A$7,0)))<>1,"",INDEX(特殊计租!$D$6:$D$7,MATCH(A21,特殊计租!$A$6:$A$7,0)))),IF(D21="设备附表",IF(COUNTIFS(设备附表!$A$6:$A$7,A21)<>1,"",IF(COUNT(INDEX(设备附表!$F$6:$F$7,MATCH(A21,设备附表!$A$6:$A$7,0)))<>1,"",INDEX(设备附表!$F$6:$F$7,MATCH(A21,设备附表!$A$6:$A$7,0)))),""))))) -> 400 | H21: =IF(L21="排除",0,IF(D21="专项计租",IF(COUNTIFS(特殊计租!$A$6:$A$7,A21)<>1,"",IF(COUNT(INDEX(特殊计租!$J$6:$J$7,MATCH(A21,特殊计租!$A$6:$A$7,0)))<>1,"",INDEX(特殊计租!$J$6:$J$7,MATCH(A21,特殊计租!$A$6:$A$7,0)))),IF(D21="设备附表",IF(COUNTIFS(设备附表!$A$6:$A$7,A21)<>1,"",IF(COUNT(INDEX(设备附表!$G$6:$G$7,MATCH(A21,设备附表!$A$6:$A$7,0)))<>1,"",INDEX(设备附表!$G$6:$G$7,MATCH(A21,设备附表!$A$6:$A$7,0)))),IF(OR(D21="资料核定",D21="租赁资料核定"),IF(COUNTIFS(租赁资料核定!$A$6:$A$7,A21)<>1,"",IF(COUNT(INDEX(租赁资料核定!$N$6:$N$7,MATCH(A21,租赁资料核定!$A$6:$A$7,0)))<>1,"",INDEX(租赁资料核定!$N$6:$N$7,MATCH(A21,租赁资料核定!$A$6:$A$7,0)))),IF(OR(COUNT(F21:G21)<>2,F21<=0),"",ROUND(F21*G21*测算参数!$B$10,2)))))) -> 4800 | I21: =IF(COUNTIFS(计租与历史!$A$6:$A$25,A21)<>1,"",IF(COUNT(INDEX(计租与历史!$D$6:$D$25,MATCH(A21,计租与历史!$A$6:$A$25,0)))<>1,"",INDEX(计租与历史!$D$6:$D$25,MATCH(A21,计租与历史!$A$6:$A$25,0)))) -> 380 | J21: =IF(OR(COUNT(G21,I21)<>2,I21<=0,L21<>"纳入"),"",G21/I21-1) -> 0.052631579 | K21: =IF(L21="排除",IF(AND(D21="不重复计租",OR(IF(COUNTIFS(计租与历史!$A$6:$A$25,A21)<>1,"",IF(INDEX(计租与历史!$G$6:$G$25,MATCH(A21,计租与历史!$A$6:$A$25,0))="","",INDEX(计租与历史!$G$6:$G$25,MATCH(A21,计租与历史!$A$6:$A$25,0))))="",COUNTIFS(资产清单!$A$6:$A$25,IF(COUNTIFS(计租与历史!$A$6:$A$25,A21)<>1,"",IF(INDEX(计租与历史!$G$6:$G$25,MATCH(A21,计租与历史!$A$6:$A$25,0))="","",INDEX(计租与历史!$G$6:$G$25,MATCH(A21,计租与历史!$A$6:$A$25,0)))))<>1)),"待核主资产","范围排除"),IF(D21="市场比较","不适用",IF(COUNT(H21)<>1,"待补专项或核定资料","独立资料核定"))) -> 独立资料核定 | L21: =IF(COUNTIFS(计租与历史!$A$6:$A$25,A21)<>1,"",IF(INDEX(计租与历史!$B$6:$B$25,MATCH(A21,计租与历史!$A$6:$A$25,0))="","",INDEX(计租与历史!$B$6:$B$25,MATCH(A21,计租与历史!$A$6:$A$25,0)))) -> 纳入 | M21: =IF(COUNTIFS(计租与历史!$A$6:$A$25,A21)<>1,"",IF(INDEX(计租与历史!$H$6:$H$25,MATCH(A21,计租与历史!$A$6:$A$25,0))="","",INDEX(计租与历史!$H$6:$H$25,MATCH(A21,计租与历史!$A$6:$A$25,0)))) -> 按相应计租口径测算 | N21: 模拟数据未真实核验
A22: RP-017 | B22: =IF(COUNTIFS(资产清单!$A$6:$A$25,A22)<>1,"",IF(INDEX(资产清单!$D$6:$D$25,MATCH(A22,资产清单!$A$6:$A$25,0))="","",INDEX(资产清单!$D$6:$D$25,MATCH(A22,资产清单!$A$6:$A$25,0)))) -> 起重设备甲 | C22: =IF(COUNTIFS(资产清单!$A$6:$A$25,A22)<>1,"",IF(INDEX(资产清单!$H$6:$H$25,MATCH(A22,资产清单!$A$6:$A$25,0))="","",INDEX(资产清单!$H$6:$H$25,MATCH(A22,资产清单!$A$6:$A$25,0)))) -> 设备 | D22: =IF(COUNTIFS(计租与历史!$A$6:$A$25,A22)<>1,"",IF(INDEX(计租与历史!$C$6:$C$25,MATCH(A22,计租与历史!$A$6:$A$25,0))="","",INDEX(计租与历史!$C$6:$C$25,MATCH(A22,计租与历史!$A$6:$A$25,0)))) -> 设备附表 | E22: =IF(COUNTIFS(资产清单!$A$6:$A$25,A22)<>1,"",IF(INDEX(资产清单!$J$6:$J$25,MATCH(A22,资产清单!$A$6:$A$25,0))="","",INDEX(资产清单!$J$6:$J$25,MATCH(A22,资产清单!$A$6:$A$25,0)))) -> 元/台/月 | F22: =IF(COUNTIFS(资产清单!$A$6:$A$25,A22)<>1,"",IF(COUNT(INDEX(资产清单!$K$6:$K$25,MATCH(A22,资产清单!$A$6:$A$25,0)))<>1,"",INDEX(资产清单!$K$6:$K$25,MATCH(A22,资产清单!$A$6:$A$25,0)))) -> 1 | G22: =IF(L22="排除",0,IF(D22="市场比较","",IF(OR(D22="资料核定",D22="租赁资料核定"),IF(COUNTIFS(租赁资料核定!$A$6:$A$7,A22)<>1,"",IF(COUNT(INDEX(租赁资料核定!$M$6:$M$7,MATCH(A22,租赁资料核定!$A$6:$A$7,0)))<>1,"",INDEX(租赁资料核定!$M$6:$M$7,MATCH(A22,租赁资料核定!$A$6:$A$7,0)))),IF(D22="专项计租",IF(COUNTIFS(特殊计租!$A$6:$A$7,A22)<>1,"",IF(COUNT(INDEX(特殊计租!$D$6:$D$7,MATCH(A22,特殊计租!$A$6:$A$7,0)))<>1,"",INDEX(特殊计租!$D$6:$D$7,MATCH(A22,特殊计租!$A$6:$A$7,0)))),IF(D22="设备附表",IF(COUNTIFS(设备附表!$A$6:$A$7,A22)<>1,"",IF(COUNT(INDEX(设备附表!$F$6:$F$7,MATCH(A22,设备附表!$A$6:$A$7,0)))<>1,"",INDEX(设备附表!$F$6:$F$7,MATCH(A22,设备附表!$A$6:$A$7,0)))),""))))) -> 300 | H22: =IF(L22="排除",0,IF(D22="专项计租",IF(COUNTIFS(特殊计租!$A$6:$A$7,A22)<>1,"",IF(COUNT(INDEX(特殊计租!$J$6:$J$7,MATCH(A22,特殊计租!$A$6:$A$7,0)))<>1,"",INDEX(特殊计租!$J$6:$J$7,MATCH(A22,特殊计租!$A$6:$A$7,0)))),IF(D22="设备附表",IF(COUNTIFS(设备附表!$A$6:$A$7,A22)<>1,"",IF(COUNT(INDEX(设备附表!$G$6:$G$7,MATCH(A22,设备附表!$A$6:$A$7,0)))<>1,"",INDEX(设备附表!$G$6:$G$7,MATCH(A22,设备附表!$A$6:$A$7,0)))),IF(OR(D22="资料核定",D22="租赁资料核定"),IF(COUNTIFS(租赁资料核定!$A$6:$A$7,A22)<>1,"",IF(COUNT(INDEX(租赁资料核定!$N$6:$N$7,MATCH(A22,租赁资料核定!$A$6:$A$7,0)))<>1,"",INDEX(租赁资料核定!$N$6:$N$7,MATCH(A22,租赁资料核定!$A$6:$A$7,0)))),IF(OR(COUNT(F22:G22)<>2,F22<=0),"",ROUND(F22*G22*测算参数!$B$10,2)))))) -> 3600 | I22: =IF(COUNTIFS(计租与历史!$A$6:$A$25,A22)<>1,"",IF(COUNT(INDEX(计租与历史!$D$6:$D$25,MATCH(A22,计租与历史!$A$6:$A$25,0)))<>1,"",INDEX(计租与历史!$D$6:$D$25,MATCH(A22,计租与历史!$A$6:$A$25,0)))) -> 266.66667 | J22: =IF(OR(COUNT(G22,I22)<>2,I22<=0,L22<>"纳入"),"",G22/I22-1) -> 0.125 | K22: =IF(L22="排除",IF(AND(D22="不重复计租",OR(IF(COUNTIFS(计租与历史!$A$6:$A$25,A22)<>1,"",IF(INDEX(计租与历史!$G$6:$G$25,MATCH(A22,计租与历史!$A$6:$A$25,0))="","",INDEX(计租与历史!$G$6:$G$25,MATCH(A22,计租与历史!$A$6:$A$25,0))))="",COUNTIFS(资产清单!$A$6:$A$25,IF(COUNTIFS(计租与历史!$A$6:$A$25,A22)<>1,"",IF(INDEX(计租与历史!$G$6:$G$25,MATCH(A22,计租与历史!$A$6:$A$25,0))="","",INDEX(计租与历史!$G$6:$G$25,MATCH(A22,计租与历史!$A$6:$A$25,0)))))<>1)),"待核主资产","范围排除"),IF(D22="市场比较","不适用",IF(COUNT(H22)<>1,"待补专项或核定资料","独立资料核定"))) -> 独立资料核定 | L22: =IF(COUNTIFS(计租与历史!$A$6:$A$25,A22)<>1,"",IF(INDEX(计租与历史!$B$6:$B$25,MATCH(A22,计租与历史!$A$6:$A$25,0))="","",INDEX(计租与历史!$B$6:$B$25,MATCH(A22,计租与历史!$A$6:$A$25,0)))) -> 纳入 | M22: =IF(COUNTIFS(计租与历史!$A$6:$A$25,A22)<>1,"",IF(INDEX(计租与历史!$H$6:$H$25,MATCH(A22,计租与历史!$A$6:$A$25,0))="","",INDEX(计租与历史!$H$6:$H$25,MATCH(A22,计租与历史!$A$6:$A$25,0)))) -> 仅接收设备附表的年租金结论 | N22: 模拟数据未真实核验
A23: RP-018 | B23: =IF(COUNTIFS(资产清单!$A$6:$A$25,A23)<>1,"",IF(INDEX(资产清单!$D$6:$D$25,MATCH(A23,资产清单!$A$6:$A$25,0))="","",INDEX(资产清单!$D$6:$D$25,MATCH(A23,资产清单!$A$6:$A$25,0)))) -> 加工设备乙 | C23: =IF(COUNTIFS(资产清单!$A$6:$A$25,A23)<>1,"",IF(INDEX(资产清单!$H$6:$H$25,MATCH(A23,资产清单!$A$6:$A$25,0))="","",INDEX(资产清单!$H$6:$H$25,MATCH(A23,资产清单!$A$6:$A$25,0)))) -> 设备 | D23: =IF(COUNTIFS(计租与历史!$A$6:$A$25,A23)<>1,"",IF(INDEX(计租与历史!$C$6:$C$25,MATCH(A23,计租与历史!$A$6:$A$25,0))="","",INDEX(计租与历史!$C$6:$C$25,MATCH(A23,计租与历史!$A$6:$A$25,0)))) -> 设备附表 | E23: =IF(COUNTIFS(资产清单!$A$6:$A$25,A23)<>1,"",IF(INDEX(资产清单!$J$6:$J$25,MATCH(A23,资产清单!$A$6:$A$25,0))="","",INDEX(资产清单!$J$6:$J$25,MATCH(A23,资产清单!$A$6:$A$25,0)))) -> 元/台/月 | F23: =IF(COUNTIFS(资产清单!$A$6:$A$25,A23)<>1,"",IF(COUNT(INDEX(资产清单!$K$6:$K$25,MATCH(A23,资产清单!$A$6:$A$25,0)))<>1,"",INDEX(资产清单!$K$6:$K$25,MATCH(A23,资产清单!$A$6:$A$25,0)))) -> 1 | G23: =IF(L23="排除",0,IF(D23="市场比较","",IF(OR(D23="资料核定",D23="租赁资料核定"),IF(COUNTIFS(租赁资料核定!$A$6:$A$7,A23)<>1,"",IF(COUNT(INDEX(租赁资料核定!$M$6:$M$7,MATCH(A23,租赁资料核定!$A$6:$A$7,0)))<>1,"",INDEX(租赁资料核定!$M$6:$M$7,MATCH(A23,租赁资料核定!$A$6:$A$7,0)))),IF(D23="专项计租",IF(COUNTIFS(特殊计租!$A$6:$A$7,A23)<>1,"",IF(COUNT(INDEX(特殊计租!$D$6:$D$7,MATCH(A23,特殊计租!$A$6:$A$7,0)))<>1,"",INDEX(特殊计租!$D$6:$D$7,MATCH(A23,特殊计租!$A$6:$A$7,0)))),IF(D23="设备附表",IF(COUNTIFS(设备附表!$A$6:$A$7,A23)<>1,"",IF(COUNT(INDEX(设备附表!$F$6:$F$7,MATCH(A23,设备附表!$A$6:$A$7,0)))<>1,"",INDEX(设备附表!$F$6:$F$7,MATCH(A23,设备附表!$A$6:$A$7,0)))),""))))) -> 150 | H23: =IF(L23="排除",0,IF(D23="专项计租",IF(COUNTIFS(特殊计租!$A$6:$A$7,A23)<>1,"",IF(COUNT(INDEX(特殊计租!$J$6:$J$7,MATCH(A23,特殊计租!$A$6:$A$7,0)))<>1,"",INDEX(特殊计租!$J$6:$J$7,MATCH(A23,特殊计租!$A$6:$A$7,0)))),IF(D23="设备附表",IF(COUNTIFS(设备附表!$A$6:$A$7,A23)<>1,"",IF(COUNT(INDEX(设备附表!$G$6:$G$7,MATCH(A23,设备附表!$A$6:$A$7,0)))<>1,"",INDEX(设备附表!$G$6:$G$7,MATCH(A23,设备附表!$A$6:$A$7,0)))),IF(OR(D23="资料核定",D23="租赁资料核定"),IF(COUNTIFS(租赁资料核定!$A$6:$A$7,A23)<>1,"",IF(COUNT(INDEX(租赁资料核定!$N$6:$N$7,MATCH(A23,租赁资料核定!$A$6:$A$7,0)))<>1,"",INDEX(租赁资料核定!$N$6:$N$7,MATCH(A23,租赁资料核定!$A$6:$A$7,0)))),IF(OR(COUNT(F23:G23)<>2,F23<=0),"",ROUND(F23*G23*测算参数!$B$10,2)))))) -> 1800 | I23: =IF(COUNTIFS(计租与历史!$A$6:$A$25,A23)<>1,"",IF(COUNT(INDEX(计租与历史!$D$6:$D$25,MATCH(A23,计租与历史!$A$6:$A$25,0)))<>1,"",INDEX(计租与历史!$D$6:$D$25,MATCH(A23,计租与历史!$A$6:$A$25,0)))) -> 133.33333 | J23: =IF(OR(COUNT(G23,I23)<>2,I23<=0,L23<>"纳入"),"",G23/I23-1) -> 0.125 | K23: =IF(L23="排除",IF(AND(D23="不重复计租",OR(IF(COUNTIFS(计租与历史!$A$6:$A$25,A23)<>1,"",IF(INDEX(计租与历史!$G$6:$G$25,MATCH(A23,计租与历史!$A$6:$A$25,0))="","",INDEX(计租与历史!$G$6:$G$25,MATCH(A23,计租与历史!$A$6:$A$25,0))))="",COUNTIFS(资产清单!$A$6:$A$25,IF(COUNTIFS(计租与历史!$A$6:$A$25,A23)<>1,"",IF(INDEX(计租与历史!$G$6:$G$25,MATCH(A23,计租与历史!$A$6:$A$25,0))="","",INDEX(计租与历史!$G$6:$G$25,MATCH(A23,计租与历史!$A$6:$A$25,0)))))<>1)),"待核主资产","范围排除"),IF(D23="市场比较","不适用",IF(COUNT(H23)<>1,"待补专项或核定资料","独立资料核定"))) -> 独立资料核定 | L23: =IF(COUNTIFS(计租与历史!$A$6:$A$25,A23)<>1,"",IF(INDEX(计租与历史!$B$6:$B$25,MATCH(A23,计租与历史!$A$6:$A$25,0))="","",INDEX(计租与历史!$B$6:$B$25,MATCH(A23,计租与历史!$A$6:$A$25,0)))) -> 纳入 | M23: =IF(COUNTIFS(计租与历史!$A$6:$A$25,A23)<>1,"",IF(INDEX(计租与历史!$H$6:$H$25,MATCH(A23,计租与历史!$A$6:$A$25,0))="","",INDEX(计租与历史!$H$6:$H$25,MATCH(A23,计租与历史!$A$6:$A$25,0)))) -> 仅接收设备附表的年租金结论 | N23: 模拟数据未真实核验
A24: RP-019 | B24: =IF(COUNTIFS(资产清单!$A$6:$A$25,A24)<>1,"",IF(INDEX(资产清单!$D$6:$D$25,MATCH(A24,资产清单!$A$6:$A$25,0))="","",INDEX(资产清单!$D$6:$D$25,MATCH(A24,资产清单!$A$6:$A$25,0)))) -> 库房重复记录 | C24: =IF(COUNTIFS(资产清单!$A$6:$A$25,A24)<>1,"",IF(INDEX(资产清单!$H$6:$H$25,MATCH(A24,资产清单!$A$6:$A$25,0))="","",INDEX(资产清单!$H$6:$H$25,MATCH(A24,资产清单!$A$6:$A$25,0)))) -> 仓储 | D24: =IF(COUNTIFS(计租与历史!$A$6:$A$25,A24)<>1,"",IF(INDEX(计租与历史!$C$6:$C$25,MATCH(A24,计租与历史!$A$6:$A$25,0))="","",INDEX(计租与历史!$C$6:$C$25,MATCH(A24,计租与历史!$A$6:$A$25,0)))) -> 不重复计租 | E24: =IF(COUNTIFS(资产清单!$A$6:$A$25,A24)<>1,"",IF(INDEX(资产清单!$J$6:$J$25,MATCH(A24,资产清单!$A$6:$A$25,0))="","",INDEX(资产清单!$J$6:$J$25,MATCH(A24,资产清单!$A$6:$A$25,0)))) -> 元/㎡/月 | F24: =IF(COUNTIFS(资产清单!$A$6:$A$25,A24)<>1,"",IF(COUNT(INDEX(资产清单!$K$6:$K$25,MATCH(A24,资产清单!$A$6:$A$25,0)))<>1,"",INDEX(资产清单!$K$6:$K$25,MATCH(A24,资产清单!$A$6:$A$25,0)))) -> 500 | G24: =IF(L24="排除",0,IF(D24="市场比较","",IF(OR(D24="资料核定",D24="租赁资料核定"),IF(COUNTIFS(租赁资料核定!$A$6:$A$7,A24)<>1,"",IF(COUNT(INDEX(租赁资料核定!$M$6:$M$7,MATCH(A24,租赁资料核定!$A$6:$A$7,0)))<>1,"",INDEX(租赁资料核定!$M$6:$M$7,MATCH(A24,租赁资料核定!$A$6:$A$7,0)))),IF(D24="专项计租",IF(COUNTIFS(特殊计租!$A$6:$A$7,A24)<>1,"",IF(COUNT(INDEX(特殊计租!$D$6:$D$7,MATCH(A24,特殊计租!$A$6:$A$7,0)))<>1,"",INDEX(特殊计租!$D$6:$D$7,MATCH(A24,特殊计租!$A$6:$A$7,0)))),IF(D24="设备附表",IF(COUNTIFS(设备附表!$A$6:$A$7,A24)<>1,"",IF(COUNT(INDEX(设备附表!$F$6:$F$7,MATCH(A24,设备附表!$A$6:$A$7,0)))<>1,"",INDEX(设备附表!$F$6:$F$7,MATCH(A24,设备附表!$A$6:$A$7,0)))),""))))) -> 0 | H24: =IF(L24="排除",0,IF(D24="专项计租",IF(COUNTIFS(特殊计租!$A$6:$A$7,A24)<>1,"",IF(COUNT(INDEX(特殊计租!$J$6:$J$7,MATCH(A24,特殊计租!$A$6:$A$7,0)))<>1,"",INDEX(特殊计租!$J$6:$J$7,MATCH(A24,特殊计租!$A$6:$A$7,0)))),IF(D24="设备附表",IF(COUNTIFS(设备附表!$A$6:$A$7,A24)<>1,"",IF(COUNT(INDEX(设备附表!$G$6:$G$7,MATCH(A24,设备附表!$A$6:$A$7,0)))<>1,"",INDEX(设备附表!$G$6:$G$7,MATCH(A24,设备附表!$A$6:$A$7,0)))),IF(OR(D24="资料核定",D24="租赁资料核定"),IF(COUNTIFS(租赁资料核定!$A$6:$A$7,A24)<>1,"",IF(COUNT(INDEX(租赁资料核定!$N$6:$N$7,MATCH(A24,租赁资料核定!$A$6:$A$7,0)))<>1,"",INDEX(租赁资料核定!$N$6:$N$7,MATCH(A24,租赁资料核定!$A$6:$A$7,0)))),IF(OR(COUNT(F24:G24)<>2,F24<=0),"",ROUND(F24*G24*测算参数!$B$10,2)))))) -> 0 | I24: =IF(COUNTIFS(计租与历史!$A$6:$A$25,A24)<>1,"",IF(COUNT(INDEX(计租与历史!$D$6:$D$25,MATCH(A24,计租与历史!$A$6:$A$25,0)))<>1,"",INDEX(计租与历史!$D$6:$D$25,MATCH(A24,计租与历史!$A$6:$A$25,0)))) | J24: =IF(OR(COUNT(G24,I24)<>2,I24<=0,L24<>"纳入"),"",G24/I24-1) | K24: =IF(L24="排除",IF(AND(D24="不重复计租",OR(IF(COUNTIFS(计租与历史!$A$6:$A$25,A24)<>1,"",IF(INDEX(计租与历史!$G$6:$G$25,MATCH(A24,计租与历史!$A$6:$A$25,0))="","",INDEX(计租与历史!$G$6:$G$25,MATCH(A24,计租与历史!$A$6:$A$25,0))))="",COUNTIFS(资产清单!$A$6:$A$25,IF(COUNTIFS(计租与历史!$A$6:$A$25,A24)<>1,"",IF(INDEX(计租与历史!$G$6:$G$25,MATCH(A24,计租与历史!$A$6:$A$25,0))="","",INDEX(计租与历史!$G$6:$G$25,MATCH(A24,计租与历史!$A$6:$A$25,0)))))<>1)),"待核主资产","范围排除"),IF(D24="市场比较","不适用",IF(COUNT(H24)<>1,"待补专项或核定资料","独立资料核定"))) -> 范围排除 | L24: =IF(COUNTIFS(计租与历史!$A$6:$A$25,A24)<>1,"",IF(INDEX(计租与历史!$B$6:$B$25,MATCH(A24,计租与历史!$A$6:$A$25,0))="","",INDEX(计租与历史!$B$6:$B$25,MATCH(A24,计租与历史!$A$6:$A$25,0)))) -> 排除 | M24: =IF(COUNTIFS(计租与历史!$A$6:$A$25,A24)<>1,"",IF(INDEX(计租与历史!$H$6:$H$25,MATCH(A24,计租与历史!$A$6:$A$25,0))="","",INDEX(计租与历史!$H$6:$H$25,MATCH(A24,计租与历史!$A$6:$A$25,0)))) -> 同一标的重复登记，保留主记录计租 | N24: 模拟数据未真实核验
A25: RP-020 | B25: =IF(COUNTIFS(资产清单!$A$6:$A$25,A25)<>1,"",IF(INDEX(资产清单!$D$6:$D$25,MATCH(A25,资产清单!$A$6:$A$25,0))="","",INDEX(资产清单!$D$6:$D$25,MATCH(A25,资产清单!$A$6:$A$25,0)))) -> 范围外房屋 | C25: =IF(COUNTIFS(资产清单!$A$6:$A$25,A25)<>1,"",IF(INDEX(资产清单!$H$6:$H$25,MATCH(A25,资产清单!$A$6:$A$25,0))="","",INDEX(资产清单!$H$6:$H$25,MATCH(A25,资产清单!$A$6:$A$25,0)))) -> 办公 | D25: =IF(COUNTIFS(计租与历史!$A$6:$A$25,A25)<>1,"",IF(INDEX(计租与历史!$C$6:$C$25,MATCH(A25,计租与历史!$A$6:$A$25,0))="","",INDEX(计租与历史!$C$6:$C$25,MATCH(A25,计租与历史!$A$6:$A$25,0)))) -> 不纳入 | E25: =IF(COUNTIFS(资产清单!$A$6:$A$25,A25)<>1,"",IF(INDEX(资产清单!$J$6:$J$25,MATCH(A25,资产清单!$A$6:$A$25,0))="","",INDEX(资产清单!$J$6:$J$25,MATCH(A25,资产清单!$A$6:$A$25,0)))) -> 元/㎡/月 | F25: =IF(COUNTIFS(资产清单!$A$6:$A$25,A25)<>1,"",IF(COUNT(INDEX(资产清单!$K$6:$K$25,MATCH(A25,资产清单!$A$6:$A$25,0)))<>1,"",INDEX(资产清单!$K$6:$K$25,MATCH(A25,资产清单!$A$6:$A$25,0)))) -> 80 | G25: =IF(L25="排除",0,IF(D25="市场比较","",IF(OR(D25="资料核定",D25="租赁资料核定"),IF(COUNTIFS(租赁资料核定!$A$6:$A$7,A25)<>1,"",IF(COUNT(INDEX(租赁资料核定!$M$6:$M$7,MATCH(A25,租赁资料核定!$A$6:$A$7,0)))<>1,"",INDEX(租赁资料核定!$M$6:$M$7,MATCH(A25,租赁资料核定!$A$6:$A$7,0)))),IF(D25="专项计租",IF(COUNTIFS(特殊计租!$A$6:$A$7,A25)<>1,"",IF(COUNT(INDEX(特殊计租!$D$6:$D$7,MATCH(A25,特殊计租!$A$6:$A$7,0)))<>1,"",INDEX(特殊计租!$D$6:$D$7,MATCH(A25,特殊计租!$A$6:$A$7,0)))),IF(D25="设备附表",IF(COUNTIFS(设备附表!$A$6:$A$7,A25)<>1,"",IF(COUNT(INDEX(设备附表!$F$6:$F$7,MATCH(A25,设备附表!$A$6:$A$7,0)))<>1,"",INDEX(设备附表!$F$6:$F$7,MATCH(A25,设备附表!$A$6:$A$7,0)))),""))))) -> 0 | H25: =IF(L25="排除",0,IF(D25="专项计租",IF(COUNTIFS(特殊计租!$A$6:$A$7,A25)<>1,"",IF(COUNT(INDEX(特殊计租!$J$6:$J$7,MATCH(A25,特殊计租!$A$6:$A$7,0)))<>1,"",INDEX(特殊计租!$J$6:$J$7,MATCH(A25,特殊计租!$A$6:$A$7,0)))),IF(D25="设备附表",IF(COUNTIFS(设备附表!$A$6:$A$7,A25)<>1,"",IF(COUNT(INDEX(设备附表!$G$6:$G$7,MATCH(A25,设备附表!$A$6:$A$7,0)))<>1,"",INDEX(设备附表!$G$6:$G$7,MATCH(A25,设备附表!$A$6:$A$7,0)))),IF(OR(D25="资料核定",D25="租赁资料核定"),IF(COUNTIFS(租赁资料核定!$A$6:$A$7,A25)<>1,"",IF(COUNT(INDEX(租赁资料核定!$N$6:$N$7,MATCH(A25,租赁资料核定!$A$6:$A$7,0)))<>1,"",INDEX(租赁资料核定!$N$6:$N$7,MATCH(A25,租赁资料核定!$A$6:$A$7,0)))),IF(OR(COUNT(F25:G25)<>2,F25<=0),"",ROUND(F25*G25*测算参数!$B$10,2)))))) -> 0 | I25: =IF(COUNTIFS(计租与历史!$A$6:$A$25,A25)<>1,"",IF(COUNT(INDEX(计租与历史!$D$6:$D$25,MATCH(A25,计租与历史!$A$6:$A$25,0)))<>1,"",INDEX(计租与历史!$D$6:$D$25,MATCH(A25,计租与历史!$A$6:$A$25,0)))) | J25: =IF(OR(COUNT(G25,I25)<>2,I25<=0,L25<>"纳入"),"",G25/I25-1) | K25: =IF(L25="排除",IF(AND(D25="不重复计租",OR(IF(COUNTIFS(计租与历史!$A$6:$A$25,A25)<>1,"",IF(INDEX(计租与历史!$G$6:$G$25,MATCH(A25,计租与历史!$A$6:$A$25,0))="","",INDEX(计租与历史!$G$6:$G$25,MATCH(A25,计租与历史!$A$6:$A$25,0))))="",COUNTIFS(资产清单!$A$6:$A$25,IF(COUNTIFS(计租与历史!$A$6:$A$25,A25)<>1,"",IF(INDEX(计租与历史!$G$6:$G$25,MATCH(A25,计租与历史!$A$6:$A$25,0))="","",INDEX(计租与历史!$G$6:$G$25,MATCH(A25,计租与历史!$A$6:$A$25,0)))))<>1)),"待核主资产","范围排除"),IF(D25="市场比较","不适用",IF(COUNT(H25)<>1,"待补专项或核定资料","独立资料核定"))) -> 范围排除 | L25: =IF(COUNTIFS(计租与历史!$A$6:$A$25,A25)<>1,"",IF(INDEX(计租与历史!$B$6:$B$25,MATCH(A25,计租与历史!$A$6:$A$25,0))="","",INDEX(计租与历史!$B$6:$B$25,MATCH(A25,计租与历史!$A$6:$A$25,0)))) -> 排除 | M25: =IF(COUNTIFS(计租与历史!$A$6:$A$25,A25)<>1,"",IF(INDEX(计租与历史!$H$6:$H$25,MATCH(A25,计租与历史!$A$6:$A$25,0))="","",INDEX(计租与历史!$H$6:$H$25,MATCH(A25,计租与历史!$A$6:$A$25,0)))) -> 模拟委托清单明确不纳入 | N25: 模拟数据未真实核验
A27: 范围排除的0表示不纳入本次计租，不表示该资产没有市场租金。缺少必要资料的年额保持为空。
A28: 不同单价单位不求平均。设备按每台年结论计租；活动场馆不乘面积；按间和按处数量独立记录。

Sheet 资产分类汇总
A2: 资产分类与计租路线汇总
A3: 全部业务数据及依据记录均为模拟。用于试用复算，未核验真实来源。
A5: 分类维度 | B5: 范围内项数 | C5: 范围外项数 | D5: 本年年租金元 | E5: 说明
A6: 商业 | B6: =COUNTIFS(测算结果!$C$6:$C$25,A6,测算结果!$L$6:$L$25,"纳入") -> 4 | C6: =COUNTIFS(测算结果!$C$6:$C$25,A6,测算结果!$L$6:$L$25,"排除") -> 0 | D6: =IF(COUNT(测算结果!$H$6:$H$25)<>20,"",SUMIFS(测算结果!$H$6:$H$25,测算结果!$C$6:$C$25,A6,测算结果!$L$6:$L$25,"纳入")) -> 186788.4 | E6: 按确认实际用途分类
A7: 办公 | B7: =COUNTIFS(测算结果!$C$6:$C$25,A7,测算结果!$L$6:$L$25,"纳入") -> 2 | C7: =COUNTIFS(测算结果!$C$6:$C$25,A7,测算结果!$L$6:$L$25,"排除") -> 1 | D7: =IF(COUNT(测算结果!$H$6:$H$25)<>20,"",SUMIFS(测算结果!$H$6:$H$25,测算结果!$C$6:$C$25,A7,测算结果!$L$6:$L$25,"纳入")) -> 100896 | E7: 按确认实际用途分类
A8: 仓储 | B8: =COUNTIFS(测算结果!$C$6:$C$25,A8,测算结果!$L$6:$L$25,"纳入") -> 2 | C8: =COUNTIFS(测算结果!$C$6:$C$25,A8,测算结果!$L$6:$L$25,"排除") -> 1 | D8: =IF(COUNT(测算结果!$H$6:$H$25)<>20,"",SUMIFS(测算结果!$H$6:$H$25,测算结果!$C$6:$C$25,A8,测算结果!$L$6:$L$25,"纳入")) -> 74040 | E8: 按确认实际用途分类
A9: 厂房 | B9: =COUNTIFS(测算结果!$C$6:$C$25,A9,测算结果!$L$6:$L$25,"纳入") -> 1 | C9: =COUNTIFS(测算结果!$C$6:$C$25,A9,测算结果!$L$6:$L$25,"排除") -> 0 | D9: =IF(COUNT(测算结果!$H$6:$H$25)<>20,"",SUMIFS(测算结果!$H$6:$H$25,测算结果!$C$6:$C$25,A9,测算结果!$L$6:$L$25,"纳入")) -> 239040 | E9: 按确认实际用途分类
A10: 场地 | B10: =COUNTIFS(测算结果!$C$6:$C$25,A10,测算结果!$L$6:$L$25,"纳入") -> 2 | C10: =COUNTIFS(测算结果!$C$6:$C$25,A10,测算结果!$L$6:$L$25,"排除") -> 0 | D10: =IF(COUNT(测算结果!$H$6:$H$25)<>20,"",SUMIFS(测算结果!$H$6:$H$25,测算结果!$C$6:$C$25,A10,测算结果!$L$6:$L$25,"纳入")) -> 45120 | E10: 按确认实际用途分类
A11: 车位 | B11: =COUNTIFS(测算结果!$C$6:$C$25,A11,测算结果!$L$6:$L$25,"纳入") -> 1 | C11: =COUNTIFS(测算结果!$C$6:$C$25,A11,测算结果!$L$6:$L$25,"排除") -> 0 | D11: =IF(COUNT(测算结果!$H$6:$H$25)<>20,"",SUMIFS(测算结果!$H$6:$H$25,测算结果!$C$6:$C$25,A11,测算结果!$L$6:$L$25,"纳入")) -> 22200 | E11: 按确认实际用途分类
A12: 住宅 | B12: =COUNTIFS(测算结果!$C$6:$C$25,A12,测算结果!$L$6:$L$25,"纳入") -> 1 | C12: =COUNTIFS(测算结果!$C$6:$C$25,A12,测算结果!$L$6:$L$25,"排除") -> 0 | D12: =IF(COUNT(测算结果!$H$6:$H$25)<>20,"",SUMIFS(测算结果!$H$6:$H$25,测算结果!$C$6:$C$25,A12,测算结果!$L$6:$L$25,"纳入")) -> 7972.8 | E12: 按确认实际用途分类
A13: 通信基站 | B13: =COUNTIFS(测算结果!$C$6:$C$25,A13,测算结果!$L$6:$L$25,"纳入") -> 1 | C13: =COUNTIFS(测算结果!$C$6:$C$25,A13,测算结果!$L$6:$L$25,"排除") -> 0 | D13: =IF(COUNT(测算结果!$H$6:$H$25)<>20,"",SUMIFS(测算结果!$H$6:$H$25,测算结果!$C$6:$C$25,A13,测算结果!$L$6:$L$25,"纳入")) -> 8628 | E13: 按确认实际用途分类
A14: 场馆 | B14: =COUNTIFS(测算结果!$C$6:$C$25,A14,测算结果!$L$6:$L$25,"纳入") -> 1 | C14: =COUNTIFS(测算结果!$C$6:$C$25,A14,测算结果!$L$6:$L$25,"排除") -> 0 | D14: =IF(COUNT(测算结果!$H$6:$H$25)<>20,"",SUMIFS(测算结果!$H$6:$H$25,测算结果!$C$6:$C$25,A14,测算结果!$L$6:$L$25,"纳入")) -> 70200 | E14: 按确认实际用途分类
A15: 广告位 | B15: =COUNTIFS(测算结果!$C$6:$C$25,A15,测算结果!$L$6:$L$25,"纳入") -> 1 | C15: =COUNTIFS(测算结果!$C$6:$C$25,A15,测算结果!$L$6:$L$25,"排除") -> 0 | D15: =IF(COUNT(测算结果!$H$6:$H$25)<>20,"",SUMIFS(测算结果!$H$6:$H$25,测算结果!$C$6:$C$25,A15,测算结果!$L$6:$L$25,"纳入")) -> 4800 | E15: 按确认实际用途分类
A16: 设备 | B16: =COUNTIFS(测算结果!$C$6:$C$25,A16,测算结果!$L$6:$L$25,"纳入") -> 2 | C16: =COUNTIFS(测算结果!$C$6:$C$25,A16,测算结果!$L$6:$L$25,"排除") -> 0 | D16: =IF(COUNT(测算结果!$H$6:$H$25)<>20,"",SUMIFS(测算结果!$H$6:$H$25,测算结果!$C$6:$C$25,A16,测算结果!$L$6:$L$25,"纳入")) -> 5400 | E16: 设备金额单列，不进入非设备占比分母
A18: 合计 | B18: =SUM(B6:B16) -> 18 | C18: =SUM(C6:C16) -> 2 | D18: =IF(COUNT(D6:D16)<>11,"",SUM(D6:D16)) -> 765085.2

Sheet 两年金额对比
A2: 同一资产集合两年年租金对比
A3: 全部业务数据及依据记录均为模拟。用于试用复算，未核验真实来源。
A5: 资产编码 | B5: 资产名称 | C5: 路线 | D5: 上期有效年额 | E5: 本期年额 | F5: 是否同口径可比 | G5: 可比上期年额 | H5: 可比本期年额
A6: =测算结果!A6 -> RP-001 | B6: =测算结果!B6 -> 沿街商铺一 | C6: =测算结果!D6 -> 市场比较 | D6: =IF(COUNTIFS(计租与历史!$A$6:$A$25,A6)<>1,"",IF(COUNT(INDEX(计租与历史!$E$6:$E$25,MATCH(A6,计租与历史!$A$6:$A$25,0)))<>1,"",INDEX(计租与历史!$E$6:$E$25,MATCH(A6,计租与历史!$A$6:$A$25,0)))) -> 34560 | E6: =IF(COUNT(测算结果!H6)<>1,"",测算结果!H6) -> 39384 | F6: =IF(AND(测算结果!L6="纳入",C6<>"设备附表",COUNT(D6:E6)=2,D6>0),"可比","不纳入可比") -> 可比 | G6: =IF(F6="可比",D6,0) -> 34560 | H6: =IF(F6="可比",E6,0) -> 39384
A7: =测算结果!A7 -> RP-002 | B7: =测算结果!B7 -> 沿街商铺二 | C7: =测算结果!D7 -> 市场比较 | D7: =IF(COUNTIFS(计租与历史!$A$6:$A$25,A7)<>1,"",IF(COUNT(INDEX(计租与历史!$E$6:$E$25,MATCH(A7,计租与历史!$A$6:$A$25,0)))<>1,"",INDEX(计租与历史!$E$6:$E$25,MATCH(A7,计租与历史!$A$6:$A$25,0)))) -> 62040 | E7: =IF(COUNT(测算结果!H7)<>1,"",测算结果!H7) -> 68904 | F7: =IF(AND(测算结果!L7="纳入",C7<>"设备附表",COUNT(D7:E7)=2,D7>0),"可比","不纳入可比") -> 可比 | G7: =IF(F7="可比",D7,0) -> 62040 | H7: =IF(F7="可比",E7,0) -> 68904
A8: =测算结果!A8 -> RP-003 | B8: =测算结果!B8 -> 二层商铺 | C8: =测算结果!D8 -> 市场比较 | D8: =IF(COUNTIFS(计租与历史!$A$6:$A$25,A8)<>1,"",IF(COUNT(INDEX(计租与历史!$E$6:$E$25,MATCH(A8,计租与历史!$A$6:$A$25,0)))<>1,"",INDEX(计租与历史!$E$6:$E$25,MATCH(A8,计租与历史!$A$6:$A$25,0)))) -> 47880 | E8: =IF(COUNT(测算结果!H8)<>1,"",测算结果!H8) -> 50274 | F8: =IF(AND(测算结果!L8="纳入",C8<>"设备附表",COUNT(D8:E8)=2,D8>0),"可比","不纳入可比") -> 可比 | G8: =IF(F8="可比",D8,0) -> 47880 | H8: =IF(F8="可比",E8,0) -> 50274
A9: =测算结果!A9 -> RP-004 | B9: =测算结果!B9 -> 内部通道商铺 | C9: =测算结果!D9 -> 市场比较 | D9: =IF(COUNTIFS(计租与历史!$A$6:$A$25,A9)<>1,"",IF(COUNT(INDEX(计租与历史!$E$6:$E$25,MATCH(A9,计租与历史!$A$6:$A$25,0)))<>1,"",INDEX(计租与历史!$E$6:$E$25,MATCH(A9,计租与历史!$A$6:$A$25,0)))) -> 22800 | E9: =IF(COUNT(测算结果!H9)<>1,"",测算结果!H9) -> 28226.4 | F9: =IF(AND(测算结果!L9="纳入",C9<>"设备附表",COUNT(D9:E9)=2,D9>0),"可比","不纳入可比") -> 可比 | G9: =IF(F9="可比",D9,0) -> 22800 | H9: =IF(F9="可比",E9,0) -> 28226.4
A10: =测算结果!A10 -> RP-005 | B10: =测算结果!B10 -> 办公用房一 | C10: =测算结果!D10 -> 市场比较 | D10: =IF(COUNTIFS(计租与历史!$A$6:$A$25,A10)<>1,"",IF(COUNT(INDEX(计租与历史!$E$6:$E$25,MATCH(A10,计租与历史!$A$6:$A$25,0)))<>1,"",INDEX(计租与历史!$E$6:$E$25,MATCH(A10,计租与历史!$A$6:$A$25,0)))) -> 23520 | E10: =IF(COUNT(测算结果!H10)<>1,"",测算结果!H10) -> 44520 | F10: =IF(AND(测算结果!L10="纳入",C10<>"设备附表",COUNT(D10:E10)=2,D10>0),"可比","不纳入可比") -> 可比 | G10: =IF(F10="可比",D10,0) -> 23520 | H10: =IF(F10="可比",E10,0) -> 44520
A11: =测算结果!A11 -> RP-006 | B11: =测算结果!B11 -> 办公用房二 | C11: =测算结果!D11 -> 市场比较 | D11: =IF(COUNTIFS(计租与历史!$A$6:$A$25,A11)<>1,"",IF(COUNT(INDEX(计租与历史!$E$6:$E$25,MATCH(A11,计租与历史!$A$6:$A$25,0)))<>1,"",INDEX(计租与历史!$E$6:$E$25,MATCH(A11,计租与历史!$A$6:$A$25,0)))) -> 69120 | E11: =IF(COUNT(测算结果!H11)<>1,"",测算结果!H11) -> 56376 | F11: =IF(AND(测算结果!L11="纳入",C11<>"设备附表",COUNT(D11:E11)=2,D11>0),"可比","不纳入可比") -> 可比 | G11: =IF(F11="可比",D11,0) -> 69120 | H11: =IF(F11="可比",E11,0) -> 56376
A12: =测算结果!A12 -> RP-007 | B12: =测算结果!B12 -> 仓储库房 | C12: =测算结果!D12 -> 市场比较 | D12: =IF(COUNTIFS(计租与历史!$A$6:$A$25,A12)<>1,"",IF(COUNT(INDEX(计租与历史!$E$6:$E$25,MATCH(A12,计租与历史!$A$6:$A$25,0)))<>1,"",INDEX(计租与历史!$E$6:$E$25,MATCH(A12,计租与历史!$A$6:$A$25,0)))) -> 66000 | E12: =IF(COUNT(测算结果!H12)<>1,"",测算结果!H12) -> 72600 | F12: =IF(AND(测算结果!L12="纳入",C12<>"设备附表",COUNT(D12:E12)=2,D12>0),"可比","不纳入可比") -> 可比 | G12: =IF(F12="可比",D12,0) -> 66000 | H12: =IF(F12="可比",E12,0) -> 72600
A13: =测算结果!A13 -> RP-008 | B13: =测算结果!B13 -> 工业厂房 | C13: =测算结果!D13 -> 市场比较 | D13: =IF(COUNTIFS(计租与历史!$A$6:$A$25,A13)<>1,"",IF(COUNT(INDEX(计租与历史!$E$6:$E$25,MATCH(A13,计租与历史!$A$6:$A$25,0)))<>1,"",INDEX(计租与历史!$E$6:$E$25,MATCH(A13,计租与历史!$A$6:$A$25,0)))) -> 216000 | E13: =IF(COUNT(测算结果!H13)<>1,"",测算结果!H13) -> 239040 | F13: =IF(AND(测算结果!L13="纳入",C13<>"设备附表",COUNT(D13:E13)=2,D13>0),"可比","不纳入可比") -> 可比 | G13: =IF(F13="可比",D13,0) -> 216000 | H13: =IF(F13="可比",E13,0) -> 239040
A14: =测算结果!A14 -> RP-009 | B14: =测算结果!B14 -> 露天场地 | C14: =测算结果!D14 -> 市场比较 | D14: =IF(COUNTIFS(计租与历史!$A$6:$A$25,A14)<>1,"",IF(COUNT(INDEX(计租与历史!$E$6:$E$25,MATCH(A14,计租与历史!$A$6:$A$25,0)))<>1,"",INDEX(计租与历史!$E$6:$E$25,MATCH(A14,计租与历史!$A$6:$A$25,0)))) -> 32400 | E14: =IF(COUNT(测算结果!H14)<>1,"",测算结果!H14) -> 36720 | F14: =IF(AND(测算结果!L14="纳入",C14<>"设备附表",COUNT(D14:E14)=2,D14>0),"可比","不纳入可比") -> 可比 | G14: =IF(F14="可比",D14,0) -> 32400 | H14: =IF(F14="可比",E14,0) -> 36720
A15: =测算结果!A15 -> RP-010 | B15: =测算结果!B15 -> 地面停车位组 | C15: =测算结果!D15 -> 市场比较 | D15: =IF(COUNTIFS(计租与历史!$A$6:$A$25,A15)<>1,"",IF(COUNT(INDEX(计租与历史!$E$6:$E$25,MATCH(A15,计租与历史!$A$6:$A$25,0)))<>1,"",INDEX(计租与历史!$E$6:$E$25,MATCH(A15,计租与历史!$A$6:$A$25,0)))) -> 21000 | E15: =IF(COUNT(测算结果!H15)<>1,"",测算结果!H15) -> 22200 | F15: =IF(AND(测算结果!L15="纳入",C15<>"设备附表",COUNT(D15:E15)=2,D15>0),"可比","不纳入可比") -> 可比 | G15: =IF(F15="可比",D15,0) -> 21000 | H15: =IF(F15="可比",E15,0) -> 22200
A16: =测算结果!A16 -> RP-011 | B16: =测算结果!B16 -> 按间计租宿舍 | C16: =测算结果!D16 -> 市场比较 | D16: =IF(COUNTIFS(计租与历史!$A$6:$A$25,A16)<>1,"",IF(COUNT(INDEX(计租与历史!$E$6:$E$25,MATCH(A16,计租与历史!$A$6:$A$25,0)))<>1,"",INDEX(计租与历史!$E$6:$E$25,MATCH(A16,计租与历史!$A$6:$A$25,0)))) -> 7440 | E16: =IF(COUNT(测算结果!H16)<>1,"",测算结果!H16) -> 7972.8 | F16: =IF(AND(测算结果!L16="纳入",C16<>"设备附表",COUNT(D16:E16)=2,D16>0),"可比","不纳入可比") -> 可比 | G16: =IF(F16="可比",D16,0) -> 7440 | H16: =IF(F16="可比",E16,0) -> 7972.8
A17: =测算结果!A17 -> RP-012 | B17: =测算结果!B17 -> 通信基站点位 | C17: =测算结果!D17 -> 市场比较 | D17: =IF(COUNTIFS(计租与历史!$A$6:$A$25,A17)<>1,"",IF(COUNT(INDEX(计租与历史!$E$6:$E$25,MATCH(A17,计租与历史!$A$6:$A$25,0)))<>1,"",INDEX(计租与历史!$E$6:$E$25,MATCH(A17,计租与历史!$A$6:$A$25,0)))) -> 8160 | E17: =IF(COUNT(测算结果!H17)<>1,"",测算结果!H17) -> 8628 | F17: =IF(AND(测算结果!L17="纳入",C17<>"设备附表",COUNT(D17:E17)=2,D17>0),"可比","不纳入可比") -> 可比 | G17: =IF(F17="可比",D17,0) -> 8160 | H17: =IF(F17="可比",E17,0) -> 8628
... A25: =测算结果!A25 -> RP-020 | B25: =测算结果!B25 -> 范围外房屋 | C25: =测算结果!D25 -> 不纳入 | D25: =IF(COUNTIFS(计租与历史!$A$6:$A$25,A25)<>1,"",IF(COUNT(INDEX(计租与历史!$E$6:$E$25,MATCH(A25,计租与历史!$A$6:$A$25,0)))<>1,"",INDEX(计租与历史!$E$6:$E$25,MATCH(A25,计租与历史!$A$6:$A$25,0)))) | E25: =IF(COUNT(测算结果!H25)<>1,"",测算结果!H25) -> 0 | F25: =IF(AND(测算结果!L25="纳入",C25<>"设备附表",COUNT(D25:E25)=2,D25>0),"可比","不纳入可比") -> 不纳入可比 | G25: =IF(F25="可比",D25,0) -> 0 | H25: =IF(F25="可比",E25,0) -> 0
A27: 可比合计 | G27: =SUM(G6:G25) -> 689280 | H27: =SUM(H6:H25) -> 759685.2
A28: 同口径金额差异率 | D28: =IF(G27<=0,"",H27/G27-1) -> 0.10214311 | F28: 可比资产数 | H28: =COUNTIFS(F6:F25,"可比") -> 16
A30: 仅汇总两年均有有效年额且口径可比的非设备资产。可比集合会随资料完整性变化，应同时看可比资产数。

Sheet 识别与分组
A2: 用途识别与三类分组
A3: 全部业务数据及依据记录均为模拟。用于试用复算，未核验真实来源。
A5: 资产编码 | B5: 资产名称 | C5: 台账用途 | D5: 识别建议 | E5: 确认实际用途 | F5: 确认状态 | G5: 市场案例池 | H5: 精确案例共享组 | I5: 历史比较组 | J5: 分组复核说明
A6: RP-001 | B6: =IF(COUNTIFS(资产清单!$A$6:$A$25,A6)<>1,"",IF(INDEX(资产清单!$D$6:$D$25,MATCH(A6,资产清单!$A$6:$A$25,0))="","",INDEX(资产清单!$D$6:$D$25,MATCH(A6,资产清单!$A$6:$A$25,0)))) -> 沿街商铺一 | C6: =IF(COUNTIFS(资产清单!$A$6:$A$25,A6)<>1,"",IF(INDEX(资产清单!$F$6:$F$25,MATCH(A6,资产清单!$A$6:$A$25,0))="","",INDEX(资产清单!$F$6:$F$25,MATCH(A6,资产清单!$A$6:$A$25,0)))) -> 商业 | D6: =IF(ISNUMBER(SEARCH("通信基站",IF(COUNTIFS(资产清单!$A$6:$A$25,A6)<>1,"",IF(INDEX(资产清单!$G$6:$G$25,MATCH(A6,资产清单!$A$6:$A$25,0))="","",INDEX(资产清单!$G$6:$G$25,MATCH(A6,资产清单!$A$6:$A$25,0)))))),"通信基站",IF(ISNUMBER(SEARCH("广告",IF(COUNTIFS(资产清单!$A$6:$A$25,A6)<>1,"",IF(INDEX(资产清单!$G$6:$G$25,MATCH(A6,资产清单!$A$6:$A$25,0))="","",INDEX(资产清单!$G$6:$G$25,MATCH(A6,资产清单!$A$6:$A$25,0)))))),"广告位",IF(ISNUMBER(SEARCH("设备",IF(COUNTIFS(资产清单!$A$6:$A$25,A6)<>1,"",IF(INDEX(资产清单!$G$6:$G$25,MATCH(A6,资产清单!$A$6:$A$25,0))="","",INDEX(资产清单!$G$6:$G$25,MATCH(A6,资产清单!$A$6:$A$25,0)))))),"设备",IF(ISNUMBER(SEARCH("停车位",IF(COUNTIFS(资产清单!$A$6:$A$25,A6)<>1,"",IF(INDEX(资产清单!$G$6:$G$25,MATCH(A6,资产清单!$A$6:$A$25,0))="","",INDEX(资产清单!$G$6:$G$25,MATCH(A6,资产清单!$A$6:$A$25,0)))))),"车位",IF(ISNUMBER(SEARCH("内部通道商铺",IF(COUNTIFS(资产清单!$A$6:$A$25,A6)<>1,"",IF(INDEX(资产清单!$G$6:$G$25,MATCH(A6,资产清单!$A$6:$A$25,0))="","",INDEX(资产清单!$G$6:$G$25,MATCH(A6,资产清单!$A$6:$A$25,0)))))),"商业",IF(ISNUMBER(SEARCH("活动场馆",IF(COUNTIFS(资产清单!$A$6:$A$25,A6)<>1,"",IF(INDEX(资产清单!$G$6:$G$25,MATCH(A6,资产清单!$A$6:$A$25,0))="","",INDEX(资产清单!$G$6:$G$25,MATCH(A6,资产清单!$A$6:$A$25,0)))))),"场馆",IF(ISNUMBER(SEARCH("场地",IF(COUNTIFS(资产清单!$A$6:$A$25,A6)<>1,"",IF(INDEX(资产清单!$G$6:$G$25,MATCH(A6,资产清单!$A$6:$A$25,0))="","",INDEX(资产清单!$G$6:$G$25,MATCH(A6,资产清单!$A$6:$A$25,0)))))),"场地",C6))))))) -> 商业 | E6: =IF(COUNTIFS(资产清单!$A$6:$A$25,A6)<>1,"",IF(INDEX(资产清单!$H$6:$H$25,MATCH(A6,资产清单!$A$6:$A$25,0))="","",INDEX(资产清单!$H$6:$H$25,MATCH(A6,资产清单!$A$6:$A$25,0)))) -> 商业 | F6: =IF(E6="","待确认用途",IF(D6=E6,"候选与确认一致","已人工确认差异")) -> 候选与确认一致 | G6: =E6&"|"&IF(COUNTIFS(资产清单!$A$6:$A$25,A6)<>1,"",IF(INDEX(资产清单!$J$6:$J$25,MATCH(A6,资产清单!$A$6:$A$25,0))="","",INDEX(资产清单!$J$6:$J$25,MATCH(A6,资产清单!$A$6:$A$25,0)))) -> 商业|元/㎡/月 | H6: =IF(COUNTIFS(资产清单!$A$6:$A$25,A6)<>1,"",IF(INDEX(资产清单!$E$6:$E$25,MATCH(A6,资产清单!$A$6:$A$25,0))="","",INDEX(资产清单!$E$6:$E$25,MATCH(A6,资产清单!$A$6:$A$25,0))))&"|"&E6&"|"&IF(COUNTIFS(资产清单!$A$6:$A$25,A6)<>1,"",IF(INDEX(资产清单!$I$6:$I$25,MATCH(A6,资产清单!$A$6:$A$25,0))="","",INDEX(资产清单!$I$6:$I$25,MATCH(A6,资产清单!$A$6:$A$25,0))))&"|"&IF(COUNTIFS(资产清单!$A$6:$A$25,A6)<>1,"",IF(INDEX(资产清单!$J$6:$J$25,MATCH(A6,资产清单!$A$6:$A$25,0))="","",INDEX(资产清单!$J$6:$J$25,MATCH(A6,资产清单!$A$6:$A$25,0))))&"|"&IF(IF(COUNTIFS(资产清单!$A$6:$A$25,A6)<>1,"",IF(COUNT(INDEX(资产清单!$M$6:$M$25,MATCH(A6,资产清单!$A$6:$A$25,0)))<>1,"",INDEX(资产清单!$M$6:$M$25,MATCH(A6,资产清单!$A$6:$A$25,0))))="","不适用",IF(COUNTIFS(资产清单!$A$6:$A$25,A6)<>1,"",IF(COUNT(INDEX(资产清单!$M$6:$M$25,MATCH(A6,资产清单!$A$6:$A$25,0)))<>1,"",INDEX(资产清单!$M$6:$M$25,MATCH(A6,资产清单!$A$6:$A$25,0))))) -> 模拟商业楼A|商业|临街商铺|元/㎡/月|1 | I6: =H6 -> 模拟商业楼A|商业|临街商铺|元/㎡/月|1 | J6: 同址同用途同形态同层共享，面积仍逐项修正
A7: RP-002 | B7: =IF(COUNTIFS(资产清单!$A$6:$A$25,A7)<>1,"",IF(INDEX(资产清单!$D$6:$D$25,MATCH(A7,资产清单!$A$6:$A$25,0))="","",INDEX(资产清单!$D$6:$D$25,MATCH(A7,资产清单!$A$6:$A$25,0)))) -> 沿街商铺二 | C7: =IF(COUNTIFS(资产清单!$A$6:$A$25,A7)<>1,"",IF(INDEX(资产清单!$F$6:$F$25,MATCH(A7,资产清单!$A$6:$A$25,0))="","",INDEX(资产清单!$F$6:$F$25,MATCH(A7,资产清单!$A$6:$A$25,0)))) -> 商业 | D7: =IF(ISNUMBER(SEARCH("通信基站",IF(COUNTIFS(资产清单!$A$6:$A$25,A7)<>1,"",IF(INDEX(资产清单!$G$6:$G$25,MATCH(A7,资产清单!$A$6:$A$25,0))="","",INDEX(资产清单!$G$6:$G$25,MATCH(A7,资产清单!$A$6:$A$25,0)))))),"通信基站",IF(ISNUMBER(SEARCH("广告",IF(COUNTIFS(资产清单!$A$6:$A$25,A7)<>1,"",IF(INDEX(资产清单!$G$6:$G$25,MATCH(A7,资产清单!$A$6:$A$25,0))="","",INDEX(资产清单!$G$6:$G$25,MATCH(A7,资产清单!$A$6:$A$25,0)))))),"广告位",IF(ISNUMBER(SEARCH("设备",IF(COUNTIFS(资产清单!$A$6:$A$25,A7)<>1,"",IF(INDEX(资产清单!$G$6:$G$25,MATCH(A7,资产清单!$A$6:$A$25,0))="","",INDEX(资产清单!$G$6:$G$25,MATCH(A7,资产清单!$A$6:$A$25,0)))))),"设备",IF(ISNUMBER(SEARCH("停车位",IF(COUNTIFS(资产清单!$A$6:$A$25,A7)<>1,"",IF(INDEX(资产清单!$G$6:$G$25,MATCH(A7,资产清单!$A$6:$A$25,0))="","",INDEX(资产清单!$G$6:$G$25,MATCH(A7,资产清单!$A$6:$A$25,0)))))),"车位",IF(ISNUMBER(SEARCH("内部通道商铺",IF(COUNTIFS(资产清单!$A$6:$A$25,A7)<>1,"",IF(INDEX(资产清单!$G$6:$G$25,MATCH(A7,资产清单!$A$6:$A$25,0))="","",INDEX(资产清单!$G$6:$G$25,MATCH(A7,资产清单!$A$6:$A$25,0)))))),"商业",IF(ISNUMBER(SEARCH("活动场馆",IF(COUNTIFS(资产清单!$A$6:$A$25,A7)<>1,"",IF(INDEX(资产清单!$G$6:$G$25,MATCH(A7,资产清单!$A$6:$A$25,0))="","",INDEX(资产清单!$G$6:$G$25,MATCH(A7,资产清单!$A$6:$A$25,0)))))),"场馆",IF(ISNUMBER(SEARCH("场地",IF(COUNTIFS(资产清单!$A$6:$A$25,A7)<>1,"",IF(INDEX(资产清单!$G$6:$G$25,MATCH(A7,资产清单!$A$6:$A$25,0))="","",INDEX(资产清单!$G$6:$G$25,MATCH(A7,资产清单!$A$6:$A$25,0)))))),"场地",C7))))))) -> 商业 | E7: =IF(COUNTIFS(资产清单!$A$6:$A$25,A7)<>1,"",IF(INDEX(资产清单!$H$6:$H$25,MATCH(A7,资产清单!$A$6:$A$25,0))="","",INDEX(资产清单!$H$6:$H$25,MATCH(A7,资产清单!$A$6:$A$25,0)))) -> 商业 | F7: =IF(E7="","待确认用途",IF(D7=E7,"候选与确认一致","已人工确认差异")) -> 候选与确认一致 | G7: =E7&"|"&IF(COUNTIFS(资产清单!$A$6:$A$25,A7)<>1,"",IF(INDEX(资产清单!$J$6:$J$25,MATCH(A7,资产清单!$A$6:$A$25,0))="","",INDEX(资产清单!$J$6:$J$25,MATCH(A7,资产清单!$A$6:$A$25,0)))) -> 商业|元/㎡/月 | H7: =IF(COUNTIFS(资产清单!$A$6:$A$25,A7)<>1,"",IF(INDEX(资产清单!$E$6:$E$25,MATCH(A7,资产清单!$A$6:$A$25,0))="","",INDEX(资产清单!$E$6:$E$25,MATCH(A7,资产清单!$A$6:$A$25,0))))&"|"&E7&"|"&IF(COUNTIFS(资产清单!$A$6:$A$25,A7)<>1,"",IF(INDEX(资产清单!$I$6:$I$25,MATCH(A7,资产清单!$A$6:$A$25,0))="","",INDEX(资产清单!$I$6:$I$25,MATCH(A7,资产清单!$A$6:$A$25,0))))&"|"&IF(COUNTIFS(资产清单!$A$6:$A$25,A7)<>1,"",IF(INDEX(资产清单!$J$6:$J$25,MATCH(A7,资产清单!$A$6:$A$25,0))="","",INDEX(资产清单!$J$6:$J$25,MATCH(A7,资产清单!$A$6:$A$25,0))))&"|"&IF(IF(COUNTIFS(资产清单!$A$6:$A$25,A7)<>1,"",IF(COUNT(INDEX(资产清单!$M$6:$M$25,MATCH(A7,资产清单!$A$6:$A$25,0)))<>1,"",INDEX(资产清单!$M$6:$M$25,MATCH(A7,资产清单!$A$6:$A$25,0))))="","不适用",IF(COUNTIFS(资产清单!$A$6:$A$25,A7)<>1,"",IF(COUNT(INDEX(资产清单!$M$6:$M$25,MATCH(A7,资产清单!$A$6:$A$25,0)))<>1,"",INDEX(资产清单!$M$6:$M$25,MATCH(A7,资产清单!$A$6:$A$25,0))))) -> 模拟商业楼A|商业|临街商铺|元/㎡/月|1 | I7: =H7 -> 模拟商业楼A|商业|临街商铺|元/㎡/月|1 | J7: 同址同用途同形态同层共享，面积仍逐项修正
A8: RP-003 | B8: =IF(COUNTIFS(资产清单!$A$6:$A$25,A8)<>1,"",IF(INDEX(资产清单!$D$6:$D$25,MATCH(A8,资产清单!$A$6:$A$25,0))="","",INDEX(资产清单!$D$6:$D$25,MATCH(A8,资产清单!$A$6:$A$25,0)))) -> 二层商铺 | C8: =IF(COUNTIFS(资产清单!$A$6:$A$25,A8)<>1,"",IF(INDEX(资产清单!$F$6:$F$25,MATCH(A8,资产清单!$A$6:$A$25,0))="","",INDEX(资产清单!$F$6:$F$25,MATCH(A8,资产清单!$A$6:$A$25,0)))) -> 商业 | D8: =IF(ISNUMBER(SEARCH("通信基站",IF(COUNTIFS(资产清单!$A$6:$A$25,A8)<>1,"",IF(INDEX(资产清单!$G$6:$G$25,MATCH(A8,资产清单!$A$6:$A$25,0))="","",INDEX(资产清单!$G$6:$G$25,MATCH(A8,资产清单!$A$6:$A$25,0)))))),"通信基站",IF(ISNUMBER(SEARCH("广告",IF(COUNTIFS(资产清单!$A$6:$A$25,A8)<>1,"",IF(INDEX(资产清单!$G$6:$G$25,MATCH(A8,资产清单!$A$6:$A$25,0))="","",INDEX(资产清单!$G$6:$G$25,MATCH(A8,资产清单!$A$6:$A$25,0)))))),"广告位",IF(ISNUMBER(SEARCH("设备",IF(COUNTIFS(资产清单!$A$6:$A$25,A8)<>1,"",IF(INDEX(资产清单!$G$6:$G$25,MATCH(A8,资产清单!$A$6:$A$25,0))="","",INDEX(资产清单!$G$6:$G$25,MATCH(A8,资产清单!$A$6:$A$25,0)))))),"设备",IF(ISNUMBER(SEARCH("停车位",IF(COUNTIFS(资产清单!$A$6:$A$25,A8)<>1,"",IF(INDEX(资产清单!$G$6:$G$25,MATCH(A8,资产清单!$A$6:$A$25,0))="","",INDEX(资产清单!$G$6:$G$25,MATCH(A8,资产清单!$A$6:$A$25,0)))))),"车位",IF(ISNUMBER(SEARCH("内部通道商铺",IF(COUNTIFS(资产清单!$A$6:$A$25,A8)<>1,"",IF(INDEX(资产清单!$G$6:$G$25,MATCH(A8,资产清单!$A$6:$A$25,0))="","",INDEX(资产清单!$G$6:$G$25,MATCH(A8,资产清单!$A$6:$A$25,0)))))),"商业",IF(ISNUMBER(SEARCH("活动场馆",IF(COUNTIFS(资产清单!$A$6:$A$25,A8)<>1,"",IF(INDEX(资产清单!$G$6:$G$25,MATCH(A8,资产清单!$A$6:$A$25,0))="","",INDEX(资产清单!$G$6:$G$25,MATCH(A8,资产清单!$A$6:$A$25,0)))))),"场馆",IF(ISNUMBER(SEARCH("场地",IF(COUNTIFS(资产清单!$A$6:$A$25,A8)<>1,"",IF(INDEX(资产清单!$G$6:$G$25,MATCH(A8,资产清单!$A$6:$A$25,0))="","",INDEX(资产清单!$G$6:$G$25,MATCH(A8,资产清单!$A$6:$A$25,0)))))),"场地",C8))))))) -> 商业 | E8: =IF(COUNTIFS(资产清单!$A$6:$A$25,A8)<>1,"",IF(INDEX(资产清单!$H$6:$H$25,MATCH(A8,资产清单!$A$6:$A$25,0))="","",INDEX(资产清单!$H$6:$H$25,MATCH(A8,资产清单!$A$6:$A$25,0)))) -> 商业 | F8: =IF(E8="","待确认用途",IF(D8=E8,"候选与确认一致","已人工确认差异")) -> 候选与确认一致 | G8: =E8&"|"&IF(COUNTIFS(资产清单!$A$6:$A$25,A8)<>1,"",IF(INDEX(资产清单!$J$6:$J$25,MATCH(A8,资产清单!$A$6:$A$25,0))="","",INDEX(资产清单!$J$6:$J$25,MATCH(A8,资产清单!$A$6:$A$25,0)))) -> 商业|元/㎡/月 | H8: =IF(COUNTIFS(资产清单!$A$6:$A$25,A8)<>1,"",IF(INDEX(资产清单!$E$6:$E$25,MATCH(A8,资产清单!$A$6:$A$25,0))="","",INDEX(资产清单!$E$6:$E$25,MATCH(A8,资产清单!$A$6:$A$25,0))))&"|"&E8&"|"&IF(COUNTIFS(资产清单!$A$6:$A$25,A8)<>1,"",IF(INDEX(资产清单!$I$6:$I$25,MATCH(A8,资产清单!$A$6:$A$25,0))="","",INDEX(资产清单!$I$6:$I$25,MATCH(A8,资产清单!$A$6:$A$25,0))))&"|"&IF(COUNTIFS(资产清单!$A$6:$A$25,A8)<>1,"",IF(INDEX(资产清单!$J$6:$J$25,MATCH(A8,资产清单!$A$6:$A$25,0))="","",INDEX(资产清单!$J$6:$J$25,MATCH(A8,资产清单!$A$6:$A$25,0))))&"|"&IF(IF(COUNTIFS(资产清单!$A$6:$A$25,A8)<>1,"",IF(COUNT(INDEX(资产清单!$M$6:$M$25,MATCH(A8,资产清单!$A$6:$A$25,0)))<>1,"",INDEX(资产清单!$M$6:$M$25,MATCH(A8,资产清单!$A$6:$A$25,0))))="","不适用",IF(COUNTIFS(资产清单!$A$6:$A$25,A8)<>1,"",IF(COUNT(INDEX(资产清单!$M$6:$M$25,MATCH(A8,资产清单!$A$6:$A$25,0)))<>1,"",INDEX(资产清单!$M$6:$M$25,MATCH(A8,资产清单!$A$6:$A$25,0))))) -> 模拟商业楼A|商业|临街商铺|元/㎡/月|2 | I8: =H8 -> 模拟商业楼A|商业|临街商铺|元/㎡/月|2 | J8: 与一层分组分开
A9: RP-004 | B9: =IF(COUNTIFS(资产清单!$A$6:$A$25,A9)<>1,"",IF(INDEX(资产清单!$D$6:$D$25,MATCH(A9,资产清单!$A$6:$A$25,0))="","",INDEX(资产清单!$D$6:$D$25,MATCH(A9,资产清单!$A$6:$A$25,0)))) -> 内部通道商铺 | C9: =IF(COUNTIFS(资产清单!$A$6:$A$25,A9)<>1,"",IF(INDEX(资产清单!$F$6:$F$25,MATCH(A9,资产清单!$A$6:$A$25,0))="","",INDEX(资产清单!$F$6:$F$25,MATCH(A9,资产清单!$A$6:$A$25,0)))) -> 办公 | D9: =IF(ISNUMBER(SEARCH("通信基站",IF(COUNTIFS(资产清单!$A$6:$A$25,A9)<>1,"",IF(INDEX(资产清单!$G$6:$G$25,MATCH(A9,资产清单!$A$6:$A$25,0))="","",INDEX(资产清单!$G$6:$G$25,MATCH(A9,资产清单!$A$6:$A$25,0)))))),"通信基站",IF(ISNUMBER(SEARCH("广告",IF(COUNTIFS(资产清单!$A$6:$A$25,A9)<>1,"",IF(INDEX(资产清单!$G$6:$G$25,MATCH(A9,资产清单!$A$6:$A$25,0))="","",INDEX(资产清单!$G$6:$G$25,MATCH(A9,资产清单!$A$6:$A$25,0)))))),"广告位",IF(ISNUMBER(SEARCH("设备",IF(COUNTIFS(资产清单!$A$6:$A$25,A9)<>1,"",IF(INDEX(资产清单!$G$6:$G$25,MATCH(A9,资产清单!$A$6:$A$25,0))="","",INDEX(资产清单!$G$6:$G$25,MATCH(A9,资产清单!$A$6:$A$25,0)))))),"设备",IF(ISNUMBER(SEARCH("停车位",IF(COUNTIFS(资产清单!$A$6:$A$25,A9)<>1,"",IF(INDEX(资产清单!$G$6:$G$25,MATCH(A9,资产清单!$A$6:$A$25,0))="","",INDEX(资产清单!$G$6:$G$25,MATCH(A9,资产清单!$A$6:$A$25,0)))))),"车位",IF(ISNUMBER(SEARCH("内部通道商铺",IF(COUNTIFS(资产清单!$A$6:$A$25,A9)<>1,"",IF(INDEX(资产清单!$G$6:$G$25,MATCH(A9,资产清单!$A$6:$A$25,0))="","",INDEX(资产清单!$G$6:$G$25,MATCH(A9,资产清单!$A$6:$A$25,0)))))),"商业",IF(ISNUMBER(SEARCH("活动场馆",IF(COUNTIFS(资产清单!$A$6:$A$25,A9)<>1,"",IF(INDEX(资产清单!$G$6:$G$25,MATCH(A9,资产清单!$A$6:$A$25,0))="","",INDEX(资产清单!$G$6:$G$25,MATCH(A9,资产清单!$A$6:$A$25,0)))))),"场馆",IF(ISNUMBER(SEARCH("场地",IF(COUNTIFS(资产清单!$A$6:$A$25,A9)<>1,"",IF(INDEX(资产清单!$G$6:$G$25,MATCH(A9,资产清单!$A$6:$A$25,0))="","",INDEX(资产清单!$G$6:$G$25,MATCH(A9,资产清单!$A$6:$A$25,0)))))),"场地",C9))))))) -> 商业 | E9: =IF(COUNTIFS(资产清单!$A$6:$A$25,A9)<>1,"",IF(INDEX(资产清单!$H$6:$H$25,MATCH(A9,资产清单!$A$6:$A$25,0))="","",INDEX(资产清单!$H$6:$H$25,MATCH(A9,资产清单!$A$6:$A$25,0)))) -> 商业 | F9: =IF(E9="","待确认用途",IF(D9=E9,"候选与确认一致","已人工确认差异")) -> 候选与确认一致 | G9: =E9&"|"&IF(COUNTIFS(资产清单!$A$6:$A$25,A9)<>1,"",IF(INDEX(资产清单!$J$6:$J$25,MATCH(A9,资产清单!$A$6:$A$25,0))="","",INDEX(资产清单!$J$6:$J$25,MATCH(A9,资产清单!$A$6:$A$25,0)))) -> 商业|元/㎡/月 | H9: =IF(COUNTIFS(资产清单!$A$6:$A$25,A9)<>1,"",IF(INDEX(资产清单!$E$6:$E$25,MATCH(A9,资产清单!$A$6:$A$25,0))="","",INDEX(资产清单!$E$6:$E$25,MATCH(A9,资产清单!$A$6:$A$25,0))))&"|"&E9&"|"&IF(COUNTIFS(资产清单!$A$6:$A$25,A9)<>1,"",IF(INDEX(资产清单!$I$6:$I$25,MATCH(A9,资产清单!$A$6:$A$25,0))="","",INDEX(资产清单!$I$6:$I$25,MATCH(A9,资产清单!$A$6:$A$25,0))))&"|"&IF(COUNTIFS(资产清单!$A$6:$A$25,A9)<>1,"",IF(INDEX(资产清单!$J$6:$J$25,MATCH(A9,资产清单!$A$6:$A$25,0))="","",INDEX(资产清单!$J$6:$J$25,MATCH(A9,资产清单!$A$6:$A$25,0))))&"|"&IF(IF(COUNTIFS(资产清单!$A$6:$A$25,A9)<>1,"",IF(COUNT(INDEX(资产清单!$M$6:$M$25,MATCH(A9,资产清单!$A$6:$A$25,0)))<>1,"",INDEX(资产清单!$M$6:$M$25,MATCH(A9,资产清单!$A$6:$A$25,0))))="","不适用",IF(COUNTIFS(资产清单!$A$6:$A$25,A9)<>1,"",IF(COUNT(INDEX(资产清单!$M$6:$M$25,MATCH(A9,资产清单!$A$6:$A$25,0)))<>1,"",INDEX(资产清单!$M$6:$M$25,MATCH(A9,资产清单!$A$6:$A$25,0))))) -> 模拟商业楼B|商业|内部通道商铺|元/㎡/月|1 | I9: =H9 -> 模拟商业楼B|商业|内部通道商铺|元/㎡/月|1 | J9: 内部通道与临街物业分组分开
A10: RP-005 | B10: =IF(COUNTIFS(资产清单!$A$6:$A$25,A10)<>1,"",IF(INDEX(资产清单!$D$6:$D$25,MATCH(A10,资产清单!$A$6:$A$25,0))="","",INDEX(资产清单!$D$6:$D$25,MATCH(A10,资产清单!$A$6:$A$25,0)))) -> 办公用房一 | C10: =IF(COUNTIFS(资产清单!$A$6:$A$25,A10)<>1,"",IF(INDEX(资产清单!$F$6:$F$25,MATCH(A10,资产清单!$A$6:$A$25,0))="","",INDEX(资产清单!$F$6:$F$25,MATCH(A10,资产清单!$A$6:$A$25,0)))) -> 办公 | D10: =IF(ISNUMBER(SEARCH("通信基站",IF(COUNTIFS(资产清单!$A$6:$A$25,A10)<>1,"",IF(INDEX(资产清单!$G$6:$G$25,MATCH(A10,资产清单!$A$6:$A$25,0))="","",INDEX(资产清单!$G$6:$G$25,MATCH(A10,资产清单!$A$6:$A$25,0)))))),"通信基站",IF(ISNUMBER(SEARCH("广告",IF(COUNTIFS(资产清单!$A$6:$A$25,A10)<>1,"",IF(INDEX(资产清单!$G$6:$G$25,MATCH(A10,资产清单!$A$6:$A$25,0))="","",INDEX(资产清单!$G$6:$G$25,MATCH(A10,资产清单!$A$6:$A$25,0)))))),"广告位",IF(ISNUMBER(SEARCH("设备",IF(COUNTIFS(资产清单!$A$6:$A$25,A10)<>1,"",IF(INDEX(资产清单!$G$6:$G$25,MATCH(A10,资产清单!$A$6:$A$25,0))="","",INDEX(资产清单!$G$6:$G$25,MATCH(A10,资产清单!$A$6:$A$25,0)))))),"设备",IF(ISNUMBER(SEARCH("停车位",IF(COUNTIFS(资产清单!$A$6:$A$25,A10)<>1,"",IF(INDEX(资产清单!$G$6:$G$25,MATCH(A10,资产清单!$A$6:$A$25,0))="","",INDEX(资产清单!$G$6:$G$25,MATCH(A10,资产清单!$A$6:$A$25,0)))))),"车位",IF(ISNUMBER(SEARCH("内部通道商铺",IF(COUNTIFS(资产清单!$A$6:$A$25,A10)<>1,"",IF(INDEX(资产清单!$G$6:$G$25,MATCH(A10,资产清单!$A$6:$A$25,0))="","",INDEX(资产清单!$G$6:$G$25,MATCH(A10,资产清单!$A$6:$A$25,0)))))),"商业",IF(ISNUMBER(SEARCH("活动场馆",IF(COUNTIFS(资产清单!$A$6:$A$25,A10)<>1,"",IF(INDEX(资产清单!$G$6:$G$25,MATCH(A10,资产清单!$A$6:$A$25,0))="","",INDEX(资产清单!$G$6:$G$25,MATCH(A10,资产清单!$A$6:$A$25,0)))))),"场馆",IF(ISNUMBER(SEARCH("场地",IF(COUNTIFS(资产清单!$A$6:$A$25,A10)<>1,"",IF(INDEX(资产清单!$G$6:$G$25,MATCH(A10,资产清单!$A$6:$A$25,0))="","",INDEX(资产清单!$G$6:$G$25,MATCH(A10,资产清单!$A$6:$A$25,0)))))),"场地",C10))))))) -> 办公 | E10: =IF(COUNTIFS(资产清单!$A$6:$A$25,A10)<>1,"",IF(INDEX(资产清单!$H$6:$H$25,MATCH(A10,资产清单!$A$6:$A$25,0))="","",INDEX(资产清单!$H$6:$H$25,MATCH(A10,资产清单!$A$6:$A$25,0)))) -> 办公 | F10: =IF(E10="","待确认用途",IF(D10=E10,"候选与确认一致","已人工确认差异")) -> 候选与确认一致 | G10: =E10&"|"&IF(COUNTIFS(资产清单!$A$6:$A$25,A10)<>1,"",IF(INDEX(资产清单!$J$6:$J$25,MATCH(A10,资产清单!$A$6:$A$25,0))="","",INDEX(资产清单!$J$6:$J$25,MATCH(A10,资产清单!$A$6:$A$25,0)))) -> 办公|元/㎡/月 | H10: =IF(COUNTIFS(资产清单!$A$6:$A$25,A10)<>1,"",IF(INDEX(资产清单!$E$6:$E$25,MATCH(A10,资产清单!$A$6:$A$25,0))="","",INDEX(资产清单!$E$6:$E$25,MATCH(A10,资产清单!$A$6:$A$25,0))))&"|"&E10&"|"&IF(COUNTIFS(资产清单!$A$6:$A$25,A10)<>1,"",IF(INDEX(资产清单!$I$6:$I$25,MATCH(A10,资产清单!$A$6:$A$25,0))="","",INDEX(资产清单!$I$6:$I$25,MATCH(A10,资产清单!$A$6:$A$25,0))))&"|"&IF(COUNTIFS(资产清单!$A$6:$A$25,A10)<>1,"",IF(INDEX(资产清单!$J$6:$J$25,MATCH(A10,资产清单!$A$6:$A$25,0))="","",INDEX(资产清单!$J$6:$J$25,MATCH(A10,资产清单!$A$6:$A$25,0))))&"|"&IF(IF(COUNTIFS(资产清单!$A$6:$A$25,A10)<>1,"",IF(COUNT(INDEX(资产清单!$M$6:$M$25,MATCH(A10,资产清单!$A$6:$A$25,0)))<>1,"",INDEX(资产清单!$M$6:$M$25,MATCH(A10,资产清单!$A$6:$A$25,0))))="","不适用",IF(COUNTIFS(资产清单!$A$6:$A$25,A10)<>1,"",IF(COUNT(INDEX(资产清单!$M$6:$M$25,MATCH(A10,资产清单!$A$6:$A$25,0)))<>1,"",INDEX(资产清单!$M$6:$M$25,MATCH(A10,资产清单!$A$6:$A$25,0))))) -> 模拟办公楼C|办公|办公用房|元/㎡/月|3 | I10: =H10 -> 模拟办公楼C|办公|办公用房|元/㎡/月|3 | J10: 历史差价不作为拆分组依据
A11: RP-006 | B11: =IF(COUNTIFS(资产清单!$A$6:$A$25,A11)<>1,"",IF(INDEX(资产清单!$D$6:$D$25,MATCH(A11,资产清单!$A$6:$A$25,0))="","",INDEX(资产清单!$D$6:$D$25,MATCH(A11,资产清单!$A$6:$A$25,0)))) -> 办公用房二 | C11: =IF(COUNTIFS(资产清单!$A$6:$A$25,A11)<>1,"",IF(INDEX(资产清单!$F$6:$F$25,MATCH(A11,资产清单!$A$6:$A$25,0))="","",INDEX(资产清单!$F$6:$F$25,MATCH(A11,资产清单!$A$6:$A$25,0)))) -> 办公 | D11: =IF(ISNUMBER(SEARCH("通信基站",IF(COUNTIFS(资产清单!$A$6:$A$25,A11)<>1,"",IF(INDEX(资产清单!$G$6:$G$25,MATCH(A11,资产清单!$A$6:$A$25,0))="","",INDEX(资产清单!$G$6:$G$25,MATCH(A11,资产清单!$A$6:$A$25,0)))))),"通信基站",IF(ISNUMBER(SEARCH("广告",IF(COUNTIFS(资产清单!$A$6:$A$25,A11)<>1,"",IF(INDEX(资产清单!$G$6:$G$25,MATCH(A11,资产清单!$A$6:$A$25,0))="","",INDEX(资产清单!$G$6:$G$25,MATCH(A11,资产清单!$A$6:$A$25,0)))))),"广告位",IF(ISNUMBER(SEARCH("设备",IF(COUNTIFS(资产清单!$A$6:$A$25,A11)<>1,"",IF(INDEX(资产清单!$G$6:$G$25,MATCH(A11,资产清单!$A$6:$A$25,0))="","",INDEX(资产清单!$G$6:$G$25,MATCH(A11,资产清单!$A$6:$A$25,0)))))),"设备",IF(ISNUMBER(SEARCH("停车位",IF(COUNTIFS(资产清单!$A$6:$A$25,A11)<>1,"",IF(INDEX(资产清单!$G$6:$G$25,MATCH(A11,资产清单!$A$6:$A$25,0))="","",INDEX(资产清单!$G$6:$G$25,MATCH(A11,资产清单!$A$6:$A$25,0)))))),"车位",IF(ISNUMBER(SEARCH("内部通道商铺",IF(COUNTIFS(资产清单!$A$6:$A$25,A11)<>1,"",IF(INDEX(资产清单!$G$6:$G$25,MATCH(A11,资产清单!$A$6:$A$25,0))="","",INDEX(资产清单!$G$6:$G$25,MATCH(A11,资产清单!$A$6:$A$25,0)))))),"商业",IF(ISNUMBER(SEARCH("活动场馆",IF(COUNTIFS(资产清单!$A$6:$A$25,A11)<>1,"",IF(INDEX(资产清单!$G$6:$G$25,MATCH(A11,资产清单!$A$6:$A$25,0))="","",INDEX(资产清单!$G$6:$G$25,MATCH(A11,资产清单!$A$6:$A$25,0)))))),"场馆",IF(ISNUMBER(SEARCH("场地",IF(COUNTIFS(资产清单!$A$6:$A$25,A11)<>1,"",IF(INDEX(资产清单!$G$6:$G$25,MATCH(A11,资产清单!$A$6:$A$25,0))="","",INDEX(资产清单!$G$6:$G$25,MATCH(A11,资产清单!$A$6:$A$25,0)))))),"场地",C11))))))) -> 办公 | E11: =IF(COUNTIFS(资产清单!$A$6:$A$25,A11)<>1,"",IF(INDEX(资产清单!$H$6:$H$25,MATCH(A11,资产清单!$A$6:$A$25,0))="","",INDEX(资产清单!$H$6:$H$25,MATCH(A11,资产清单!$A$6:$A$25,0)))) -> 办公 | F11: =IF(E11="","待确认用途",IF(D11=E11,"候选与确认一致","已人工确认差异")) -> 候选与确认一致 | G11: =E11&"|"&IF(COUNTIFS(资产清单!$A$6:$A$25,A11)<>1,"",IF(INDEX(资产清单!$J$6:$J$25,MATCH(A11,资产清单!$A$6:$A$25,0))="","",INDEX(资产清单!$J$6:$J$25,MATCH(A11,资产清单!$A$6:$A$25,0)))) -> 办公|元/㎡/月 | H11: =IF(COUNTIFS(资产清单!$A$6:$A$25,A11)<>1,"",IF(INDEX(资产清单!$E$6:$E$25,MATCH(A11,资产清单!$A$6:$A$25,0))="","",INDEX(资产清单!$E$6:$E$25,MATCH(A11,资产清单!$A$6:$A$25,0))))&"|"&E11&"|"&IF(COUNTIFS(资产清单!$A$6:$A$25,A11)<>1,"",IF(INDEX(资产清单!$I$6:$I$25,MATCH(A11,资产清单!$A$6:$A$25,0))="","",INDEX(资产清单!$I$6:$I$25,MATCH(A11,资产清单!$A$6:$A$25,0))))&"|"&IF(COUNTIFS(资产清单!$A$6:$A$25,A11)<>1,"",IF(INDEX(资产清单!$J$6:$J$25,MATCH(A11,资产清单!$A$6:$A$25,0))="","",INDEX(资产清单!$J$6:$J$25,MATCH(A11,资产清单!$A$6:$A$25,0))))&"|"&IF(IF(COUNTIFS(资产清单!$A$6:$A$25,A11)<>1,"",IF(COUNT(INDEX(资产清单!$M$6:$M$25,MATCH(A11,资产清单!$A$6:$A$25,0)))<>1,"",INDEX(资产清单!$M$6:$M$25,MATCH(A11,资产清单!$A$6:$A$25,0))))="","不适用",IF(COUNTIFS(资产清单!$A$6:$A$25,A11)<>1,"",IF(COUNT(INDEX(资产清单!$M$6:$M$25,MATCH(A11,资产清单!$A$6:$A$25,0)))<>1,"",INDEX(资产清单!$M$6:$M$25,MATCH(A11,资产清单!$A$6:$A$25,0))))) -> 模拟办公楼C|办公|办公用房|元/㎡/月|3 | I11: =H11 -> 模拟办公楼C|办公|办公用房|元/㎡/月|3 | J11: 历史差价不作为拆分组依据
A12: RP-007 | B12: =IF(COUNTIFS(资产清单!$A$6:$A$25,A12)<>1,"",IF(INDEX(资产清单!$D$6:$D$25,MATCH(A12,资产清单!$A$6:$A$25,0))="","",INDEX(资产清单!$D$6:$D$25,MATCH(A12,资产清单!$A$6:$A$25,0)))) -> 仓储库房 | C12: =IF(COUNTIFS(资产清单!$A$6:$A$25,A12)<>1,"",IF(INDEX(资产清单!$F$6:$F$25,MATCH(A12,资产清单!$A$6:$A$25,0))="","",INDEX(资产清单!$F$6:$F$25,MATCH(A12,资产清单!$A$6:$A$25,0)))) -> 仓储 | D12: =IF(ISNUMBER(SEARCH("通信基站",IF(COUNTIFS(资产清单!$A$6:$A$25,A12)<>1,"",IF(INDEX(资产清单!$G$6:$G$25,MATCH(A12,资产清单!$A$6:$A$25,0))="","",INDEX(资产清单!$G$6:$G$25,MATCH(A12,资产清单!$A$6:$A$25,0)))))),"通信基站",IF(ISNUMBER(SEARCH("广告",IF(COUNTIFS(资产清单!$A$6:$A$25,A12)<>1,"",IF(INDEX(资产清单!$G$6:$G$25,MATCH(A12,资产清单!$A$6:$A$25,0))="","",INDEX(资产清单!$G$6:$G$25,MATCH(A12,资产清单!$A$6:$A$25,0)))))),"广告位",IF(ISNUMBER(SEARCH("设备",IF(COUNTIFS(资产清单!$A$6:$A$25,A12)<>1,"",IF(INDEX(资产清单!$G$6:$G$25,MATCH(A12,资产清单!$A$6:$A$25,0))="","",INDEX(资产清单!$G$6:$G$25,MATCH(A12,资产清单!$A$6:$A$25,0)))))),"设备",IF(ISNUMBER(SEARCH("停车位",IF(COUNTIFS(资产清单!$A$6:$A$25,A12)<>1,"",IF(INDEX(资产清单!$G$6:$G$25,MATCH(A12,资产清单!$A$6:$A$25,0))="","",INDEX(资产清单!$G$6:$G$25,MATCH(A12,资产清单!$A$6:$A$25,0)))))),"车位",IF(ISNUMBER(SEARCH("内部通道商铺",IF(COUNTIFS(资产清单!$A$6:$A$25,A12)<>1,"",IF(INDEX(资产清单!$G$6:$G$25,MATCH(A12,资产清单!$A$6:$A$25,0))="","",INDEX(资产清单!$G$6:$G$25,MATCH(A12,资产清单!$A$6:$A$25,0)))))),"商业",IF(ISNUMBER(SEARCH("活动场馆",IF(COUNTIFS(资产清单!$A$6:$A$25,A12)<>1,"",IF(INDEX(资产清单!$G$6:$G$25,MATCH(A12,资产清单!$A$6:$A$25,0))="","",INDEX(资产清单!$G$6:$G$25,MATCH(A12,资产清单!$A$6:$A$25,0)))))),"场馆",IF(ISNUMBER(SEARCH("场地",IF(COUNTIFS(资产清单!$A$6:$A$25,A12)<>1,"",IF(INDEX(资产清单!$G$6:$G$25,MATCH(A12,资产清单!$A$6:$A$25,0))="","",INDEX(资产清单!$G$6:$G$25,MATCH(A12,资产清单!$A$6:$A$25,0)))))),"场地",C12))))))) -> 仓储 | E12: =IF(COUNTIFS(资产清单!$A$6:$A$25,A12)<>1,"",IF(INDEX(资产清单!$H$6:$H$25,MATCH(A12,资产清单!$A$6:$A$25,0))="","",INDEX(资产清单!$H$6:$H$25,MATCH(A12,资产清单!$A$6:$A$25,0)))) -> 仓储 | F12: =IF(E12="","待确认用途",IF(D12=E12,"候选与确认一致","已人工确认差异")) -> 候选与确认一致 | G12: =E12&"|"&IF(COUNTIFS(资产清单!$A$6:$A$25,A12)<>1,"",IF(INDEX(资产清单!$J$6:$J$25,MATCH(A12,资产清单!$A$6:$A$25,0))="","",INDEX(资产清单!$J$6:$J$25,MATCH(A12,资产清单!$A$6:$A$25,0)))) -> 仓储|元/㎡/月 | H12: =IF(COUNTIFS(资产清单!$A$6:$A$25,A12)<>1,"",IF(INDEX(资产清单!$E$6:$E$25,MATCH(A12,资产清单!$A$6:$A$25,0))="","",INDEX(资产清单!$E$6:$E$25,MATCH(A12,资产清单!$A$6:$A$25,0))))&"|"&E12&"|"&IF(COUNTIFS(资产清单!$A$6:$A$25,A12)<>1,"",IF(INDEX(资产清单!$I$6:$I$25,MATCH(A12,资产清单!$A$6:$A$25,0))="","",INDEX(资产清单!$I$6:$I$25,MATCH(A12,资产清单!$A$6:$A$25,0))))&"|"&IF(COUNTIFS(资产清单!$A$6:$A$25,A12)<>1,"",IF(INDEX(资产清单!$J$6:$J$25,MATCH(A12,资产清单!$A$6:$A$25,0))="","",INDEX(资产清单!$J$6:$J$25,MATCH(A12,资产清单!$A$6:$A$25,0))))&"|"&IF(IF(COUNTIFS(资产清单!$A$6:$A$25,A12)<>1,"",IF(COUNT(INDEX(资产清单!$M$6:$M$25,MATCH(A12,资产清单!$A$6:$A$25,0)))<>1,"",INDEX(资产清单!$M$6:$M$25,MATCH(A12,资产清单!$A$6:$A$25,0))))="","不适用",IF(COUNTIFS(资产清单!$A$6:$A$25,A12)<>1,"",IF(COUNT(INDEX(资产清单!$M$6:$M$25,MATCH(A12,资产清单!$A$6:$A$25,0)))<>1,"",INDEX(资产清单!$M$6:$M$25,MATCH(A12,资产清单!$A$6:$A$25,0))))) -> 模拟仓储楼D|仓储|仓储用房|元/㎡/月|1 | I12: =H12 -> 模拟仓储楼D|仓储|仓储用房|元/㎡/月|1 | J12: 区域和管理单元不代替市场区位判断
A13: RP-008 | B13: =IF(COUNTIFS(资产清单!$A$6:$A$25,A13)<>1,"",IF(INDEX(资产清单!$D$6:$D$25,MATCH(A13,资产清单!$A$6:$A$25,0))="","",INDEX(资产清单!$D$6:$D$25,MATCH(A13,资产清单!$A$6:$A$25,0)))) -> 工业厂房 | C13: =IF(COUNTIFS(资产清单!$A$6:$A$25,A13)<>1,"",IF(INDEX(资产清单!$F$6:$F$25,MATCH(A13,资产清单!$A$6:$A$25,0))="","",INDEX(资产清单!$F$6:$F$25,MATCH(A13,资产清单!$A$6:$A$25,0)))) -> 厂房 | D13: =IF(ISNUMBER(SEARCH("通信基站",IF(COUNTIFS(资产清单!$A$6:$A$25,A13)<>1,"",IF(INDEX(资产清单!$G$6:$G$25,MATCH(A13,资产清单!$A$6:$A$25,0))="","",INDEX(资产清单!$G$6:$G$25,MATCH(A13,资产清单!$A$6:$A$25,0)))))),"通信基站",IF(ISNUMBER(SEARCH("广告",IF(COUNTIFS(资产清单!$A$6:$A$25,A13)<>1,"",IF(INDEX(资产清单!$G$6:$G$25,MATCH(A13,资产清单!$A$6:$A$25,0))="","",INDEX(资产清单!$G$6:$G$25,MATCH(A13,资产清单!$A$6:$A$25,0)))))),"广告位",IF(ISNUMBER(SEARCH("设备",IF(COUNTIFS(资产清单!$A$6:$A$25,A13)<>1,"",IF(INDEX(资产清单!$G$6:$G$25,MATCH(A13,资产清单!$A$6:$A$25,0))="","",INDEX(资产清单!$G$6:$G$25,MATCH(A13,资产清单!$A$6:$A$25,0)))))),"设备",IF(ISNUMBER(SEARCH("停车位",IF(COUNTIFS(资产清单!$A$6:$A$25,A13)<>1,"",IF(INDEX(资产清单!$G$6:$G$25,MATCH(A13,资产清单!$A$6:$A$25,0))="","",INDEX(资产清单!$G$6:$G$25,MATCH(A13,资产清单!$A$6:$A$25,0)))))),"车位",IF(ISNUMBER(SEARCH("内部通道商铺",IF(COUNTIFS(资产清单!$A$6:$A$25,A13)<>1,"",IF(INDEX(资产清单!$G$6:$G$25,MATCH(A13,资产清单!$A$6:$A$25,0))="","",INDEX(资产清单!$G$6:$G$25,MATCH(A13,资产清单!$A$6:$A$25,0)))))),"商业",IF(ISNUMBER(SEARCH("活动场馆",IF(COUNTIFS(资产清单!$A$6:$A$25,A13)<>1,"",IF(INDEX(资产清单!$G$6:$G$25,MATCH(A13,资产清单!$A$6:$A$25,0))="","",INDEX(资产清单!$G$6:$G$25,MATCH(A13,资产清单!$A$6:$A$25,0)))))),"场馆",IF(ISNUMBER(SEARCH("场地",IF(COUNTIFS(资产清单!$A$6:$A$25,A13)<>1,"",IF(INDEX(资产清单!$G$6:$G$25,MATCH(A13,资产清单!$A$6:$A$25,0))="","",INDEX(资产清单!$G$6:$G$25,MATCH(A13,资产清单!$A$6:$A$25,0)))))),"场地",C13))))))) -> 厂房 | E13: =IF(COUNTIFS(资产清单!$A$6:$A$25,A13)<>1,"",IF(INDEX(资产清单!$H$6:$H$25,MATCH(A13,资产清单!$A$6:$A$25,0))="","",INDEX(资产清单!$H$6:$H$25,MATCH(A13,资产清单!$A$6:$A$25,0)))) -> 厂房 | F13: =IF(E13="","待确认用途",IF(D13=E13,"候选与确认一致","已人工确认差异")) -> 候选与确认一致 | G13: =E13&"|"&IF(COUNTIFS(资产清单!$A$6:$A$25,A13)<>1,"",IF(INDEX(资产清单!$J$6:$J$25,MATCH(A13,资产清单!$A$6:$A$25,0))="","",INDEX(资产清单!$J$6:$J$25,MATCH(A13,资产清单!$A$6:$A$25,0)))) -> 厂房|元/㎡/月 | H13: =IF(COUNTIFS(资产清单!$A$6:$A$25,A13)<>1,"",IF(INDEX(资产清单!$E$6:$E$25,MATCH(A13,资产清单!$A$6:$A$25,0))="","",INDEX(资产清单!$E$6:$E$25,MATCH(A13,资产清单!$A$6:$A$25,0))))&"|"&E13&"|"&IF(COUNTIFS(资产清单!$A$6:$A$25,A13)<>1,"",IF(INDEX(资产清单!$I$6:$I$25,MATCH(A13,资产清单!$A$6:$A$25,0))="","",INDEX(资产清单!$I$6:$I$25,MATCH(A13,资产清单!$A$6:$A$25,0))))&"|"&IF(COUNTIFS(资产清单!$A$6:$A$25,A13)<>1,"",IF(INDEX(资产清单!$J$6:$J$25,MATCH(A13,资产清单!$A$6:$A$25,0))="","",INDEX(资产清单!$J$6:$J$25,MATCH(A13,资产清单!$A$6:$A$25,0))))&"|"&IF(IF(COUNTIFS(资产清单!$A$6:$A$25,A13)<>1,"",IF(COUNT(INDEX(资产清单!$M$6:$M$25,MATCH(A13,资产清单!$A$6:$A$25,0)))<>1,"",INDEX(资产清单!$M$6:$M$25,MATCH(A13,资产清单!$A$6:$A$25,0))))="","不适用",IF(COUNTIFS(资产清单!$A$6:$A$25,A13)<>1,"",IF(COUNT(INDEX(资产清单!$M$6:$M$25,MATCH(A13,资产清单!$A$6:$A$25,0)))<>1,"",INDEX(资产清单!$M$6:$M$25,MATCH(A13,资产清单!$A$6:$A$25,0))))) -> 模拟工业园E|厂房|工业厂房|元/㎡/月|1 | I13: =H13 -> 模拟工业园E|厂房|工业厂房|元/㎡/月|1 | J13: 区域和管理单元不代替市场区位判断
A14: RP-009 | B14: =IF(COUNTIFS(资产清单!$A$6:$A$25,A14)<>1,"",IF(INDEX(资产清单!$D$6:$D$25,MATCH(A14,资产清单!$A$6:$A$25,0))="","",INDEX(资产清单!$D$6:$D$25,MATCH(A14,资产清单!$A$6:$A$25,0)))) -> 露天场地 | C14: =IF(COUNTIFS(资产清单!$A$6:$A$25,A14)<>1,"",IF(INDEX(资产清单!$F$6:$F$25,MATCH(A14,资产清单!$A$6:$A$25,0))="","",INDEX(资产清单!$F$6:$F$25,MATCH(A14,资产清单!$A$6:$A$25,0)))) -> 场地 | D14: =IF(ISNUMBER(SEARCH("通信基站",IF(COUNTIFS(资产清单!$A$6:$A$25,A14)<>1,"",IF(INDEX(资产清单!$G$6:$G$25,MATCH(A14,资产清单!$A$6:$A$25,0))="","",INDEX(资产清单!$G$6:$G$25,MATCH(A14,资产清单!$A$6:$A$25,0)))))),"通信基站",IF(ISNUMBER(SEARCH("广告",IF(COUNTIFS(资产清单!$A$6:$A$25,A14)<>1,"",IF(INDEX(资产清单!$G$6:$G$25,MATCH(A14,资产清单!$A$6:$A$25,0))="","",INDEX(资产清单!$G$6:$G$25,MATCH(A14,资产清单!$A$6:$A$25,0)))))),"广告位",IF(ISNUMBER(SEARCH("设备",IF(COUNTIFS(资产清单!$A$6:$A$25,A14)<>1,"",IF(INDEX(资产清单!$G$6:$G$25,MATCH(A14,资产清单!$A$6:$A$25,0))="","",INDEX(资产清单!$G$6:$G$25,MATCH(A14,资产清单!$A$6:$A$25,0)))))),"设备",IF(ISNUMBER(SEARCH("停车位",IF(COUNTIFS(资产清单!$A$6:$A$25,A14)<>1,"",IF(INDEX(资产清单!$G$6:$G$25,MATCH(A14,资产清单!$A$6:$A$25,0))="","",INDEX(资产清单!$G$6:$G$25,MATCH(A14,资产清单!$A$6:$A$25,0)))))),"车位",IF(ISNUMBER(SEARCH("内部通道商铺",IF(COUNTIFS(资产清单!$A$6:$A$25,A14)<>1,"",IF(INDEX(资产清单!$G$6:$G$25,MATCH(A14,资产清单!$A$6:$A$25,0))="","",INDEX(资产清单!$G$6:$G$25,MATCH(A14,资产清单!$A$6:$A$25,0)))))),"商业",IF(ISNUMBER(SEARCH("活动场馆",IF(COUNTIFS(资产清单!$A$6:$A$25,A14)<>1,"",IF(INDEX(资产清单!$G$6:$G$25,MATCH(A14,资产清单!$A$6:$A$25,0))="","",INDEX(资产清单!$G$6:$G$25,MATCH(A14,资产清单!$A$6:$A$25,0)))))),"场馆",IF(ISNUMBER(SEARCH("场地",IF(COUNTIFS(资产清单!$A$6:$A$25,A14)<>1,"",IF(INDEX(资产清单!$G$6:$G$25,MATCH(A14,资产清单!$A$6:$A$25,0))="","",INDEX(资产清单!$G$6:$G$25,MATCH(A14,资产清单!$A$6:$A$25,0)))))),"场地",C14))))))) -> 场地 | E14: =IF(COUNTIFS(资产清单!$A$6:$A$25,A14)<>1,"",IF(INDEX(资产清单!$H$6:$H$25,MATCH(A14,资产清单!$A$6:$A$25,0))="","",INDEX(资产清单!$H$6:$H$25,MATCH(A14,资产清单!$A$6:$A$25,0)))) -> 场地 | F14: =IF(E14="","待确认用途",IF(D14=E14,"候选与确认一致","已人工确认差异")) -> 候选与确认一致 | G14: =E14&"|"&IF(COUNTIFS(资产清单!$A$6:$A$25,A14)<>1,"",IF(INDEX(资产清单!$J$6:$J$25,MATCH(A14,资产清单!$A$6:$A$25,0))="","",INDEX(资产清单!$J$6:$J$25,MATCH(A14,资产清单!$A$6:$A$25,0)))) -> 场地|元/㎡/月 | H14: =IF(COUNTIFS(资产清单!$A$6:$A$25,A14)<>1,"",IF(INDEX(资产清单!$E$6:$E$25,MATCH(A14,资产清单!$A$6:$A$25,0))="","",INDEX(资产清单!$E$6:$E$25,MATCH(A14,资产清单!$A$6:$A$25,0))))&"|"&E14&"|"&IF(COUNTIFS(资产清单!$A$6:$A$25,A14)<>1,"",IF(INDEX(资产清单!$I$6:$I$25,MATCH(A14,资产清单!$A$6:$A$25,0))="","",INDEX(资产清单!$I$6:$I$25,MATCH(A14,资产清单!$A$6:$A$25,0))))&"|"&IF(COUNTIFS(资产清单!$A$6:$A$25,A14)<>1,"",IF(INDEX(资产清单!$J$6:$J$25,MATCH(A14,资产清单!$A$6:$A$25,0))="","",INDEX(资产清单!$J$6:$J$25,MATCH(A14,资产清单!$A$6:$A$25,0))))&"|"&IF(IF(COUNTIFS(资产清单!$A$6:$A$25,A14)<>1,"",IF(COUNT(INDEX(资产清单!$M$6:$M$25,MATCH(A14,资产清单!$A$6:$A$25,0)))<>1,"",INDEX(资产清单!$M$6:$M$25,MATCH(A14,资产清单!$A$6:$A$25,0))))="","不适用",IF(COUNTIFS(资产清单!$A$6:$A$25,A14)<>1,"",IF(COUNT(INDEX(资产清单!$M$6:$M$25,MATCH(A14,资产清单!$A$6:$A$25,0)))<>1,"",INDEX(资产清单!$M$6:$M$25,MATCH(A14,资产清单!$A$6:$A$25,0))))) -> 模拟场地F|场地|露天场地|元/㎡/月|不适用 | I14: =H14 -> 模拟场地F|场地|露天场地|元/㎡/月|不适用 | J14: 区域和管理单元不代替市场区位判断
A15: RP-010 | B15: =IF(COUNTIFS(资产清单!$A$6:$A$25,A15)<>1,"",IF(INDEX(资产清单!$D$6:$D$25,MATCH(A15,资产清单!$A$6:$A$25,0))="","",INDEX(资产清单!$D$6:$D$25,MATCH(A15,资产清单!$A$6:$A$25,0)))) -> 地面停车位组 | C15: =IF(COUNTIFS(资产清单!$A$6:$A$25,A15)<>1,"",IF(INDEX(资产清单!$F$6:$F$25,MATCH(A15,资产清单!$A$6:$A$25,0))="","",INDEX(资产清单!$F$6:$F$25,MATCH(A15,资产清单!$A$6:$A$25,0)))) -> 停车设施 | D15: =IF(ISNUMBER(SEARCH("通信基站",IF(COUNTIFS(资产清单!$A$6:$A$25,A15)<>1,"",IF(INDEX(资产清单!$G$6:$G$25,MATCH(A15,资产清单!$A$6:$A$25,0))="","",INDEX(资产清单!$G$6:$G$25,MATCH(A15,资产清单!$A$6:$A$25,0)))))),"通信基站",IF(ISNUMBER(SEARCH("广告",IF(COUNTIFS(资产清单!$A$6:$A$25,A15)<>1,"",IF(INDEX(资产清单!$G$6:$G$25,MATCH(A15,资产清单!$A$6:$A$25,0))="","",INDEX(资产清单!$G$6:$G$25,MATCH(A15,资产清单!$A$6:$A$25,0)))))),"广告位",IF(ISNUMBER(SEARCH("设备",IF(COUNTIFS(资产清单!$A$6:$A$25,A15)<>1,"",IF(INDEX(资产清单!$G$6:$G$25,MATCH(A15,资产清单!$A$6:$A$25,0))="","",INDEX(资产清单!$G$6:$G$25,MATCH(A15,资产清单!$A$6:$A$25,0)))))),"设备",IF(ISNUMBER(SEARCH("停车位",IF(COUNTIFS(资产清单!$A$6:$A$25,A15)<>1,"",IF(INDEX(资产清单!$G$6:$G$25,MATCH(A15,资产清单!$A$6:$A$25,0))="","",INDEX(资产清单!$G$6:$G$25,MATCH(A15,资产清单!$A$6:$A$25,0)))))),"车位",IF(ISNUMBER(SEARCH("内部通道商铺",IF(COUNTIFS(资产清单!$A$6:$A$25,A15)<>1,"",IF(INDEX(资产清单!$G$6:$G$25,MATCH(A15,资产清单!$A$6:$A$25,0))="","",INDEX(资产清单!$G$6:$G$25,MATCH(A15,资产清单!$A$6:$A$25,0)))))),"商业",IF(ISNUMBER(SEARCH("活动场馆",IF(COUNTIFS(资产清单!$A$6:$A$25,A15)<>1,"",IF(INDEX(资产清单!$G$6:$G$25,MATCH(A15,资产清单!$A$6:$A$25,0))="","",INDEX(资产清单!$G$6:$G$25,MATCH(A15,资产清单!$A$6:$A$25,0)))))),"场馆",IF(ISNUMBER(SEARCH("场地",IF(COUNTIFS(资产清单!$A$6:$A$25,A15)<>1,"",IF(INDEX(资产清单!$G$6:$G$25,MATCH(A15,资产清单!$A$6:$A$25,0))="","",INDEX(资产清单!$G$6:$G$25,MATCH(A15,资产清单!$A$6:$A$25,0)))))),"场地",C15))))))) -> 车位 | E15: =IF(COUNTIFS(资产清单!$A$6:$A$25,A15)<>1,"",IF(INDEX(资产清单!$H$6:$H$25,MATCH(A15,资产清单!$A$6:$A$25,0))="","",INDEX(资产清单!$H$6:$H$25,MATCH(A15,资产清单!$A$6:$A$25,0)))) -> 车位 | F15: =IF(E15="","待确认用途",IF(D15=E15,"候选与确认一致","已人工确认差异")) -> 候选与确认一致 | G15: =E15&"|"&IF(COUNTIFS(资产清单!$A$6:$A$25,A15)<>1,"",IF(INDEX(资产清单!$J$6:$J$25,MATCH(A15,资产清单!$A$6:$A$25,0))="","",INDEX(资产清单!$J$6:$J$25,MATCH(A15,资产清单!$A$6:$A$25,0)))) -> 车位|元/个/月 | H15: =IF(COUNTIFS(资产清单!$A$6:$A$25,A15)<>1,"",IF(INDEX(资产清单!$E$6:$E$25,MATCH(A15,资产清单!$A$6:$A$25,0))="","",INDEX(资产清单!$E$6:$E$25,MATCH(A15,资产清单!$A$6:$A$25,0))))&"|"&E15&"|"&IF(COUNTIFS(资产清单!$A$6:$A$25,A15)<>1,"",IF(INDEX(资产清单!$I$6:$I$25,MATCH(A15,资产清单!$A$6:$A$25,0))="","",INDEX(资产清单!$I$6:$I$25,MATCH(A15,资产清单!$A$6:$A$25,0))))&"|"&IF(COUNTIFS(资产清单!$A$6:$A$25,A15)<>1,"",IF(INDEX(资产清单!$J$6:$J$25,MATCH(A15,资产清单!$A$6:$A$25,0))="","",INDEX(资产清单!$J$6:$J$25,MATCH(A15,资产清单!$A$6:$A$25,0))))&"|"&IF(IF(COUNTIFS(资产清单!$A$6:$A$25,A15)<>1,"",IF(COUNT(INDEX(资产清单!$M$6:$M$25,MATCH(A15,资产清单!$A$6:$A$25,0)))<>1,"",INDEX(资产清单!$M$6:$M$25,MATCH(A15,资产清单!$A$6:$A$25,0))))="","不适用",IF(COUNTIFS(资产清单!$A$6:$A$25,A15)<>1,"",IF(COUNT(INDEX(资产清单!$M$6:$M$25,MATCH(A15,资产清单!$A$6:$A$25,0)))<>1,"",INDEX(资产清单!$M$6:$M$25,MATCH(A15,资产清单!$A$6:$A$25,0))))) -> 模拟停车区G|车位|停车位|元/个/月|不适用 | I15: =H15 -> 模拟停车区G|车位|停车位|元/个/月|不适用 | J15: 区域和管理单元不代替市场区位判断
A16: RP-011 | B16: =IF(COUNTIFS(资产清单!$A$6:$A$25,A16)<>1,"",IF(INDEX(资产清单!$D$6:$D$25,MATCH(A16,资产清单!$A$6:$A$25,0))="","",INDEX(资产清单!$D$6:$D$25,MATCH(A16,资产清单!$A$6:$A$25,0)))) -> 按间计租宿舍 | C16: =IF(COUNTIFS(资产清单!$A$6:$A$25,A16)<>1,"",IF(INDEX(资产清单!$F$6:$F$25,MATCH(A16,资产清单!$A$6:$A$25,0))="","",INDEX(资产清单!$F$6:$F$25,MATCH(A16,资产清单!$A$6:$A$25,0)))) -> 住宅 | D16: =IF(ISNUMBER(SEARCH("通信基站",IF(COUNTIFS(资产清单!$A$6:$A$25,A16)<>1,"",IF(INDEX(资产清单!$G$6:$G$25,MATCH(A16,资产清单!$A$6:$A$25,0))="","",INDEX(资产清单!$G$6:$G$25,MATCH(A16,资产清单!$A$6:$A$25,0)))))),"通信基站",IF(ISNUMBER(SEARCH("广告",IF(COUNTIFS(资产清单!$A$6:$A$25,A16)<>1,"",IF(INDEX(资产清单!$G$6:$G$25,MATCH(A16,资产清单!$A$6:$A$25,0))="","",INDEX(资产清单!$G$6:$G$25,MATCH(A16,资产清单!$A$6:$A$25,0)))))),"广告位",IF(ISNUMBER(SEARCH("设备",IF(COUNTIFS(资产清单!$A$6:$A$25,A16)<>1,"",IF(INDEX(资产清单!$G$6:$G$25,MATCH(A16,资产清单!$A$6:$A$25,0))="","",INDEX(资产清单!$G$6:$G$25,MATCH(A16,资产清单!$A$6:$A$25,0)))))),"设备",IF(ISNUMBER(SEARCH("停车位",IF(COUNTIFS(资产清单!$A$6:$A$25,A16)<>1,"",IF(INDEX(资产清单!$G$6:$G$25,MATCH(A16,资产清单!$A$6:$A$25,0))="","",INDEX(资产清单!$G$6:$G$25,MATCH(A16,资产清单!$A$6:$A$25,0)))))),"车位",IF(ISNUMBER(SEARCH("内部通道商铺",IF(COUNTIFS(资产清单!$A$6:$A$25,A16)<>1,"",IF(INDEX(资产清单!$G$6:$G$25,MATCH(A16,资产清单!$A$6:$A$25,0))="","",INDEX(资产清单!$G$6:$G$25,MATCH(A16,资产清单!$A$6:$A$25,0)))))),"商业",IF(ISNUMBER(SEARCH("活动场馆",IF(COUNTIFS(资产清单!$A$6:$A$25,A16)<>1,"",IF(INDEX(资产清单!$G$6:$G$25,MATCH(A16,资产清单!$A$6:$A$25,0))="","",INDEX(资产清单!$G$6:$G$25,MATCH(A16,资产清单!$A$6:$A$25,0)))))),"场馆",IF(ISNUMBER(SEARCH("场地",IF(COUNTIFS(资产清单!$A$6:$A$25,A16)<>1,"",IF(INDEX(资产清单!$G$6:$G$25,MATCH(A16,资产清单!$A$6:$A$25,0))="","",INDEX(资产清单!$G$6:$G$25,MATCH(A16,资产清单!$A$6:$A$25,0)))))),"场地",C16))))))) -> 住宅 | E16: =IF(COUNTIFS(资产清单!$A$6:$A$25,A16)<>1,"",IF(INDEX(资产清单!$H$6:$H$25,MATCH(A16,资产清单!$A$6:$A$25,0))="","",INDEX(资产清单!$H$6:$H$25,MATCH(A16,资产清单!$A$6:$A$25,0)))) -> 住宅 | F16: =IF(E16="","待确认用途",IF(D16=E16,"候选与确认一致","已人工确认差异")) -> 候选与确认一致 | G16: =E16&"|"&IF(COUNTIFS(资产清单!$A$6:$A$25,A16)<>1,"",IF(INDEX(资产清单!$J$6:$J$25,MATCH(A16,资产清单!$A$6:$A$25,0))="","",INDEX(资产清单!$J$6:$J$25,MATCH(A16,资产清单!$A$6:$A$25,0)))) -> 住宅|元/间/月 | H16: =IF(COUNTIFS(资产清单!$A$6:$A$25,A16)<>1,"",IF(INDEX(资产清单!$E$6:$E$25,MATCH(A16,资产清单!$A$6:$A$25,0))="","",INDEX(资产清单!$E$6:$E$25,MATCH(A16,资产清单!$A$6:$A$25,0))))&"|"&E16&"|"&IF(COUNTIFS(资产清单!$A$6:$A$25,A16)<>1,"",IF(INDEX(资产清单!$I$6:$I$25,MATCH(A16,资产清单!$A$6:$A$25,0))="","",INDEX(资产清单!$I$6:$I$25,MATCH(A16,资产清单!$A$6:$A$25,0))))&"|"&IF(COUNTIFS(资产清单!$A$6:$A$25,A16)<>1,"",IF(INDEX(资产清单!$J$6:$J$25,MATCH(A16,资产清单!$A$6:$A$25,0))="","",INDEX(资产清单!$J$6:$J$25,MATCH(A16,资产清单!$A$6:$A$25,0))))&"|"&IF(IF(COUNTIFS(资产清单!$A$6:$A$25,A16)<>1,"",IF(COUNT(INDEX(资产清单!$M$6:$M$25,MATCH(A16,资产清单!$A$6:$A$25,0)))<>1,"",INDEX(资产清单!$M$6:$M$25,MATCH(A16,资产清单!$A$6:$A$25,0))))="","不适用",IF(COUNTIFS(资产清单!$A$6:$A$25,A16)<>1,"",IF(COUNT(INDEX(资产清单!$M$6:$M$25,MATCH(A16,资产清单!$A$6:$A$25,0)))<>1,"",INDEX(资产清单!$M$6:$M$25,MATCH(A16,资产清单!$A$6:$A$25,0))))) -> 模拟宿舍楼H|住宅|宿舍|元/间/月|2 | I16: =H16 -> 模拟宿舍楼H|住宅|宿舍|元/间/月|2 | J16: 区域和管理单元不代替市场区位判断
A17: RP-012 | B17: =IF(COUNTIFS(资产清单!$A$6:$A$25,A17)<>1,"",IF(INDEX(资产清单!$D$6:$D$25,MATCH(A17,资产清单!$A$6:$A$25,0))="","",INDEX(资产清单!$D$6:$D$25,MATCH(A17,资产清单!$A$6:$A$25,0)))) -> 通信基站点位 | C17: =IF(COUNTIFS(资产清单!$A$6:$A$25,A17)<>1,"",IF(INDEX(资产清单!$F$6:$F$25,MATCH(A17,资产清单!$A$6:$A$25,0))="","",INDEX(资产清单!$F$6:$F$25,MATCH(A17,资产清单!$A$6:$A$25,0)))) -> 办公 | D17: =IF(ISNUMBER(SEARCH("通信基站",IF(COUNTIFS(资产清单!$A$6:$A$25,A17)<>1,"",IF(INDEX(资产清单!$G$6:$G$25,MATCH(A17,资产清单!$A$6:$A$25,0))="","",INDEX(资产清单!$G$6:$G$25,MATCH(A17,资产清单!$A$6:$A$25,0)))))),"通信基站",IF(ISNUMBER(SEARCH("广告",IF(COUNTIFS(资产清单!$A$6:$A$25,A17)<>1,"",IF(INDEX(资产清单!$G$6:$G$25,MATCH(A17,资产清单!$A$6:$A$25,0))="","",INDEX(资产清单!$G$6:$G$25,MATCH(A17,资产清单!$A$6:$A$25,0)))))),"广告位",IF(ISNUMBER(SEARCH("设备",IF(COUNTIFS(资产清单!$A$6:$A$25,A17)<>1,"",IF(INDEX(资产清单!$G$6:$G$25,MATCH(A17,资产清单!$A$6:$A$25,0))="","",INDEX(资产清单!$G$6:$G$25,MATCH(A17,资产清单!$A$6:$A$25,0)))))),"设备",IF(ISNUMBER(SEARCH("停车位",IF(COUNTIFS(资产清单!$A$6:$A$25,A17)<>1,"",IF(INDEX(资产清单!$G$6:$G$25,MATCH(A17,资产清单!$A$6:$A$25,0))="","",INDEX(资产清单!$G$6:$G$25,MATCH(A17,资产清单!$A$6:$A$25,0)))))),"车位",IF(ISNUMBER(SEARCH("内部通道商铺",IF(COUNTIFS(资产清单!$A$6:$A$25,A17)<>1,"",IF(INDEX(资产清单!$G$6:$G$25,MATCH(A17,资产清单!$A$6:$A$25,0))="","",INDEX(资产清单!$G$6:$G$25,MATCH(A17,资产清单!$A$6:$A$25,0)))))),"商业",IF(ISNUMBER(SEARCH("活动场馆",IF(COUNTIFS(资产清单!$A$6:$A$25,A17)<>1,"",IF(INDEX(资产清单!$G$6:$G$25,MATCH(A17,资产清单!$A$6:$A$25,0))="","",INDEX(资产清单!$G$6:$G$25,MATCH(A17,资产清单!$A$6:$A$25,0)))))),"场馆",IF(ISNUMBER(SEARCH("场地",IF(COUNTIFS(资产清单!$A$6:$A$25,A17)<>1,"",IF(INDEX(资产清单!$G$6:$G$25,MATCH(A17,资产清单!$A$6:$A$25,0))="","",INDEX(资产清单!$G$6:$G$25,MATCH(A17,资产清单!$A$6:$A$25,0)))))),"场地",C17))))))) -> 通信基站 | E17: =IF(COUNTIFS(资产清单!$A$6:$A$25,A17)<>1,"",IF(INDEX(资产清单!$H$6:$H$25,MATCH(A17,资产清单!$A$6:$A$25,0))="","",INDEX(资产清单!$H$6:$H$25,MATCH(A17,资产清单!$A$6:$A$25,0)))) -> 通信基站 | F17: =IF(E17="","待确认用途",IF(D17=E17,"候选与确认一致","已人工确认差异")) -> 候选与确认一致 | G17: =E17&"|"&IF(COUNTIFS(资产清单!$A$6:$A$25,A17)<>1,"",IF(INDEX(资产清单!$J$6:$J$25,MATCH(A17,资产清单!$A$6:$A$25,0))="","",INDEX(资产清单!$J$6:$J$25,MATCH(A17,资产清单!$A$6:$A$25,0)))) -> 通信基站|元/处/月 | H17: =IF(COUNTIFS(资产清单!$A$6:$A$25,A17)<>1,"",IF(INDEX(资产清单!$E$6:$E$25,MATCH(A17,资产清单!$A$6:$A$25,0))="","",INDEX(资产清单!$E$6:$E$25,MATCH(A17,资产清单!$A$6:$A$25,0))))&"|"&E17&"|"&IF(COUNTIFS(资产清单!$A$6:$A$25,A17)<>1,"",IF(INDEX(资产清单!$I$6:$I$25,MATCH(A17,资产清单!$A$6:$A$25,0))="","",INDEX(资产清单!$I$6:$I$25,MATCH(A17,资产清单!$A$6:$A$25,0))))&"|"&IF(COUNTIFS(资产清单!$A$6:$A$25,A17)<>1,"",IF(INDEX(资产清单!$J$6:$J$25,MATCH(A17,资产清单!$A$6:$A$25,0))="","",INDEX(资产清单!$J$6:$J$25,MATCH(A17,资产清单!$A$6:$A$25,0))))&"|"&IF(IF(COUNTIFS(资产清单!$A$6:$A$25,A17)<>1,"",IF(COUNT(INDEX(资产清单!$M$6:$M$25,MATCH(A17,资产清单!$A$6:$A$25,0)))<>1,"",INDEX(资产清单!$M$6:$M$25,MATCH(A17,资产清单!$A$6:$A$25,0))))="","不适用",IF(COUNTIFS(资产清单!$A$6:$A$25,A17)<>1,"",IF(COUNT(INDEX(资产清单!$M$6:$M$25,MATCH(A17,资产清单!$A$6:$A$25,0)))<>1,"",INDEX(资产清单!$M$6:$M$25,MATCH(A17,资产清单!$A$6:$A$25,0))))) -> 模拟屋顶I|通信基站|屋顶点位|元/处/月|不适用 | I17: =H17 -> 模拟屋顶I|通信基站|屋顶点位|元/处/月|不适用 | J17: 区域和管理单元不代替市场区位判断
... A25: RP-020 | B25: =IF(COUNTIFS(资产清单!$A$6:$A$25,A25)<>1,"",IF(INDEX(资产清单!$D$6:$D$25,MATCH(A25,资产清单!$A$6:$A$25,0))="","",INDEX(资产清单!$D$6:$D$25,MATCH(A25,资产清单!$A$6:$A$25,0)))) -> 范围外房屋 | C25: =IF(COUNTIFS(资产清单!$A$6:$A$25,A25)<>1,"",IF(INDEX(资产清单!$F$6:$F$25,MATCH(A25,资产清单!$A$6:$A$25,0))="","",INDEX(资产清单!$F$6:$F$25,MATCH(A25,资产清单!$A$6:$A$25,0)))) -> 办公 | D25: =IF(ISNUMBER(SEARCH("通信基站",IF(COUNTIFS(资产清单!$A$6:$A$25,A25)<>1,"",IF(INDEX(资产清单!$G$6:$G$25,MATCH(A25,资产清单!$A$6:$A$25,0))="","",INDEX(资产清单!$G$6:$G$25,MATCH(A25,资产清单!$A$6:$A$25,0)))))),"通信基站",IF(ISNUMBER(SEARCH("广告",IF(COUNTIFS(资产清单!$A$6:$A$25,A25)<>1,"",IF(INDEX(资产清单!$G$6:$G$25,MATCH(A25,资产清单!$A$6:$A$25,0))="","",INDEX(资产清单!$G$6:$G$25,MATCH(A25,资产清单!$A$6:$A$25,0)))))),"广告位",IF(ISNUMBER(SEARCH("设备",IF(COUNTIFS(资产清单!$A$6:$A$25,A25)<>1,"",IF(INDEX(资产清单!$G$6:$G$25,MATCH(A25,资产清单!$A$6:$A$25,0))="","",INDEX(资产清单!$G$6:$G$25,MATCH(A25,资产清单!$A$6:$A$25,0)))))),"设备",IF(ISNUMBER(SEARCH("停车位",IF(COUNTIFS(资产清单!$A$6:$A$25,A25)<>1,"",IF(INDEX(资产清单!$G$6:$G$25,MATCH(A25,资产清单!$A$6:$A$25,0))="","",INDEX(资产清单!$G$6:$G$25,MATCH(A25,资产清单!$A$6:$A$25,0)))))),"车位",IF(ISNUMBER(SEARCH("内部通道商铺",IF(COUNTIFS(资产清单!$A$6:$A$25,A25)<>1,"",IF(INDEX(资产清单!$G$6:$G$25,MATCH(A25,资产清单!$A$6:$A$25,0))="","",INDEX(资产清单!$G$6:$G$25,MATCH(A25,资产清单!$A$6:$A$25,0)))))),"商业",IF(ISNUMBER(SEARCH("活动场馆",IF(COUNTIFS(资产清单!$A$6:$A$25,A25)<>1,"",IF(INDEX(资产清单!$G$6:$G$25,MATCH(A25,资产清单!$A$6:$A$25,0))="","",INDEX(资产清单!$G$6:$G$25,MATCH(A25,资产清单!$A$6:$A$25,0)))))),"场馆",IF(ISNUMBER(SEARCH("场地",IF(COUNTIFS(资产清单!$A$6:$A$25,A25)<>1,"",IF(INDEX(资产清单!$G$6:$G$25,MATCH(A25,资产清单!$A$6:$A$25,0))="","",INDEX(资产清单!$G$6:$G$25,MATCH(A25,资产清单!$A$6:$A$25,0)))))),"场地",C25))))))) -> 办公 | E25: =IF(COUNTIFS(资产清单!$A$6:$A$25,A25)<>1,"",IF(INDEX(资产清单!$H$6:$H$25,MATCH(A25,资产清单!$A$6:$A$25,0))="","",INDEX(资产清单!$H$6:$H$25,MATCH(A25,资产清单!$A$6:$A$25,0)))) -> 办公 | F25: =IF(E25="","待确认用途",IF(D25=E25,"候选与确认一致","已人工确认差异")) -> 候选与确认一致 | G25: =E25&"|"&IF(COUNTIFS(资产清单!$A$6:$A$25,A25)<>1,"",IF(INDEX(资产清单!$J$6:$J$25,MATCH(A25,资产清单!$A$6:$A$25,0))="","",INDEX(资产清单!$J$6:$J$25,MATCH(A25,资产清单!$A$6:$A$25,0)))) -> 办公|元/㎡/月 | H25: =IF(COUNTIFS(资产清单!$A$6:$A$25,A25)<>1,"",IF(INDEX(资产清单!$E$6:$E$25,MATCH(A25,资产清单!$A$6:$A$25,0))="","",INDEX(资产清单!$E$6:$E$25,MATCH(A25,资产清单!$A$6:$A$25,0))))&"|"&E25&"|"&IF(COUNTIFS(资产清单!$A$6:$A$25,A25)<>1,"",IF(INDEX(资产清单!$I$6:$I$25,MATCH(A25,资产清单!$A$6:$A$25,0))="","",INDEX(资产清单!$I$6:$I$25,MATCH(A25,资产清单!$A$6:$A$25,0))))&"|"&IF(COUNTIFS(资产清单!$A$6:$A$25,A25)<>1,"",IF(INDEX(资产清单!$J$6:$J$25,MATCH(A25,资产清单!$A$6:$A$25,0))="","",INDEX(资产清单!$J$6:$J$25,MATCH(A25,资产清单!$A$6:$A$25,0))))&"|"&IF(IF(COUNTIFS(资产清单!$A$6:$A$25,A25)<>1,"",IF(COUNT(INDEX(资产清单!$M$6:$M$25,MATCH(A25,资产清单!$A$6:$A$25,0)))<>1,"",INDEX(资产清单!$M$6:$M$25,MATCH(A25,资产清单!$A$6:$A$25,0))))="","不适用",IF(COUNTIFS(资产清单!$A$6:$A$25,A25)<>1,"",IF(COUNT(INDEX(资产清单!$M$6:$M$25,MATCH(A25,资产清单!$A$6:$A$25,0)))<>1,"",INDEX(资产清单!$M$6:$M$25,MATCH(A25,资产清单!$A$6:$A$25,0))))) -> 模拟范围外楼N|办公|办公用房|元/㎡/月|2 | I25: =H25 -> 模拟范围外楼N|办公|办公用房|元/㎡/月|2 | J25: 区域和管理单元不代替市场区位判断
A27: 识别建议仅用于初筛。最终用途须结合现场状况、资料和实际可出租功能人工确认。

Sheet 三案例选用
A2: 三案例选用与组合核对
A3: 全部业务数据及依据记录均为模拟。用于试用复算，未核验真实来源。
A5: 资产编码 | B5: 案例1编号 | C5: 案例2编号 | D5: 案例3编号 | E5: 选择及可比理由 | F5: 案例组合检查 | G5: 用途口径检查 | H5: 评分绑定检查 | I5: 真实证据状态
A6: RP-001 | B6: SC-001 | C6: SC-002 | D6: SC-003 | E6: 精确同址同类同层，可共享案例；面积逐项修正 | F6: =IF(NOT(AND(COUNTIFS(市场案例库!$A$6:$A$35,B6)=1,COUNTIFS(市场案例库!$A$6:$A$35,C6)=1,COUNTIFS(市场案例库!$A$6:$A$35,D6)=1)),"待补有效案例",IF(OR(B6=C6,B6=D6,C6=D6,IF(COUNTIFS(市场案例库!$A$6:$A$35,B6)<>1,"",IF(INDEX(市场案例库!$C$6:$C$35,MATCH(B6,市场案例库!$A$6:$A$35,0))="","",INDEX(市场案例库!$C$6:$C$35,MATCH(B6,市场案例库!$A$6:$A$35,0))))=IF(COUNTIFS(市场案例库!$A$6:$A$35,C6)<>1,"",IF(INDEX(市场案例库!$C$6:$C$35,MATCH(C6,市场案例库!$A$6:$A$35,0))="","",INDEX(市场案例库!$C$6:$C$35,MATCH(C6,市场案例库!$A$6:$A$35,0)))),IF(COUNTIFS(市场案例库!$A$6:$A$35,B6)<>1,"",IF(INDEX(市场案例库!$C$6:$C$35,MATCH(B6,市场案例库!$A$6:$A$35,0))="","",INDEX(市场案例库!$C$6:$C$35,MATCH(B6,市场案例库!$A$6:$A$35,0))))=IF(COUNTIFS(市场案例库!$A$6:$A$35,D6)<>1,"",IF(INDEX(市场案例库!$C$6:$C$35,MATCH(D6,市场案例库!$A$6:$A$35,0))="","",INDEX(市场案例库!$C$6:$C$35,MATCH(D6,市场案例库!$A$6:$A$35,0)))),IF(COUNTIFS(市场案例库!$A$6:$A$35,C6)<>1,"",IF(INDEX(市场案例库!$C$6:$C$35,MATCH(C6,市场案例库!$A$6:$A$35,0))="","",INDEX(市场案例库!$C$6:$C$35,MATCH(C6,市场案例库!$A$6:$A$35,0))))=IF(COUNTIFS(市场案例库!$A$6:$A$35,D6)<>1,"",IF(INDEX(市场案例库!$C$6:$C$35,MATCH(D6,市场案例库!$A$6:$A$35,0))="","",INDEX(市场案例库!$C$6:$C$35,MATCH(D6,市场案例库!$A$6:$A$35,0)))),IF(COUNTIFS(市场案例库!$A$6:$A$35,B6)<>1,"",IF(INDEX(市场案例库!$D$6:$D$35,MATCH(B6,市场案例库!$A$6:$A$35,0))="","",INDEX(市场案例库!$D$6:$D$35,MATCH(B6,市场案例库!$A$6:$A$35,0))))=IF(COUNTIFS(市场案例库!$A$6:$A$35,C6)<>1,"",IF(INDEX(市场案例库!$D$6:$D$35,MATCH(C6,市场案例库!$A$6:$A$35,0))="","",INDEX(市场案例库!$D$6:$D$35,MATCH(C6,市场案例库!$A$6:$A$35,0)))),IF(COUNTIFS(市场案例库!$A$6:$A$35,B6)<>1,"",IF(INDEX(市场案例库!$D$6:$D$35,MATCH(B6,市场案例库!$A$6:$A$35,0))="","",INDEX(市场案例库!$D$6:$D$35,MATCH(B6,市场案例库!$A$6:$A$35,0))))=IF(COUNTIFS(市场案例库!$A$6:$A$35,D6)<>1,"",IF(INDEX(市场案例库!$D$6:$D$35,MATCH(D6,市场案例库!$A$6:$A$35,0))="","",INDEX(市场案例库!$D$6:$D$35,MATCH(D6,市场案例库!$A$6:$A$35,0)))),IF(COUNTIFS(市场案例库!$A$6:$A$35,C6)<>1,"",IF(INDEX(市场案例库!$D$6:$D$35,MATCH(C6,市场案例库!$A$6:$A$35,0))="","",INDEX(市场案例库!$D$6:$D$35,MATCH(C6,市场案例库!$A$6:$A$35,0))))=IF(COUNTIFS(市场案例库!$A$6:$A$35,D6)<>1,"",IF(INDEX(市场案例库!$D$6:$D$35,MATCH(D6,市场案例库!$A$6:$A$35,0))="","",INDEX(市场案例库!$D$6:$D$35,MATCH(D6,市场案例库!$A$6:$A$35,0))))),"重复待复核","三案例齐全")) -> 三案例齐全 | G6: =IF(F6<>"三案例齐全","待补组合",IF(AND(IF(COUNTIFS(市场案例库!$A$6:$A$35,B6)<>1,"",IF(INDEX(市场案例库!$F$6:$F$35,MATCH(B6,市场案例库!$A$6:$A$35,0))="","",INDEX(市场案例库!$F$6:$F$35,MATCH(B6,市场案例库!$A$6:$A$35,0))))=IF(COUNTIFS(资产清单!$A$6:$A$25,A6)<>1,"",IF(INDEX(资产清单!$J$6:$J$25,MATCH(A6,资产清单!$A$6:$A$25,0))="","",INDEX(资产清单!$J$6:$J$25,MATCH(A6,资产清单!$A$6:$A$25,0)))),IF(COUNTIFS(市场案例库!$A$6:$A$35,B6)<>1,"",IF(INDEX(市场案例库!$E$6:$E$35,MATCH(B6,市场案例库!$A$6:$A$35,0))="","",INDEX(市场案例库!$E$6:$E$35,MATCH(B6,市场案例库!$A$6:$A$35,0))))=IF(COUNTIFS(资产清单!$A$6:$A$25,A6)<>1,"",IF(INDEX(资产清单!$H$6:$H$25,MATCH(A6,资产清单!$A$6:$A$25,0))="","",INDEX(资产清单!$H$6:$H$25,MATCH(A6,资产清单!$A$6:$A$25,0)))),IF(COUNTIFS(市场案例库!$A$6:$A$35,C6)<>1,"",IF(INDEX(市场案例库!$F$6:$F$35,MATCH(C6,市场案例库!$A$6:$A$35,0))="","",INDEX(市场案例库!$F$6:$F$35,MATCH(C6,市场案例库!$A$6:$A$35,0))))=IF(COUNTIFS(资产清单!$A$6:$A$25,A6)<>1,"",IF(INDEX(资产清单!$J$6:$J$25,MATCH(A6,资产清单!$A$6:$A$25,0))="","",INDEX(资产清单!$J$6:$J$25,MATCH(A6,资产清单!$A$6:$A$25,0)))),IF(COUNTIFS(市场案例库!$A$6:$A$35,C6)<>1,"",IF(INDEX(市场案例库!$E$6:$E$35,MATCH(C6,市场案例库!$A$6:$A$35,0))="","",INDEX(市场案例库!$E$6:$E$35,MATCH(C6,市场案例库!$A$6:$A$35,0))))=IF(COUNTIFS(资产清单!$A$6:$A$25,A6)<>1,"",IF(INDEX(资产清单!$H$6:$H$25,MATCH(A6,资产清单!$A$6:$A$25,0))="","",INDEX(资产清单!$H$6:$H$25,MATCH(A6,资产清单!$A$6:$A$25,0)))),IF(COUNTIFS(市场案例库!$A$6:$A$35,D6)<>1,"",IF(INDEX(市场案例库!$F$6:$F$35,MATCH(D6,市场案例库!$A$6:$A$35,0))="","",INDEX(市场案例库!$F$6:$F$35,MATCH(D6,市场案例库!$A$6:$A$35,0))))=IF(COUNTIFS(资产清单!$A$6:$A$25,A6)<>1,"",IF(INDEX(资产清单!$J$6:$J$25,MATCH(A6,资产清单!$A$6:$A$25,0))="","",INDEX(资产清单!$J$6:$J$25,MATCH(A6,资产清单!$A$6:$A$25,0)))),IF(COUNTIFS(市场案例库!$A$6:$A$35,D6)<>1,"",IF(INDEX(市场案例库!$E$6:$E$35,MATCH(D6,市场案例库!$A$6:$A$35,0))="","",INDEX(市场案例库!$E$6:$E$35,MATCH(D6,市场案例库!$A$6:$A$35,0))))=IF(COUNTIFS(资产清单!$A$6:$A$25,A6)<>1,"",IF(INDEX(资产清单!$H$6:$H$25,MATCH(A6,资产清单!$A$6:$A$25,0))="","",INDEX(资产清单!$H$6:$H$25,MATCH(A6,资产清单!$A$6:$A$25,0))))),"用途口径一致","用途口径不一致")) -> 用途口径一致 | H6: =IF(AND(COUNTIFS(修正明细!$N$6:$N$21,B6)=16,COUNTIFS(修正明细!$N$22:$N$37,C6)=16,COUNTIFS(修正明细!$N$38:$N$53,D6)=16),"绑定有效","待重判评分") -> 绑定有效 | I6: 模拟资料未真实核验
A7: RP-002 | B7: SC-001 | C7: SC-002 | D7: SC-003 | E7: 精确同址同类同层，可共享案例；面积逐项修正 | F7: =IF(NOT(AND(COUNTIFS(市场案例库!$A$6:$A$35,B7)=1,COUNTIFS(市场案例库!$A$6:$A$35,C7)=1,COUNTIFS(市场案例库!$A$6:$A$35,D7)=1)),"待补有效案例",IF(OR(B7=C7,B7=D7,C7=D7,IF(COUNTIFS(市场案例库!$A$6:$A$35,B7)<>1,"",IF(INDEX(市场案例库!$C$6:$C$35,MATCH(B7,市场案例库!$A$6:$A$35,0))="","",INDEX(市场案例库!$C$6:$C$35,MATCH(B7,市场案例库!$A$6:$A$35,0))))=IF(COUNTIFS(市场案例库!$A$6:$A$35,C7)<>1,"",IF(INDEX(市场案例库!$C$6:$C$35,MATCH(C7,市场案例库!$A$6:$A$35,0))="","",INDEX(市场案例库!$C$6:$C$35,MATCH(C7,市场案例库!$A$6:$A$35,0)))),IF(COUNTIFS(市场案例库!$A$6:$A$35,B7)<>1,"",IF(INDEX(市场案例库!$C$6:$C$35,MATCH(B7,市场案例库!$A$6:$A$35,0))="","",INDEX(市场案例库!$C$6:$C$35,MATCH(B7,市场案例库!$A$6:$A$35,0))))=IF(COUNTIFS(市场案例库!$A$6:$A$35,D7)<>1,"",IF(INDEX(市场案例库!$C$6:$C$35,MATCH(D7,市场案例库!$A$6:$A$35,0))="","",INDEX(市场案例库!$C$6:$C$35,MATCH(D7,市场案例库!$A$6:$A$35,0)))),IF(COUNTIFS(市场案例库!$A$6:$A$35,C7)<>1,"",IF(INDEX(市场案例库!$C$6:$C$35,MATCH(C7,市场案例库!$A$6:$A$35,0))="","",INDEX(市场案例库!$C$6:$C$35,MATCH(C7,市场案例库!$A$6:$A$35,0))))=IF(COUNTIFS(市场案例库!$A$6:$A$35,D7)<>1,"",IF(INDEX(市场案例库!$C$6:$C$35,MATCH(D7,市场案例库!$A$6:$A$35,0))="","",INDEX(市场案例库!$C$6:$C$35,MATCH(D7,市场案例库!$A$6:$A$35,0)))),IF(COUNTIFS(市场案例库!$A$6:$A$35,B7)<>1,"",IF(INDEX(市场案例库!$D$6:$D$35,MATCH(B7,市场案例库!$A$6:$A$35,0))="","",INDEX(市场案例库!$D$6:$D$35,MATCH(B7,市场案例库!$A$6:$A$35,0))))=IF(COUNTIFS(市场案例库!$A$6:$A$35,C7)<>1,"",IF(INDEX(市场案例库!$D$6:$D$35,MATCH(C7,市场案例库!$A$6:$A$35,0))="","",INDEX(市场案例库!$D$6:$D$35,MATCH(C7,市场案例库!$A$6:$A$35,0)))),IF(COUNTIFS(市场案例库!$A$6:$A$35,B7)<>1,"",IF(INDEX(市场案例库!$D$6:$D$35,MATCH(B7,市场案例库!$A$6:$A$35,0))="","",INDEX(市场案例库!$D$6:$D$35,MATCH(B7,市场案例库!$A$6:$A$35,0))))=IF(COUNTIFS(市场案例库!$A$6:$A$35,D7)<>1,"",IF(INDEX(市场案例库!$D$6:$D$35,MATCH(D7,市场案例库!$A$6:$A$35,0))="","",INDEX(市场案例库!$D$6:$D$35,MATCH(D7,市场案例库!$A$6:$A$35,0)))),IF(COUNTIFS(市场案例库!$A$6:$A$35,C7)<>1,"",IF(INDEX(市场案例库!$D$6:$D$35,MATCH(C7,市场案例库!$A$6:$A$35,0))="","",INDEX(市场案例库!$D$6:$D$35,MATCH(C7,市场案例库!$A$6:$A$35,0))))=IF(COUNTIFS(市场案例库!$A$6:$A$35,D7)<>1,"",IF(INDEX(市场案例库!$D$6:$D$35,MATCH(D7,市场案例库!$A$6:$A$35,0))="","",INDEX(市场案例库!$D$6:$D$35,MATCH(D7,市场案例库!$A$6:$A$35,0))))),"重复待复核","三案例齐全")) -> 三案例齐全 | G7: =IF(F7<>"三案例齐全","待补组合",IF(AND(IF(COUNTIFS(市场案例库!$A$6:$A$35,B7)<>1,"",IF(INDEX(市场案例库!$F$6:$F$35,MATCH(B7,市场案例库!$A$6:$A$35,0))="","",INDEX(市场案例库!$F$6:$F$35,MATCH(B7,市场案例库!$A$6:$A$35,0))))=IF(COUNTIFS(资产清单!$A$6:$A$25,A7)<>1,"",IF(INDEX(资产清单!$J$6:$J$25,MATCH(A7,资产清单!$A$6:$A$25,0))="","",INDEX(资产清单!$J$6:$J$25,MATCH(A7,资产清单!$A$6:$A$25,0)))),IF(COUNTIFS(市场案例库!$A$6:$A$35,B7)<>1,"",IF(INDEX(市场案例库!$E$6:$E$35,MATCH(B7,市场案例库!$A$6:$A$35,0))="","",INDEX(市场案例库!$E$6:$E$35,MATCH(B7,市场案例库!$A$6:$A$35,0))))=IF(COUNTIFS(资产清单!$A$6:$A$25,A7)<>1,"",IF(INDEX(资产清单!$H$6:$H$25,MATCH(A7,资产清单!$A$6:$A$25,0))="","",INDEX(资产清单!$H$6:$H$25,MATCH(A7,资产清单!$A$6:$A$25,0)))),IF(COUNTIFS(市场案例库!$A$6:$A$35,C7)<>1,"",IF(INDEX(市场案例库!$F$6:$F$35,MATCH(C7,市场案例库!$A$6:$A$35,0))="","",INDEX(市场案例库!$F$6:$F$35,MATCH(C7,市场案例库!$A$6:$A$35,0))))=IF(COUNTIFS(资产清单!$A$6:$A$25,A7)<>1,"",IF(INDEX(资产清单!$J$6:$J$25,MATCH(A7,资产清单!$A$6:$A$25,0))="","",INDEX(资产清单!$J$6:$J$25,MATCH(A7,资产清单!$A$6:$A$25,0)))),IF(COUNTIFS(市场案例库!$A$6:$A$35,C7)<>1,"",IF(INDEX(市场案例库!$E$6:$E$35,MATCH(C7,市场案例库!$A$6:$A$35,0))="","",INDEX(市场案例库!$E$6:$E$35,MATCH(C7,市场案例库!$A$6:$A$35,0))))=IF(COUNTIFS(资产清单!$A$6:$A$25,A7)<>1,"",IF(INDEX(资产清单!$H$6:$H$25,MATCH(A7,资产清单!$A$6:$A$25,0))="","",INDEX(资产清单!$H$6:$H$25,MATCH(A7,资产清单!$A$6:$A$25,0)))),IF(COUNTIFS(市场案例库!$A$6:$A$35,D7)<>1,"",IF(INDEX(市场案例库!$F$6:$F$35,MATCH(D7,市场案例库!$A$6:$A$35,0))="","",INDEX(市场案例库!$F$6:$F$35,MATCH(D7,市场案例库!$A$6:$A$35,0))))=IF(COUNTIFS(资产清单!$A$6:$A$25,A7)<>1,"",IF(INDEX(资产清单!$J$6:$J$25,MATCH(A7,资产清单!$A$6:$A$25,0))="","",INDEX(资产清单!$J$6:$J$25,MATCH(A7,资产清单!$A$6:$A$25,0)))),IF(COUNTIFS(市场案例库!$A$6:$A$35,D7)<>1,"",IF(INDEX(市场案例库!$E$6:$E$35,MATCH(D7,市场案例库!$A$6:$A$35,0))="","",INDEX(市场案例库!$E$6:$E$35,MATCH(D7,市场案例库!$A$6:$A$35,0))))=IF(COUNTIFS(资产清单!$A$6:$A$25,A7)<>1,"",IF(INDEX(资产清单!$H$6:$H$25,MATCH(A7,资产清单!$A$6:$A$25,0))="","",INDEX(资产清单!$H$6:$H$25,MATCH(A7,资产清单!$A$6:$A$25,0))))),"用途口径一致","用途口径不一致")) -> 用途口径一致 | H7: =IF(AND(COUNTIFS(修正明细!$N$54:$N$69,B7)=16,COUNTIFS(修正明细!$N$70:$N$85,C7)=16,COUNTIFS(修正明细!$N$86:$N$101,D7)=16),"绑定有效","待重判评分") -> 绑定有效 | I7: 模拟资料未真实核验
A8: RP-003 | B8: SC-004 | C8: SC-005 | D8: SC-006 | E8: 同用途同计租口径，保留楼层等差异 | F8: =IF(NOT(AND(COUNTIFS(市场案例库!$A$6:$A$35,B8)=1,COUNTIFS(市场案例库!$A$6:$A$35,C8)=1,COUNTIFS(市场案例库!$A$6:$A$35,D8)=1)),"待补有效案例",IF(OR(B8=C8,B8=D8,C8=D8,IF(COUNTIFS(市场案例库!$A$6:$A$35,B8)<>1,"",IF(INDEX(市场案例库!$C$6:$C$35,MATCH(B8,市场案例库!$A$6:$A$35,0))="","",INDEX(市场案例库!$C$6:$C$35,MATCH(B8,市场案例库!$A$6:$A$35,0))))=IF(COUNTIFS(市场案例库!$A$6:$A$35,C8)<>1,"",IF(INDEX(市场案例库!$C$6:$C$35,MATCH(C8,市场案例库!$A$6:$A$35,0))="","",INDEX(市场案例库!$C$6:$C$35,MATCH(C8,市场案例库!$A$6:$A$35,0)))),IF(COUNTIFS(市场案例库!$A$6:$A$35,B8)<>1,"",IF(INDEX(市场案例库!$C$6:$C$35,MATCH(B8,市场案例库!$A$6:$A$35,0))="","",INDEX(市场案例库!$C$6:$C$35,MATCH(B8,市场案例库!$A$6:$A$35,0))))=IF(COUNTIFS(市场案例库!$A$6:$A$35,D8)<>1,"",IF(INDEX(市场案例库!$C$6:$C$35,MATCH(D8,市场案例库!$A$6:$A$35,0))="","",INDEX(市场案例库!$C$6:$C$35,MATCH(D8,市场案例库!$A$6:$A$35,0)))),IF(COUNTIFS(市场案例库!$A$6:$A$35,C8)<>1,"",IF(INDEX(市场案例库!$C$6:$C$35,MATCH(C8,市场案例库!$A$6:$A$35,0))="","",INDEX(市场案例库!$C$6:$C$35,MATCH(C8,市场案例库!$A$6:$A$35,0))))=IF(COUNTIFS(市场案例库!$A$6:$A$35,D8)<>1,"",IF(INDEX(市场案例库!$C$6:$C$35,MATCH(D8,市场案例库!$A$6:$A$35,0))="","",INDEX(市场案例库!$C$6:$C$35,MATCH(D8,市场案例库!$A$6:$A$35,0)))),IF(COUNTIFS(市场案例库!$A$6:$A$35,B8)<>1,"",IF(INDEX(市场案例库!$D$6:$D$35,MATCH(B8,市场案例库!$A$6:$A$35,0))="","",INDEX(市场案例库!$D$6:$D$35,MATCH(B8,市场案例库!$A$6:$A$35,0))))=IF(COUNTIFS(市场案例库!$A$6:$A$35,C8)<>1,"",IF(INDEX(市场案例库!$D$6:$D$35,MATCH(C8,市场案例库!$A$6:$A$35,0))="","",INDEX(市场案例库!$D$6:$D$35,MATCH(C8,市场案例库!$A$6:$A$35,0)))),IF(COUNTIFS(市场案例库!$A$6:$A$35,B8)<>1,"",IF(INDEX(市场案例库!$D$6:$D$35,MATCH(B8,市场案例库!$A$6:$A$35,0))="","",INDEX(市场案例库!$D$6:$D$35,MATCH(B8,市场案例库!$A$6:$A$35,0))))=IF(COUNTIFS(市场案例库!$A$6:$A$35,D8)<>1,"",IF(INDEX(市场案例库!$D$6:$D$35,MATCH(D8,市场案例库!$A$6:$A$35,0))="","",INDEX(市场案例库!$D$6:$D$35,MATCH(D8,市场案例库!$A$6:$A$35,0)))),IF(COUNTIFS(市场案例库!$A$6:$A$35,C8)<>1,"",IF(INDEX(市场案例库!$D$6:$D$35,MATCH(C8,市场案例库!$A$6:$A$35,0))="","",INDEX(市场案例库!$D$6:$D$35,MATCH(C8,市场案例库!$A$6:$A$35,0))))=IF(COUNTIFS(市场案例库!$A$6:$A$35,D8)<>1,"",IF(INDEX(市场案例库!$D$6:$D$35,MATCH(D8,市场案例库!$A$6:$A$35,0))="","",INDEX(市场案例库!$D$6:$D$35,MATCH(D8,市场案例库!$A$6:$A$35,0))))),"重复待复核","三案例齐全")) -> 三案例齐全 | G8: =IF(F8<>"三案例齐全","待补组合",IF(AND(IF(COUNTIFS(市场案例库!$A$6:$A$35,B8)<>1,"",IF(INDEX(市场案例库!$F$6:$F$35,MATCH(B8,市场案例库!$A$6:$A$35,0))="","",INDEX(市场案例库!$F$6:$F$35,MATCH(B8,市场案例库!$A$6:$A$35,0))))=IF(COUNTIFS(资产清单!$A$6:$A$25,A8)<>1,"",IF(INDEX(资产清单!$J$6:$J$25,MATCH(A8,资产清单!$A$6:$A$25,0))="","",INDEX(资产清单!$J$6:$J$25,MATCH(A8,资产清单!$A$6:$A$25,0)))),IF(COUNTIFS(市场案例库!$A$6:$A$35,B8)<>1,"",IF(INDEX(市场案例库!$E$6:$E$35,MATCH(B8,市场案例库!$A$6:$A$35,0))="","",INDEX(市场案例库!$E$6:$E$35,MATCH(B8,市场案例库!$A$6:$A$35,0))))=IF(COUNTIFS(资产清单!$A$6:$A$25,A8)<>1,"",IF(INDEX(资产清单!$H$6:$H$25,MATCH(A8,资产清单!$A$6:$A$25,0))="","",INDEX(资产清单!$H$6:$H$25,MATCH(A8,资产清单!$A$6:$A$25,0)))),IF(COUNTIFS(市场案例库!$A$6:$A$35,C8)<>1,"",IF(INDEX(市场案例库!$F$6:$F$35,MATCH(C8,市场案例库!$A$6:$A$35,0))="","",INDEX(市场案例库!$F$6:$F$35,MATCH(C8,市场案例库!$A$6:$A$35,0))))=IF(COUNTIFS(资产清单!$A$6:$A$25,A8)<>1,"",IF(INDEX(资产清单!$J$6:$J$25,MATCH(A8,资产清单!$A$6:$A$25,0))="","",INDEX(资产清单!$J$6:$J$25,MATCH(A8,资产清单!$A$6:$A$25,0)))),IF(COUNTIFS(市场案例库!$A$6:$A$35,C8)<>1,"",IF(INDEX(市场案例库!$E$6:$E$35,MATCH(C8,市场案例库!$A$6:$A$35,0))="","",INDEX(市场案例库!$E$6:$E$35,MATCH(C8,市场案例库!$A$6:$A$35,0))))=IF(COUNTIFS(资产清单!$A$6:$A$25,A8)<>1,"",IF(INDEX(资产清单!$H$6:$H$25,MATCH(A8,资产清单!$A$6:$A$25,0))="","",INDEX(资产清单!$H$6:$H$25,MATCH(A8,资产清单!$A$6:$A$25,0)))),IF(COUNTIFS(市场案例库!$A$6:$A$35,D8)<>1,"",IF(INDEX(市场案例库!$F$6:$F$35,MATCH(D8,市场案例库!$A$6:$A$35,0))="","",INDEX(市场案例库!$F$6:$F$35,MATCH(D8,市场案例库!$A$6:$A$35,0))))=IF(COUNTIFS(资产清单!$A$6:$A$25,A8)<>1,"",IF(INDEX(资产清单!$J$6:$J$25,MATCH(A8,资产清单!$A$6:$A$25,0))="","",INDEX(资产清单!$J$6:$J$25,MATCH(A8,资产清单!$A$6:$A$25,0)))),IF(COUNTIFS(市场案例库!$A$6:$A$35,D8)<>1,"",IF(INDEX(市场案例库!$E$6:$E$35,MATCH(D8,市场案例库!$A$6:$A$35,0))="","",INDEX(市场案例库!$E$6:$E$35,MATCH(D8,市场案例库!$A$6:$A$35,0))))=IF(COUNTIFS(资产清单!$A$6:$A$25,A8)<>1,"",IF(INDEX(资产清单!$H$6:$H$25,MATCH(A8,资产清单!$A$6:$A$25,0))="","",INDEX(资产清单!$H$6:$H$25,MATCH(A8,资产清单!$A$6:$A$25,0))))),"用途口径一致","用途口径不一致")) -> 用途口径一致 | H8: =IF(AND(COUNTIFS(修正明细!$N$102:$N$117,B8)=16,COUNTIFS(修正明细!$N$118:$N$133,C8)=16,COUNTIFS(修正明细!$N$134:$N$149,D8)=16),"绑定有效","待重判评分") -> 绑定有效 | I8: 模拟资料未真实核验
A9: RP-004 | B9: SC-007 | C9: SC-008 | D9: SC-009 | E9: 模拟形态不同，以逐项依据修正 | F9: =IF(NOT(AND(COUNTIFS(市场案例库!$A$6:$A$35,B9)=1,COUNTIFS(市场案例库!$A$6:$A$35,C9)=1,COUNTIFS(市场案例库!$A$6:$A$35,D9)=1)),"待补有效案例",IF(OR(B9=C9,B9=D9,C9=D9,IF(COUNTIFS(市场案例库!$A$6:$A$35,B9)<>1,"",IF(INDEX(市场案例库!$C$6:$C$35,MATCH(B9,市场案例库!$A$6:$A$35,0))="","",INDEX(市场案例库!$C$6:$C$35,MATCH(B9,市场案例库!$A$6:$A$35,0))))=IF(COUNTIFS(市场案例库!$A$6:$A$35,C9)<>1,"",IF(INDEX(市场案例库!$C$6:$C$35,MATCH(C9,市场案例库!$A$6:$A$35,0))="","",INDEX(市场案例库!$C$6:$C$35,MATCH(C9,市场案例库!$A$6:$A$35,0)))),IF(COUNTIFS(市场案例库!$A$6:$A$35,B9)<>1,"",IF(INDEX(市场案例库!$C$6:$C$35,MATCH(B9,市场案例库!$A$6:$A$35,0))="","",INDEX(市场案例库!$C$6:$C$35,MATCH(B9,市场案例库!$A$6:$A$35,0))))=IF(COUNTIFS(市场案例库!$A$6:$A$35,D9)<>1,"",IF(INDEX(市场案例库!$C$6:$C$35,MATCH(D9,市场案例库!$A$6:$A$35,0))="","",INDEX(市场案例库!$C$6:$C$35,MATCH(D9,市场案例库!$A$6:$A$35,0)))),IF(COUNTIFS(市场案例库!$A$6:$A$35,C9)<>1,"",IF(INDEX(市场案例库!$C$6:$C$35,MATCH(C9,市场案例库!$A$6:$A$35,0))="","",INDEX(市场案例库!$C$6:$C$35,MATCH(C9,市场案例库!$A$6:$A$35,0))))=IF(COUNTIFS(市场案例库!$A$6:$A$35,D9)<>1,"",IF(INDEX(市场案例库!$C$6:$C$35,MATCH(D9,市场案例库!$A$6:$A$35,0))="","",INDEX(市场案例库!$C$6:$C$35,MATCH(D9,市场案例库!$A$6:$A$35,0)))),IF(COUNTIFS(市场案例库!$A$6:$A$35,B9)<>1,"",IF(INDEX(市场案例库!$D$6:$D$35,MATCH(B9,市场案例库!$A$6:$A$35,0))="","",INDEX(市场案例库!$D$6:$D$35,MATCH(B9,市场案例库!$A$6:$A$35,0))))=IF(COUNTIFS(市场案例库!$A$6:$A$35,C9)<>1,"",IF(INDEX(市场案例库!$D$6:$D$35,MATCH(C9,市场案例库!$A$6:$A$35,0))="","",INDEX(市场案例库!$D$6:$D$35,MATCH(C9,市场案例库!$A$6:$A$35,0)))),IF(COUNTIFS(市场案例库!$A$6:$A$35,B9)<>1,"",IF(INDEX(市场案例库!$D$6:$D$35,MATCH(B9,市场案例库!$A$6:$A$35,0))="","",INDEX(市场案例库!$D$6:$D$35,MATCH(B9,市场案例库!$A$6:$A$35,0))))=IF(COUNTIFS(市场案例库!$A$6:$A$35,D9)<>1,"",IF(INDEX(市场案例库!$D$6:$D$35,MATCH(D9,市场案例库!$A$6:$A$35,0))="","",INDEX(市场案例库!$D$6:$D$35,MATCH(D9,市场案例库!$A$6:$A$35,0)))),IF(COUNTIFS(市场案例库!$A$6:$A$35,C9)<>1,"",IF(INDEX(市场案例库!$D$6:$D$35,MATCH(C9,市场案例库!$A$6:$A$35,0))="","",INDEX(市场案例库!$D$6:$D$35,MATCH(C9,市场案例库!$A$6:$A$35,0))))=IF(COUNTIFS(市场案例库!$A$6:$A$35,D9)<>1,"",IF(INDEX(市场案例库!$D$6:$D$35,MATCH(D9,市场案例库!$A$6:$A$35,0))="","",INDEX(市场案例库!$D$6:$D$35,MATCH(D9,市场案例库!$A$6:$A$35,0))))),"重复待复核","三案例齐全")) -> 三案例齐全 | G9: =IF(F9<>"三案例齐全","待补组合",IF(AND(IF(COUNTIFS(市场案例库!$A$6:$A$35,B9)<>1,"",IF(INDEX(市场案例库!$F$6:$F$35,MATCH(B9,市场案例库!$A$6:$A$35,0))="","",INDEX(市场案例库!$F$6:$F$35,MATCH(B9,市场案例库!$A$6:$A$35,0))))=IF(COUNTIFS(资产清单!$A$6:$A$25,A9)<>1,"",IF(INDEX(资产清单!$J$6:$J$25,MATCH(A9,资产清单!$A$6:$A$25,0))="","",INDEX(资产清单!$J$6:$J$25,MATCH(A9,资产清单!$A$6:$A$25,0)))),IF(COUNTIFS(市场案例库!$A$6:$A$35,B9)<>1,"",IF(INDEX(市场案例库!$E$6:$E$35,MATCH(B9,市场案例库!$A$6:$A$35,0))="","",INDEX(市场案例库!$E$6:$E$35,MATCH(B9,市场案例库!$A$6:$A$35,0))))=IF(COUNTIFS(资产清单!$A$6:$A$25,A9)<>1,"",IF(INDEX(资产清单!$H$6:$H$25,MATCH(A9,资产清单!$A$6:$A$25,0))="","",INDEX(资产清单!$H$6:$H$25,MATCH(A9,资产清单!$A$6:$A$25,0)))),IF(COUNTIFS(市场案例库!$A$6:$A$35,C9)<>1,"",IF(INDEX(市场案例库!$F$6:$F$35,MATCH(C9,市场案例库!$A$6:$A$35,0))="","",INDEX(市场案例库!$F$6:$F$35,MATCH(C9,市场案例库!$A$6:$A$35,0))))=IF(COUNTIFS(资产清单!$A$6:$A$25,A9)<>1,"",IF(INDEX(资产清单!$J$6:$J$25,MATCH(A9,资产清单!$A$6:$A$25,0))="","",INDEX(资产清单!$J$6:$J$25,MATCH(A9,资产清单!$A$6:$A$25,0)))),IF(COUNTIFS(市场案例库!$A$6:$A$35,C9)<>1,"",IF(INDEX(市场案例库!$E$6:$E$35,MATCH(C9,市场案例库!$A$6:$A$35,0))="","",INDEX(市场案例库!$E$6:$E$35,MATCH(C9,市场案例库!$A$6:$A$35,0))))=IF(COUNTIFS(资产清单!$A$6:$A$25,A9)<>1,"",IF(INDEX(资产清单!$H$6:$H$25,MATCH(A9,资产清单!$A$6:$A$25,0))="","",INDEX(资产清单!$H$6:$H$25,MATCH(A9,资产清单!$A$6:$A$25,0)))),IF(COUNTIFS(市场案例库!$A$6:$A$35,D9)<>1,"",IF(INDEX(市场案例库!$F$6:$F$35,MATCH(D9,市场案例库!$A$6:$A$35,0))="","",INDEX(市场案例库!$F$6:$F$35,MATCH(D9,市场案例库!$A$6:$A$35,0))))=IF(COUNTIFS(资产清单!$A$6:$A$25,A9)<>1,"",IF(INDEX(资产清单!$J$6:$J$25,MATCH(A9,资产清单!$A$6:$A$25,0))="","",INDEX(资产清单!$J$6:$J$25,MATCH(A9,资产清单!$A$6:$A$25,0)))),IF(COUNTIFS(市场案例库!$A$6:$A$35,D9)<>1,"",IF(INDEX(市场案例库!$E$6:$E$35,MATCH(D9,市场案例库!$A$6:$A$35,0))="","",INDEX(市场案例库!$E$6:$E$35,MATCH(D9,市场案例库!$A$6:$A$35,0))))=IF(COUNTIFS(资产清单!$A$6:$A$25,A9)<>1,"",IF(INDEX(资产清单!$H$6:$H$25,MATCH(A9,资产清单!$A$6:$A$25,0))="","",INDEX(资产清单!$H$6:$H$25,MATCH(A9,资产清单!$A$6:$A$25,0))))),"用途口径一致","用途口径不一致")) -> 用途口径一致 | H9: =IF(AND(COUNTIFS(修正明细!$N$150:$N$165,B9)=16,COUNTIFS(修正明细!$N$166:$N$181,C9)=16,COUNTIFS(修正明细!$N$182:$N$197,D9)=16),"绑定有效","待重判评分") -> 绑定有效 | I9: 模拟资料未真实核验
A10: RP-005 | B10: SC-010 | C10: SC-011 | D10: SC-012 | E10: 精确同址同类同层，可共享案例；面积逐项修正 | F10: =IF(NOT(AND(COUNTIFS(市场案例库!$A$6:$A$35,B10)=1,COUNTIFS(市场案例库!$A$6:$A$35,C10)=1,COUNTIFS(市场案例库!$A$6:$A$35,D10)=1)),"待补有效案例",IF(OR(B10=C10,B10=D10,C10=D10,IF(COUNTIFS(市场案例库!$A$6:$A$35,B10)<>1,"",IF(INDEX(市场案例库!$C$6:$C$35,MATCH(B10,市场案例库!$A$6:$A$35,0))="","",INDEX(市场案例库!$C$6:$C$35,MATCH(B10,市场案例库!$A$6:$A$35,0))))=IF(COUNTIFS(市场案例库!$A$6:$A$35,C10)<>1,"",IF(INDEX(市场案例库!$C$6:$C$35,MATCH(C10,市场案例库!$A$6:$A$35,0))="","",INDEX(市场案例库!$C$6:$C$35,MATCH(C10,市场案例库!$A$6:$A$35,0)))),IF(COUNTIFS(市场案例库!$A$6:$A$35,B10)<>1,"",IF(INDEX(市场案例库!$C$6:$C$35,MATCH(B10,市场案例库!$A$6:$A$35,0))="","",INDEX(市场案例库!$C$6:$C$35,MATCH(B10,市场案例库!$A$6:$A$35,0))))=IF(COUNTIFS(市场案例库!$A$6:$A$35,D10)<>1,"",IF(INDEX(市场案例库!$C$6:$C$35,MATCH(D10,市场案例库!$A$6:$A$35,0))="","",INDEX(市场案例库!$C$6:$C$35,MATCH(D10,市场案例库!$A$6:$A$35,0)))),IF(COUNTIFS(市场案例库!$A$6:$A$35,C10)<>1,"",IF(INDEX(市场案例库!$C$6:$C$35,MATCH(C10,市场案例库!$A$6:$A$35,0))="","",INDEX(市场案例库!$C$6:$C$35,MATCH(C10,市场案例库!$A$6:$A$35,0))))=IF(COUNTIFS(市场案例库!$A$6:$A$35,D10)<>1,"",IF(INDEX(市场案例库!$C$6:$C$35,MATCH(D10,市场案例库!$A$6:$A$35,0))="","",INDEX(市场案例库!$C$6:$C$35,MATCH(D10,市场案例库!$A$6:$A$35,0)))),IF(COUNTIFS(市场案例库!$A$6:$A$35,B10)<>1,"",IF(INDEX(市场案例库!$D$6:$D$35,MATCH(B10,市场案例库!$A$6:$A$35,0))="","",INDEX(市场案例库!$D$6:$D$35,MATCH(B10,市场案例库!$A$6:$A$35,0))))=IF(COUNTIFS(市场案例库!$A$6:$A$35,C10)<>1,"",IF(INDEX(市场案例库!$D$6:$D$35,MATCH(C10,市场案例库!$A$6:$A$35,0))="","",INDEX(市场案例库!$D$6:$D$35,MATCH(C10,市场案例库!$A$6:$A$35,0)))),IF(COUNTIFS(市场案例库!$A$6:$A$35,B10)<>1,"",IF(INDEX(市场案例库!$D$6:$D$35,MATCH(B10,市场案例库!$A$6:$A$35,0))="","",INDEX(市场案例库!$D$6:$D$35,MATCH(B10,市场案例库!$A$6:$A$35,0))))=IF(COUNTIFS(市场案例库!$A$6:$A$35,D10)<>1,"",IF(INDEX(市场案例库!$D$6:$D$35,MATCH(D10,市场案例库!$A$6:$A$35,0))="","",INDEX(市场案例库!$D$6:$D$35,MATCH(D10,市场案例库!$A$6:$A$35,0)))),IF(COUNTIFS(市场案例库!$A$6:$A$35,C10)<>1,"",IF(INDEX(市场案例库!$D$6:$D$35,MATCH(C10,市场案例库!$A$6:$A$35,0))="","",INDEX(市场案例库!$D$6:$D$35,MATCH(C10,市场案例库!$A$6:$A$35,0))))=IF(COUNTIFS(市场案例库!$A$6:$A$35,D10)<>1,"",IF(INDEX(市场案例库!$D$6:$D$35,MATCH(D10,市场案例库!$A$6:$A$35,0))="","",INDEX(市场案例库!$D$6:$D$35,MATCH(D10,市场案例库!$A$6:$A$35,0))))),"重复待复核","三案例齐全")) -> 三案例齐全 | G10: =IF(F10<>"三案例齐全","待补组合",IF(AND(IF(COUNTIFS(市场案例库!$A$6:$A$35,B10)<>1,"",IF(INDEX(市场案例库!$F$6:$F$35,MATCH(B10,市场案例库!$A$6:$A$35,0))="","",INDEX(市场案例库!$F$6:$F$35,MATCH(B10,市场案例库!$A$6:$A$35,0))))=IF(COUNTIFS(资产清单!$A$6:$A$25,A10)<>1,"",IF(INDEX(资产清单!$J$6:$J$25,MATCH(A10,资产清单!$A$6:$A$25,0))="","",INDEX(资产清单!$J$6:$J$25,MATCH(A10,资产清单!$A$6:$A$25,0)))),IF(COUNTIFS(市场案例库!$A$6:$A$35,B10)<>1,"",IF(INDEX(市场案例库!$E$6:$E$35,MATCH(B10,市场案例库!$A$6:$A$35,0))="","",INDEX(市场案例库!$E$6:$E$35,MATCH(B10,市场案例库!$A$6:$A$35,0))))=IF(COUNTIFS(资产清单!$A$6:$A$25,A10)<>1,"",IF(INDEX(资产清单!$H$6:$H$25,MATCH(A10,资产清单!$A$6:$A$25,0))="","",INDEX(资产清单!$H$6:$H$25,MATCH(A10,资产清单!$A$6:$A$25,0)))),IF(COUNTIFS(市场案例库!$A$6:$A$35,C10)<>1,"",IF(INDEX(市场案例库!$F$6:$F$35,MATCH(C10,市场案例库!$A$6:$A$35,0))="","",INDEX(市场案例库!$F$6:$F$35,MATCH(C10,市场案例库!$A$6:$A$35,0))))=IF(COUNTIFS(资产清单!$A$6:$A$25,A10)<>1,"",IF(INDEX(资产清单!$J$6:$J$25,MATCH(A10,资产清单!$A$6:$A$25,0))="","",INDEX(资产清单!$J$6:$J$25,MATCH(A10,资产清单!$A$6:$A$25,0)))),IF(COUNTIFS(市场案例库!$A$6:$A$35,C10)<>1,"",IF(INDEX(市场案例库!$E$6:$E$35,MATCH(C10,市场案例库!$A$6:$A$35,0))="","",INDEX(市场案例库!$E$6:$E$35,MATCH(C10,市场案例库!$A$6:$A$35,0))))=IF(COUNTIFS(资产清单!$A$6:$A$25,A10)<>1,"",IF(INDEX(资产清单!$H$6:$H$25,MATCH(A10,资产清单!$A$6:$A$25,0))="","",INDEX(资产清单!$H$6:$H$25,MATCH(A10,资产清单!$A$6:$A$25,0)))),IF(COUNTIFS(市场案例库!$A$6:$A$35,D10)<>1,"",IF(INDEX(市场案例库!$F$6:$F$35,MATCH(D10,市场案例库!$A$6:$A$35,0))="","",INDEX(市场案例库!$F$6:$F$35,MATCH(D10,市场案例库!$A$6:$A$35,0))))=IF(COUNTIFS(资产清单!$A$6:$A$25,A10)<>1,"",IF(INDEX(资产清单!$J$6:$J$25,MATCH(A10,资产清单!$A$6:$A$25,0))="","",INDEX(资产清单!$J$6:$J$25,MATCH(A10,资产清单!$A$6:$A$25,0)))),IF(COUNTIFS(市场案例库!$A$6:$A$35,D10)<>1,"",IF(INDEX(市场案例库!$E$6:$E$35,MATCH(D10,市场案例库!$A$6:$A$35,0))="","",INDEX(市场案例库!$E$6:$E$35,MATCH(D10,市场案例库!$A$6:$A$35,0))))=IF(COUNTIFS(资产清单!$A$6:$A$25,A10)<>1,"",IF(INDEX(资产清单!$H$6:$H$25,MATCH(A10,资产清单!$A$6:$A$25,0))="","",INDEX(资产清单!$H$6:$H$25,MATCH(A10,资产清单!$A$6:$A$25,0))))),"用途口径一致","用途口径不一致")) -> 用途口径一致 | H10: =IF(AND(COUNTIFS(修正明细!$N$198:$N$213,B10)=16,COUNTIFS(修正明细!$N$214:$N$229,C10)=16,COUNTIFS(修正明细!$N$230:$N$245,D10)=16),"绑定有效","待重判评分") -> 绑定有效 | I10: 模拟资料未真实核验
A11: RP-006 | B11: SC-010 | C11: SC-011 | D11: SC-012 | E11: 精确同址同类同层，可共享案例；面积逐项修正 | F11: =IF(NOT(AND(COUNTIFS(市场案例库!$A$6:$A$35,B11)=1,COUNTIFS(市场案例库!$A$6:$A$35,C11)=1,COUNTIFS(市场案例库!$A$6:$A$35,D11)=1)),"待补有效案例",IF(OR(B11=C11,B11=D11,C11=D11,IF(COUNTIFS(市场案例库!$A$6:$A$35,B11)<>1,"",IF(INDEX(市场案例库!$C$6:$C$35,MATCH(B11,市场案例库!$A$6:$A$35,0))="","",INDEX(市场案例库!$C$6:$C$35,MATCH(B11,市场案例库!$A$6:$A$35,0))))=IF(COUNTIFS(市场案例库!$A$6:$A$35,C11)<>1,"",IF(INDEX(市场案例库!$C$6:$C$35,MATCH(C11,市场案例库!$A$6:$A$35,0))="","",INDEX(市场案例库!$C$6:$C$35,MATCH(C11,市场案例库!$A$6:$A$35,0)))),IF(COUNTIFS(市场案例库!$A$6:$A$35,B11)<>1,"",IF(INDEX(市场案例库!$C$6:$C$35,MATCH(B11,市场案例库!$A$6:$A$35,0))="","",INDEX(市场案例库!$C$6:$C$35,MATCH(B11,市场案例库!$A$6:$A$35,0))))=IF(COUNTIFS(市场案例库!$A$6:$A$35,D11)<>1,"",IF(INDEX(市场案例库!$C$6:$C$35,MATCH(D11,市场案例库!$A$6:$A$35,0))="","",INDEX(市场案例库!$C$6:$C$35,MATCH(D11,市场案例库!$A$6:$A$35,0)))),IF(COUNTIFS(市场案例库!$A$6:$A$35,C11)<>1,"",IF(INDEX(市场案例库!$C$6:$C$35,MATCH(C11,市场案例库!$A$6:$A$35,0))="","",INDEX(市场案例库!$C$6:$C$35,MATCH(C11,市场案例库!$A$6:$A$35,0))))=IF(COUNTIFS(市场案例库!$A$6:$A$35,D11)<>1,"",IF(INDEX(市场案例库!$C$6:$C$35,MATCH(D11,市场案例库!$A$6:$A$35,0))="","",INDEX(市场案例库!$C$6:$C$35,MATCH(D11,市场案例库!$A$6:$A$35,0)))),IF(COUNTIFS(市场案例库!$A$6:$A$35,B11)<>1,"",IF(INDEX(市场案例库!$D$6:$D$35,MATCH(B11,市场案例库!$A$6:$A$35,0))="","",INDEX(市场案例库!$D$6:$D$35,MATCH(B11,市场案例库!$A$6:$A$35,0))))=IF(COUNTIFS(市场案例库!$A$6:$A$35,C11)<>1,"",IF(INDEX(市场案例库!$D$6:$D$35,MATCH(C11,市场案例库!$A$6:$A$35,0))="","",INDEX(市场案例库!$D$6:$D$35,MATCH(C11,市场案例库!$A$6:$A$35,0)))),IF(COUNTIFS(市场案例库!$A$6:$A$35,B11)<>1,"",IF(INDEX(市场案例库!$D$6:$D$35,MATCH(B11,市场案例库!$A$6:$A$35,0))="","",INDEX(市场案例库!$D$6:$D$35,MATCH(B11,市场案例库!$A$6:$A$35,0))))=IF(COUNTIFS(市场案例库!$A$6:$A$35,D11)<>1,"",IF(INDEX(市场案例库!$D$6:$D$35,MATCH(D11,市场案例库!$A$6:$A$35,0))="","",INDEX(市场案例库!$D$6:$D$35,MATCH(D11,市场案例库!$A$6:$A$35,0)))),IF(COUNTIFS(市场案例库!$A$6:$A$35,C11)<>1,"",IF(INDEX(市场案例库!$D$6:$D$35,MATCH(C11,市场案例库!$A$6:$A$35,0))="","",INDEX(市场案例库!$D$6:$D$35,MATCH(C11,市场案例库!$A$6:$A$35,0))))=IF(COUNTIFS(市场案例库!$A$6:$A$35,D11)<>1,"",IF(INDEX(市场案例库!$D$6:$D$35,MATCH(D11,市场案例库!$A$6:$A$35,0))="","",INDEX(市场案例库!$D$6:$D$35,MATCH(D11,市场案例库!$A$6:$A$35,0))))),"重复待复核","三案例齐全")) -> 三案例齐全 | G11: =IF(F11<>"三案例齐全","待补组合",IF(AND(IF(COUNTIFS(市场案例库!$A$6:$A$35,B11)<>1,"",IF(INDEX(市场案例库!$F$6:$F$35,MATCH(B11,市场案例库!$A$6:$A$35,0))="","",INDEX(市场案例库!$F$6:$F$35,MATCH(B11,市场案例库!$A$6:$A$35,0))))=IF(COUNTIFS(资产清单!$A$6:$A$25,A11)<>1,"",IF(INDEX(资产清单!$J$6:$J$25,MATCH(A11,资产清单!$A$6:$A$25,0))="","",INDEX(资产清单!$J$6:$J$25,MATCH(A11,资产清单!$A$6:$A$25,0)))),IF(COUNTIFS(市场案例库!$A$6:$A$35,B11)<>1,"",IF(INDEX(市场案例库!$E$6:$E$35,MATCH(B11,市场案例库!$A$6:$A$35,0))="","",INDEX(市场案例库!$E$6:$E$35,MATCH(B11,市场案例库!$A$6:$A$35,0))))=IF(COUNTIFS(资产清单!$A$6:$A$25,A11)<>1,"",IF(INDEX(资产清单!$H$6:$H$25,MATCH(A11,资产清单!$A$6:$A$25,0))="","",INDEX(资产清单!$H$6:$H$25,MATCH(A11,资产清单!$A$6:$A$25,0)))),IF(COUNTIFS(市场案例库!$A$6:$A$35,C11)<>1,"",IF(INDEX(市场案例库!$F$6:$F$35,MATCH(C11,市场案例库!$A$6:$A$35,0))="","",INDEX(市场案例库!$F$6:$F$35,MATCH(C11,市场案例库!$A$6:$A$35,0))))=IF(COUNTIFS(资产清单!$A$6:$A$25,A11)<>1,"",IF(INDEX(资产清单!$J$6:$J$25,MATCH(A11,资产清单!$A$6:$A$25,0))="","",INDEX(资产清单!$J$6:$J$25,MATCH(A11,资产清单!$A$6:$A$25,0)))),IF(COUNTIFS(市场案例库!$A$6:$A$35,C11)<>1,"",IF(INDEX(市场案例库!$E$6:$E$35,MATCH(C11,市场案例库!$A$6:$A$35,0))="","",INDEX(市场案例库!$E$6:$E$35,MATCH(C11,市场案例库!$A$6:$A$35,0))))=IF(COUNTIFS(资产清单!$A$6:$A$25,A11)<>1,"",IF(INDEX(资产清单!$H$6:$H$25,MATCH(A11,资产清单!$A$6:$A$25,0))="","",INDEX(资产清单!$H$6:$H$25,MATCH(A11,资产清单!$A$6:$A$25,0)))),IF(COUNTIFS(市场案例库!$A$6:$A$35,D11)<>1,"",IF(INDEX(市场案例库!$F$6:$F$35,MATCH(D11,市场案例库!$A$6:$A$35,0))="","",INDEX(市场案例库!$F$6:$F$35,MATCH(D11,市场案例库!$A$6:$A$35,0))))=IF(COUNTIFS(资产清单!$A$6:$A$25,A11)<>1,"",IF(INDEX(资产清单!$J$6:$J$25,MATCH(A11,资产清单!$A$6:$A$25,0))="","",INDEX(资产清单!$J$6:$J$25,MATCH(A11,资产清单!$A$6:$A$25,0)))),IF(COUNTIFS(市场案例库!$A$6:$A$35,D11)<>1,"",IF(INDEX(市场案例库!$E$6:$E$35,MATCH(D11,市场案例库!$A$6:$A$35,0))="","",INDEX(市场案例库!$E$6:$E$35,MATCH(D11,市场案例库!$A$6:$A$35,0))))=IF(COUNTIFS(资产清单!$A$6:$A$25,A11)<>1,"",IF(INDEX(资产清单!$H$6:$H$25,MATCH(A11,资产清单!$A$6:$A$25,0))="","",INDEX(资产清单!$H$6:$H$25,MATCH(A11,资产清单!$A$6:$A$25,0))))),"用途口径一致","用途口径不一致")) -> 用途口径一致 | H11: =IF(AND(COUNTIFS(修正明细!$N$246:$N$261,B11)=16,COUNTIFS(修正明细!$N$262:$N$277,C11)=16,COUNTIFS(修正明细!$N$278:$N$293,D11)=16),"绑定有效","待重判评分") -> 绑定有效 | I11: 模拟资料未真实核验
A12: RP-007 | B12: SC-013 | C12: SC-014 | D12: SC-015 | E12: 同用途同计租口径，保留楼层等差异 | F12: =IF(NOT(AND(COUNTIFS(市场案例库!$A$6:$A$35,B12)=1,COUNTIFS(市场案例库!$A$6:$A$35,C12)=1,COUNTIFS(市场案例库!$A$6:$A$35,D12)=1)),"待补有效案例",IF(OR(B12=C12,B12=D12,C12=D12,IF(COUNTIFS(市场案例库!$A$6:$A$35,B12)<>1,"",IF(INDEX(市场案例库!$C$6:$C$35,MATCH(B12,市场案例库!$A$6:$A$35,0))="","",INDEX(市场案例库!$C$6:$C$35,MATCH(B12,市场案例库!$A$6:$A$35,0))))=IF(COUNTIFS(市场案例库!$A$6:$A$35,C12)<>1,"",IF(INDEX(市场案例库!$C$6:$C$35,MATCH(C12,市场案例库!$A$6:$A$35,0))="","",INDEX(市场案例库!$C$6:$C$35,MATCH(C12,市场案例库!$A$6:$A$35,0)))),IF(COUNTIFS(市场案例库!$A$6:$A$35,B12)<>1,"",IF(INDEX(市场案例库!$C$6:$C$35,MATCH(B12,市场案例库!$A$6:$A$35,0))="","",INDEX(市场案例库!$C$6:$C$35,MATCH(B12,市场案例库!$A$6:$A$35,0))))=IF(COUNTIFS(市场案例库!$A$6:$A$35,D12)<>1,"",IF(INDEX(市场案例库!$C$6:$C$35,MATCH(D12,市场案例库!$A$6:$A$35,0))="","",INDEX(市场案例库!$C$6:$C$35,MATCH(D12,市场案例库!$A$6:$A$35,0)))),IF(COUNTIFS(市场案例库!$A$6:$A$35,C12)<>1,"",IF(INDEX(市场案例库!$C$6:$C$35,MATCH(C12,市场案例库!$A$6:$A$35,0))="","",INDEX(市场案例库!$C$6:$C$35,MATCH(C12,市场案例库!$A$6:$A$35,0))))=IF(COUNTIFS(市场案例库!$A$6:$A$35,D12)<>1,"",IF(INDEX(市场案例库!$C$6:$C$35,MATCH(D12,市场案例库!$A$6:$A$35,0))="","",INDEX(市场案例库!$C$6:$C$35,MATCH(D12,市场案例库!$A$6:$A$35,0)))),IF(COUNTIFS(市场案例库!$A$6:$A$35,B12)<>1,"",IF(INDEX(市场案例库!$D$6:$D$35,MATCH(B12,市场案例库!$A$6:$A$35,0))="","",INDEX(市场案例库!$D$6:$D$35,MATCH(B12,市场案例库!$A$6:$A$35,0))))=IF(COUNTIFS(市场案例库!$A$6:$A$35,C12)<>1,"",IF(INDEX(市场案例库!$D$6:$D$35,MATCH(C12,市场案例库!$A$6:$A$35,0))="","",INDEX(市场案例库!$D$6:$D$35,MATCH(C12,市场案例库!$A$6:$A$35,0)))),IF(COUNTIFS(市场案例库!$A$6:$A$35,B12)<>1,"",IF(INDEX(市场案例库!$D$6:$D$35,MATCH(B12,市场案例库!$A$6:$A$35,0))="","",INDEX(市场案例库!$D$6:$D$35,MATCH(B12,市场案例库!$A$6:$A$35,0))))=IF(COUNTIFS(市场案例库!$A$6:$A$35,D12)<>1,"",IF(INDEX(市场案例库!$D$6:$D$35,MATCH(D12,市场案例库!$A$6:$A$35,0))="","",INDEX(市场案例库!$D$6:$D$35,MATCH(D12,市场案例库!$A$6:$A$35,0)))),IF(COUNTIFS(市场案例库!$A$6:$A$35,C12)<>1,"",IF(INDEX(市场案例库!$D$6:$D$35,MATCH(C12,市场案例库!$A$6:$A$35,0))="","",INDEX(市场案例库!$D$6:$D$35,MATCH(C12,市场案例库!$A$6:$A$35,0))))=IF(COUNTIFS(市场案例库!$A$6:$A$35,D12)<>1,"",IF(INDEX(市场案例库!$D$6:$D$35,MATCH(D12,市场案例库!$A$6:$A$35,0))="","",INDEX(市场案例库!$D$6:$D$35,MATCH(D12,市场案例库!$A$6:$A$35,0))))),"重复待复核","三案例齐全")) -> 三案例齐全 | G12: =IF(F12<>"三案例齐全","待补组合",IF(AND(IF(COUNTIFS(市场案例库!$A$6:$A$35,B12)<>1,"",IF(INDEX(市场案例库!$F$6:$F$35,MATCH(B12,市场案例库!$A$6:$A$35,0))="","",INDEX(市场案例库!$F$6:$F$35,MATCH(B12,市场案例库!$A$6:$A$35,0))))=IF(COUNTIFS(资产清单!$A$6:$A$25,A12)<>1,"",IF(INDEX(资产清单!$J$6:$J$25,MATCH(A12,资产清单!$A$6:$A$25,0))="","",INDEX(资产清单!$J$6:$J$25,MATCH(A12,资产清单!$A$6:$A$25,0)))),IF(COUNTIFS(市场案例库!$A$6:$A$35,B12)<>1,"",IF(INDEX(市场案例库!$E$6:$E$35,MATCH(B12,市场案例库!$A$6:$A$35,0))="","",INDEX(市场案例库!$E$6:$E$35,MATCH(B12,市场案例库!$A$6:$A$35,0))))=IF(COUNTIFS(资产清单!$A$6:$A$25,A12)<>1,"",IF(INDEX(资产清单!$H$6:$H$25,MATCH(A12,资产清单!$A$6:$A$25,0))="","",INDEX(资产清单!$H$6:$H$25,MATCH(A12,资产清单!$A$6:$A$25,0)))),IF(COUNTIFS(市场案例库!$A$6:$A$35,C12)<>1,"",IF(INDEX(市场案例库!$F$6:$F$35,MATCH(C12,市场案例库!$A$6:$A$35,0))="","",INDEX(市场案例库!$F$6:$F$35,MATCH(C12,市场案例库!$A$6:$A$35,0))))=IF(COUNTIFS(资产清单!$A$6:$A$25,A12)<>1,"",IF(INDEX(资产清单!$J$6:$J$25,MATCH(A12,资产清单!$A$6:$A$25,0))="","",INDEX(资产清单!$J$6:$J$25,MATCH(A12,资产清单!$A$6:$A$25,0)))),IF(COUNTIFS(市场案例库!$A$6:$A$35,C12)<>1,"",IF(INDEX(市场案例库!$E$6:$E$35,MATCH(C12,市场案例库!$A$6:$A$35,0))="","",INDEX(市场案例库!$E$6:$E$35,MATCH(C12,市场案例库!$A$6:$A$35,0))))=IF(COUNTIFS(资产清单!$A$6:$A$25,A12)<>1,"",IF(INDEX(资产清单!$H$6:$H$25,MATCH(A12,资产清单!$A$6:$A$25,0))="","",INDEX(资产清单!$H$6:$H$25,MATCH(A12,资产清单!$A$6:$A$25,0)))),IF(COUNTIFS(市场案例库!$A$6:$A$35,D12)<>1,"",IF(INDEX(市场案例库!$F$6:$F$35,MATCH(D12,市场案例库!$A$6:$A$35,0))="","",INDEX(市场案例库!$F$6:$F$35,MATCH(D12,市场案例库!$A$6:$A$35,0))))=IF(COUNTIFS(资产清单!$A$6:$A$25,A12)<>1,"",IF(INDEX(资产清单!$J$6:$J$25,MATCH(A12,资产清单!$A$6:$A$25,0))="","",INDEX(资产清单!$J$6:$J$25,MATCH(A12,资产清单!$A$6:$A$25,0)))),IF(COUNTIFS(市场案例库!$A$6:$A$35,D12)<>1,"",IF(INDEX(市场案例库!$E$6:$E$35,MATCH(D12,市场案例库!$A$6:$A$35,0))="","",INDEX(市场案例库!$E$6:$E$35,MATCH(D12,市场案例库!$A$6:$A$35,0))))=IF(COUNTIFS(资产清单!$A$6:$A$25,A12)<>1,"",IF(INDEX(资产清单!$H$6:$H$25,MATCH(A12,资产清单!$A$6:$A$25,0))="","",INDEX(资产清单!$H$6:$H$25,MATCH(A12,资产清单!$A$6:$A$25,0))))),"用途口径一致","用途口径不一致")) -> 用途口径一致 | H12: =IF(AND(COUNTIFS(修正明细!$N$294:$N$309,B12)=16,COUNTIFS(修正明细!$N$310:$N$325,C12)=16,COUNTIFS(修正明细!$N$326:$N$341,D12)=16),"绑定有效","待重判评分") -> 绑定有效 | I12: 模拟资料未真实核验
A13: RP-008 | B13: SC-016 | C13: SC-017 | D13: SC-018 | E13: 同用途同计租口径，保留楼层等差异 | F13: =IF(NOT(AND(COUNTIFS(市场案例库!$A$6:$A$35,B13)=1,COUNTIFS(市场案例库!$A$6:$A$35,C13)=1,COUNTIFS(市场案例库!$A$6:$A$35,D13)=1)),"待补有效案例",IF(OR(B13=C13,B13=D13,C13=D13,IF(COUNTIFS(市场案例库!$A$6:$A$35,B13)<>1,"",IF(INDEX(市场案例库!$C$6:$C$35,MATCH(B13,市场案例库!$A$6:$A$35,0))="","",INDEX(市场案例库!$C$6:$C$35,MATCH(B13,市场案例库!$A$6:$A$35,0))))=IF(COUNTIFS(市场案例库!$A$6:$A$35,C13)<>1,"",IF(INDEX(市场案例库!$C$6:$C$35,MATCH(C13,市场案例库!$A$6:$A$35,0))="","",INDEX(市场案例库!$C$6:$C$35,MATCH(C13,市场案例库!$A$6:$A$35,0)))),IF(COUNTIFS(市场案例库!$A$6:$A$35,B13)<>1,"",IF(INDEX(市场案例库!$C$6:$C$35,MATCH(B13,市场案例库!$A$6:$A$35,0))="","",INDEX(市场案例库!$C$6:$C$35,MATCH(B13,市场案例库!$A$6:$A$35,0))))=IF(COUNTIFS(市场案例库!$A$6:$A$35,D13)<>1,"",IF(INDEX(市场案例库!$C$6:$C$35,MATCH(D13,市场案例库!$A$6:$A$35,0))="","",INDEX(市场案例库!$C$6:$C$35,MATCH(D13,市场案例库!$A$6:$A$35,0)))),IF(COUNTIFS(市场案例库!$A$6:$A$35,C13)<>1,"",IF(INDEX(市场案例库!$C$6:$C$35,MATCH(C13,市场案例库!$A$6:$A$35,0))="","",INDEX(市场案例库!$C$6:$C$35,MATCH(C13,市场案例库!$A$6:$A$35,0))))=IF(COUNTIFS(市场案例库!$A$6:$A$35,D13)<>1,"",IF(INDEX(市场案例库!$C$6:$C$35,MATCH(D13,市场案例库!$A$6:$A$35,0))="","",INDEX(市场案例库!$C$6:$C$35,MATCH(D13,市场案例库!$A$6:$A$35,0)))),IF(COUNTIFS(市场案例库!$A$6:$A$35,B13)<>1,"",IF(INDEX(市场案例库!$D$6:$D$35,MATCH(B13,市场案例库!$A$6:$A$35,0))="","",INDEX(市场案例库!$D$6:$D$35,MATCH(B13,市场案例库!$A$6:$A$35,0))))=IF(COUNTIFS(市场案例库!$A$6:$A$35,C13)<>1,"",IF(INDEX(市场案例库!$D$6:$D$35,MATCH(C13,市场案例库!$A$6:$A$35,0))="","",INDEX(市场案例库!$D$6:$D$35,MATCH(C13,市场案例库!$A$6:$A$35,0)))),IF(COUNTIFS(市场案例库!$A$6:$A$35,B13)<>1,"",IF(INDEX(市场案例库!$D$6:$D$35,MATCH(B13,市场案例库!$A$6:$A$35,0))="","",INDEX(市场案例库!$D$6:$D$35,MATCH(B13,市场案例库!$A$6:$A$35,0))))=IF(COUNTIFS(市场案例库!$A$6:$A$35,D13)<>1,"",IF(INDEX(市场案例库!$D$6:$D$35,MATCH(D13,市场案例库!$A$6:$A$35,0))="","",INDEX(市场案例库!$D$6:$D$35,MATCH(D13,市场案例库!$A$6:$A$35,0)))),IF(COUNTIFS(市场案例库!$A$6:$A$35,C13)<>1,"",IF(INDEX(市场案例库!$D$6:$D$35,MATCH(C13,市场案例库!$A$6:$A$35,0))="","",INDEX(市场案例库!$D$6:$D$35,MATCH(C13,市场案例库!$A$6:$A$35,0))))=IF(COUNTIFS(市场案例库!$A$6:$A$35,D13)<>1,"",IF(INDEX(市场案例库!$D$6:$D$35,MATCH(D13,市场案例库!$A$6:$A$35,0))="","",INDEX(市场案例库!$D$6:$D$35,MATCH(D13,市场案例库!$A$6:$A$35,0))))),"重复待复核","三案例齐全")) -> 三案例齐全 | G13: =IF(F13<>"三案例齐全","待补组合",IF(AND(IF(COUNTIFS(市场案例库!$A$6:$A$35,B13)<>1,"",IF(INDEX(市场案例库!$F$6:$F$35,MATCH(B13,市场案例库!$A$6:$A$35,0))="","",INDEX(市场案例库!$F$6:$F$35,MATCH(B13,市场案例库!$A$6:$A$35,0))))=IF(COUNTIFS(资产清单!$A$6:$A$25,A13)<>1,"",IF(INDEX(资产清单!$J$6:$J$25,MATCH(A13,资产清单!$A$6:$A$25,0))="","",INDEX(资产清单!$J$6:$J$25,MATCH(A13,资产清单!$A$6:$A$25,0)))),IF(COUNTIFS(市场案例库!$A$6:$A$35,B13)<>1,"",IF(INDEX(市场案例库!$E$6:$E$35,MATCH(B13,市场案例库!$A$6:$A$35,0))="","",INDEX(市场案例库!$E$6:$E$35,MATCH(B13,市场案例库!$A$6:$A$35,0))))=IF(COUNTIFS(资产清单!$A$6:$A$25,A13)<>1,"",IF(INDEX(资产清单!$H$6:$H$25,MATCH(A13,资产清单!$A$6:$A$25,0))="","",INDEX(资产清单!$H$6:$H$25,MATCH(A13,资产清单!$A$6:$A$25,0)))),IF(COUNTIFS(市场案例库!$A$6:$A$35,C13)<>1,"",IF(INDEX(市场案例库!$F$6:$F$35,MATCH(C13,市场案例库!$A$6:$A$35,0))="","",INDEX(市场案例库!$F$6:$F$35,MATCH(C13,市场案例库!$A$6:$A$35,0))))=IF(COUNTIFS(资产清单!$A$6:$A$25,A13)<>1,"",IF(INDEX(资产清单!$J$6:$J$25,MATCH(A13,资产清单!$A$6:$A$25,0))="","",INDEX(资产清单!$J$6:$J$25,MATCH(A13,资产清单!$A$6:$A$25,0)))),IF(COUNTIFS(市场案例库!$A$6:$A$35,C13)<>1,"",IF(INDEX(市场案例库!$E$6:$E$35,MATCH(C13,市场案例库!$A$6:$A$35,0))="","",INDEX(市场案例库!$E$6:$E$35,MATCH(C13,市场案例库!$A$6:$A$35,0))))=IF(COUNTIFS(资产清单!$A$6:$A$25,A13)<>1,"",IF(INDEX(资产清单!$H$6:$H$25,MATCH(A13,资产清单!$A$6:$A$25,0))="","",INDEX(资产清单!$H$6:$H$25,MATCH(A13,资产清单!$A$6:$A$25,0)))),IF(COUNTIFS(市场案例库!$A$6:$A$35,D13)<>1,"",IF(INDEX(市场案例库!$F$6:$F$35,MATCH(D13,市场案例库!$A$6:$A$35,0))="","",INDEX(市场案例库!$F$6:$F$35,MATCH(D13,市场案例库!$A$6:$A$35,0))))=IF(COUNTIFS(资产清单!$A$6:$A$25,A13)<>1,"",IF(INDEX(资产清单!$J$6:$J$25,MATCH(A13,资产清单!$A$6:$A$25,0))="","",INDEX(资产清单!$J$6:$J$25,MATCH(A13,资产清单!$A$6:$A$25,0)))),IF(COUNTIFS(市场案例库!$A$6:$A$35,D13)<>1,"",IF(INDEX(市场案例库!$E$6:$E$35,MATCH(D13,市场案例库!$A$6:$A$35,0))="","",INDEX(市场案例库!$E$6:$E$35,MATCH(D13,市场案例库!$A$6:$A$35,0))))=IF(COUNTIFS(资产清单!$A$6:$A$25,A13)<>1,"",IF(INDEX(资产清单!$H$6:$H$25,MATCH(A13,资产清单!$A$6:$A$25,0))="","",INDEX(资产清单!$H$6:$H$25,MATCH(A13,资产清单!$A$6:$A$25,0))))),"用途口径一致","用途口径不一致")) -> 用途口径一致 | H13: =IF(AND(COUNTIFS(修正明细!$N$342:$N$357,B13)=16,COUNTIFS(修正明细!$N$358:$N$373,C13)=16,COUNTIFS(修正明细!$N$374:$N$389,D13)=16),"绑定有效","待重判评分") -> 绑定有效 | I13: 模拟资料未真实核验
A14: RP-009 | B14: SC-019 | C14: SC-020 | D14: SC-021 | E14: 同用途同计租口径，保留楼层等差异 | F14: =IF(NOT(AND(COUNTIFS(市场案例库!$A$6:$A$35,B14)=1,COUNTIFS(市场案例库!$A$6:$A$35,C14)=1,COUNTIFS(市场案例库!$A$6:$A$35,D14)=1)),"待补有效案例",IF(OR(B14=C14,B14=D14,C14=D14,IF(COUNTIFS(市场案例库!$A$6:$A$35,B14)<>1,"",IF(INDEX(市场案例库!$C$6:$C$35,MATCH(B14,市场案例库!$A$6:$A$35,0))="","",INDEX(市场案例库!$C$6:$C$35,MATCH(B14,市场案例库!$A$6:$A$35,0))))=IF(COUNTIFS(市场案例库!$A$6:$A$35,C14)<>1,"",IF(INDEX(市场案例库!$C$6:$C$35,MATCH(C14,市场案例库!$A$6:$A$35,0))="","",INDEX(市场案例库!$C$6:$C$35,MATCH(C14,市场案例库!$A$6:$A$35,0)))),IF(COUNTIFS(市场案例库!$A$6:$A$35,B14)<>1,"",IF(INDEX(市场案例库!$C$6:$C$35,MATCH(B14,市场案例库!$A$6:$A$35,0))="","",INDEX(市场案例库!$C$6:$C$35,MATCH(B14,市场案例库!$A$6:$A$35,0))))=IF(COUNTIFS(市场案例库!$A$6:$A$35,D14)<>1,"",IF(INDEX(市场案例库!$C$6:$C$35,MATCH(D14,市场案例库!$A$6:$A$35,0))="","",INDEX(市场案例库!$C$6:$C$35,MATCH(D14,市场案例库!$A$6:$A$35,0)))),IF(COUNTIFS(市场案例库!$A$6:$A$35,C14)<>1,"",IF(INDEX(市场案例库!$C$6:$C$35,MATCH(C14,市场案例库!$A$6:$A$35,0))="","",INDEX(市场案例库!$C$6:$C$35,MATCH(C14,市场案例库!$A$6:$A$35,0))))=IF(COUNTIFS(市场案例库!$A$6:$A$35,D14)<>1,"",IF(INDEX(市场案例库!$C$6:$C$35,MATCH(D14,市场案例库!$A$6:$A$35,0))="","",INDEX(市场案例库!$C$6:$C$35,MATCH(D14,市场案例库!$A$6:$A$35,0)))),IF(COUNTIFS(市场案例库!$A$6:$A$35,B14)<>1,"",IF(INDEX(市场案例库!$D$6:$D$35,MATCH(B14,市场案例库!$A$6:$A$35,0))="","",INDEX(市场案例库!$D$6:$D$35,MATCH(B14,市场案例库!$A$6:$A$35,0))))=IF(COUNTIFS(市场案例库!$A$6:$A$35,C14)<>1,"",IF(INDEX(市场案例库!$D$6:$D$35,MATCH(C14,市场案例库!$A$6:$A$35,0))="","",INDEX(市场案例库!$D$6:$D$35,MATCH(C14,市场案例库!$A$6:$A$35,0)))),IF(COUNTIFS(市场案例库!$A$6:$A$35,B14)<>1,"",IF(INDEX(市场案例库!$D$6:$D$35,MATCH(B14,市场案例库!$A$6:$A$35,0))="","",INDEX(市场案例库!$D$6:$D$35,MATCH(B14,市场案例库!$A$6:$A$35,0))))=IF(COUNTIFS(市场案例库!$A$6:$A$35,D14)<>1,"",IF(INDEX(市场案例库!$D$6:$D$35,MATCH(D14,市场案例库!$A$6:$A$35,0))="","",INDEX(市场案例库!$D$6:$D$35,MATCH(D14,市场案例库!$A$6:$A$35,0)))),IF(COUNTIFS(市场案例库!$A$6:$A$35,C14)<>1,"",IF(INDEX(市场案例库!$D$6:$D$35,MATCH(C14,市场案例库!$A$6:$A$35,0))="","",INDEX(市场案例库!$D$6:$D$35,MATCH(C14,市场案例库!$A$6:$A$35,0))))=IF(COUNTIFS(市场案例库!$A$6:$A$35,D14)<>1,"",IF(INDEX(市场案例库!$D$6:$D$35,MATCH(D14,市场案例库!$A$6:$A$35,0))="","",INDEX(市场案例库!$D$6:$D$35,MATCH(D14,市场案例库!$A$6:$A$35,0))))),"重复待复核","三案例齐全")) -> 三案例齐全 | G14: =IF(F14<>"三案例齐全","待补组合",IF(AND(IF(COUNTIFS(市场案例库!$A$6:$A$35,B14)<>1,"",IF(INDEX(市场案例库!$F$6:$F$35,MATCH(B14,市场案例库!$A$6:$A$35,0))="","",INDEX(市场案例库!$F$6:$F$35,MATCH(B14,市场案例库!$A$6:$A$35,0))))=IF(COUNTIFS(资产清单!$A$6:$A$25,A14)<>1,"",IF(INDEX(资产清单!$J$6:$J$25,MATCH(A14,资产清单!$A$6:$A$25,0))="","",INDEX(资产清单!$J$6:$J$25,MATCH(A14,资产清单!$A$6:$A$25,0)))),IF(COUNTIFS(市场案例库!$A$6:$A$35,B14)<>1,"",IF(INDEX(市场案例库!$E$6:$E$35,MATCH(B14,市场案例库!$A$6:$A$35,0))="","",INDEX(市场案例库!$E$6:$E$35,MATCH(B14,市场案例库!$A$6:$A$35,0))))=IF(COUNTIFS(资产清单!$A$6:$A$25,A14)<>1,"",IF(INDEX(资产清单!$H$6:$H$25,MATCH(A14,资产清单!$A$6:$A$25,0))="","",INDEX(资产清单!$H$6:$H$25,MATCH(A14,资产清单!$A$6:$A$25,0)))),IF(COUNTIFS(市场案例库!$A$6:$A$35,C14)<>1,"",IF(INDEX(市场案例库!$F$6:$F$35,MATCH(C14,市场案例库!$A$6:$A$35,0))="","",INDEX(市场案例库!$F$6:$F$35,MATCH(C14,市场案例库!$A$6:$A$35,0))))=IF(COUNTIFS(资产清单!$A$6:$A$25,A14)<>1,"",IF(INDEX(资产清单!$J$6:$J$25,MATCH(A14,资产清单!$A$6:$A$25,0))="","",INDEX(资产清单!$J$6:$J$25,MATCH(A14,资产清单!$A$6:$A$25,0)))),IF(COUNTIFS(市场案例库!$A$6:$A$35,C14)<>1,"",IF(INDEX(市场案例库!$E$6:$E$35,MATCH(C14,市场案例库!$A$6:$A$35,0))="","",INDEX(市场案例库!$E$6:$E$35,MATCH(C14,市场案例库!$A$6:$A$35,0))))=IF(COUNTIFS(资产清单!$A$6:$A$25,A14)<>1,"",IF(INDEX(资产清单!$H$6:$H$25,MATCH(A14,资产清单!$A$6:$A$25,0))="","",INDEX(资产清单!$H$6:$H$25,MATCH(A14,资产清单!$A$6:$A$25,0)))),IF(COUNTIFS(市场案例库!$A$6:$A$35,D14)<>1,"",IF(INDEX(市场案例库!$F$6:$F$35,MATCH(D14,市场案例库!$A$6:$A$35,0))="","",INDEX(市场案例库!$F$6:$F$35,MATCH(D14,市场案例库!$A$6:$A$35,0))))=IF(COUNTIFS(资产清单!$A$6:$A$25,A14)<>1,"",IF(INDEX(资产清单!$J$6:$J$25,MATCH(A14,资产清单!$A$6:$A$25,0))="","",INDEX(资产清单!$J$6:$J$25,MATCH(A14,资产清单!$A$6:$A$25,0)))),IF(COUNTIFS(市场案例库!$A$6:$A$35,D14)<>1,"",IF(INDEX(市场案例库!$E$6:$E$35,MATCH(D14,市场案例库!$A$6:$A$35,0))="","",INDEX(市场案例库!$E$6:$E$35,MATCH(D14,市场案例库!$A$6:$A$35,0))))=IF(COUNTIFS(资产清单!$A$6:$A$25,A14)<>1,"",IF(INDEX(资产清单!$H$6:$H$25,MATCH(A14,资产清单!$A$6:$A$25,0))="","",INDEX(资产清单!$H$6:$H$25,MATCH(A14,资产清单!$A$6:$A$25,0))))),"用途口径一致","用途口径不一致")) -> 用途口径一致 | H14: =IF(AND(COUNTIFS(修正明细!$N$390:$N$405,B14)=16,COUNTIFS(修正明细!$N$406:$N$421,C14)=16,COUNTIFS(修正明细!$N$422:$N$437,D14)=16),"绑定有效","待重判评分") -> 绑定有效 | I14: 模拟资料未真实核验
A15: RP-010 | B15: SC-022 | C15: SC-023 | D15: SC-024 | E15: 同用途同计租口径，保留楼层等差异 | F15: =IF(NOT(AND(COUNTIFS(市场案例库!$A$6:$A$35,B15)=1,COUNTIFS(市场案例库!$A$6:$A$35,C15)=1,COUNTIFS(市场案例库!$A$6:$A$35,D15)=1)),"待补有效案例",IF(OR(B15=C15,B15=D15,C15=D15,IF(COUNTIFS(市场案例库!$A$6:$A$35,B15)<>1,"",IF(INDEX(市场案例库!$C$6:$C$35,MATCH(B15,市场案例库!$A$6:$A$35,0))="","",INDEX(市场案例库!$C$6:$C$35,MATCH(B15,市场案例库!$A$6:$A$35,0))))=IF(COUNTIFS(市场案例库!$A$6:$A$35,C15)<>1,"",IF(INDEX(市场案例库!$C$6:$C$35,MATCH(C15,市场案例库!$A$6:$A$35,0))="","",INDEX(市场案例库!$C$6:$C$35,MATCH(C15,市场案例库!$A$6:$A$35,0)))),IF(COUNTIFS(市场案例库!$A$6:$A$35,B15)<>1,"",IF(INDEX(市场案例库!$C$6:$C$35,MATCH(B15,市场案例库!$A$6:$A$35,0))="","",INDEX(市场案例库!$C$6:$C$35,MATCH(B15,市场案例库!$A$6:$A$35,0))))=IF(COUNTIFS(市场案例库!$A$6:$A$35,D15)<>1,"",IF(INDEX(市场案例库!$C$6:$C$35,MATCH(D15,市场案例库!$A$6:$A$35,0))="","",INDEX(市场案例库!$C$6:$C$35,MATCH(D15,市场案例库!$A$6:$A$35,0)))),IF(COUNTIFS(市场案例库!$A$6:$A$35,C15)<>1,"",IF(INDEX(市场案例库!$C$6:$C$35,MATCH(C15,市场案例库!$A$6:$A$35,0))="","",INDEX(市场案例库!$C$6:$C$35,MATCH(C15,市场案例库!$A$6:$A$35,0))))=IF(COUNTIFS(市场案例库!$A$6:$A$35,D15)<>1,"",IF(INDEX(市场案例库!$C$6:$C$35,MATCH(D15,市场案例库!$A$6:$A$35,0))="","",INDEX(市场案例库!$C$6:$C$35,MATCH(D15,市场案例库!$A$6:$A$35,0)))),IF(COUNTIFS(市场案例库!$A$6:$A$35,B15)<>1,"",IF(INDEX(市场案例库!$D$6:$D$35,MATCH(B15,市场案例库!$A$6:$A$35,0))="","",INDEX(市场案例库!$D$6:$D$35,MATCH(B15,市场案例库!$A$6:$A$35,0))))=IF(COUNTIFS(市场案例库!$A$6:$A$35,C15)<>1,"",IF(INDEX(市场案例库!$D$6:$D$35,MATCH(C15,市场案例库!$A$6:$A$35,0))="","",INDEX(市场案例库!$D$6:$D$35,MATCH(C15,市场案例库!$A$6:$A$35,0)))),IF(COUNTIFS(市场案例库!$A$6:$A$35,B15)<>1,"",IF(INDEX(市场案例库!$D$6:$D$35,MATCH(B15,市场案例库!$A$6:$A$35,0))="","",INDEX(市场案例库!$D$6:$D$35,MATCH(B15,市场案例库!$A$6:$A$35,0))))=IF(COUNTIFS(市场案例库!$A$6:$A$35,D15)<>1,"",IF(INDEX(市场案例库!$D$6:$D$35,MATCH(D15,市场案例库!$A$6:$A$35,0))="","",INDEX(市场案例库!$D$6:$D$35,MATCH(D15,市场案例库!$A$6:$A$35,0)))),IF(COUNTIFS(市场案例库!$A$6:$A$35,C15)<>1,"",IF(INDEX(市场案例库!$D$6:$D$35,MATCH(C15,市场案例库!$A$6:$A$35,0))="","",INDEX(市场案例库!$D$6:$D$35,MATCH(C15,市场案例库!$A$6:$A$35,0))))=IF(COUNTIFS(市场案例库!$A$6:$A$35,D15)<>1,"",IF(INDEX(市场案例库!$D$6:$D$35,MATCH(D15,市场案例库!$A$6:$A$35,0))="","",INDEX(市场案例库!$D$6:$D$35,MATCH(D15,市场案例库!$A$6:$A$35,0))))),"重复待复核","三案例齐全")) -> 三案例齐全 | G15: =IF(F15<>"三案例齐全","待补组合",IF(AND(IF(COUNTIFS(市场案例库!$A$6:$A$35,B15)<>1,"",IF(INDEX(市场案例库!$F$6:$F$35,MATCH(B15,市场案例库!$A$6:$A$35,0))="","",INDEX(市场案例库!$F$6:$F$35,MATCH(B15,市场案例库!$A$6:$A$35,0))))=IF(COUNTIFS(资产清单!$A$6:$A$25,A15)<>1,"",IF(INDEX(资产清单!$J$6:$J$25,MATCH(A15,资产清单!$A$6:$A$25,0))="","",INDEX(资产清单!$J$6:$J$25,MATCH(A15,资产清单!$A$6:$A$25,0)))),IF(COUNTIFS(市场案例库!$A$6:$A$35,B15)<>1,"",IF(INDEX(市场案例库!$E$6:$E$35,MATCH(B15,市场案例库!$A$6:$A$35,0))="","",INDEX(市场案例库!$E$6:$E$35,MATCH(B15,市场案例库!$A$6:$A$35,0))))=IF(COUNTIFS(资产清单!$A$6:$A$25,A15)<>1,"",IF(INDEX(资产清单!$H$6:$H$25,MATCH(A15,资产清单!$A$6:$A$25,0))="","",INDEX(资产清单!$H$6:$H$25,MATCH(A15,资产清单!$A$6:$A$25,0)))),IF(COUNTIFS(市场案例库!$A$6:$A$35,C15)<>1,"",IF(INDEX(市场案例库!$F$6:$F$35,MATCH(C15,市场案例库!$A$6:$A$35,0))="","",INDEX(市场案例库!$F$6:$F$35,MATCH(C15,市场案例库!$A$6:$A$35,0))))=IF(COUNTIFS(资产清单!$A$6:$A$25,A15)<>1,"",IF(INDEX(资产清单!$J$6:$J$25,MATCH(A15,资产清单!$A$6:$A$25,0))="","",INDEX(资产清单!$J$6:$J$25,MATCH(A15,资产清单!$A$6:$A$25,0)))),IF(COUNTIFS(市场案例库!$A$6:$A$35,C15)<>1,"",IF(INDEX(市场案例库!$E$6:$E$35,MATCH(C15,市场案例库!$A$6:$A$35,0))="","",INDEX(市场案例库!$E$6:$E$35,MATCH(C15,市场案例库!$A$6:$A$35,0))))=IF(COUNTIFS(资产清单!$A$6:$A$25,A15)<>1,"",IF(INDEX(资产清单!$H$6:$H$25,MATCH(A15,资产清单!$A$6:$A$25,0))="","",INDEX(资产清单!$H$6:$H$25,MATCH(A15,资产清单!$A$6:$A$25,0)))),IF(COUNTIFS(市场案例库!$A$6:$A$35,D15)<>1,"",IF(INDEX(市场案例库!$F$6:$F$35,MATCH(D15,市场案例库!$A$6:$A$35,0))="","",INDEX(市场案例库!$F$6:$F$35,MATCH(D15,市场案例库!$A$6:$A$35,0))))=IF(COUNTIFS(资产清单!$A$6:$A$25,A15)<>1,"",IF(INDEX(资产清单!$J$6:$J$25,MATCH(A15,资产清单!$A$6:$A$25,0))="","",INDEX(资产清单!$J$6:$J$25,MATCH(A15,资产清单!$A$6:$A$25,0)))),IF(COUNTIFS(市场案例库!$A$6:$A$35,D15)<>1,"",IF(INDEX(市场案例库!$E$6:$E$35,MATCH(D15,市场案例库!$A$6:$A$35,0))="","",INDEX(市场案例库!$E$6:$E$35,MATCH(D15,市场案例库!$A$6:$A$35,0))))=IF(COUNTIFS(资产清单!$A$6:$A$25,A15)<>1,"",IF(INDEX(资产清单!$H$6:$H$25,MATCH(A15,资产清单!$A$6:$A$25,0))="","",INDEX(资产清单!$H$6:$H$25,MATCH(A15,资产清单!$A$6:$A$25,0))))),"用途口径一致","用途口径不一致")) -> 用途口径一致 | H15: =IF(AND(COUNTIFS(修正明细!$N$438:$N$453,B15)=16,COUNTIFS(修正明细!$N$454:$N$469,C15)=16,COUNTIFS(修正明细!$N$470:$N$485,D15)=16),"绑定有效","待重判评分") -> 绑定有效 | I15: 模拟资料未真实核验
A16: RP-011 | B16: SC-025 | C16: SC-026 | D16: SC-027 | E16: 同用途同计租口径，保留楼层等差异 | F16: =IF(NOT(AND(COUNTIFS(市场案例库!$A$6:$A$35,B16)=1,COUNTIFS(市场案例库!$A$6:$A$35,C16)=1,COUNTIFS(市场案例库!$A$6:$A$35,D16)=1)),"待补有效案例",IF(OR(B16=C16,B16=D16,C16=D16,IF(COUNTIFS(市场案例库!$A$6:$A$35,B16)<>1,"",IF(INDEX(市场案例库!$C$6:$C$35,MATCH(B16,市场案例库!$A$6:$A$35,0))="","",INDEX(市场案例库!$C$6:$C$35,MATCH(B16,市场案例库!$A$6:$A$35,0))))=IF(COUNTIFS(市场案例库!$A$6:$A$35,C16)<>1,"",IF(INDEX(市场案例库!$C$6:$C$35,MATCH(C16,市场案例库!$A$6:$A$35,0))="","",INDEX(市场案例库!$C$6:$C$35,MATCH(C16,市场案例库!$A$6:$A$35,0)))),IF(COUNTIFS(市场案例库!$A$6:$A$35,B16)<>1,"",IF(INDEX(市场案例库!$C$6:$C$35,MATCH(B16,市场案例库!$A$6:$A$35,0))="","",INDEX(市场案例库!$C$6:$C$35,MATCH(B16,市场案例库!$A$6:$A$35,0))))=IF(COUNTIFS(市场案例库!$A$6:$A$35,D16)<>1,"",IF(INDEX(市场案例库!$C$6:$C$35,MATCH(D16,市场案例库!$A$6:$A$35,0))="","",INDEX(市场案例库!$C$6:$C$35,MATCH(D16,市场案例库!$A$6:$A$35,0)))),IF(COUNTIFS(市场案例库!$A$6:$A$35,C16)<>1,"",IF(INDEX(市场案例库!$C$6:$C$35,MATCH(C16,市场案例库!$A$6:$A$35,0))="","",INDEX(市场案例库!$C$6:$C$35,MATCH(C16,市场案例库!$A$6:$A$35,0))))=IF(COUNTIFS(市场案例库!$A$6:$A$35,D16)<>1,"",IF(INDEX(市场案例库!$C$6:$C$35,MATCH(D16,市场案例库!$A$6:$A$35,0))="","",INDEX(市场案例库!$C$6:$C$35,MATCH(D16,市场案例库!$A$6:$A$35,0)))),IF(COUNTIFS(市场案例库!$A$6:$A$35,B16)<>1,"",IF(INDEX(市场案例库!$D$6:$D$35,MATCH(B16,市场案例库!$A$6:$A$35,0))="","",INDEX(市场案例库!$D$6:$D$35,MATCH(B16,市场案例库!$A$6:$A$35,0))))=IF(COUNTIFS(市场案例库!$A$6:$A$35,C16)<>1,"",IF(INDEX(市场案例库!$D$6:$D$35,MATCH(C16,市场案例库!$A$6:$A$35,0))="","",INDEX(市场案例库!$D$6:$D$35,MATCH(C16,市场案例库!$A$6:$A$35,0)))),IF(COUNTIFS(市场案例库!$A$6:$A$35,B16)<>1,"",IF(INDEX(市场案例库!$D$6:$D$35,MATCH(B16,市场案例库!$A$6:$A$35,0))="","",INDEX(市场案例库!$D$6:$D$35,MATCH(B16,市场案例库!$A$6:$A$35,0))))=IF(COUNTIFS(市场案例库!$A$6:$A$35,D16)<>1,"",IF(INDEX(市场案例库!$D$6:$D$35,MATCH(D16,市场案例库!$A$6:$A$35,0))="","",INDEX(市场案例库!$D$6:$D$35,MATCH(D16,市场案例库!$A$6:$A$35,0)))),IF(COUNTIFS(市场案例库!$A$6:$A$35,C16)<>1,"",IF(INDEX(市场案例库!$D$6:$D$35,MATCH(C16,市场案例库!$A$6:$A$35,0))="","",INDEX(市场案例库!$D$6:$D$35,MATCH(C16,市场案例库!$A$6:$A$35,0))))=IF(COUNTIFS(市场案例库!$A$6:$A$35,D16)<>1,"",IF(INDEX(市场案例库!$D$6:$D$35,MATCH(D16,市场案例库!$A$6:$A$35,0))="","",INDEX(市场案例库!$D$6:$D$35,MATCH(D16,市场案例库!$A$6:$A$35,0))))),"重复待复核","三案例齐全")) -> 三案例齐全 | G16: =IF(F16<>"三案例齐全","待补组合",IF(AND(IF(COUNTIFS(市场案例库!$A$6:$A$35,B16)<>1,"",IF(INDEX(市场案例库!$F$6:$F$35,MATCH(B16,市场案例库!$A$6:$A$35,0))="","",INDEX(市场案例库!$F$6:$F$35,MATCH(B16,市场案例库!$A$6:$A$35,0))))=IF(COUNTIFS(资产清单!$A$6:$A$25,A16)<>1,"",IF(INDEX(资产清单!$J$6:$J$25,MATCH(A16,资产清单!$A$6:$A$25,0))="","",INDEX(资产清单!$J$6:$J$25,MATCH(A16,资产清单!$A$6:$A$25,0)))),IF(COUNTIFS(市场案例库!$A$6:$A$35,B16)<>1,"",IF(INDEX(市场案例库!$E$6:$E$35,MATCH(B16,市场案例库!$A$6:$A$35,0))="","",INDEX(市场案例库!$E$6:$E$35,MATCH(B16,市场案例库!$A$6:$A$35,0))))=IF(COUNTIFS(资产清单!$A$6:$A$25,A16)<>1,"",IF(INDEX(资产清单!$H$6:$H$25,MATCH(A16,资产清单!$A$6:$A$25,0))="","",INDEX(资产清单!$H$6:$H$25,MATCH(A16,资产清单!$A$6:$A$25,0)))),IF(COUNTIFS(市场案例库!$A$6:$A$35,C16)<>1,"",IF(INDEX(市场案例库!$F$6:$F$35,MATCH(C16,市场案例库!$A$6:$A$35,0))="","",INDEX(市场案例库!$F$6:$F$35,MATCH(C16,市场案例库!$A$6:$A$35,0))))=IF(COUNTIFS(资产清单!$A$6:$A$25,A16)<>1,"",IF(INDEX(资产清单!$J$6:$J$25,MATCH(A16,资产清单!$A$6:$A$25,0))="","",INDEX(资产清单!$J$6:$J$25,MATCH(A16,资产清单!$A$6:$A$25,0)))),IF(COUNTIFS(市场案例库!$A$6:$A$35,C16)<>1,"",IF(INDEX(市场案例库!$E$6:$E$35,MATCH(C16,市场案例库!$A$6:$A$35,0))="","",INDEX(市场案例库!$E$6:$E$35,MATCH(C16,市场案例库!$A$6:$A$35,0))))=IF(COUNTIFS(资产清单!$A$6:$A$25,A16)<>1,"",IF(INDEX(资产清单!$H$6:$H$25,MATCH(A16,资产清单!$A$6:$A$25,0))="","",INDEX(资产清单!$H$6:$H$25,MATCH(A16,资产清单!$A$6:$A$25,0)))),IF(COUNTIFS(市场案例库!$A$6:$A$35,D16)<>1,"",IF(INDEX(市场案例库!$F$6:$F$35,MATCH(D16,市场案例库!$A$6:$A$35,0))="","",INDEX(市场案例库!$F$6:$F$35,MATCH(D16,市场案例库!$A$6:$A$35,0))))=IF(COUNTIFS(资产清单!$A$6:$A$25,A16)<>1,"",IF(INDEX(资产清单!$J$6:$J$25,MATCH(A16,资产清单!$A$6:$A$25,0))="","",INDEX(资产清单!$J$6:$J$25,MATCH(A16,资产清单!$A$6:$A$25,0)))),IF(COUNTIFS(市场案例库!$A$6:$A$35,D16)<>1,"",IF(INDEX(市场案例库!$E$6:$E$35,MATCH(D16,市场案例库!$A$6:$A$35,0))="","",INDEX(市场案例库!$E$6:$E$35,MATCH(D16,市场案例库!$A$6:$A$35,0))))=IF(COUNTIFS(资产清单!$A$6:$A$25,A16)<>1,"",IF(INDEX(资产清单!$H$6:$H$25,MATCH(A16,资产清单!$A$6:$A$25,0))="","",INDEX(资产清单!$H$6:$H$25,MATCH(A16,资产清单!$A$6:$A$25,0))))),"用途口径一致","用途口径不一致")) -> 用途口径一致 | H16: =IF(AND(COUNTIFS(修正明细!$N$486:$N$501,B16)=16,COUNTIFS(修正明细!$N$502:$N$517,C16)=16,COUNTIFS(修正明细!$N$518:$N$533,D16)=16),"绑定有效","待重判评分") -> 绑定有效 | I16: 模拟资料未真实核验
A17: RP-012 | B17: SC-028 | C17: SC-029 | D17: SC-030 | E17: 同用途同计租口径，保留楼层等差异 | F17: =IF(NOT(AND(COUNTIFS(市场案例库!$A$6:$A$35,B17)=1,COUNTIFS(市场案例库!$A$6:$A$35,C17)=1,COUNTIFS(市场案例库!$A$6:$A$35,D17)=1)),"待补有效案例",IF(OR(B17=C17,B17=D17,C17=D17,IF(COUNTIFS(市场案例库!$A$6:$A$35,B17)<>1,"",IF(INDEX(市场案例库!$C$6:$C$35,MATCH(B17,市场案例库!$A$6:$A$35,0))="","",INDEX(市场案例库!$C$6:$C$35,MATCH(B17,市场案例库!$A$6:$A$35,0))))=IF(COUNTIFS(市场案例库!$A$6:$A$35,C17)<>1,"",IF(INDEX(市场案例库!$C$6:$C$35,MATCH(C17,市场案例库!$A$6:$A$35,0))="","",INDEX(市场案例库!$C$6:$C$35,MATCH(C17,市场案例库!$A$6:$A$35,0)))),IF(COUNTIFS(市场案例库!$A$6:$A$35,B17)<>1,"",IF(INDEX(市场案例库!$C$6:$C$35,MATCH(B17,市场案例库!$A$6:$A$35,0))="","",INDEX(市场案例库!$C$6:$C$35,MATCH(B17,市场案例库!$A$6:$A$35,0))))=IF(COUNTIFS(市场案例库!$A$6:$A$35,D17)<>1,"",IF(INDEX(市场案例库!$C$6:$C$35,MATCH(D17,市场案例库!$A$6:$A$35,0))="","",INDEX(市场案例库!$C$6:$C$35,MATCH(D17,市场案例库!$A$6:$A$35,0)))),IF(COUNTIFS(市场案例库!$A$6:$A$35,C17)<>1,"",IF(INDEX(市场案例库!$C$6:$C$35,MATCH(C17,市场案例库!$A$6:$A$35,0))="","",INDEX(市场案例库!$C$6:$C$35,MATCH(C17,市场案例库!$A$6:$A$35,0))))=IF(COUNTIFS(市场案例库!$A$6:$A$35,D17)<>1,"",IF(INDEX(市场案例库!$C$6:$C$35,MATCH(D17,市场案例库!$A$6:$A$35,0))="","",INDEX(市场案例库!$C$6:$C$35,MATCH(D17,市场案例库!$A$6:$A$35,0)))),IF(COUNTIFS(市场案例库!$A$6:$A$35,B17)<>1,"",IF(INDEX(市场案例库!$D$6:$D$35,MATCH(B17,市场案例库!$A$6:$A$35,0))="","",INDEX(市场案例库!$D$6:$D$35,MATCH(B17,市场案例库!$A$6:$A$35,0))))=IF(COUNTIFS(市场案例库!$A$6:$A$35,C17)<>1,"",IF(INDEX(市场案例库!$D$6:$D$35,MATCH(C17,市场案例库!$A$6:$A$35,0))="","",INDEX(市场案例库!$D$6:$D$35,MATCH(C17,市场案例库!$A$6:$A$35,0)))),IF(COUNTIFS(市场案例库!$A$6:$A$35,B17)<>1,"",IF(INDEX(市场案例库!$D$6:$D$35,MATCH(B17,市场案例库!$A$6:$A$35,0))="","",INDEX(市场案例库!$D$6:$D$35,MATCH(B17,市场案例库!$A$6:$A$35,0))))=IF(COUNTIFS(市场案例库!$A$6:$A$35,D17)<>1,"",IF(INDEX(市场案例库!$D$6:$D$35,MATCH(D17,市场案例库!$A$6:$A$35,0))="","",INDEX(市场案例库!$D$6:$D$35,MATCH(D17,市场案例库!$A$6:$A$35,0)))),IF(COUNTIFS(市场案例库!$A$6:$A$35,C17)<>1,"",IF(INDEX(市场案例库!$D$6:$D$35,MATCH(C17,市场案例库!$A$6:$A$35,0))="","",INDEX(市场案例库!$D$6:$D$35,MATCH(C17,市场案例库!$A$6:$A$35,0))))=IF(COUNTIFS(市场案例库!$A$6:$A$35,D17)<>1,"",IF(INDEX(市场案例库!$D$6:$D$35,MATCH(D17,市场案例库!$A$6:$A$35,0))="","",INDEX(市场案例库!$D$6:$D$35,MATCH(D17,市场案例库!$A$6:$A$35,0))))),"重复待复核","三案例齐全")) -> 三案例齐全 | G17: =IF(F17<>"三案例齐全","待补组合",IF(AND(IF(COUNTIFS(市场案例库!$A$6:$A$35,B17)<>1,"",IF(INDEX(市场案例库!$F$6:$F$35,MATCH(B17,市场案例库!$A$6:$A$35,0))="","",INDEX(市场案例库!$F$6:$F$35,MATCH(B17,市场案例库!$A$6:$A$35,0))))=IF(COUNTIFS(资产清单!$A$6:$A$25,A17)<>1,"",IF(INDEX(资产清单!$J$6:$J$25,MATCH(A17,资产清单!$A$6:$A$25,0))="","",INDEX(资产清单!$J$6:$J$25,MATCH(A17,资产清单!$A$6:$A$25,0)))),IF(COUNTIFS(市场案例库!$A$6:$A$35,B17)<>1,"",IF(INDEX(市场案例库!$E$6:$E$35,MATCH(B17,市场案例库!$A$6:$A$35,0))="","",INDEX(市场案例库!$E$6:$E$35,MATCH(B17,市场案例库!$A$6:$A$35,0))))=IF(COUNTIFS(资产清单!$A$6:$A$25,A17)<>1,"",IF(INDEX(资产清单!$H$6:$H$25,MATCH(A17,资产清单!$A$6:$A$25,0))="","",INDEX(资产清单!$H$6:$H$25,MATCH(A17,资产清单!$A$6:$A$25,0)))),IF(COUNTIFS(市场案例库!$A$6:$A$35,C17)<>1,"",IF(INDEX(市场案例库!$F$6:$F$35,MATCH(C17,市场案例库!$A$6:$A$35,0))="","",INDEX(市场案例库!$F$6:$F$35,MATCH(C17,市场案例库!$A$6:$A$35,0))))=IF(COUNTIFS(资产清单!$A$6:$A$25,A17)<>1,"",IF(INDEX(资产清单!$J$6:$J$25,MATCH(A17,资产清单!$A$6:$A$25,0))="","",INDEX(资产清单!$J$6:$J$25,MATCH(A17,资产清单!$A$6:$A$25,0)))),IF(COUNTIFS(市场案例库!$A$6:$A$35,C17)<>1,"",IF(INDEX(市场案例库!$E$6:$E$35,MATCH(C17,市场案例库!$A$6:$A$35,0))="","",INDEX(市场案例库!$E$6:$E$35,MATCH(C17,市场案例库!$A$6:$A$35,0))))=IF(COUNTIFS(资产清单!$A$6:$A$25,A17)<>1,"",IF(INDEX(资产清单!$H$6:$H$25,MATCH(A17,资产清单!$A$6:$A$25,0))="","",INDEX(资产清单!$H$6:$H$25,MATCH(A17,资产清单!$A$6:$A$25,0)))),IF(COUNTIFS(市场案例库!$A$6:$A$35,D17)<>1,"",IF(INDEX(市场案例库!$F$6:$F$35,MATCH(D17,市场案例库!$A$6:$A$35,0))="","",INDEX(市场案例库!$F$6:$F$35,MATCH(D17,市场案例库!$A$6:$A$35,0))))=IF(COUNTIFS(资产清单!$A$6:$A$25,A17)<>1,"",IF(INDEX(资产清单!$J$6:$J$25,MATCH(A17,资产清单!$A$6:$A$25,0))="","",INDEX(资产清单!$J$6:$J$25,MATCH(A17,资产清单!$A$6:$A$25,0)))),IF(COUNTIFS(市场案例库!$A$6:$A$35,D17)<>1,"",IF(INDEX(市场案例库!$E$6:$E$35,MATCH(D17,市场案例库!$A$6:$A$35,0))="","",INDEX(市场案例库!$E$6:$E$35,MATCH(D17,市场案例库!$A$6:$A$35,0))))=IF(COUNTIFS(资产清单!$A$6:$A$25,A17)<>1,"",IF(INDEX(资产清单!$H$6:$H$25,MATCH(A17,资产清单!$A$6:$A$25,0))="","",INDEX(资产清单!$H$6:$H$25,MATCH(A17,资产清单!$A$6:$A$25,0))))),"用途口径一致","用途口径不一致")) -> 用途口径一致 | H17: =IF(AND(COUNTIFS(修正明细!$N$534:$N$549,B17)=16,COUNTIFS(修正明细!$N$550:$N$565,C17)=16,COUNTIFS(修正明细!$N$566:$N$581,D17)=16),"绑定有效","待重判评分") -> 绑定有效 | I17: 模拟资料未真实核验
A19: 更换案例后，修正明细中的绑定编号及逐项评分必须重新核对。不要把旧案例评分直接套入新案例。

Sheet 三案例测算
A2: 三案例综合修正与单案例复核
A3: 全部业务数据及依据记录均为模拟。用于试用复算，未核验真实来源。
A5: 资产编码 | B5: 案例序号 | C5: 案例编号 | D5: 案例名称 | E5: 案例原租金 | F5: 计租单位 | G5: 综合修正系数 | H5: 修正后租金 | I5: 单案例修正幅度 | J5: 单案例20%校验 | K5: 计算资料状态
A6: RP-001 | B6: 1 | C6: =三案例选用!B6 -> SC-001 | D6: =IF(COUNTIFS(市场案例库!$A$6:$A$35,C6)<>1,"",IF(INDEX(市场案例库!$B$6:$B$35,MATCH(C6,市场案例库!$A$6:$A$35,0))="","",INDEX(市场案例库!$B$6:$B$35,MATCH(C6,市场案例库!$A$6:$A$35,0)))) -> 模拟案例01 | E6: =IF(COUNTIFS(市场案例库!$A$6:$A$35,C6)<>1,"",IF(COUNT(INDEX(市场案例库!$J$6:$J$35,MATCH(C6,市场案例库!$A$6:$A$35,0)))<>1,"",INDEX(市场案例库!$J$6:$J$35,MATCH(C6,市场案例库!$A$6:$A$35,0)))) -> 53 | F6: =IF(COUNTIFS(市场案例库!$A$6:$A$35,C6)<>1,"",IF(INDEX(市场案例库!$F$6:$F$35,MATCH(C6,市场案例库!$A$6:$A$35,0))="","",INDEX(市场案例库!$F$6:$F$35,MATCH(C6,市场案例库!$A$6:$A$35,0)))) -> 元/㎡/月 | G6: =IF(OR(COUNT(修正明细!J6:J21)<>16,COUNTIFS(修正明细!M6:M21,"模拟评分记录完整")<>16),"",PRODUCT(修正明细!J6:J21)) -> 0.97087756 | H6: =IF(OR(COUNT(E6,G6)<>2,E6<=0,三案例选用!F6<>"三案例齐全",三案例选用!G6<>"用途口径一致",三案例选用!H6<>"绑定有效"),"",E6*G6) -> 51.456511 | I6: =IF(COUNT(H6)<>1,"",H6/E6-1) -> -0.029122443 | J6: =IF(COUNT(I6)<>1,"待补计算资料",IF(ABS(I6)<=测算参数!$B$7,"通过","超限待复核")) -> 通过 | K6: =IF(COUNT(H6)<>1,"待补资料或重判评分","模拟计算可复算") -> 模拟计算可复算
A7: RP-001 | B7: 2 | C7: =三案例选用!C6 -> SC-002 | D7: =IF(COUNTIFS(市场案例库!$A$6:$A$35,C7)<>1,"",IF(INDEX(市场案例库!$B$6:$B$35,MATCH(C7,市场案例库!$A$6:$A$35,0))="","",INDEX(市场案例库!$B$6:$B$35,MATCH(C7,市场案例库!$A$6:$A$35,0)))) -> 模拟案例02 | E7: =IF(COUNTIFS(市场案例库!$A$6:$A$35,C7)<>1,"",IF(COUNT(INDEX(市场案例库!$J$6:$J$35,MATCH(C7,市场案例库!$A$6:$A$35,0)))<>1,"",INDEX(市场案例库!$J$6:$J$35,MATCH(C7,市场案例库!$A$6:$A$35,0)))) -> 56 | F7: =IF(COUNTIFS(市场案例库!$A$6:$A$35,C7)<>1,"",IF(INDEX(市场案例库!$F$6:$F$35,MATCH(C7,市场案例库!$A$6:$A$35,0))="","",INDEX(市场案例库!$F$6:$F$35,MATCH(C7,市场案例库!$A$6:$A$35,0)))) -> 元/㎡/月 | G7: =IF(OR(COUNT(修正明细!J22:J37)<>16,COUNTIFS(修正明细!M22:M37,"模拟评分记录完整")<>16),"",PRODUCT(修正明细!J22:J37)) -> 0.99069138 | H7: =IF(OR(COUNT(E7,G7)<>2,E7<=0,三案例选用!F6<>"三案例齐全",三案例选用!G6<>"用途口径一致",三案例选用!H6<>"绑定有效"),"",E7*G7) -> 55.478718 | I7: =IF(COUNT(H7)<>1,"",H7/E7-1) -> -0.0093086155 | J7: =IF(COUNT(I7)<>1,"待补计算资料",IF(ABS(I7)<=测算参数!$B$7,"通过","超限待复核")) -> 通过 | K7: =IF(COUNT(H7)<>1,"待补资料或重判评分","模拟计算可复算") -> 模拟计算可复算
A8: RP-001 | B8: 3 | C8: =三案例选用!D6 -> SC-003 | D8: =IF(COUNTIFS(市场案例库!$A$6:$A$35,C8)<>1,"",IF(INDEX(市场案例库!$B$6:$B$35,MATCH(C8,市场案例库!$A$6:$A$35,0))="","",INDEX(市场案例库!$B$6:$B$35,MATCH(C8,市场案例库!$A$6:$A$35,0)))) -> 模拟案例03 | E8: =IF(COUNTIFS(市场案例库!$A$6:$A$35,C8)<>1,"",IF(COUNT(INDEX(市场案例库!$J$6:$J$35,MATCH(C8,市场案例库!$A$6:$A$35,0)))<>1,"",INDEX(市场案例库!$J$6:$J$35,MATCH(C8,市场案例库!$A$6:$A$35,0)))) -> 55 | F8: =IF(COUNTIFS(市场案例库!$A$6:$A$35,C8)<>1,"",IF(INDEX(市场案例库!$F$6:$F$35,MATCH(C8,市场案例库!$A$6:$A$35,0))="","",INDEX(市场案例库!$F$6:$F$35,MATCH(C8,市场案例库!$A$6:$A$35,0)))) -> 元/㎡/月 | G8: =IF(OR(COUNT(修正明细!J38:J53)<>16,COUNTIFS(修正明细!M38:M53,"模拟评分记录完整")<>16),"",PRODUCT(修正明细!J38:J53)) -> 1.0419772 | H8: =IF(OR(COUNT(E8,G8)<>2,E8<=0,三案例选用!F6<>"三案例齐全",三案例选用!G6<>"用途口径一致",三案例选用!H6<>"绑定有效"),"",E8*G8) -> 57.308745 | I8: =IF(COUNT(H8)<>1,"",H8/E8-1) -> 0.041977176 | J8: =IF(COUNT(I8)<>1,"待补计算资料",IF(ABS(I8)<=测算参数!$B$7,"通过","超限待复核")) -> 通过 | K8: =IF(COUNT(H8)<>1,"待补资料或重判评分","模拟计算可复算") -> 模拟计算可复算
A9: RP-002 | B9: 1 | C9: =三案例选用!B7 -> SC-001 | D9: =IF(COUNTIFS(市场案例库!$A$6:$A$35,C9)<>1,"",IF(INDEX(市场案例库!$B$6:$B$35,MATCH(C9,市场案例库!$A$6:$A$35,0))="","",INDEX(市场案例库!$B$6:$B$35,MATCH(C9,市场案例库!$A$6:$A$35,0)))) -> 模拟案例01 | E9: =IF(COUNTIFS(市场案例库!$A$6:$A$35,C9)<>1,"",IF(COUNT(INDEX(市场案例库!$J$6:$J$35,MATCH(C9,市场案例库!$A$6:$A$35,0)))<>1,"",INDEX(市场案例库!$J$6:$J$35,MATCH(C9,市场案例库!$A$6:$A$35,0)))) -> 53 | F9: =IF(COUNTIFS(市场案例库!$A$6:$A$35,C9)<>1,"",IF(INDEX(市场案例库!$F$6:$F$35,MATCH(C9,市场案例库!$A$6:$A$35,0))="","",INDEX(市场案例库!$F$6:$F$35,MATCH(C9,市场案例库!$A$6:$A$35,0)))) -> 元/㎡/月 | G9: =IF(OR(COUNT(修正明细!J54:J69)<>16,COUNTIFS(修正明细!M54:M69,"模拟评分记录完整")<>16),"",PRODUCT(修正明细!J54:J69)) -> 0.93370682 | H9: =IF(OR(COUNT(E9,G9)<>2,E9<=0,三案例选用!F7<>"三案例齐全",三案例选用!G7<>"用途口径一致",三案例选用!H7<>"绑定有效"),"",E9*G9) -> 49.486461 | I9: =IF(COUNT(H9)<>1,"",H9/E9-1) -> -0.066293184 | J9: =IF(COUNT(I9)<>1,"待补计算资料",IF(ABS(I9)<=测算参数!$B$7,"通过","超限待复核")) -> 通过 | K9: =IF(COUNT(H9)<>1,"待补资料或重判评分","模拟计算可复算") -> 模拟计算可复算
A10: RP-002 | B10: 2 | C10: =三案例选用!C7 -> SC-002 | D10: =IF(COUNTIFS(市场案例库!$A$6:$A$35,C10)<>1,"",IF(INDEX(市场案例库!$B$6:$B$35,MATCH(C10,市场案例库!$A$6:$A$35,0))="","",INDEX(市场案例库!$B$6:$B$35,MATCH(C10,市场案例库!$A$6:$A$35,0)))) -> 模拟案例02 | E10: =IF(COUNTIFS(市场案例库!$A$6:$A$35,C10)<>1,"",IF(COUNT(INDEX(市场案例库!$J$6:$J$35,MATCH(C10,市场案例库!$A$6:$A$35,0)))<>1,"",INDEX(市场案例库!$J$6:$J$35,MATCH(C10,市场案例库!$A$6:$A$35,0)))) -> 56 | F10: =IF(COUNTIFS(市场案例库!$A$6:$A$35,C10)<>1,"",IF(INDEX(市场案例库!$F$6:$F$35,MATCH(C10,市场案例库!$A$6:$A$35,0))="","",INDEX(市场案例库!$F$6:$F$35,MATCH(C10,市场案例库!$A$6:$A$35,0)))) -> 元/㎡/月 | G10: =IF(OR(COUNT(修正明细!J70:J85)<>16,COUNTIFS(修正明细!M70:M85,"模拟评分记录完整")<>16),"",PRODUCT(修正明细!J70:J85)) -> 0.94232233 | H10: =IF(OR(COUNT(E10,G10)<>2,E10<=0,三案例选用!F7<>"三案例齐全",三案例选用!G7<>"用途口径一致",三案例选用!H7<>"绑定有效"),"",E10*G10) -> 52.770051 | I10: =IF(COUNT(H10)<>1,"",H10/E10-1) -> -0.057677665 | J10: =IF(COUNT(I10)<>1,"待补计算资料",IF(ABS(I10)<=测算参数!$B$7,"通过","超限待复核")) -> 通过 | K10: =IF(COUNT(H10)<>1,"待补资料或重判评分","模拟计算可复算") -> 模拟计算可复算
A11: RP-002 | B11: 3 | C11: =三案例选用!D7 -> SC-003 | D11: =IF(COUNTIFS(市场案例库!$A$6:$A$35,C11)<>1,"",IF(INDEX(市场案例库!$B$6:$B$35,MATCH(C11,市场案例库!$A$6:$A$35,0))="","",INDEX(市场案例库!$B$6:$B$35,MATCH(C11,市场案例库!$A$6:$A$35,0)))) -> 模拟案例03 | E11: =IF(COUNTIFS(市场案例库!$A$6:$A$35,C11)<>1,"",IF(COUNT(INDEX(市场案例库!$J$6:$J$35,MATCH(C11,市场案例库!$A$6:$A$35,0)))<>1,"",INDEX(市场案例库!$J$6:$J$35,MATCH(C11,市场案例库!$A$6:$A$35,0)))) -> 55 | F11: =IF(COUNTIFS(市场案例库!$A$6:$A$35,C11)<>1,"",IF(INDEX(市场案例库!$F$6:$F$35,MATCH(C11,市场案例库!$A$6:$A$35,0))="","",INDEX(市场案例库!$F$6:$F$35,MATCH(C11,市场案例库!$A$6:$A$35,0)))) -> 元/㎡/月 | G11: =IF(OR(COUNT(修正明细!J86:J101)<>16,COUNTIFS(修正明细!M86:M101,"模拟评分记录完整")<>16),"",PRODUCT(修正明细!J86:J101)) -> 0.99029511 | H11: =IF(OR(COUNT(E11,G11)<>2,E11<=0,三案例选用!F7<>"三案例齐全",三案例选用!G7<>"用途口径一致",三案例选用!H7<>"绑定有效"),"",E11*G11) -> 54.466231 | I11: =IF(COUNT(H11)<>1,"",H11/E11-1) -> -0.0097048921 | J11: =IF(COUNT(I11)<>1,"待补计算资料",IF(ABS(I11)<=测算参数!$B$7,"通过","超限待复核")) -> 通过 | K11: =IF(COUNT(H11)<>1,"待补资料或重判评分","模拟计算可复算") -> 模拟计算可复算
A12: RP-003 | B12: 1 | C12: =三案例选用!B8 -> SC-004 | D12: =IF(COUNTIFS(市场案例库!$A$6:$A$35,C12)<>1,"",IF(INDEX(市场案例库!$B$6:$B$35,MATCH(C12,市场案例库!$A$6:$A$35,0))="","",INDEX(市场案例库!$B$6:$B$35,MATCH(C12,市场案例库!$A$6:$A$35,0)))) -> 模拟案例04 | E12: =IF(COUNTIFS(市场案例库!$A$6:$A$35,C12)<>1,"",IF(COUNT(INDEX(市场案例库!$J$6:$J$35,MATCH(C12,市场案例库!$A$6:$A$35,0)))<>1,"",INDEX(市场案例库!$J$6:$J$35,MATCH(C12,市场案例库!$A$6:$A$35,0)))) -> 44 | F12: =IF(COUNTIFS(市场案例库!$A$6:$A$35,C12)<>1,"",IF(INDEX(市场案例库!$F$6:$F$35,MATCH(C12,市场案例库!$A$6:$A$35,0))="","",INDEX(市场案例库!$F$6:$F$35,MATCH(C12,市场案例库!$A$6:$A$35,0)))) -> 元/㎡/月 | G12: =IF(OR(COUNT(修正明细!J102:J117)<>16,COUNTIFS(修正明细!M102:M117,"模拟评分记录完整")<>16),"",PRODUCT(修正明细!J102:J117)) -> 0.9706853 | H12: =IF(OR(COUNT(E12,G12)<>2,E12<=0,三案例选用!F8<>"三案例齐全",三案例选用!G8<>"用途口径一致",三案例选用!H8<>"绑定有效"),"",E12*G12) -> 42.710153 | I12: =IF(COUNT(H12)<>1,"",H12/E12-1) -> -0.029314696 | J12: =IF(COUNT(I12)<>1,"待补计算资料",IF(ABS(I12)<=测算参数!$B$7,"通过","超限待复核")) -> 通过 | K12: =IF(COUNT(H12)<>1,"待补资料或重判评分","模拟计算可复算") -> 模拟计算可复算
A13: RP-003 | B13: 2 | C13: =三案例选用!C8 -> SC-005 | D13: =IF(COUNTIFS(市场案例库!$A$6:$A$35,C13)<>1,"",IF(INDEX(市场案例库!$B$6:$B$35,MATCH(C13,市场案例库!$A$6:$A$35,0))="","",INDEX(市场案例库!$B$6:$B$35,MATCH(C13,市场案例库!$A$6:$A$35,0)))) -> 模拟案例05 | E13: =IF(COUNTIFS(市场案例库!$A$6:$A$35,C13)<>1,"",IF(COUNT(INDEX(市场案例库!$J$6:$J$35,MATCH(C13,市场案例库!$A$6:$A$35,0)))<>1,"",INDEX(市场案例库!$J$6:$J$35,MATCH(C13,市场案例库!$A$6:$A$35,0)))) -> 46 | F13: =IF(COUNTIFS(市场案例库!$A$6:$A$35,C13)<>1,"",IF(INDEX(市场案例库!$F$6:$F$35,MATCH(C13,市场案例库!$A$6:$A$35,0))="","",INDEX(市场案例库!$F$6:$F$35,MATCH(C13,市场案例库!$A$6:$A$35,0)))) -> 元/㎡/月 | G13: =IF(OR(COUNT(修正明细!J118:J133)<>16,COUNTIFS(修正明细!M118:M133,"模拟评分记录完整")<>16),"",PRODUCT(修正明细!J118:J133)) -> 0.96116878 | H13: =IF(OR(COUNT(E13,G13)<>2,E13<=0,三案例选用!F8<>"三案例齐全",三案例选用!G8<>"用途口径一致",三案例选用!H8<>"绑定有效"),"",E13*G13) -> 44.213764 | I13: =IF(COUNT(H13)<>1,"",H13/E13-1) -> -0.038831219 | J13: =IF(COUNT(I13)<>1,"待补计算资料",IF(ABS(I13)<=测算参数!$B$7,"通过","超限待复核")) -> 通过 | K13: =IF(COUNT(H13)<>1,"待补资料或重判评分","模拟计算可复算") -> 模拟计算可复算
A14: RP-003 | B14: 3 | C14: =三案例选用!D8 -> SC-006 | D14: =IF(COUNTIFS(市场案例库!$A$6:$A$35,C14)<>1,"",IF(INDEX(市场案例库!$B$6:$B$35,MATCH(C14,市场案例库!$A$6:$A$35,0))="","",INDEX(市场案例库!$B$6:$B$35,MATCH(C14,市场案例库!$A$6:$A$35,0)))) -> 模拟案例06 | E14: =IF(COUNTIFS(市场案例库!$A$6:$A$35,C14)<>1,"",IF(COUNT(INDEX(市场案例库!$J$6:$J$35,MATCH(C14,市场案例库!$A$6:$A$35,0)))<>1,"",INDEX(市场案例库!$J$6:$J$35,MATCH(C14,市场案例库!$A$6:$A$35,0)))) -> 45 | F14: =IF(COUNTIFS(市场案例库!$A$6:$A$35,C14)<>1,"",IF(INDEX(市场案例库!$F$6:$F$35,MATCH(C14,市场案例库!$A$6:$A$35,0))="","",INDEX(市场案例库!$F$6:$F$35,MATCH(C14,市场案例库!$A$6:$A$35,0)))) -> 元/㎡/月 | G14: =IF(OR(COUNT(修正明细!J134:J149)<>16,COUNTIFS(修正明细!M134:M149,"模拟评分记录完整")<>16),"",PRODUCT(修正明细!J134:J149)) -> 1.0105052 | H14: =IF(OR(COUNT(E14,G14)<>2,E14<=0,三案例选用!F8<>"三案例齐全",三案例选用!G8<>"用途口径一致",三案例选用!H8<>"绑定有效"),"",E14*G14) -> 45.472735 | I14: =IF(COUNT(H14)<>1,"",H14/E14-1) -> 0.010505212 | J14: =IF(COUNT(I14)<>1,"待补计算资料",IF(ABS(I14)<=测算参数!$B$7,"通过","超限待复核")) -> 通过 | K14: =IF(COUNT(H14)<>1,"待补资料或重判评分","模拟计算可复算") -> 模拟计算可复算
A15: RP-004 | B15: 1 | C15: =三案例选用!B9 -> SC-007 | D15: =IF(COUNTIFS(市场案例库!$A$6:$A$35,C15)<>1,"",IF(INDEX(市场案例库!$B$6:$B$35,MATCH(C15,市场案例库!$A$6:$A$35,0))="","",INDEX(市场案例库!$B$6:$B$35,MATCH(C15,市场案例库!$A$6:$A$35,0)))) -> 模拟案例07 | E15: =IF(COUNTIFS(市场案例库!$A$6:$A$35,C15)<>1,"",IF(COUNT(INDEX(市场案例库!$J$6:$J$35,MATCH(C15,市场案例库!$A$6:$A$35,0)))<>1,"",INDEX(市场案例库!$J$6:$J$35,MATCH(C15,市场案例库!$A$6:$A$35,0)))) -> 66 | F15: =IF(COUNTIFS(市场案例库!$A$6:$A$35,C15)<>1,"",IF(INDEX(市场案例库!$F$6:$F$35,MATCH(C15,市场案例库!$A$6:$A$35,0))="","",INDEX(市场案例库!$F$6:$F$35,MATCH(C15,市场案例库!$A$6:$A$35,0)))) -> 元/㎡/月 | G15: =IF(OR(COUNT(修正明细!J150:J165)<>16,COUNTIFS(修正明细!M150:M165,"模拟评分记录完整")<>16),"",PRODUCT(修正明细!J150:J165)) -> 0.93370682 | H15: =IF(OR(COUNT(E15,G15)<>2,E15<=0,三案例选用!F9<>"三案例齐全",三案例选用!G9<>"用途口径一致",三案例选用!H9<>"绑定有效"),"",E15*G15) -> 61.62465 | I15: =IF(COUNT(H15)<>1,"",H15/E15-1) -> -0.066293184 | J15: =IF(COUNT(I15)<>1,"待补计算资料",IF(ABS(I15)<=测算参数!$B$7,"通过","超限待复核")) -> 通过 | K15: =IF(COUNT(H15)<>1,"待补资料或重判评分","模拟计算可复算") -> 模拟计算可复算
A16: RP-004 | B16: 2 | C16: =三案例选用!C9 -> SC-008 | D16: =IF(COUNTIFS(市场案例库!$A$6:$A$35,C16)<>1,"",IF(INDEX(市场案例库!$B$6:$B$35,MATCH(C16,市场案例库!$A$6:$A$35,0))="","",INDEX(市场案例库!$B$6:$B$35,MATCH(C16,市场案例库!$A$6:$A$35,0)))) -> 模拟案例08 | E16: =IF(COUNTIFS(市场案例库!$A$6:$A$35,C16)<>1,"",IF(COUNT(INDEX(市场案例库!$J$6:$J$35,MATCH(C16,市场案例库!$A$6:$A$35,0)))<>1,"",INDEX(市场案例库!$J$6:$J$35,MATCH(C16,市场案例库!$A$6:$A$35,0)))) -> 68 | F16: =IF(COUNTIFS(市场案例库!$A$6:$A$35,C16)<>1,"",IF(INDEX(市场案例库!$F$6:$F$35,MATCH(C16,市场案例库!$A$6:$A$35,0))="","",INDEX(市场案例库!$F$6:$F$35,MATCH(C16,市场案例库!$A$6:$A$35,0)))) -> 元/㎡/月 | G16: =IF(OR(COUNT(修正明细!J166:J181)<>16,COUNTIFS(修正明细!M166:M181,"模拟评分记录完整")<>16),"",PRODUCT(修正明细!J166:J181)) -> 0.91539884 | H16: =IF(OR(COUNT(E16,G16)<>2,E16<=0,三案例选用!F9<>"三案例齐全",三案例选用!G9<>"用途口径一致",三案例选用!H9<>"绑定有效"),"",E16*G16) -> 62.247121 | I16: =IF(COUNT(H16)<>1,"",H16/E16-1) -> -0.084601161 | J16: =IF(COUNT(I16)<>1,"待补计算资料",IF(ABS(I16)<=测算参数!$B$7,"通过","超限待复核")) -> 通过 | K16: =IF(COUNT(H16)<>1,"待补资料或重判评分","模拟计算可复算") -> 模拟计算可复算
A17: RP-004 | B17: 3 | C17: =三案例选用!D9 -> SC-009 | D17: =IF(COUNTIFS(市场案例库!$A$6:$A$35,C17)<>1,"",IF(INDEX(市场案例库!$B$6:$B$35,MATCH(C17,市场案例库!$A$6:$A$35,0))="","",INDEX(市场案例库!$B$6:$B$35,MATCH(C17,市场案例库!$A$6:$A$35,0)))) -> 模拟案例09 | E17: =IF(COUNTIFS(市场案例库!$A$6:$A$35,C17)<>1,"",IF(COUNT(INDEX(市场案例库!$J$6:$J$35,MATCH(C17,市场案例库!$A$6:$A$35,0)))<>1,"",INDEX(市场案例库!$J$6:$J$35,MATCH(C17,市场案例库!$A$6:$A$35,0)))) -> 65 | F17: =IF(COUNTIFS(市场案例库!$A$6:$A$35,C17)<>1,"",IF(INDEX(市场案例库!$F$6:$F$35,MATCH(C17,市场案例库!$A$6:$A$35,0))="","",INDEX(市场案例库!$F$6:$F$35,MATCH(C17,市场案例库!$A$6:$A$35,0)))) -> 元/㎡/月 | G17: =IF(OR(COUNT(修正明细!J182:J197)<>16,COUNTIFS(修正明细!M182:M197,"模拟评分记录完整")<>16),"",PRODUCT(修正明细!J182:J197)) -> 0.95276206 | H17: =IF(OR(COUNT(E17,G17)<>2,E17<=0,三案例选用!F9<>"三案例齐全",三案例选用!G9<>"用途口径一致",三案例选用!H9<>"绑定有效"),"",E17*G17) -> 61.929534 | I17: =IF(COUNT(H17)<>1,"",H17/E17-1) -> -0.047237943 | J17: =IF(COUNT(I17)<>1,"待补计算资料",IF(ABS(I17)<=测算参数!$B$7,"通过","超限待复核")) -> 通过 | K17: =IF(COUNT(H17)<>1,"待补资料或重判评分","模拟计算可复算") -> 模拟计算可复算
A18: RP-005 | B18: 1 | C18: =三案例选用!B10 -> SC-010 | D18: =IF(COUNTIFS(市场案例库!$A$6:$A$35,C18)<>1,"",IF(INDEX(市场案例库!$B$6:$B$35,MATCH(C18,市场案例库!$A$6:$A$35,0))="","",INDEX(市场案例库!$B$6:$B$35,MATCH(C18,市场案例库!$A$6:$A$35,0)))) -> 模拟案例10 | E18: =IF(COUNTIFS(市场案例库!$A$6:$A$35,C18)<>1,"",IF(COUNT(INDEX(市场案例库!$J$6:$J$35,MATCH(C18,市场案例库!$A$6:$A$35,0)))<>1,"",INDEX(市场案例库!$J$6:$J$35,MATCH(C18,市场案例库!$A$6:$A$35,0)))) -> 26 | F18: =IF(COUNTIFS(市场案例库!$A$6:$A$35,C18)<>1,"",IF(INDEX(市场案例库!$F$6:$F$35,MATCH(C18,市场案例库!$A$6:$A$35,0))="","",INDEX(市场案例库!$F$6:$F$35,MATCH(C18,市场案例库!$A$6:$A$35,0)))) -> 元/㎡/月 | G18: =IF(OR(COUNT(修正明细!J198:J213)<>16,COUNTIFS(修正明细!M198:M213,"模拟评分记录完整")<>16),"",PRODUCT(修正明细!J198:J213)) -> 0.9706853 | H18: =IF(OR(COUNT(E18,G18)<>2,E18<=0,三案例选用!F10<>"三案例齐全",三案例选用!G10<>"用途口径一致",三案例选用!H10<>"绑定有效"),"",E18*G18) -> 25.237818 | I18: =IF(COUNT(H18)<>1,"",H18/E18-1) -> -0.029314696 | J18: =IF(COUNT(I18)<>1,"待补计算资料",IF(ABS(I18)<=测算参数!$B$7,"通过","超限待复核")) -> 通过 | K18: =IF(COUNT(H18)<>1,"待补资料或重判评分","模拟计算可复算") -> 模拟计算可复算
A19: RP-005 | B19: 2 | C19: =三案例选用!C10 -> SC-011 | D19: =IF(COUNTIFS(市场案例库!$A$6:$A$35,C19)<>1,"",IF(INDEX(市场案例库!$B$6:$B$35,MATCH(C19,市场案例库!$A$6:$A$35,0))="","",INDEX(市场案例库!$B$6:$B$35,MATCH(C19,市场案例库!$A$6:$A$35,0)))) -> 模拟案例11 | E19: =IF(COUNTIFS(市场案例库!$A$6:$A$35,C19)<>1,"",IF(COUNT(INDEX(市场案例库!$J$6:$J$35,MATCH(C19,市场案例库!$A$6:$A$35,0)))<>1,"",INDEX(市场案例库!$J$6:$J$35,MATCH(C19,市场案例库!$A$6:$A$35,0)))) -> 27 | F19: =IF(COUNTIFS(市场案例库!$A$6:$A$35,C19)<>1,"",IF(INDEX(市场案例库!$F$6:$F$35,MATCH(C19,市场案例库!$A$6:$A$35,0))="","",INDEX(市场案例库!$F$6:$F$35,MATCH(C19,市场案例库!$A$6:$A$35,0)))) -> 元/㎡/月 | G19: =IF(OR(COUNT(修正明细!J214:J229)<>16,COUNTIFS(修正明细!M214:M229,"模拟评分记录完整")<>16),"",PRODUCT(修正明细!J214:J229)) -> 0.98078447 | H19: =IF(OR(COUNT(E19,G19)<>2,E19<=0,三案例选用!F10<>"三案例齐全",三案例选用!G10<>"用途口径一致",三案例选用!H10<>"绑定有效"),"",E19*G19) -> 26.481181 | I19: =IF(COUNT(H19)<>1,"",H19/E19-1) -> -0.019215529 | J19: =IF(COUNT(I19)<>1,"待补计算资料",IF(ABS(I19)<=测算参数!$B$7,"通过","超限待复核")) -> 通过 | K19: =IF(COUNT(H19)<>1,"待补资料或重判评分","模拟计算可复算") -> 模拟计算可复算
A20: RP-005 | B20: 3 | C20: =三案例选用!D10 -> SC-012 | D20: =IF(COUNTIFS(市场案例库!$A$6:$A$35,C20)<>1,"",IF(INDEX(市场案例库!$B$6:$B$35,MATCH(C20,市场案例库!$A$6:$A$35,0))="","",INDEX(市场案例库!$B$6:$B$35,MATCH(C20,市场案例库!$A$6:$A$35,0)))) -> 模拟案例12 | E20: =IF(COUNTIFS(市场案例库!$A$6:$A$35,C20)<>1,"",IF(COUNT(INDEX(市场案例库!$J$6:$J$35,MATCH(C20,市场案例库!$A$6:$A$35,0)))<>1,"",INDEX(市场案例库!$J$6:$J$35,MATCH(C20,市场案例库!$A$6:$A$35,0)))) -> 28 | F20: =IF(COUNTIFS(市场案例库!$A$6:$A$35,C20)<>1,"",IF(INDEX(市场案例库!$F$6:$F$35,MATCH(C20,市场案例库!$A$6:$A$35,0))="","",INDEX(市场案例库!$F$6:$F$35,MATCH(C20,市场案例库!$A$6:$A$35,0)))) -> 元/㎡/月 | G20: =IF(OR(COUNT(修正明细!J230:J245)<>16,COUNTIFS(修正明细!M230:M245,"模拟评分记录完整")<>16),"",PRODUCT(修正明细!J230:J245)) -> 0.99029511 | H20: =IF(OR(COUNT(E20,G20)<>2,E20<=0,三案例选用!F10<>"三案例齐全",三案例选用!G10<>"用途口径一致",三案例选用!H10<>"绑定有效"),"",E20*G20) -> 27.728263 | I20: =IF(COUNT(H20)<>1,"",H20/E20-1) -> -0.0097048921 | J20: =IF(COUNT(I20)<>1,"待补计算资料",IF(ABS(I20)<=测算参数!$B$7,"通过","超限待复核")) -> 通过 | K20: =IF(COUNT(H20)<>1,"待补资料或重判评分","模拟计算可复算") -> 模拟计算可复算
A21: RP-006 | B21: 1 | C21: =三案例选用!B11 -> SC-010 | D21: =IF(COUNTIFS(市场案例库!$A$6:$A$35,C21)<>1,"",IF(INDEX(市场案例库!$B$6:$B$35,MATCH(C21,市场案例库!$A$6:$A$35,0))="","",INDEX(市场案例库!$B$6:$B$35,MATCH(C21,市场案例库!$A$6:$A$35,0)))) -> 模拟案例10 | E21: =IF(COUNTIFS(市场案例库!$A$6:$A$35,C21)<>1,"",IF(COUNT(INDEX(市场案例库!$J$6:$J$35,MATCH(C21,市场案例库!$A$6:$A$35,0)))<>1,"",INDEX(市场案例库!$J$6:$J$35,MATCH(C21,市场案例库!$A$6:$A$35,0)))) -> 26 | F21: =IF(COUNTIFS(市场案例库!$A$6:$A$35,C21)<>1,"",IF(INDEX(市场案例库!$F$6:$F$35,MATCH(C21,市场案例库!$A$6:$A$35,0))="","",INDEX(市场案例库!$F$6:$F$35,MATCH(C21,市场案例库!$A$6:$A$35,0)))) -> 元/㎡/月 | G21: =IF(OR(COUNT(修正明细!J246:J261)<>16,COUNTIFS(修正明细!M246:M261,"模拟评分记录完整")<>16),"",PRODUCT(修正明细!J246:J261)) -> 0.95165226 | H21: =IF(OR(COUNT(E21,G21)<>2,E21<=0,三案例选用!F11<>"三案例齐全",三案例选用!G11<>"用途口径一致",三案例选用!H11<>"绑定有效"),"",E21*G21) -> 24.742959 | I21: =IF(COUNT(H21)<>1,"",H21/E21-1) -> -0.048347741 | J21: =IF(COUNT(I21)<>1,"待补计算资料",IF(ABS(I21)<=测算参数!$B$7,"通过","超限待复核")) -> 通过 | K21: =IF(COUNT(H21)<>1,"待补资料或重判评分","模拟计算可复算") -> 模拟计算可复算
A22: RP-006 | B22: 2 | C22: =三案例选用!C11 -> SC-011 | D22: =IF(COUNTIFS(市场案例库!$A$6:$A$35,C22)<>1,"",IF(INDEX(市场案例库!$B$6:$B$35,MATCH(C22,市场案例库!$A$6:$A$35,0))="","",INDEX(市场案例库!$B$6:$B$35,MATCH(C22,市场案例库!$A$6:$A$35,0)))) -> 模拟案例11 | E22: =IF(COUNTIFS(市场案例库!$A$6:$A$35,C22)<>1,"",IF(COUNT(INDEX(市场案例库!$J$6:$J$35,MATCH(C22,市场案例库!$A$6:$A$35,0)))<>1,"",INDEX(市场案例库!$J$6:$J$35,MATCH(C22,市场案例库!$A$6:$A$35,0)))) -> 27 | F22: =IF(COUNTIFS(市场案例库!$A$6:$A$35,C22)<>1,"",IF(INDEX(市场案例库!$F$6:$F$35,MATCH(C22,市场案例库!$A$6:$A$35,0))="","",INDEX(市场案例库!$F$6:$F$35,MATCH(C22,市场案例库!$A$6:$A$35,0)))) -> 元/㎡/月 | G22: =IF(OR(COUNT(修正明细!J262:J277)<>16,COUNTIFS(修正明细!M262:M277,"模拟评分记录完整")<>16),"",PRODUCT(修正明细!J262:J277)) -> 0.96116878 | H22: =IF(OR(COUNT(E22,G22)<>2,E22<=0,三案例选用!F11<>"三案例齐全",三案例选用!G11<>"用途口径一致",三案例选用!H11<>"绑定有效"),"",E22*G22) -> 25.951557 | I22: =IF(COUNT(H22)<>1,"",H22/E22-1) -> -0.038831219 | J22: =IF(COUNT(I22)<>1,"待补计算资料",IF(ABS(I22)<=测算参数!$B$7,"通过","超限待复核")) -> 通过 | K22: =IF(COUNT(H22)<>1,"待补资料或重判评分","模拟计算可复算") -> 模拟计算可复算
A23: RP-006 | B23: 3 | C23: =三案例选用!D11 -> SC-012 | D23: =IF(COUNTIFS(市场案例库!$A$6:$A$35,C23)<>1,"",IF(INDEX(市场案例库!$B$6:$B$35,MATCH(C23,市场案例库!$A$6:$A$35,0))="","",INDEX(市场案例库!$B$6:$B$35,MATCH(C23,市场案例库!$A$6:$A$35,0)))) -> 模拟案例12 | E23: =IF(COUNTIFS(市场案例库!$A$6:$A$35,C23)<>1,"",IF(COUNT(INDEX(市场案例库!$J$6:$J$35,MATCH(C23,市场案例库!$A$6:$A$35,0)))<>1,"",INDEX(市场案例库!$J$6:$J$35,MATCH(C23,市场案例库!$A$6:$A$35,0)))) -> 28 | F23: =IF(COUNTIFS(市场案例库!$A$6:$A$35,C23)<>1,"",IF(INDEX(市场案例库!$F$6:$F$35,MATCH(C23,市场案例库!$A$6:$A$35,0))="","",INDEX(市场案例库!$F$6:$F$35,MATCH(C23,市场案例库!$A$6:$A$35,0)))) -> 元/㎡/月 | G23: =IF(OR(COUNT(修正明细!J278:J293)<>16,COUNTIFS(修正明细!M278:M293,"模拟评分记录完整")<>16),"",PRODUCT(修正明细!J278:J293)) -> 0.99029511 | H23: =IF(OR(COUNT(E23,G23)<>2,E23<=0,三案例选用!F11<>"三案例齐全",三案例选用!G11<>"用途口径一致",三案例选用!H11<>"绑定有效"),"",E23*G23) -> 27.728263 | I23: =IF(COUNT(H23)<>1,"",H23/E23-1) -> -0.0097048921 | J23: =IF(COUNT(I23)<>1,"待补计算资料",IF(ABS(I23)<=测算参数!$B$7,"通过","超限待复核")) -> 通过 | K23: =IF(COUNT(H23)<>1,"待补资料或重判评分","模拟计算可复算") -> 模拟计算可复算
A24: RP-007 | B24: 1 | C24: =三案例选用!B12 -> SC-013 | D24: =IF(COUNTIFS(市场案例库!$A$6:$A$35,C24)<>1,"",IF(INDEX(市场案例库!$B$6:$B$35,MATCH(C24,市场案例库!$A$6:$A$35,0))="","",INDEX(市场案例库!$B$6:$B$35,MATCH(C24,市场案例库!$A$6:$A$35,0)))) -> 模拟案例13 | E24: =IF(COUNTIFS(市场案例库!$A$6:$A$35,C24)<>1,"",IF(COUNT(INDEX(市场案例库!$J$6:$J$35,MATCH(C24,市场案例库!$A$6:$A$35,0)))<>1,"",INDEX(市场案例库!$J$6:$J$35,MATCH(C24,市场案例库!$A$6:$A$35,0)))) -> 12.5 | F24: =IF(COUNTIFS(市场案例库!$A$6:$A$35,C24)<>1,"",IF(INDEX(市场案例库!$F$6:$F$35,MATCH(C24,市场案例库!$A$6:$A$35,0))="","",INDEX(市场案例库!$F$6:$F$35,MATCH(C24,市场案例库!$A$6:$A$35,0)))) -> 元/㎡/月 | G24: =IF(OR(COUNT(修正明细!J294:J309)<>16,COUNTIFS(修正明细!M294:M309,"模拟评分记录完整")<>16),"",PRODUCT(修正明细!J294:J309)) -> 0.93370682 | H24: =IF(OR(COUNT(E24,G24)<>2,E24<=0,三案例选用!F12<>"三案例齐全",三案例选用!G12<>"用途口径一致",三案例选用!H12<>"绑定有效"),"",E24*G24) -> 11.671335 | I24: =IF(COUNT(H24)<>1,"",H24/E24-1) -> -0.066293184 | J24: =IF(COUNT(I24)<>1,"待补计算资料",IF(ABS(I24)<=测算参数!$B$7,"通过","超限待复核")) -> 通过 | K24: =IF(COUNT(H24)<>1,"待补资料或重判评分","模拟计算可复算") -> 模拟计算可复算
A25: RP-007 | B25: 2 | C25: =三案例选用!C12 -> SC-014 | D25: =IF(COUNTIFS(市场案例库!$A$6:$A$35,C25)<>1,"",IF(INDEX(市场案例库!$B$6:$B$35,MATCH(C25,市场案例库!$A$6:$A$35,0))="","",INDEX(市场案例库!$B$6:$B$35,MATCH(C25,市场案例库!$A$6:$A$35,0)))) -> 模拟案例14 | E25: =IF(COUNTIFS(市场案例库!$A$6:$A$35,C25)<>1,"",IF(COUNT(INDEX(市场案例库!$J$6:$J$35,MATCH(C25,市场案例库!$A$6:$A$35,0)))<>1,"",INDEX(市场案例库!$J$6:$J$35,MATCH(C25,市场案例库!$A$6:$A$35,0)))) -> 13 | F25: =IF(COUNTIFS(市场案例库!$A$6:$A$35,C25)<>1,"",IF(INDEX(市场案例库!$F$6:$F$35,MATCH(C25,市场案例库!$A$6:$A$35,0))="","",INDEX(市场案例库!$F$6:$F$35,MATCH(C25,市场案例库!$A$6:$A$35,0)))) -> 元/㎡/月 | G25: =IF(OR(COUNT(修正明细!J310:J325)<>16,COUNTIFS(修正明细!M310:M325,"模拟评分记录完整")<>16),"",PRODUCT(修正明细!J310:J325)) -> 0.98078447 | H25: =IF(OR(COUNT(E25,G25)<>2,E25<=0,三案例选用!F12<>"三案例齐全",三案例选用!G12<>"用途口径一致",三案例选用!H12<>"绑定有效"),"",E25*G25) -> 12.750198 | I25: =IF(COUNT(H25)<>1,"",H25/E25-1) -> -0.019215529 | J25: =IF(COUNT(I25)<>1,"待补计算资料",IF(ABS(I25)<=测算参数!$B$7,"通过","超限待复核")) -> 通过 | K25: =IF(COUNT(H25)<>1,"待补资料或重判评分","模拟计算可复算") -> 模拟计算可复算
A26: RP-007 | B26: 3 | C26: =三案例选用!D12 -> SC-015 | D26: =IF(COUNTIFS(市场案例库!$A$6:$A$35,C26)<>1,"",IF(INDEX(市场案例库!$B$6:$B$35,MATCH(C26,市场案例库!$A$6:$A$35,0))="","",INDEX(市场案例库!$B$6:$B$35,MATCH(C26,市场案例库!$A$6:$A$35,0)))) -> 模拟案例15 | E26: =IF(COUNTIFS(市场案例库!$A$6:$A$35,C26)<>1,"",IF(COUNT(INDEX(市场案例库!$J$6:$J$35,MATCH(C26,市场案例库!$A$6:$A$35,0)))<>1,"",INDEX(市场案例库!$J$6:$J$35,MATCH(C26,市场案例库!$A$6:$A$35,0)))) -> 12 | F26: =IF(COUNTIFS(市场案例库!$A$6:$A$35,C26)<>1,"",IF(INDEX(市场案例库!$F$6:$F$35,MATCH(C26,市场案例库!$A$6:$A$35,0))="","",INDEX(市场案例库!$F$6:$F$35,MATCH(C26,市场案例库!$A$6:$A$35,0)))) -> 元/㎡/月 | G26: =IF(OR(COUNT(修正明细!J326:J341)<>16,COUNTIFS(修正明细!M326:M341,"模拟评分记录完整")<>16),"",PRODUCT(修正明细!J326:J341)) -> 0.98039216 | H26: =IF(OR(COUNT(E26,G26)<>2,E26<=0,三案例选用!F12<>"三案例齐全",三案例选用!G12<>"用途口径一致",三案例选用!H12<>"绑定有效"),"",E26*G26) -> 11.764706 | I26: =IF(COUNT(H26)<>1,"",H26/E26-1) -> -0.019607843 | J26: =IF(COUNT(I26)<>1,"待补计算资料",IF(ABS(I26)<=测算参数!$B$7,"通过","超限待复核")) -> 通过 | K26: =IF(COUNT(H26)<>1,"待补资料或重判评分","模拟计算可复算") -> 模拟计算可复算
A27: RP-008 | B27: 1 | C27: =三案例选用!B13 -> SC-016 | D27: =IF(COUNTIFS(市场案例库!$A$6:$A$35,C27)<>1,"",IF(INDEX(市场案例库!$B$6:$B$35,MATCH(C27,市场案例库!$A$6:$A$35,0))="","",INDEX(市场案例库!$B$6:$B$35,MATCH(C27,市场案例库!$A$6:$A$35,0)))) -> 模拟案例16 | E27: =IF(COUNTIFS(市场案例库!$A$6:$A$35,C27)<>1,"",IF(COUNT(INDEX(市场案例库!$J$6:$J$35,MATCH(C27,市场案例库!$A$6:$A$35,0)))<>1,"",INDEX(市场案例库!$J$6:$J$35,MATCH(C27,市场案例库!$A$6:$A$35,0)))) -> 18 | F27: =IF(COUNTIFS(市场案例库!$A$6:$A$35,C27)<>1,"",IF(INDEX(市场案例库!$F$6:$F$35,MATCH(C27,市场案例库!$A$6:$A$35,0))="","",INDEX(市场案例库!$F$6:$F$35,MATCH(C27,市场案例库!$A$6:$A$35,0)))) -> 元/㎡/月 | G27: =IF(OR(COUNT(修正明细!J342:J357)<>16,COUNTIFS(修正明细!M342:M357,"模拟评分记录完整")<>16),"",PRODUCT(修正明细!J342:J357)) -> 0.89693731 | H27: =IF(OR(COUNT(E27,G27)<>2,E27<=0,三案例选用!F13<>"三案例齐全",三案例选用!G13<>"用途口径一致",三案例选用!H13<>"绑定有效"),"",E27*G27) -> 16.144872 | I27: =IF(COUNT(H27)<>1,"",H27/E27-1) -> -0.10306269 | J27: =IF(COUNT(I27)<>1,"待补计算资料",IF(ABS(I27)<=测算参数!$B$7,"通过","超限待复核")) -> 通过 | K27: =IF(COUNT(H27)<>1,"待补资料或重判评分","模拟计算可复算") -> 模拟计算可复算
A28: RP-008 | B28: 2 | C28: =三案例选用!C13 -> SC-017 | D28: =IF(COUNTIFS(市场案例库!$A$6:$A$35,C28)<>1,"",IF(INDEX(市场案例库!$B$6:$B$35,MATCH(C28,市场案例库!$A$6:$A$35,0))="","",INDEX(市场案例库!$B$6:$B$35,MATCH(C28,市场案例库!$A$6:$A$35,0)))) -> 模拟案例17 | E28: =IF(COUNTIFS(市场案例库!$A$6:$A$35,C28)<>1,"",IF(COUNT(INDEX(市场案例库!$J$6:$J$35,MATCH(C28,市场案例库!$A$6:$A$35,0)))<>1,"",INDEX(市场案例库!$J$6:$J$35,MATCH(C28,市场案例库!$A$6:$A$35,0)))) -> 19 | F28: =IF(COUNTIFS(市场案例库!$A$6:$A$35,C28)<>1,"",IF(INDEX(市场案例库!$F$6:$F$35,MATCH(C28,市场案例库!$A$6:$A$35,0))="","",INDEX(市场案例库!$F$6:$F$35,MATCH(C28,市场案例库!$A$6:$A$35,0)))) -> 元/㎡/月 | G28: =IF(OR(COUNT(修正明细!J358:J373)<>16,COUNTIFS(修正明细!M358:M373,"模拟评分记录完整")<>16),"",PRODUCT(修正明细!J358:J373)) -> 0.89729623 | H28: =IF(OR(COUNT(E28,G28)<>2,E28<=0,三案例选用!F13<>"三案例齐全",三案例选用!G13<>"用途口径一致",三案例选用!H13<>"绑定有效"),"",E28*G28) -> 17.048628 | I28: =IF(COUNT(H28)<>1,"",H28/E28-1) -> -0.10270377 | J28: =IF(COUNT(I28)<>1,"待补计算资料",IF(ABS(I28)<=测算参数!$B$7,"通过","超限待复核")) -> 通过 | K28: =IF(COUNT(H28)<>1,"待补资料或重判评分","模拟计算可复算") -> 模拟计算可复算
A29: RP-008 | B29: 3 | C29: =三案例选用!D13 -> SC-018 | D29: =IF(COUNTIFS(市场案例库!$A$6:$A$35,C29)<>1,"",IF(INDEX(市场案例库!$B$6:$B$35,MATCH(C29,市场案例库!$A$6:$A$35,0))="","",INDEX(市场案例库!$B$6:$B$35,MATCH(C29,市场案例库!$A$6:$A$35,0)))) -> 模拟案例18 | E29: =IF(COUNTIFS(市场案例库!$A$6:$A$35,C29)<>1,"",IF(COUNT(INDEX(市场案例库!$J$6:$J$35,MATCH(C29,市场案例库!$A$6:$A$35,0)))<>1,"",INDEX(市场案例库!$J$6:$J$35,MATCH(C29,市场案例库!$A$6:$A$35,0)))) -> 18.5 | F29: =IF(COUNTIFS(市场案例库!$A$6:$A$35,C29)<>1,"",IF(INDEX(市场案例库!$F$6:$F$35,MATCH(C29,市场案例库!$A$6:$A$35,0))="","",INDEX(市场案例库!$F$6:$F$35,MATCH(C29,市场案例库!$A$6:$A$35,0)))) -> 元/㎡/月 | G29: =IF(OR(COUNT(修正明细!J374:J389)<>16,COUNTIFS(修正明细!M374:M389,"模拟评分记录完整")<>16),"",PRODUCT(修正明细!J374:J389)) -> 0.89693731 | H29: =IF(OR(COUNT(E29,G29)<>2,E29<=0,三案例选用!F13<>"三案例齐全",三案例选用!G13<>"用途口径一致",三案例选用!H13<>"绑定有效"),"",E29*G29) -> 16.59334 | I29: =IF(COUNT(H29)<>1,"",H29/E29-1) -> -0.10306269 | J29: =IF(COUNT(I29)<>1,"待补计算资料",IF(ABS(I29)<=测算参数!$B$7,"通过","超限待复核")) -> 通过 | K29: =IF(COUNT(H29)<>1,"待补资料或重判评分","模拟计算可复算") -> 模拟计算可复算
A30: RP-009 | B30: 1 | C30: =三案例选用!B14 -> SC-019 | D30: =IF(COUNTIFS(市场案例库!$A$6:$A$35,C30)<>1,"",IF(INDEX(市场案例库!$B$6:$B$35,MATCH(C30,市场案例库!$A$6:$A$35,0))="","",INDEX(市场案例库!$B$6:$B$35,MATCH(C30,市场案例库!$A$6:$A$35,0)))) -> 模拟案例19 | E30: =IF(COUNTIFS(市场案例库!$A$6:$A$35,C30)<>1,"",IF(COUNT(INDEX(市场案例库!$J$6:$J$35,MATCH(C30,市场案例库!$A$6:$A$35,0)))<>1,"",INDEX(市场案例库!$J$6:$J$35,MATCH(C30,市场案例库!$A$6:$A$35,0)))) -> 3.4 | F30: =IF(COUNTIFS(市场案例库!$A$6:$A$35,C30)<>1,"",IF(INDEX(市场案例库!$F$6:$F$35,MATCH(C30,市场案例库!$A$6:$A$35,0))="","",INDEX(市场案例库!$F$6:$F$35,MATCH(C30,市场案例库!$A$6:$A$35,0)))) -> 元/㎡/月 | G30: =IF(OR(COUNT(修正明细!J390:J405)<>16,COUNTIFS(修正明细!M390:M405,"模拟评分记录完整")<>16),"",PRODUCT(修正明细!J390:J405)) -> 0.98039216 | H30: =IF(OR(COUNT(E30,G30)<>2,E30<=0,三案例选用!F14<>"三案例齐全",三案例选用!G14<>"用途口径一致",三案例选用!H14<>"绑定有效"),"",E30*G30) -> 3.3333333 | I30: =IF(COUNT(H30)<>1,"",H30/E30-1) -> -0.019607843 | J30: =IF(COUNT(I30)<>1,"待补计算资料",IF(ABS(I30)<=测算参数!$B$7,"通过","超限待复核")) -> 通过 | K30: =IF(COUNT(H30)<>1,"待补资料或重判评分","模拟计算可复算") -> 模拟计算可复算
A31: RP-009 | B31: 2 | C31: =三案例选用!C14 -> SC-020 | D31: =IF(COUNTIFS(市场案例库!$A$6:$A$35,C31)<>1,"",IF(INDEX(市场案例库!$B$6:$B$35,MATCH(C31,市场案例库!$A$6:$A$35,0))="","",INDEX(市场案例库!$B$6:$B$35,MATCH(C31,市场案例库!$A$6:$A$35,0)))) -> 模拟案例20 | E31: =IF(COUNTIFS(市场案例库!$A$6:$A$35,C31)<>1,"",IF(COUNT(INDEX(市场案例库!$J$6:$J$35,MATCH(C31,市场案例库!$A$6:$A$35,0)))<>1,"",INDEX(市场案例库!$J$6:$J$35,MATCH(C31,市场案例库!$A$6:$A$35,0)))) -> 3.6 | F31: =IF(COUNTIFS(市场案例库!$A$6:$A$35,C31)<>1,"",IF(INDEX(市场案例库!$F$6:$F$35,MATCH(C31,市场案例库!$A$6:$A$35,0))="","",INDEX(市场案例库!$F$6:$F$35,MATCH(C31,市场案例库!$A$6:$A$35,0)))) -> 元/㎡/月 | G31: =IF(OR(COUNT(修正明细!J406:J421)<>16,COUNTIFS(修正明细!M406:M421,"模拟评分记录完整")<>16),"",PRODUCT(修正明细!J406:J421)) -> 0.98039216 | H31: =IF(OR(COUNT(E31,G31)<>2,E31<=0,三案例选用!F14<>"三案例齐全",三案例选用!G14<>"用途口径一致",三案例选用!H14<>"绑定有效"),"",E31*G31) -> 3.5294118 | I31: =IF(COUNT(H31)<>1,"",H31/E31-1) -> -0.019607843 | J31: =IF(COUNT(I31)<>1,"待补计算资料",IF(ABS(I31)<=测算参数!$B$7,"通过","超限待复核")) -> 通过 | K31: =IF(COUNT(H31)<>1,"待补资料或重判评分","模拟计算可复算") -> 模拟计算可复算
A32: RP-009 | B32: 3 | C32: =三案例选用!D14 -> SC-021 | D32: =IF(COUNTIFS(市场案例库!$A$6:$A$35,C32)<>1,"",IF(INDEX(市场案例库!$B$6:$B$35,MATCH(C32,市场案例库!$A$6:$A$35,0))="","",INDEX(市场案例库!$B$6:$B$35,MATCH(C32,市场案例库!$A$6:$A$35,0)))) -> 模拟案例21 | E32: =IF(COUNTIFS(市场案例库!$A$6:$A$35,C32)<>1,"",IF(COUNT(INDEX(市场案例库!$J$6:$J$35,MATCH(C32,市场案例库!$A$6:$A$35,0)))<>1,"",INDEX(市场案例库!$J$6:$J$35,MATCH(C32,市场案例库!$A$6:$A$35,0)))) -> 3.5 | F32: =IF(COUNTIFS(市场案例库!$A$6:$A$35,C32)<>1,"",IF(INDEX(市场案例库!$F$6:$F$35,MATCH(C32,市场案例库!$A$6:$A$35,0))="","",INDEX(市场案例库!$F$6:$F$35,MATCH(C32,市场案例库!$A$6:$A$35,0)))) -> 元/㎡/月 | G32: =IF(OR(COUNT(修正明细!J422:J437)<>16,COUNTIFS(修正明细!M422:M437,"模拟评分记录完整")<>16),"",PRODUCT(修正明细!J422:J437)) -> 0.98039216 | H32: =IF(OR(COUNT(E32,G32)<>2,E32<=0,三案例选用!F14<>"三案例齐全",三案例选用!G14<>"用途口径一致",三案例选用!H14<>"绑定有效"),"",E32*G32) -> 3.4313725 | I32: =IF(COUNT(H32)<>1,"",H32/E32-1) -> -0.019607843 | J32: =IF(COUNT(I32)<>1,"待补计算资料",IF(ABS(I32)<=测算参数!$B$7,"通过","超限待复核")) -> 通过 | K32: =IF(COUNT(H32)<>1,"待补资料或重判评分","模拟计算可复算") -> 模拟计算可复算
A33: RP-010 | B33: 1 | C33: =三案例选用!B15 -> SC-022 | D33: =IF(COUNTIFS(市场案例库!$A$6:$A$35,C33)<>1,"",IF(INDEX(市场案例库!$B$6:$B$35,MATCH(C33,市场案例库!$A$6:$A$35,0))="","",INDEX(市场案例库!$B$6:$B$35,MATCH(C33,市场案例库!$A$6:$A$35,0)))) -> 模拟案例22 | E33: =IF(COUNTIFS(市场案例库!$A$6:$A$35,C33)<>1,"",IF(COUNT(INDEX(市场案例库!$J$6:$J$35,MATCH(C33,市场案例库!$A$6:$A$35,0)))<>1,"",INDEX(市场案例库!$J$6:$J$35,MATCH(C33,市场案例库!$A$6:$A$35,0)))) -> 185 | F33: =IF(COUNTIFS(市场案例库!$A$6:$A$35,C33)<>1,"",IF(INDEX(市场案例库!$F$6:$F$35,MATCH(C33,市场案例库!$A$6:$A$35,0))="","",INDEX(市场案例库!$F$6:$F$35,MATCH(C33,市场案例库!$A$6:$A$35,0)))) -> 元/个/月 | G33: =IF(OR(COUNT(修正明细!J438:J453)<>16,COUNTIFS(修正明细!M438:M453,"模拟评分记录完整")<>16),"",PRODUCT(修正明细!J438:J453)) -> 1 | H33: =IF(OR(COUNT(E33,G33)<>2,E33<=0,三案例选用!F15<>"三案例齐全",三案例选用!G15<>"用途口径一致",三案例选用!H15<>"绑定有效"),"",E33*G33) -> 185 | I33: =IF(COUNT(H33)<>1,"",H33/E33-1) -> 0 | J33: =IF(COUNT(I33)<>1,"待补计算资料",IF(ABS(I33)<=测算参数!$B$7,"通过","超限待复核")) -> 通过 | K33: =IF(COUNT(H33)<>1,"待补资料或重判评分","模拟计算可复算") -> 模拟计算可复算
A34: RP-010 | B34: 2 | C34: =三案例选用!C15 -> SC-023 | D34: =IF(COUNTIFS(市场案例库!$A$6:$A$35,C34)<>1,"",IF(INDEX(市场案例库!$B$6:$B$35,MATCH(C34,市场案例库!$A$6:$A$35,0))="","",INDEX(市场案例库!$B$6:$B$35,MATCH(C34,市场案例库!$A$6:$A$35,0)))) -> 模拟案例23 | E34: =IF(COUNTIFS(市场案例库!$A$6:$A$35,C34)<>1,"",IF(COUNT(INDEX(市场案例库!$J$6:$J$35,MATCH(C34,市场案例库!$A$6:$A$35,0)))<>1,"",INDEX(市场案例库!$J$6:$J$35,MATCH(C34,市场案例库!$A$6:$A$35,0)))) -> 190 | F34: =IF(COUNTIFS(市场案例库!$A$6:$A$35,C34)<>1,"",IF(INDEX(市场案例库!$F$6:$F$35,MATCH(C34,市场案例库!$A$6:$A$35,0))="","",INDEX(市场案例库!$F$6:$F$35,MATCH(C34,市场案例库!$A$6:$A$35,0)))) -> 元/个/月 | G34: =IF(OR(COUNT(修正明细!J454:J469)<>16,COUNTIFS(修正明细!M454:M469,"模拟评分记录完整")<>16),"",PRODUCT(修正明细!J454:J469)) -> 1 | H34: =IF(OR(COUNT(E34,G34)<>2,E34<=0,三案例选用!F15<>"三案例齐全",三案例选用!G15<>"用途口径一致",三案例选用!H15<>"绑定有效"),"",E34*G34) -> 190 | I34: =IF(COUNT(H34)<>1,"",H34/E34-1) -> 0 | J34: =IF(COUNT(I34)<>1,"待补计算资料",IF(ABS(I34)<=测算参数!$B$7,"通过","超限待复核")) -> 通过 | K34: =IF(COUNT(H34)<>1,"待补资料或重判评分","模拟计算可复算") -> 模拟计算可复算
A35: RP-010 | B35: 3 | C35: =三案例选用!D15 -> SC-024 | D35: =IF(COUNTIFS(市场案例库!$A$6:$A$35,C35)<>1,"",IF(INDEX(市场案例库!$B$6:$B$35,MATCH(C35,市场案例库!$A$6:$A$35,0))="","",INDEX(市场案例库!$B$6:$B$35,MATCH(C35,市场案例库!$A$6:$A$35,0)))) -> 模拟案例24 | E35: =IF(COUNTIFS(市场案例库!$A$6:$A$35,C35)<>1,"",IF(COUNT(INDEX(市场案例库!$J$6:$J$35,MATCH(C35,市场案例库!$A$6:$A$35,0)))<>1,"",INDEX(市场案例库!$J$6:$J$35,MATCH(C35,市场案例库!$A$6:$A$35,0)))) -> 180 | F35: =IF(COUNTIFS(市场案例库!$A$6:$A$35,C35)<>1,"",IF(INDEX(市场案例库!$F$6:$F$35,MATCH(C35,市场案例库!$A$6:$A$35,0))="","",INDEX(市场案例库!$F$6:$F$35,MATCH(C35,市场案例库!$A$6:$A$35,0)))) -> 元/个/月 | G35: =IF(OR(COUNT(修正明细!J470:J485)<>16,COUNTIFS(修正明细!M470:M485,"模拟评分记录完整")<>16),"",PRODUCT(修正明细!J470:J485)) -> 1 | H35: =IF(OR(COUNT(E35,G35)<>2,E35<=0,三案例选用!F15<>"三案例齐全",三案例选用!G15<>"用途口径一致",三案例选用!H15<>"绑定有效"),"",E35*G35) -> 180 | I35: =IF(COUNT(H35)<>1,"",H35/E35-1) -> 0 | J35: =IF(COUNT(I35)<>1,"待补计算资料",IF(ABS(I35)<=测算参数!$B$7,"通过","超限待复核")) -> 通过 | K35: =IF(COUNT(H35)<>1,"待补资料或重判评分","模拟计算可复算") -> 模拟计算可复算
A36: RP-011 | B36: 1 | C36: =三案例选用!B16 -> SC-025 | D36: =IF(COUNTIFS(市场案例库!$A$6:$A$35,C36)<>1,"",IF(INDEX(市场案例库!$B$6:$B$35,MATCH(C36,市场案例库!$A$6:$A$35,0))="","",INDEX(市场案例库!$B$6:$B$35,MATCH(C36,市场案例库!$A$6:$A$35,0)))) -> 模拟案例25 | E36: =IF(COUNTIFS(市场案例库!$A$6:$A$35,C36)<>1,"",IF(COUNT(INDEX(市场案例库!$J$6:$J$35,MATCH(C36,市场案例库!$A$6:$A$35,0)))<>1,"",INDEX(市场案例库!$J$6:$J$35,MATCH(C36,市场案例库!$A$6:$A$35,0)))) -> 680 | F36: =IF(COUNTIFS(市场案例库!$A$6:$A$35,C36)<>1,"",IF(INDEX(市场案例库!$F$6:$F$35,MATCH(C36,市场案例库!$A$6:$A$35,0))="","",INDEX(市场案例库!$F$6:$F$35,MATCH(C36,市场案例库!$A$6:$A$35,0)))) -> 元/间/月 | G36: =IF(OR(COUNT(修正明细!J486:J501)<>16,COUNTIFS(修正明细!M486:M501,"模拟评分记录完整")<>16),"",PRODUCT(修正明细!J486:J501)) -> 0.98039216 | H36: =IF(OR(COUNT(E36,G36)<>2,E36<=0,三案例选用!F16<>"三案例齐全",三案例选用!G16<>"用途口径一致",三案例选用!H16<>"绑定有效"),"",E36*G36) -> 666.66667 | I36: =IF(COUNT(H36)<>1,"",H36/E36-1) -> -0.019607843 | J36: =IF(COUNT(I36)<>1,"待补计算资料",IF(ABS(I36)<=测算参数!$B$7,"通过","超限待复核")) -> 通过 | K36: =IF(COUNT(H36)<>1,"待补资料或重判评分","模拟计算可复算") -> 模拟计算可复算
